Workbook

Sheet 固定費
B4: 口座引き落とし | C4: 引き落とし日 | D4: 金額 | E4: カード払い | F4: 支払日 | G4: 金額
B5: 家賃 | C5: 毎月27日 | D5: 93000 | E5: 視点・Off Topic（note） | F5: 毎月1日 | G5: 1200
B6: 大学奨学金 | C6: 毎月27日 | D6: 13600 | E6: アイカサ | F6: 毎月1日 | G6: 280
B7: みいちゃんへの返済 | C7: 毎月27日 | D7: 40000 | E7: ディズニープラス | F7: 毎月8日 | G7: 1480
B8: カードローンへの返済 | C8: 毎月27日 | D8: 24000 | E8: postalk | F8: 毎月9日 | G8: 880
B9: ジム代 | C9: 毎月27日 | D9: 8140 | E9: Wi-Fi | F9: 毎月11日 | G9: 6000
E10: Netflix | F10: 毎月16日 | G10: 1490
E11: chapters | F11: 毎月19日 | G11: 2310
E12: コテンラジオ | F12: 毎月20日 | G12: 1100
E13: 電気代 | F13: 毎月20日 | G13: 5000
E14: つみたてNISA | F14: 毎月28日 | G14: 15000
B15: 合計金額 | D15: =SUM(D5:D9) -> 178740 | E15: 合計金額 | G15: =SUM(G5:G14) -> 34740
E17: 毎月固定費合計 | G17: =D15+G15 -> 213480
E18: 給与 | G18: 370000
E19: 残高 | G19: =G18-G17 -> 156520

Sheet 【Monthly】2023年
B1: 合計金額 | C1: 45108 | D1: 45139 | E1: 45170 | F1: 45200 | G1: 45231 | H1: 45261 | I1: 45292
A2: 収入 | B2: =SUM(C2:H2) -> 2253976 | C2: =SUMIFS('フォームの回答 1'!$E:$E,'フォームの回答 1'!$B:$B,">="&C1,'フォームの回答 1'!$H:$H,"収入")-SUMIFS('フォームの回答 1'!$E:$E,'フォームの回答 1'!$B:$B,">"&D1,'フォームの回答 1'!$H:$H,"収入") -> 294581 | D2: =SUMIFS('フォームの回答 1'!$E:$E,'フォームの回答 1'!$B:$B,">="&D1,'フォームの回答 1'!$H:$H,"収入")-SUMIFS('フォームの回答 1'!$E:$E,'フォームの回答 1'!$B:$B,">"&E1,'フォームの回答 1'!$H:$H,"収入") -> 386533 | E2: =SUMIFS('フォームの回答 1'!$E:$E,'フォームの回答 1'!$B:$B,">="&E1,'フォームの回答 1'!$H:$H,"収入")-SUMIFS('フォームの回答 1'!$E:$E,'フォームの回答 1'!$B:$B,">"&F1,'フォームの回答 1'!$H:$H,"収入") -> 467420 | F2: =SUMIFS('フォームの回答 1'!$E:$E,'フォームの回答 1'!$B:$B,">="&F1,'フォームの回答 1'!$H:$H,"収入")-SUMIFS('フォームの回答 1'!$E:$E,'フォームの回答 1'!$B:$B,">"&G1,'フォームの回答 1'!$H:$H,"収入") -> 302210 | G2: =SUMIFS('フォームの回答 1'!$E:$E,'フォームの回答 1'!$B:$B,">="&G1,'フォームの回答 1'!$H:$H,"収入")-SUMIFS('フォームの回答 1'!$E:$E,'フォームの回答 1'!$B:$B,">"&H1,'フォームの回答 1'!$H:$H,"収入") -> 387723 | H2: =SUMIFS('フォームの回答 1'!$E:$E,'フォームの回答 1'!$B:$B,">="&H1,'フォームの回答 1'!$H:$H,"収入")-SUMIFS('フォームの回答 1'!$E:$E,'フォームの回答 1'!$B:$B,">"&I1,'フォームの回答 1'!$H:$H,"収入") -> 415509 | I2: =SUMIFS('フォームの回答 1'!$E:$E,'フォームの回答 1'!$B:$B,">="&I1,'フォームの回答 1'!$H:$H,"収入")-SUMIFS('フォームの回答 1'!$E:$E,'フォームの回答 1'!$B:$B,">"&J1,'フォームの回答 1'!$H:$H,"収入") -> 11887924
A3: 支出 | B3: =SUM(C3:H3) -> 2336539 | C3: =SUMIFS('フォームの回答 1'!$E:$E,'フォームの回答 1'!$B:$B,">="&C1,'フォームの回答 1'!$H:$H,"支出")-SUMIFS('フォームの回答 1'!$E:$E,'フォームの回答 1'!$B:$B,">"&D1,'フォームの回答 1'!$H:$H,"支出") -> 349155 | D3: =SUMIFS('フォームの回答 1'!$E:$E,'フォームの回答 1'!$B:$B,">="&D1,'フォームの回答 1'!$H:$H,"支出")-SUMIFS('フォームの回答 1'!$E:$E,'フォームの回答 1'!$B:$B,">"&E1,'フォームの回答 1'!$H:$H,"支出") -> 393550 | E3: =SUMIFS('フォームの回答 1'!$E:$E,'フォームの回答 1'!$B:$B,">="&E1,'フォームの回答 1'!$H:$H,"支出")-SUMIFS('フォームの回答 1'!$E:$E,'フォームの回答 1'!$B:$B,">"&F1,'フォームの回答 1'!$H:$H,"支出") -> 425591 | F3: =SUMIFS('フォームの回答 1'!$E:$E,'フォームの回答 1'!$B:$B,">="&F1,'フォームの回答 1'!$H:$H,"支出")-SUMIFS('フォームの回答 1'!$E:$E,'フォームの回答 1'!$B:$B,">"&G1,'フォームの回答 1'!$H:$H,"支出") -> 417000 | G3: =SUMIFS('フォームの回答 1'!$E:$E,'フォームの回答 1'!$B:$B,">="&G1,'フォームの回答 1'!$H:$H,"支出")-SUMIFS('フォームの回答 1'!$E:$E,'フォームの回答 1'!$B:$B,">"&H1,'フォームの回答 1'!$H:$H,"支出") -> 321055 | H3: =SUMIFS('フォームの回答 1'!$E:$E,'フォームの回答 1'!$B:$B,">="&H1,'フォームの回答 1'!$H:$H,"支出")-SUMIFS('フォームの回答 1'!$E:$E,'フォームの回答 1'!$B:$B,">"&I1,'フォームの回答 1'!$H:$H,"支出") -> 430188 | I3: =SUMIFS('フォームの回答 1'!$E:$E,'フォームの回答 1'!$B:$B,">="&I1,'フォームの回答 1'!$H:$H,"支出")-SUMIFS('フォームの回答 1'!$E:$E,'フォームの回答 1'!$B:$B,">"&J1,'フォームの回答 1'!$H:$H,"支出") -> 11852954
A4: 差額 | B4: =SUM(C4:H4) -> -82563 | C4: =C2-C3 -> -54574 | D4: =D2-D3 -> -7017 | E4: =E2-E3 -> 41829 | F4: =F2-F3 -> -114790 | G4: =G2-G3 -> 66668 | H4: =H2-H3 -> -14679 | I4: =I2-I3 -> 34970
B5: 内訳
A6: 食費 | B6: =SUM(C6:I6) -> 1353022 | C6: =SUMIFS('フォームの回答 1'!$E:$E,'フォームの回答 1'!$B:$B,">="&C1,'フォームの回答 1'!$H:$H,"支出",'フォームの回答 1'!$D:$D,$A6)-SUMIFS('フォームの回答 1'!$E:$E,'フォームの回答 1'!$B:$B,">"&D1,'フォームの回答 1'!$H:$H,"支出",'フォームの回答 1'!$D:$D,$A6) -> 23773 | D6: =SUMIFS('フォームの回答 1'!$E:$E,'フォームの回答 1'!$B:$B,">="&D1,'フォームの回答 1'!$H:$H,"支出",'フォームの回答 1'!$D:$D,$A6)-SUMIFS('フォームの回答 1'!$E:$E,'フォームの回答 1'!$B:$B,">"&E1,'フォームの回答 1'!$H:$H,"支出",'フォームの回答 1'!$D:$D,$A6) -> 46682 | E6: =SUMIFS('フォームの回答 1'!$E:$E,'フォームの回答 1'!$B:$B,">="&E1,'フォームの回答 1'!$H:$H,"支出",'フォームの回答 1'!$D:$D,$A6)-SUMIFS('フォームの回答 1'!$E:$E,'フォームの回答 1'!$B:$B,">"&F1,'フォームの回答 1'!$H:$H,"支出",'フォームの回答 1'!$D:$D,$A6) -> 71320 | F6: =SUMIFS('フォームの回答 1'!$E:$E,'フォームの回答 1'!$B:$B,">="&F1,'フォームの回答 1'!$H:$H,"支出",'フォームの回答 1'!$D:$D,$A6)-SUMIFS('フォームの回答 1'!$E:$E,'フォームの回答 1'!$B:$B,">"&G1,'フォームの回答 1'!$H:$H,"支出",'フォームの回答 1'!$D:$D,$A6) -> 64549 | G6: =SUMIFS('フォームの回答 1'!$E:$E,'フォームの回答 1'!$B:$B,">="&G1,'フォームの回答 1'!$H:$H,"支出",'フォームの回答 1'!$D:$D,$A6)-SUMIFS('フォームの回答 1'!$E:$E,'フォームの回答 1'!$B:$B,">"&H1,'フォームの回答 1'!$H:$H,"支出",'フォームの回答 1'!$D:$D,$A6) -> 49143 | H6: =SUMIFS('フォームの回答 1'!$E:$E,'フォームの回答 1'!$B:$B,">="&H1,'フォームの回答 1'!$H:$H,"支出",'フォームの回答 1'!$D:$D,$A6)-SUMIFS('フォームの回答 1'!$E:$E,'フォームの回答 1'!$B:$B,">"&I1,'フォームの回答 1'!$H:$H,"支出",'フォームの回答 1'!$D:$D,$A6) -> 43693 | I6: =SUMIFS('フォームの回答 1'!$E:$E,'フォームの回答 1'!$B:$B,">="&I1,'フォームの回答 1'!$H:$H,"支出",'フォームの回答 1'!$D:$D,$A6)-SUMIFS('フォームの回答 1'!$E:$E,'フォームの回答 1'!$B:$B,">"&J1,'フォームの回答 1'!$H:$H,"支出",'フォームの回答 1'!$D:$D,$A6) -> 1053862
A7: 接待交際費 | B7: =SUM(C7:I7) -> 217936 | C7: =SUMIFS('フォームの回答 1'!$E:$E,'フォームの回答 1'!$B:$B,">="&C1,'フォームの回答 1'!$H:$H,"支出",'フォームの回答 1'!$D:$D,$A7)-SUMIFS('フォームの回答 1'!$E:$E,'フォームの回答 1'!$B:$B,">"&D1,'フォームの回答 1'!$H:$H,"支出",'フォームの回答 1'!$D:$D,$A7) -> 10146 | D7: =SUMIFS('フォームの回答 1'!$E:$E,'フォームの回答 1'!$B:$B,">="&D1,'フォームの回答 1'!$H:$H,"支出",'フォームの回答 1'!$D:$D,$A7)-SUMIFS('フォームの回答 1'!$E:$E,'フォームの回答 1'!$B:$B,">"&E1,'フォームの回答 1'!$H:$H,"支出",'フォームの回答 1'!$D:$D,$A7) -> 30222 | E7: =SUMIFS('フォームの回答 1'!$E:$E,'フォームの回答 1'!$B:$B,">="&E1,'フォームの回答 1'!$H:$H,"支出",'フォームの回答 1'!$D:$D,$A7)-SUMIFS('フォームの回答 1'!$E:$E,'フォームの回答 1'!$B:$B,">"&F1,'フォームの回答 1'!$H:$H,"支出",'フォームの回答 1'!$D:$D,$A7) -> 33080 | F7: =SUMIFS('フォームの回答 1'!$E:$E,'フォームの回答 1'!$B:$B,">="&F1,'フォームの回答 1'!$H:$H,"支出",'フォームの回答 1'!$D:$D,$A7)-SUMIFS('フォームの回答 1'!$E:$E,'フォームの回答 1'!$B:$B,">"&G1,'フォームの回答 1'!$H:$H,"支出",'フォームの回答 1'!$D:$D,$A7) -> 35573 | G7: =SUMIFS('フォームの回答 1'!$E:$E,'フォームの回答 1'!$B:$B,">="&G1,'フォームの回答 1'!$H:$H,"支出",'フォームの回答 1'!$D:$D,$A7)-SUMIFS('フォームの回答 1'!$E:$E,'フォームの回答 1'!$B:$B,">"&H1,'フォームの回答 1'!$H:$H,"支出",'フォームの回答 1'!$D:$D,$A7) -> 27715 | H7: =SUMIFS('フォームの回答 1'!$E:$E,'フォームの回答 1'!$B:$B,">="&H1,'フォームの回答 1'!$H:$H,"支出",'フォームの回答 1'!$D:$D,$A7)-SUMIFS('フォームの回答 1'!$E:$E,'フォームの回答 1'!$B:$B,">"&I1,'フォームの回答 1'!$H:$H,"支出",'フォームの回答 1'!$D:$D,$A7) -> 81200 | I7: =SUMIFS('フォームの回答 1'!J:J,'フォームの回答 1'!G:G,">="&I1,'フォームの回答 1'!M:M,"支出",'フォームの回答 1'!I:I,$A7)-SUMIFS('フォームの回答 1'!J:J,'フォームの回答 1'!G:G,">"&J1,'フォームの回答 1'!M:M,"支出",'フォームの回答 1'!I:I,$A7) -> 0
A8: 交通費 | B8: =SUM(C8:I8) -> 1418423 | C8: =SUMIFS('フォームの回答 1'!$E:$E,'フォームの回答 1'!$B:$B,">="&C1,'フォームの回答 1'!$H:$H,"支出",'フォームの回答 1'!$D:$D,$A8)-SUMIFS('フォームの回答 1'!$E:$E,'フォームの回答 1'!$B:$B,">"&D1,'フォームの回答 1'!$H:$H,"支出",'フォームの回答 1'!$D:$D,$A8) -> 10100 | D8: =SUMIFS('フォームの回答 1'!$E:$E,'フォームの回答 1'!$B:$B,">="&D1,'フォームの回答 1'!$H:$H,"支出",'フォームの回答 1'!$D:$D,$A8)-SUMIFS('フォームの回答 1'!$E:$E,'フォームの回答 1'!$B:$B,">"&E1,'フォームの回答 1'!$H:$H,"支出",'フォームの回答 1'!$D:$D,$A8) -> 14505 | E8: =SUMIFS('フォームの回答 1'!$E:$E,'フォームの回答 1'!$B:$B,">="&E1,'フォームの回答 1'!$H:$H,"支出",'フォームの回答 1'!$D:$D,$A8)-SUMIFS('フォームの回答 1'!$E:$E,'フォームの回答 1'!$B:$B,">"&F1,'フォームの回答 1'!$H:$H,"支出",'フォームの回答 1'!$D:$D,$A8) -> 32720 | F8: =SUMIFS('フォームの回答 1'!$E:$E,'フォームの回答 1'!$B:$B,">="&F1,'フォームの回答 1'!$H:$H,"支出",'フォームの回答 1'!$D:$D,$A8)-SUMIFS('フォームの回答 1'!$E:$E,'フォームの回答 1'!$B:$B,">"&G1,'フォームの回答 1'!$H:$H,"支出",'フォームの回答 1'!$D:$D,$A8) -> 86070 | G8: =SUMIFS('フォームの回答 1'!$E:$E,'フォームの回答 1'!$B:$B,">="&G1,'フォームの回答 1'!$H:$H,"支出",'フォームの回答 1'!$D:$D,$A8)-SUMIFS('フォームの回答 1'!$E:$E,'フォームの回答 1'!$B:$B,">"&H1,'フォームの回答 1'!$H:$H,"支出",'フォームの回答 1'!$D:$D,$A8) -> 21010 | H8: =SUMIFS('フォームの回答 1'!$E:$E,'フォームの回答 1'!$B:$B,">="&H1,'フォームの回答 1'!$H:$H,"支出",'フォームの回答 1'!$D:$D,$A8)-SUMIFS('フォームの回答 1'!$E:$E,'フォームの回答 1'!$B:$B,">"&I1,'フォームの回答 1'!$H:$H,"支出",'フォームの回答 1'!$D:$D,$A8) -> 52341 | I8: =SUMIFS('フォームの回答 1'!$E:$E,'フォームの回答 1'!$B:$B,">="&I1,'フォームの回答 1'!$H:$H,"支出",'フォームの回答 1'!$D:$D,$A8)-SUMIFS('フォームの回答 1'!$E:$E,'フォームの回答 1'!$B:$B,">"&J1,'フォームの回答 1'!$H:$H,"支出",'フォームの回答 1'!$D:$D,$A8) -> 1201677
A9: 光熱費 | B9: =SUM(C9:I9) -> 339045 | C9: =SUMIFS('フォームの回答 1'!$E:$E,'フォームの回答 1'!$B:$B,">="&C1,'フォームの回答 1'!$H:$H,"支出",'フォームの回答 1'!$D:$D,$A9)-SUMIFS('フォームの回答 1'!$E:$E,'フォームの回答 1'!$B:$B,">"&D1,'フォームの回答 1'!$H:$H,"支出",'フォームの回答 1'!$D:$D,$A9) -> 2704 | D9: =SUMIFS('フォームの回答 1'!$E:$E,'フォームの回答 1'!$B:$B,">="&D1,'フォームの回答 1'!$H:$H,"支出",'フォームの回答 1'!$D:$D,$A9)-SUMIFS('フォームの回答 1'!$E:$E,'フォームの回答 1'!$B:$B,">"&E1,'フォームの回答 1'!$H:$H,"支出",'フォームの回答 1'!$D:$D,$A9) -> 17837 | E9: =SUMIFS('フォームの回答 1'!$E:$E,'フォームの回答 1'!$B:$B,">="&E1,'フォームの回答 1'!$H:$H,"支出",'フォームの回答 1'!$D:$D,$A9)-SUMIFS('フォームの回答 1'!$E:$E,'フォームの回答 1'!$B:$B,">"&F1,'フォームの回答 1'!$H:$H,"支出",'フォームの回答 1'!$D:$D,$A9) -> 7807 | F9: =SUMIFS('フォームの回答 1'!$E:$E,'フォームの回答 1'!$B:$B,">="&F1,'フォームの回答 1'!$H:$H,"支出",'フォームの回答 1'!$D:$D,$A9)-SUMIFS('フォームの回答 1'!$E:$E,'フォームの回答 1'!$B:$B,">"&G1,'フォームの回答 1'!$H:$H,"支出",'フォームの回答 1'!$D:$D,$A9) -> 7526 | G9: =SUMIFS('フォームの回答 1'!$E:$E,'フォームの回答 1'!$B:$B,">="&G1,'フォームの回答 1'!$H:$H,"支出",'フォームの回答 1'!$D:$D,$A9)-SUMIFS('フォームの回答 1'!$E:$E,'フォームの回答 1'!$B:$B,">"&H1,'フォームの回答 1'!$H:$H,"支出",'フォームの回答 1'!$D:$D,$A9) -> 5318 | H9: =SUMIFS('フォームの回答 1'!$E:$E,'フォームの回答 1'!$B:$B,">="&H1,'フォームの回答 1'!$H:$H,"支出",'フォームの回答 1'!$D:$D,$A9)-SUMIFS('フォームの回答 1'!$E:$E,'フォームの回答 1'!$B:$B,">"&I1,'フォームの回答 1'!$H:$H,"支出",'フォームの回答 1'!$D:$D,$A9) -> 10390 | I9: =SUMIFS('フォームの回答 1'!$E:$E,'フォームの回答 1'!$B:$B,">="&I1,'フォームの回答 1'!$H:$H,"支出",'フォームの回答 1'!$D:$D,$A9)-SUMIFS('フォームの回答 1'!$E:$E,'フォームの回答 1'!$B:$B,">"&J1,'フォームの回答 1'!$H:$H,"支出",'フォームの回答 1'!$D:$D,$A9) -> 287463
A10: スマホ代 | B10: =SUM(C10:I10) -> 211638 | C10: =SUMIFS('フォームの回答 1'!$E:$E,'フォームの回答 1'!$B:$B,">="&C1,'フォームの回答 1'!$H:$H,"支出",'フォームの回答 1'!$D:$D,$A10)-SUMIFS('フォームの回答 1'!$E:$E,'フォームの回答 1'!$B:$B,">"&D1,'フォームの回答 1'!$H:$H,"支出",'フォームの回答 1'!$D:$D,$A10) -> 0 | D10: =SUMIFS('フォームの回答 1'!$E:$E,'フォームの回答 1'!$B:$B,">="&D1,'フォームの回答 1'!$H:$H,"支出",'フォームの回答 1'!$D:$D,$A10)-SUMIFS('フォームの回答 1'!$E:$E,'フォームの回答 1'!$B:$B,">"&E1,'フォームの回答 1'!$H:$H,"支出",'フォームの回答 1'!$D:$D,$A10) -> 14076 | E10: =SUMIFS('フォームの回答 1'!$E:$E,'フォームの回答 1'!$B:$B,">="&E1,'フォームの回答 1'!$H:$H,"支出",'フォームの回答 1'!$D:$D,$A10)-SUMIFS('フォームの回答 1'!$E:$E,'フォームの回答 1'!$B:$B,">"&F1,'フォームの回答 1'!$H:$H,"支出",'フォームの回答 1'!$D:$D,$A10) -> 11710 | F10: =SUMIFS('フォームの回答 1'!$E:$E,'フォームの回答 1'!$B:$B,">="&F1,'フォームの回答 1'!$H:$H,"支出",'フォームの回答 1'!$D:$D,$A10)-SUMIFS('フォームの回答 1'!$E:$E,'フォームの回答 1'!$B:$B,">"&G1,'フォームの回答 1'!$H:$H,"支出",'フォームの回答 1'!$D:$D,$A10) -> 9334 | G10: =SUMIFS('フォームの回答 1'!$E:$E,'フォームの回答 1'!$B:$B,">="&G1,'フォームの回答 1'!$H:$H,"支出",'フォームの回答 1'!$D:$D,$A10)-SUMIFS('フォームの回答 1'!$E:$E,'フォームの回答 1'!$B:$B,">"&H1,'フォームの回答 1'!$H:$H,"支出",'フォームの回答 1'!$D:$D,$A10) -> 6760 | H10: =SUMIFS('フォームの回答 1'!$E:$E,'フォームの回答 1'!$B:$B,">="&H1,'フォームの回答 1'!$H:$H,"支出",'フォームの回答 1'!$D:$D,$A10)-SUMIFS('フォームの回答 1'!$E:$E,'フォームの回答 1'!$B:$B,">"&I1,'フォームの回答 1'!$H:$H,"支出",'フォームの回答 1'!$D:$D,$A10) -> 8363 | I10: =SUMIFS('フォームの回答 1'!$E:$E,'フォームの回答 1'!$B:$B,">="&I1,'フォームの回答 1'!$H:$H,"支出",'フォームの回答 1'!$D:$D,$A10)-SUMIFS('フォームの回答 1'!$E:$E,'フォームの回答 1'!$B:$B,">"&J1,'フォームの回答 1'!$H:$H,"支出",'フォームの回答 1'!$D:$D,$A10) -> 161395
A11: 家賃 | B11: =SUM(C11:I11) -> 3236320 | C11: =SUMIFS('フォームの回答 1'!$E:$E,'フォームの回答 1'!$B:$B,">="&C1,'フォームの回答 1'!$H:$H,"支出",'フォームの回答 1'!$D:$D,$A11)-SUMIFS('フォームの回答 1'!$E:$E,'フォームの回答 1'!$B:$B,">"&D1,'フォームの回答 1'!$H:$H,"支出",'フォームの回答 1'!$D:$D,$A11) -> 35820 | D11: =SUMIFS('フォームの回答 1'!$E:$E,'フォームの回答 1'!$B:$B,">="&D1,'フォームの回答 1'!$H:$H,"支出",'フォームの回答 1'!$D:$D,$A11)-SUMIFS('フォームの回答 1'!$E:$E,'フォームの回答 1'!$B:$B,">"&E1,'フォームの回答 1'!$H:$H,"支出",'フォームの回答 1'!$D:$D,$A11) -> 93000 | E11: =SUMIFS('フォームの回答 1'!$E:$E,'フォームの回答 1'!$B:$B,">="&E1,'フォームの回答 1'!$H:$H,"支出",'フォームの回答 1'!$D:$D,$A11)-SUMIFS('フォームの回答 1'!$E:$E,'フォームの回答 1'!$B:$B,">"&F1,'フォームの回答 1'!$H:$H,"支出",'フォームの回答 1'!$D:$D,$A11) -> 93000 | F11: =SUMIFS('フォームの回答 1'!$E:$E,'フォームの回答 1'!$B:$B,">="&F1,'フォームの回答 1'!$H:$H,"支出",'フォームの回答 1'!$D:$D,$A11)-SUMIFS('フォームの回答 1'!$E:$E,'フォームの回答 1'!$B:$B,">"&G1,'フォームの回答 1'!$H:$H,"支出",'フォームの回答 1'!$D:$D,$A11) -> 93000 | G11: =SUMIFS('フォームの回答 1'!$E:$E,'フォームの回答 1'!$B:$B,">="&G1,'フォームの回答 1'!$H:$H,"支出",'フォームの回答 1'!$D:$D,$A11)-SUMIFS('フォームの回答 1'!$E:$E,'フォームの回答 1'!$B:$B,">"&H1,'フォームの回答 1'!$H:$H,"支出",'フォームの回答 1'!$D:$D,$A11) -> 93000 | H11: =SUMIFS('フォームの回答 1'!$E:$E,'フォームの回答 1'!$B:$B,">="&H1,'フォームの回答 1'!$H:$H,"支出",'フォームの回答 1'!$D:$D,$A11)-SUMIFS('フォームの回答 1'!$E:$E,'フォームの回答 1'!$B:$B,">"&I1,'フォームの回答 1'!$H:$H,"支出",'フォームの回答 1'!$D:$D,$A11) -> 93000 | I11: =SUMIFS('フォームの回答 1'!$E:$E,'フォームの回答 1'!$B:$B,">="&I1,'フォームの回答 1'!$H:$H,"支出",'フォームの回答 1'!$D:$D,$A11)-SUMIFS('フォームの回答 1'!$E:$E,'フォームの回答 1'!$B:$B,">"&J1,'フォームの回答 1'!$H:$H,"支出",'フォームの回答 1'!$D:$D,$A11) -> 2735500
A12: 医療費 | B12: =SUM(C12:I12) -> 65548 | C12: =SUMIFS('フォームの回答 1'!$E:$E,'フォームの回答 1'!$B:$B,">="&C1,'フォームの回答 1'!$H:$H,"支出",'フォームの回答 1'!$D:$D,$A12)-SUMIFS('フォームの回答 1'!$E:$E,'フォームの回答 1'!$B:$B,">"&D1,'フォームの回答 1'!$H:$H,"支出",'フォームの回答 1'!$D:$D,$A12) -> 1980 | D12: =SUMIFS('フォームの回答 1'!$E:$E,'フォームの回答 1'!$B:$B,">="&D1,'フォームの回答 1'!$H:$H,"支出",'フォームの回答 1'!$D:$D,$A12)-SUMIFS('フォームの回答 1'!$E:$E,'フォームの回答 1'!$B:$B,">"&E1,'フォームの回答 1'!$H:$H,"支出",'フォームの回答 1'!$D:$D,$A12) -> 9800 | E12: =SUMIFS('フォームの回答 1'!$E:$E,'フォームの回答 1'!$B:$B,">="&E1,'フォームの回答 1'!$H:$H,"支出",'フォームの回答 1'!$D:$D,$A12)-SUMIFS('フォームの回答 1'!$E:$E,'フォームの回答 1'!$B:$B,">"&F1,'フォームの回答 1'!$H:$H,"支出",'フォームの回答 1'!$D:$D,$A12) -> 3352 | F12: =SUMIFS('フォームの回答 1'!$E:$E,'フォームの回答 1'!$B:$B,">="&F1,'フォームの回答 1'!$H:$H,"支出",'フォームの回答 1'!$D:$D,$A12)-SUMIFS('フォームの回答 1'!$E:$E,'フォームの回答 1'!$B:$B,">"&G1,'フォームの回答 1'!$H:$H,"支出",'フォームの回答 1'!$D:$D,$A12) -> 23463 | G12: =SUMIFS('フォームの回答 1'!$E:$E,'フォームの回答 1'!$B:$B,">="&G1,'フォームの回答 1'!$H:$H,"支出",'フォームの回答 1'!$D:$D,$A12)-SUMIFS('フォームの回答 1'!$E:$E,'フォームの回答 1'!$B:$B,">"&H1,'フォームの回答 1'!$H:$H,"支出",'フォームの回答 1'!$D:$D,$A12) -> 1799 | H12: =SUMIFS('フォームの回答 1'!$E:$E,'フォームの回答 1'!$B:$B,">="&H1,'フォームの回答 1'!$H:$H,"支出",'フォームの回答 1'!$D:$D,$A12)-SUMIFS('フォームの回答 1'!$E:$E,'フォームの回答 1'!$B:$B,">"&I1,'フォームの回答 1'!$H:$H,"支出",'フォームの回答 1'!$D:$D,$A12) -> 1483 | I12: =SUMIFS('フォームの回答 1'!$E:$E,'フォームの回答 1'!$B:$B,">="&I1,'フォームの回答 1'!$H:$H,"支出",'フォームの回答 1'!$D:$D,$A12)-SUMIFS('フォームの回答 1'!$E:$E,'フォームの回答 1'!$B:$B,">"&J1,'フォームの回答 1'!$H:$H,"支出",'フォームの回答 1'!$D:$D,$A12) -> 23671
A13: 服 | B13: =SUM(C13:I13) -> 23110 | C13: =SUMIFS('フォームの回答 1'!$E:$E,'フォームの回答 1'!$B:$B,">="&C1,'フォームの回答 1'!$H:$H,"支出",'フォームの回答 1'!$D:$D,$A13)-SUMIFS('フォームの回答 1'!$E:$E,'フォームの回答 1'!$B:$B,">"&D1,'フォームの回答 1'!$H:$H,"支出",'フォームの回答 1'!$D:$D,$A13) -> 7570 | D13: =SUMIFS('フォームの回答 1'!$E:$E,'フォームの回答 1'!$B:$B,">="&D1,'フォームの回答 1'!$H:$H,"支出",'フォームの回答 1'!$D:$D,$A13)-SUMIFS('フォームの回答 1'!$E:$E,'フォームの回答 1'!$B:$B,">"&E1,'フォームの回答 1'!$H:$H,"支出",'フォームの回答 1'!$D:$D,$A13) -> 3570 | E13: =SUMIFS('フォームの回答 1'!$E:$E,'フォームの回答 1'!$B:$B,">="&E1,'フォームの回答 1'!$H:$H,"支出",'フォームの回答 1'!$D:$D,$A13)-SUMIFS('フォームの回答 1'!$E:$E,'フォームの回答 1'!$B:$B,">"&F1,'フォームの回答 1'!$H:$H,"支出",'フォームの回答 1'!$D:$D,$A13) -> 0 | F13: =SUMIFS('フォームの回答 1'!$E:$E,'フォームの回答 1'!$B:$B,">="&F1,'フォームの回答 1'!$H:$H,"支出",'フォームの回答 1'!$D:$D,$A13)-SUMIFS('フォームの回答 1'!$E:$E,'フォームの回答 1'!$B:$B,">"&G1,'フォームの回答 1'!$H:$H,"支出",'フォームの回答 1'!$D:$D,$A13) -> 1990 | G13: =SUMIFS('フォームの回答 1'!$E:$E,'フォームの回答 1'!$B:$B,">="&G1,'フォームの回答 1'!$H:$H,"支出",'フォームの回答 1'!$D:$D,$A13)-SUMIFS('フォームの回答 1'!$E:$E,'フォームの回答 1'!$B:$B,">"&H1,'フォームの回答 1'!$H:$H,"支出",'フォームの回答 1'!$D:$D,$A13) -> 9980 | H13: =SUMIFS('フォームの回答 1'!$E:$E,'フォームの回答 1'!$B:$B,">="&H1,'フォームの回答 1'!$H:$H,"支出",'フォームの回答 1'!$D:$D,$A13)-SUMIFS('フォームの回答 1'!$E:$E,'フォームの回答 1'!$B:$B,">"&I1,'フォームの回答 1'!$H:$H,"支出",'フォームの回答 1'!$D:$D,$A13) -> 0 | I13: =SUMIFS('フォームの回答 1'!$E:$E,'フォームの回答 1'!$B:$B,">="&I5,'フォームの回答 1'!$H:$H,"支出",'フォームの回答 1'!$D:$D,$A13)-SUMIFS('フォームの回答 1'!$E:$E,'フォームの回答 1'!$B:$B,">"&J5,'フォームの回答 1'!$H:$H,"支出",'フォームの回答 1'!$D:$D,$A13) -> 0
A14: 生活品 | B14: =SUM(C14:I14) -> 1162273 | C14: =SUMIFS('フォームの回答 1'!$E:$E,'フォームの回答 1'!$B:$B,">="&C1,'フォームの回答 1'!$H:$H,"支出",'フォームの回答 1'!$D:$D,$A14)-SUMIFS('フォームの回答 1'!$E:$E,'フォームの回答 1'!$B:$B,">"&D1,'フォームの回答 1'!$H:$H,"支出",'フォームの回答 1'!$D:$D,$A14) -> 41210 | D14: =SUMIFS('フォームの回答 1'!$E:$E,'フォームの回答 1'!$B:$B,">="&D1,'フォームの回答 1'!$H:$H,"支出",'フォームの回答 1'!$D:$D,$A14)-SUMIFS('フォームの回答 1'!$E:$E,'フォームの回答 1'!$B:$B,">"&E1,'フォームの回答 1'!$H:$H,"支出",'フォームの回答 1'!$D:$D,$A14) -> 23760 | E14: =SUMIFS('フォームの回答 1'!$E:$E,'フォームの回答 1'!$B:$B,">="&E1,'フォームの回答 1'!$H:$H,"支出",'フォームの回答 1'!$D:$D,$A14)-SUMIFS('フォームの回答 1'!$E:$E,'フォームの回答 1'!$B:$B,">"&F1,'フォームの回答 1'!$H:$H,"支出",'フォームの回答 1'!$D:$D,$A14) -> 27487 | F14: =SUMIFS('フォームの回答 1'!$E:$E,'フォームの回答 1'!$B:$B,">="&F1,'フォームの回答 1'!$H:$H,"支出",'フォームの回答 1'!$D:$D,$A14)-SUMIFS('フォームの回答 1'!$E:$E,'フォームの回答 1'!$B:$B,">"&G1,'フォームの回答 1'!$H:$H,"支出",'フォームの回答 1'!$D:$D,$A14) -> 15980 | G14: =SUMIFS('フォームの回答 1'!$E:$E,'フォームの回答 1'!$B:$B,">="&G1,'フォームの回答 1'!$H:$H,"支出",'フォームの回答 1'!$D:$D,$A14)-SUMIFS('フォームの回答 1'!$E:$E,'フォームの回答 1'!$B:$B,">"&H1,'フォームの回答 1'!$H:$H,"支出",'フォームの回答 1'!$D:$D,$A14) -> 30350 | H14: =SUMIFS('フォームの回答 1'!$E:$E,'フォームの回答 1'!$B:$B,">="&H1,'フォームの回答 1'!$H:$H,"支出",'フォームの回答 1'!$D:$D,$A14)-SUMIFS('フォームの回答 1'!$E:$E,'フォームの回答 1'!$B:$B,">"&I1,'フォームの回答 1'!$H:$H,"支出",'フォームの回答 1'!$D:$D,$A14) -> 51045 | I14: =SUMIFS('フォームの回答 1'!$E:$E,'フォームの回答 1'!$B:$B,">="&I1,'フォームの回答 1'!$H:$H,"支出",'フォームの回答 1'!$D:$D,$A14)-SUMIFS('フォームの回答 1'!$E:$E,'フォームの回答 1'!$B:$B,">"&J1,'フォームの回答 1'!$H:$H,"支出",'フォームの回答 1'!$D:$D,$A14) -> 972441
A15: 書籍代 | B15: =SUM(C15:I15) -> 247801 | C15: =SUMIFS('フォームの回答 1'!$E:$E,'フォームの回答 1'!$B:$B,">="&C1,'フォームの回答 1'!$H:$H,"支出",'フォームの回答 1'!$D:$D,$A15)-SUMIFS('フォームの回答 1'!$E:$E,'フォームの回答 1'!$B:$B,">"&D1,'フォームの回答 1'!$H:$H,"支出",'フォームの回答 1'!$D:$D,$A15) -> 0 | D15: =SUMIFS('フォームの回答 1'!$E:$E,'フォームの回答 1'!$B:$B,">="&D1,'フォームの回答 1'!$H:$H,"支出",'フォームの回答 1'!$D:$D,$A15)-SUMIFS('フォームの回答 1'!$E:$E,'フォームの回答 1'!$B:$B,">"&E1,'フォームの回答 1'!$H:$H,"支出",'フォームの回答 1'!$D:$D,$A15) -> 8426 | E15: =SUMIFS('フォームの回答 1'!$E:$E,'フォームの回答 1'!$B:$B,">="&E1,'フォームの回答 1'!$H:$H,"支出",'フォームの回答 1'!$D:$D,$A15)-SUMIFS('フォームの回答 1'!$E:$E,'フォームの回答 1'!$B:$B,">"&F1,'フォームの回答 1'!$H:$H,"支出",'フォームの回答 1'!$D:$D,$A15) -> 20215 | F15: =SUMIFS('フォームの回答 1'!$E:$E,'フォームの回答 1'!$B:$B,">="&F1,'フォームの回答 1'!$H:$H,"支出",'フォームの回答 1'!$D:$D,$A15)-SUMIFS('フォームの回答 1'!$E:$E,'フォームの回答 1'!$B:$B,">"&G1,'フォームの回答 1'!$H:$H,"支出",'フォームの回答 1'!$D:$D,$A15) -> 8155 | G15: =SUMIFS('フォームの回答 1'!$E:$E,'フォームの回答 1'!$B:$B,">="&G1,'フォームの回答 1'!$H:$H,"支出",'フォームの回答 1'!$D:$D,$A15)-SUMIFS('フォームの回答 1'!$E:$E,'フォームの回答 1'!$B:$B,">"&H1,'フォームの回答 1'!$H:$H,"支出",'フォームの回答 1'!$D:$D,$A15) -> 4620 | H15: =SUMIFS('フォームの回答 1'!$E:$E,'フォームの回答 1'!$B:$B,">="&H1,'フォームの回答 1'!$H:$H,"支出",'フォームの回答 1'!$D:$D,$A15)-SUMIFS('フォームの回答 1'!$E:$E,'フォームの回答 1'!$B:$B,">"&I1,'フォームの回答 1'!$H:$H,"支出",'フォームの回答 1'!$D:$D,$A15) -> 5663 | I15: =SUMIFS('フォームの回答 1'!$E:$E,'フォームの回答 1'!$B:$B,">="&I1,'フォームの回答 1'!$H:$H,"支出",'フォームの回答 1'!$D:$D,$A15)-SUMIFS('フォームの回答 1'!$E:$E,'フォームの回答 1'!$B:$B,">"&J1,'フォームの回答 1'!$H:$H,"支出",'フォームの回答 1'!$D:$D,$A15) -> 200722
A16: 奨学金・ローン返済 | B16: =SUM(C16:I16) -> 2513229 | C16: =SUMIFS('フォームの回答 1'!$E:$E,'フォームの回答 1'!$B:$B,">="&C1,'フォームの回答 1'!$H:$H,"支出",'フォームの回答 1'!$D:$D,$A16)-SUMIFS('フォームの回答 1'!$E:$E,'フォームの回答 1'!$B:$B,">"&D1,'フォームの回答 1'!$H:$H,"支出",'フォームの回答 1'!$D:$D,$A16) -> 45000 | D16: =SUMIFS('フォームの回答 1'!$E:$E,'フォームの回答 1'!$B:$B,">="&D1,'フォームの回答 1'!$H:$H,"支出",'フォームの回答 1'!$D:$D,$A16)-SUMIFS('フォームの回答 1'!$E:$E,'フォームの回答 1'!$B:$B,">"&E1,'フォームの回答 1'!$H:$H,"支出",'フォームの回答 1'!$D:$D,$A16) -> 31000 | E16: =SUMIFS('フォームの回答 1'!$E:$E,'フォームの回答 1'!$B:$B,">="&E1,'フォームの回答 1'!$H:$H,"支出",'フォームの回答 1'!$D:$D,$A16)-SUMIFS('フォームの回答 1'!$E:$E,'フォームの回答 1'!$B:$B,">"&F1,'フォームの回答 1'!$H:$H,"支出",'フォームの回答 1'!$D:$D,$A16) -> 115940 | F16: =SUMIFS('フォームの回答 1'!$E:$E,'フォームの回答 1'!$B:$B,">="&F1,'フォームの回答 1'!$H:$H,"支出",'フォームの回答 1'!$D:$D,$A16)-SUMIFS('フォームの回答 1'!$E:$E,'フォームの回答 1'!$B:$B,">"&G1,'フォームの回答 1'!$H:$H,"支出",'フォームの回答 1'!$D:$D,$A16) -> 63000 | G16: =SUMIFS('フォームの回答 1'!$E:$E,'フォームの回答 1'!$B:$B,">="&G1,'フォームの回答 1'!$H:$H,"支出",'フォームの回答 1'!$D:$D,$A16)-SUMIFS('フォームの回答 1'!$E:$E,'フォームの回答 1'!$B:$B,">"&H1,'フォームの回答 1'!$H:$H,"支出",'フォームの回答 1'!$D:$D,$A16) -> 63000 | H16: =SUMIFS('フォームの回答 1'!$E:$E,'フォームの回答 1'!$B:$B,">="&H1,'フォームの回答 1'!$H:$H,"支出",'フォームの回答 1'!$D:$D,$A16)-SUMIFS('フォームの回答 1'!$E:$E,'フォームの回答 1'!$B:$B,">"&I1,'フォームの回答 1'!$H:$H,"支出",'フォームの回答 1'!$D:$D,$A16) -> 63000 | I16: =SUMIFS('フォームの回答 1'!$E:$E,'フォームの回答 1'!$B:$B,">="&I1,'フォームの回答 1'!$H:$H,"支出",'フォームの回答 1'!$D:$D,$A16)-SUMIFS('フォームの回答 1'!$E:$E,'フォームの回答 1'!$B:$B,">"&J1,'フォームの回答 1'!$H:$H,"支出",'フォームの回答 1'!$D:$D,$A16) -> 2132289
A17: ツール | B17: =SUM(C17:I17) -> 163847 | C17: =SUMIFS('フォームの回答 1'!$E:$E,'フォームの回答 1'!$B:$B,">="&C1,'フォームの回答 1'!$H:$H,"支出",'フォームの回答 1'!$D:$D,$A17)-SUMIFS('フォームの回答 1'!$E:$E,'フォームの回答 1'!$B:$B,">"&D1,'フォームの回答 1'!$H:$H,"支出",'フォームの回答 1'!$D:$D,$A17) -> 0 | D17: =SUMIFS('フォームの回答 1'!$E:$E,'フォームの回答 1'!$B:$B,">="&D1,'フォームの回答 1'!$H:$H,"支出",'フォームの回答 1'!$D:$D,$A17)-SUMIFS('フォームの回答 1'!$E:$E,'フォームの回答 1'!$B:$B,">"&E1,'フォームの回答 1'!$H:$H,"支出",'フォームの回答 1'!$D:$D,$A17) -> 1480 | E17: =SUMIFS('フォームの回答 1'!$E:$E,'フォームの回答 1'!$B:$B,">="&E1,'フォームの回答 1'!$H:$H,"支出",'フォームの回答 1'!$D:$D,$A17)-SUMIFS('フォームの回答 1'!$E:$E,'フォームの回答 1'!$B:$B,">"&F1,'フォームの回答 1'!$H:$H,"支出",'フォームの回答 1'!$D:$D,$A17) -> 1480 | F17: =SUMIFS('フォームの回答 1'!$E:$E,'フォームの回答 1'!$B:$B,">="&F1,'フォームの回答 1'!$H:$H,"支出",'フォームの回答 1'!$D:$D,$A17)-SUMIFS('フォームの回答 1'!$E:$E,'フォームの回答 1'!$B:$B,">"&G1,'フォームの回答 1'!$H:$H,"支出",'フォームの回答 1'!$D:$D,$A17) -> 880 | G17: =SUMIFS('フォームの回答 1'!$E:$E,'フォームの回答 1'!$B:$B,">="&G1,'フォームの回答 1'!$H:$H,"支出",'フォームの回答 1'!$D:$D,$A17)-SUMIFS('フォームの回答 1'!$E:$E,'フォームの回答 1'!$B:$B,">"&H1,'フォームの回答 1'!$H:$H,"支出",'フォームの回答 1'!$D:$D,$A17) -> 880 | H17: =SUMIFS('フォームの回答 1'!$E:$E,'フォームの回答 1'!$B:$B,">="&H1,'フォームの回答 1'!$H:$H,"支出",'フォームの回答 1'!$D:$D,$A17)-SUMIFS('フォームの回答 1'!$E:$E,'フォームの回答 1'!$B:$B,">"&I1,'フォームの回答 1'!$H:$H,"支出",'フォームの回答 1'!$D:$D,$A17) -> 880 | I17: =SUMIFS('フォームの回答 1'!$E:$E,'フォームの回答 1'!$B:$B,">="&I1,'フォームの回答 1'!$H:$H,"支出",'フォームの回答 1'!$D:$D,$A17)-SUMIFS('フォームの回答 1'!$E:$E,'フォームの回答 1'!$B:$B,">"&J1,'フォームの回答 1'!$H:$H,"支出",'フォームの回答 1'!$D:$D,$A17) -> 158247
A18: 勉強費 | B18: =SUM(C18:I18) -> 254338 | C18: =SUMIFS('フォームの回答 1'!$E:$E,'フォームの回答 1'!$B:$B,">="&C1,'フォームの回答 1'!$H:$H,"支出",'フォームの回答 1'!$D:$D,$A18)-SUMIFS('フォームの回答 1'!$E:$E,'フォームの回答 1'!$B:$B,">"&D1,'フォームの回答 1'!$H:$H,"支出",'フォームの回答 1'!$D:$D,$A18) -> 6780 | D18: =SUMIFS('フォームの回答 1'!$E:$E,'フォームの回答 1'!$B:$B,">="&D1,'フォームの回答 1'!$H:$H,"支出",'フォームの回答 1'!$D:$D,$A18)-SUMIFS('フォームの回答 1'!$E:$E,'フォームの回答 1'!$B:$B,">"&E1,'フォームの回答 1'!$H:$H,"支出",'フォームの回答 1'!$D:$D,$A18) -> 7480 | E18: =SUMIFS('フォームの回答 1'!$E:$E,'フォームの回答 1'!$B:$B,">="&E1,'フォームの回答 1'!$H:$H,"支出",'フォームの回答 1'!$D:$D,$A18)-SUMIFS('フォームの回答 1'!$E:$E,'フォームの回答 1'!$B:$B,">"&F1,'フォームの回答 1'!$H:$H,"支出",'フォームの回答 1'!$D:$D,$A18) -> 7480 | F18: =SUMIFS('フォームの回答 1'!$E:$E,'フォームの回答 1'!$B:$B,">="&F1,'フォームの回答 1'!$H:$H,"支出",'フォームの回答 1'!$D:$D,$A18)-SUMIFS('フォームの回答 1'!$E:$E,'フォームの回答 1'!$B:$B,">"&G1,'フォームの回答 1'!$H:$H,"支出",'フォームの回答 1'!$D:$D,$A18) -> 7480 | G18: =SUMIFS('フォームの回答 1'!$E:$E,'フォームの回答 1'!$B:$B,">="&G1,'フォームの回答 1'!$H:$H,"支出",'フォームの回答 1'!$D:$D,$A18)-SUMIFS('フォームの回答 1'!$E:$E,'フォームの回答 1'!$B:$B,">"&H1,'フォームの回答 1'!$H:$H,"支出",'フォームの回答 1'!$D:$D,$A18) -> 7480 | H18: =SUMIFS('フォームの回答 1'!$E:$E,'フォームの回答 1'!$B:$B,">="&H1,'フォームの回答 1'!$H:$H,"支出",'フォームの回答 1'!$D:$D,$A18)-SUMIFS('フォームの回答 1'!$E:$E,'フォームの回答 1'!$B:$B,">"&I1,'フォームの回答 1'!$H:$H,"支出",'フォームの回答 1'!$D:$D,$A18) -> 7480 | I18: =SUMIFS('フォームの回答 1'!$E:$E,'フォームの回答 1'!$B:$B,">="&I1,'フォームの回答 1'!$H:$H,"支出",'フォームの回答 1'!$D:$D,$A18)-SUMIFS('フォームの回答 1'!$E:$E,'フォームの回答 1'!$B:$B,">"&J1,'フォームの回答 1'!$H:$H,"支出",'フォームの回答 1'!$D:$D,$A18) -> 210158
A19: クレジット引き落とし | C19: =SUMIFS('フォームの回答 1'!$E:$E,'フォームの回答 1'!$B:$B,">="&C1,'フォームの回答 1'!$H:$H,"支出",'フォームの回答 1'!$D:$D,$A19)-SUMIFS('フォームの回答 1'!$E:$E,'フォームの回答 1'!$B:$B,">"&D1,'フォームの回答 1'!$H:$H,"支出",'フォームの回答 1'!$D:$D,$A19) -> 156972

Sheet 【Monthly】2024年
B1: 合計金額 | C1: 45292 | D1: 45323 | E1: 45352 | F1: 45383 | G1: 45413 | H1: 45444 | I1: 45474 | J1: 45505 | K1: 45536 | L1: 45566 | M1: 45597 | N1: 45627 | O1: 平均
A2: 収入 | B2: =SUM(C2:H2) -> 2583909 | C2: =SUMIFS('フォームの回答 1'!$E:$E,'フォームの回答 1'!$B:$B,">="&C1,'フォームの回答 1'!$H:$H,"収入")-SUMIFS('フォームの回答 1'!$E:$E,'フォームの回答 1'!$B:$B,">"&D1,'フォームの回答 1'!$H:$H,"収入") -> 492780 | D2: =SUMIFS('フォームの回答 1'!$E:$E,'フォームの回答 1'!$B:$B,">="&D1,'フォームの回答 1'!$H:$H,"収入")-SUMIFS('フォームの回答 1'!$E:$E,'フォームの回答 1'!$B:$B,">"&E1,'フォームの回答 1'!$H:$H,"収入") -> 455893 | E2: =SUMIFS('フォームの回答 1'!$E:$E,'フォームの回答 1'!$B:$B,">="&E1,'フォームの回答 1'!$H:$H,"収入")-SUMIFS('フォームの回答 1'!$E:$E,'フォームの回答 1'!$B:$B,">"&F1,'フォームの回答 1'!$H:$H,"収入") -> 443820 | F2: =SUMIFS('フォームの回答 1'!$E:$E,'フォームの回答 1'!$B:$B,">="&F1,'フォームの回答 1'!$H:$H,"収入")-SUMIFS('フォームの回答 1'!$E:$E,'フォームの回答 1'!$B:$B,">"&G1,'フォームの回答 1'!$H:$H,"収入") -> 367168 | G2: =SUMIFS('フォームの回答 1'!$E:$E,'フォームの回答 1'!$B:$B,">="&G1,'フォームの回答 1'!$H:$H,"収入")-SUMIFS('フォームの回答 1'!$E:$E,'フォームの回答 1'!$B:$B,">"&H1,'フォームの回答 1'!$H:$H,"収入") -> 401043 | H2: =SUMIFS('フォームの回答 1'!$E:$E,'フォームの回答 1'!$B:$B,">="&H1,'フォームの回答 1'!$H:$H,"収入")-SUMIFS('フォームの回答 1'!$E:$E,'フォームの回答 1'!$B:$B,">"&I1,'フォームの回答 1'!$H:$H,"収入") -> 423205 | I2: =SUMIFS('フォームの回答 1'!$E:$E,'フォームの回答 1'!$B:$B,">="&I1,'フォームの回答 1'!$H:$H,"収入")-SUMIFS('フォームの回答 1'!$E:$E,'フォームの回答 1'!$B:$B,">"&J1,'フォームの回答 1'!$H:$H,"収入") -> 384500 | J2: =SUMIFS('フォームの回答 1'!$E:$E,'フォームの回答 1'!$B:$B,">="&J1,'フォームの回答 1'!$H:$H,"収入")-SUMIFS('フォームの回答 1'!$E:$E,'フォームの回答 1'!$B:$B,">"&K1,'フォームの回答 1'!$H:$H,"収入") -> 362802 | ... N2: =SUMIFS('フォームの回答 1'!$E:$E,'フォームの回答 1'!$B:$B,">="&N1,'フォームの回答 1'!$H:$H,"収入")-SUMIFS('フォームの回答 1'!$E:$E,'フォームの回答 1'!$B:$B,">"&O1,'フォームの回答 1'!$H:$H,"収入") -> 7428937
A3: 支出 | B3: =SUM(C3:H3) -> 2506457 | C3: =SUMIFS('フォームの回答 1'!$E:$E,'フォームの回答 1'!$B:$B,">="&C1,'フォームの回答 1'!$H:$H,"支出")-SUMIFS('フォームの回答 1'!$E:$E,'フォームの回答 1'!$B:$B,">"&D1,'フォームの回答 1'!$H:$H,"支出") -> 516953 | D3: =SUMIFS('フォームの回答 1'!$E:$E,'フォームの回答 1'!$B:$B,">="&D1,'フォームの回答 1'!$H:$H,"支出")-SUMIFS('フォームの回答 1'!$E:$E,'フォームの回答 1'!$B:$B,">"&E1,'フォームの回答 1'!$H:$H,"支出") -> 377067 | E3: =SUMIFS('フォームの回答 1'!$E:$E,'フォームの回答 1'!$B:$B,">="&E1,'フォームの回答 1'!$H:$H,"支出")-SUMIFS('フォームの回答 1'!$E:$E,'フォームの回答 1'!$B:$B,">"&F1,'フォームの回答 1'!$H:$H,"支出") -> 422067 | F3: =SUMIFS('フォームの回答 1'!$E:$E,'フォームの回答 1'!$B:$B,">="&F1,'フォームの回答 1'!$H:$H,"支出")-SUMIFS('フォームの回答 1'!$E:$E,'フォームの回答 1'!$B:$B,">"&G1,'フォームの回答 1'!$H:$H,"支出") -> 363280 | G3: =SUMIFS('フォームの回答 1'!$E:$E,'フォームの回答 1'!$B:$B,">="&G1,'フォームの回答 1'!$H:$H,"支出")-SUMIFS('フォームの回答 1'!$E:$E,'フォームの回答 1'!$B:$B,">"&H1,'フォームの回答 1'!$H:$H,"支出") -> 442981 | H3: =SUMIFS('フォームの回答 1'!$E:$E,'フォームの回答 1'!$B:$B,">="&H1,'フォームの回答 1'!$H:$H,"支出")-SUMIFS('フォームの回答 1'!$E:$E,'フォームの回答 1'!$B:$B,">"&I1,'フォームの回答 1'!$H:$H,"支出") -> 384109 | I3: =SUMIFS('フォームの回答 1'!$E:$E,'フォームの回答 1'!$B:$B,">="&I1,'フォームの回答 1'!$H:$H,"支出")-SUMIFS('フォームの回答 1'!$E:$E,'フォームの回答 1'!$B:$B,">"&J1,'フォームの回答 1'!$H:$H,"支出") -> 352913 | J3: =SUMIFS('フォームの回答 1'!$E:$E,'フォームの回答 1'!$B:$B,">="&J1,'フォームの回答 1'!$H:$H,"支出")-SUMIFS('フォームの回答 1'!$E:$E,'フォームの回答 1'!$B:$B,">"&K1,'フォームの回答 1'!$H:$H,"支出") -> 354855 | ... N3: =SUMIFS('フォームの回答 1'!$E:$E,'フォームの回答 1'!$B:$B,">="&N1,'フォームの回答 1'!$H:$H,"支出")-SUMIFS('フォームの回答 1'!$E:$E,'フォームの回答 1'!$B:$B,">"&O1,'フォームの回答 1'!$H:$H,"支出") -> 7556293
A4: 差額 | B4: =SUM(C4:H4) -> 77452 | C4: =C2-C3 -> -24173 | D4: =D2-D3 -> 78826 | E4: =E2-E3 -> 21753 | F4: =F2-F3 -> 3888 | G4: =G2-G3 -> -41938 | H4: =H2-H3 -> 39096 | I4: =I2-I3 -> 31587 | J4: =J2-J3 -> 7947 | ... N4: =N2-N3 -> -127356
B5: 内訳
A6: 食費 | B6: =SUM(C6:N6) -> 1065817 | C6: =SUMIFS('フォームの回答 1'!$E:$E,'フォームの回答 1'!$B:$B,">="&C1,'フォームの回答 1'!$H:$H,"支出",'フォームの回答 1'!$D:$D,$A6)-SUMIFS('フォームの回答 1'!$E:$E,'フォームの回答 1'!$B:$B,">"&D1,'フォームの回答 1'!$H:$H,"支出",'フォームの回答 1'!$D:$D,$A6) -> 34762 | D6: =SUMIFS('フォームの回答 1'!$E:$E,'フォームの回答 1'!$B:$B,">="&D1,'フォームの回答 1'!$H:$H,"支出",'フォームの回答 1'!$D:$D,$A6)-SUMIFS('フォームの回答 1'!$E:$E,'フォームの回答 1'!$B:$B,">"&E1,'フォームの回答 1'!$H:$H,"支出",'フォームの回答 1'!$D:$D,$A6) -> 41876 | E6: =SUMIFS('フォームの回答 1'!$E:$E,'フォームの回答 1'!$B:$B,">="&E1,'フォームの回答 1'!$H:$H,"支出",'フォームの回答 1'!$D:$D,$A6)-SUMIFS('フォームの回答 1'!$E:$E,'フォームの回答 1'!$B:$B,">"&F1,'フォームの回答 1'!$H:$H,"支出",'フォームの回答 1'!$D:$D,$A6) -> 40602 | F6: =SUMIFS('フォームの回答 1'!$E:$E,'フォームの回答 1'!$B:$B,">="&F1,'フォームの回答 1'!$H:$H,"支出",'フォームの回答 1'!$D:$D,$A6)-SUMIFS('フォームの回答 1'!$E:$E,'フォームの回答 1'!$B:$B,">"&G1,'フォームの回答 1'!$H:$H,"支出",'フォームの回答 1'!$D:$D,$A6) -> 35895 | G6: =SUMIFS('フォームの回答 1'!$E:$E,'フォームの回答 1'!$B:$B,">="&G1,'フォームの回答 1'!$H:$H,"支出",'フォームの回答 1'!$D:$D,$A6)-SUMIFS('フォームの回答 1'!$E:$E,'フォームの回答 1'!$B:$B,">"&H1,'フォームの回答 1'!$H:$H,"支出",'フォームの回答 1'!$D:$D,$A6) -> 42918 | H6: =SUMIFS('フォームの回答 1'!$E:$E,'フォームの回答 1'!$B:$B,">="&H1,'フォームの回答 1'!$H:$H,"支出",'フォームの回答 1'!$D:$D,$A6)-SUMIFS('フォームの回答 1'!$E:$E,'フォームの回答 1'!$B:$B,">"&I1,'フォームの回答 1'!$H:$H,"支出",'フォームの回答 1'!$D:$D,$A6) -> 33681 | I6: =SUMIFS('フォームの回答 1'!$E:$E,'フォームの回答 1'!$B:$B,">="&I1,'フォームの回答 1'!$H:$H,"支出",'フォームの回答 1'!$D:$D,$A6)-SUMIFS('フォームの回答 1'!$E:$E,'フォームの回答 1'!$B:$B,">"&J1,'フォームの回答 1'!$H:$H,"支出",'フォームの回答 1'!$D:$D,$A6) -> 31926 | J6: =SUMIFS('フォームの回答 1'!$E:$E,'フォームの回答 1'!$B:$B,">="&J1,'フォームの回答 1'!$H:$H,"支出",'フォームの回答 1'!$D:$D,$A6)-SUMIFS('フォームの回答 1'!$E:$E,'フォームの回答 1'!$B:$B,">"&K1,'フォームの回答 1'!$H:$H,"支出",'フォームの回答 1'!$D:$D,$A6) -> 31370 | ... N6: =SUMIFS('フォームの回答 1'!$E:$E,'フォームの回答 1'!$B:$B,">="&N1,'フォームの回答 1'!$H:$H,"支出",'フォームの回答 1'!$D:$D,$A6)-SUMIFS('フォームの回答 1'!$E:$E,'フォームの回答 1'!$B:$B,">"&O1,'フォームの回答 1'!$H:$H,"支出",'フォームの回答 1'!$D:$D,$A6) -> 656871 | O6: =B6/12 -> 88818.083 | Q6: =O6+O10+O14+O18+O17+O15 -> 235202.92
A7: 接待交際費 | B7: =SUM(C7:N7) -> 1927983 | C7: =SUMIFS('フォームの回答 1'!$E:$E,'フォームの回答 1'!$B:$B,">="&C1,'フォームの回答 1'!$H:$H,"支出",'フォームの回答 1'!$D:$D,$A7)-SUMIFS('フォームの回答 1'!$E:$E,'フォームの回答 1'!$B:$B,">"&D1,'フォームの回答 1'!$H:$H,"支出",'フォームの回答 1'!$D:$D,$A7) -> 118008 | D7: =SUMIFS('フォームの回答 1'!$E:$E,'フォームの回答 1'!$B:$B,">="&D1,'フォームの回答 1'!$H:$H,"支出",'フォームの回答 1'!$D:$D,$A7)-SUMIFS('フォームの回答 1'!$E:$E,'フォームの回答 1'!$B:$B,">"&E1,'フォームの回答 1'!$H:$H,"支出",'フォームの回答 1'!$D:$D,$A7) -> 39655 | E7: =SUMIFS('フォームの回答 1'!$E:$E,'フォームの回答 1'!$B:$B,">="&E1,'フォームの回答 1'!$H:$H,"支出",'フォームの回答 1'!$D:$D,$A7)-SUMIFS('フォームの回答 1'!$E:$E,'フォームの回答 1'!$B:$B,">"&F1,'フォームの回答 1'!$H:$H,"支出",'フォームの回答 1'!$D:$D,$A7) -> 92774 | F7: =SUMIFS('フォームの回答 1'!$E:$E,'フォームの回答 1'!$B:$B,">="&F1,'フォームの回答 1'!$H:$H,"支出",'フォームの回答 1'!$D:$D,$A7)-SUMIFS('フォームの回答 1'!$E:$E,'フォームの回答 1'!$B:$B,">"&G1,'フォームの回答 1'!$H:$H,"支出",'フォームの回答 1'!$D:$D,$A7) -> 66942 | G7: =SUMIFS('フォームの回答 1'!$E:$E,'フォームの回答 1'!$B:$B,">="&G1,'フォームの回答 1'!$H:$H,"支出",'フォームの回答 1'!$D:$D,$A7)-SUMIFS('フォームの回答 1'!$E:$E,'フォームの回答 1'!$B:$B,">"&H1,'フォームの回答 1'!$H:$H,"支出",'フォームの回答 1'!$D:$D,$A7) -> 59566 | H7: =SUMIFS('フォームの回答 1'!$E:$E,'フォームの回答 1'!$B:$B,">="&H1,'フォームの回答 1'!$H:$H,"支出",'フォームの回答 1'!$D:$D,$A7)-SUMIFS('フォームの回答 1'!$E:$E,'フォームの回答 1'!$B:$B,">"&I1,'フォームの回答 1'!$H:$H,"支出",'フォームの回答 1'!$D:$D,$A7) -> 73222 | I7: =SUMIFS('フォームの回答 1'!$E:$E,'フォームの回答 1'!$B:$B,">="&I1,'フォームの回答 1'!$H:$H,"支出",'フォームの回答 1'!$D:$D,$A7)-SUMIFS('フォームの回答 1'!$E:$E,'フォームの回答 1'!$B:$B,">"&J1,'フォームの回答 1'!$H:$H,"支出",'フォームの回答 1'!$D:$D,$A7) -> 56489 | J7: =SUMIFS('フォームの回答 1'!$E:$E,'フォームの回答 1'!$B:$B,">="&J1,'フォームの回答 1'!$H:$H,"支出",'フォームの回答 1'!$D:$D,$A7)-SUMIFS('フォームの回答 1'!$E:$E,'フォームの回答 1'!$B:$B,">"&K1,'フォームの回答 1'!$H:$H,"支出",'フォームの回答 1'!$D:$D,$A7) -> 46220 | ... N7: =SUMIFS('フォームの回答 1'!$E:$E,'フォームの回答 1'!$B:$B,">="&N1,'フォームの回答 1'!$H:$H,"支出",'フォームの回答 1'!$D:$D,$A7)-SUMIFS('フォームの回答 1'!$E:$E,'フォームの回答 1'!$B:$B,">"&O1,'フォームの回答 1'!$H:$H,"支出",'フォームの回答 1'!$D:$D,$A7) -> 1197655 | O7: =B7/12 -> 160665.25
A8: 交通費 | B8: =SUM(C8:N8) -> 1220607 | C8: =SUMIFS('フォームの回答 1'!$E:$E,'フォームの回答 1'!$B:$B,">="&C1,'フォームの回答 1'!$H:$H,"支出",'フォームの回答 1'!$D:$D,$A8)-SUMIFS('フォームの回答 1'!$E:$E,'フォームの回答 1'!$B:$B,">"&D1,'フォームの回答 1'!$H:$H,"支出",'フォームの回答 1'!$D:$D,$A8) -> 27960 | D8: =SUMIFS('フォームの回答 1'!$E:$E,'フォームの回答 1'!$B:$B,">="&D1,'フォームの回答 1'!$H:$H,"支出",'フォームの回答 1'!$D:$D,$A8)-SUMIFS('フォームの回答 1'!$E:$E,'フォームの回答 1'!$B:$B,">"&E1,'フォームの回答 1'!$H:$H,"支出",'フォームの回答 1'!$D:$D,$A8) -> 67770 | E8: =SUMIFS('フォームの回答 1'!$E:$E,'フォームの回答 1'!$B:$B,">="&E1,'フォームの回答 1'!$H:$H,"支出",'フォームの回答 1'!$D:$D,$A8)-SUMIFS('フォームの回答 1'!$E:$E,'フォームの回答 1'!$B:$B,">"&F1,'フォームの回答 1'!$H:$H,"支出",'フォームの回答 1'!$D:$D,$A8) -> 19010 | F8: =SUMIFS('フォームの回答 1'!$E:$E,'フォームの回答 1'!$B:$B,">="&F1,'フォームの回答 1'!$H:$H,"支出",'フォームの回答 1'!$D:$D,$A8)-SUMIFS('フォームの回答 1'!$E:$E,'フォームの回答 1'!$B:$B,">"&G1,'フォームの回答 1'!$H:$H,"支出",'フォームの回答 1'!$D:$D,$A8) -> 7600 | G8: =SUMIFS('フォームの回答 1'!$E:$E,'フォームの回答 1'!$B:$B,">="&G1,'フォームの回答 1'!$H:$H,"支出",'フォームの回答 1'!$D:$D,$A8)-SUMIFS('フォームの回答 1'!$E:$E,'フォームの回答 1'!$B:$B,">"&H1,'フォームの回答 1'!$H:$H,"支出",'フォームの回答 1'!$D:$D,$A8) -> 52480 | H8: =SUMIFS('フォームの回答 1'!$E:$E,'フォームの回答 1'!$B:$B,">="&H1,'フォームの回答 1'!$H:$H,"支出",'フォームの回答 1'!$D:$D,$A8)-SUMIFS('フォームの回答 1'!$E:$E,'フォームの回答 1'!$B:$B,">"&I1,'フォームの回答 1'!$H:$H,"支出",'フォームの回答 1'!$D:$D,$A8) -> 33140 | I8: =SUMIFS('フォームの回答 1'!$E:$E,'フォームの回答 1'!$B:$B,">="&I1,'フォームの回答 1'!$H:$H,"支出",'フォームの回答 1'!$D:$D,$A8)-SUMIFS('フォームの回答 1'!$E:$E,'フォームの回答 1'!$B:$B,">"&J1,'フォームの回答 1'!$H:$H,"支出",'フォームの回答 1'!$D:$D,$A8) -> 20500 | J8: =SUMIFS('フォームの回答 1'!$E:$E,'フォームの回答 1'!$B:$B,">="&J1,'フォームの回答 1'!$H:$H,"支出",'フォームの回答 1'!$D:$D,$A8)-SUMIFS('フォームの回答 1'!$E:$E,'フォームの回答 1'!$B:$B,">"&K1,'フォームの回答 1'!$H:$H,"支出",'フォームの回答 1'!$D:$D,$A8) -> 45680 | ... N8: =SUMIFS('フォームの回答 1'!$E:$E,'フォームの回答 1'!$B:$B,">="&N1,'フォームの回答 1'!$H:$H,"支出",'フォームの回答 1'!$D:$D,$A8)-SUMIFS('フォームの回答 1'!$E:$E,'フォームの回答 1'!$B:$B,">"&O1,'フォームの回答 1'!$H:$H,"支出",'フォームの回答 1'!$D:$D,$A8) -> 811163 | O8: =B8/12 -> 101717.25
A9: 光熱費 | B9: =SUM(C9:N9) -> 287463 | C9: =SUMIFS('フォームの回答 1'!$E:$E,'フォームの回答 1'!$B:$B,">="&C1,'フォームの回答 1'!$H:$H,"支出",'フォームの回答 1'!$D:$D,$A9)-SUMIFS('フォームの回答 1'!$E:$E,'フォームの回答 1'!$B:$B,">"&D1,'フォームの回答 1'!$H:$H,"支出",'フォームの回答 1'!$D:$D,$A9) -> 10991 | D9: =SUMIFS('フォームの回答 1'!$E:$E,'フォームの回答 1'!$B:$B,">="&D1,'フォームの回答 1'!$H:$H,"支出",'フォームの回答 1'!$D:$D,$A9)-SUMIFS('フォームの回答 1'!$E:$E,'フォームの回答 1'!$B:$B,">"&E1,'フォームの回答 1'!$H:$H,"支出",'フォームの回答 1'!$D:$D,$A9) -> 8466 | E9: =SUMIFS('フォームの回答 1'!$E:$E,'フォームの回答 1'!$B:$B,">="&E1,'フォームの回答 1'!$H:$H,"支出",'フォームの回答 1'!$D:$D,$A9)-SUMIFS('フォームの回答 1'!$E:$E,'フォームの回答 1'!$B:$B,">"&F1,'フォームの回答 1'!$H:$H,"支出",'フォームの回答 1'!$D:$D,$A9) -> 5318 | F9: =SUMIFS('フォームの回答 1'!$E:$E,'フォームの回答 1'!$B:$B,">="&F1,'フォームの回答 1'!$H:$H,"支出",'フォームの回答 1'!$D:$D,$A9)-SUMIFS('フォームの回答 1'!$E:$E,'フォームの回答 1'!$B:$B,">"&G1,'フォームの回答 1'!$H:$H,"支出",'フォームの回答 1'!$D:$D,$A9) -> 8490 | G9: =SUMIFS('フォームの回答 1'!$E:$E,'フォームの回答 1'!$B:$B,">="&G1,'フォームの回答 1'!$H:$H,"支出",'フォームの回答 1'!$D:$D,$A9)-SUMIFS('フォームの回答 1'!$E:$E,'フォームの回答 1'!$B:$B,">"&H1,'フォームの回答 1'!$H:$H,"支出",'フォームの回答 1'!$D:$D,$A9) -> 5318 | H9: =SUMIFS('フォームの回答 1'!$E:$E,'フォームの回答 1'!$B:$B,">="&H1,'フォームの回答 1'!$H:$H,"支出",'フォームの回答 1'!$D:$D,$A9)-SUMIFS('フォームの回答 1'!$E:$E,'フォームの回答 1'!$B:$B,">"&I1,'フォームの回答 1'!$H:$H,"支出",'フォームの回答 1'!$D:$D,$A9) -> 8514 | I9: =SUMIFS('フォームの回答 1'!$E:$E,'フォームの回答 1'!$B:$B,">="&I1,'フォームの回答 1'!$H:$H,"支出",'フォームの回答 1'!$D:$D,$A9)-SUMIFS('フォームの回答 1'!$E:$E,'フォームの回答 1'!$B:$B,">"&J1,'フォームの回答 1'!$H:$H,"支出",'フォームの回答 1'!$D:$D,$A9) -> 5318 | J9: =SUMIFS('フォームの回答 1'!$E:$E,'フォームの回答 1'!$B:$B,">="&J1,'フォームの回答 1'!$H:$H,"支出",'フォームの回答 1'!$D:$D,$A9)-SUMIFS('フォームの回答 1'!$E:$E,'フォームの回答 1'!$B:$B,">"&K1,'フォームの回答 1'!$H:$H,"支出",'フォームの回答 1'!$D:$D,$A9) -> 8490 | ... N9: =SUMIFS('フォームの回答 1'!$E:$E,'フォームの回答 1'!$B:$B,">="&N1,'フォームの回答 1'!$H:$H,"支出",'フォームの回答 1'!$D:$D,$A9)-SUMIFS('フォームの回答 1'!$E:$E,'フォームの回答 1'!$B:$B,">"&O1,'フォームの回答 1'!$H:$H,"支出",'フォームの回答 1'!$D:$D,$A9) -> 206235 | O9: =B9/12 -> 23955.25
A10: スマホ代 | B10: =SUM(C10:N10) -> 164365 | C10: =SUMIFS('フォームの回答 1'!$E:$E,'フォームの回答 1'!$B:$B,">="&C1,'フォームの回答 1'!$H:$H,"支出",'フォームの回答 1'!$D:$D,$A10)-SUMIFS('フォームの回答 1'!$E:$E,'フォームの回答 1'!$B:$B,">"&D1,'フォームの回答 1'!$H:$H,"支出",'フォームの回答 1'!$D:$D,$A10) -> 5492 | D10: =SUMIFS('フォームの回答 1'!$E:$E,'フォームの回答 1'!$B:$B,">="&D1,'フォームの回答 1'!$H:$H,"支出",'フォームの回答 1'!$D:$D,$A10)-SUMIFS('フォームの回答 1'!$E:$E,'フォームの回答 1'!$B:$B,">"&E1,'フォームの回答 1'!$H:$H,"支出",'フォームの回答 1'!$D:$D,$A10) -> 4810 | E10: =SUMIFS('フォームの回答 1'!$E:$E,'フォームの回答 1'!$B:$B,">="&E1,'フォームの回答 1'!$H:$H,"支出",'フォームの回答 1'!$D:$D,$A10)-SUMIFS('フォームの回答 1'!$E:$E,'フォームの回答 1'!$B:$B,">"&F1,'フォームの回答 1'!$H:$H,"支出",'フォームの回答 1'!$D:$D,$A10) -> 5780 | F10: =SUMIFS('フォームの回答 1'!$E:$E,'フォームの回答 1'!$B:$B,">="&F1,'フォームの回答 1'!$H:$H,"支出",'フォームの回答 1'!$D:$D,$A10)-SUMIFS('フォームの回答 1'!$E:$E,'フォームの回答 1'!$B:$B,">"&G1,'フォームの回答 1'!$H:$H,"支出",'フォームの回答 1'!$D:$D,$A10) -> 3652 | G10: =SUMIFS('フォームの回答 1'!$E:$E,'フォームの回答 1'!$B:$B,">="&G1,'フォームの回答 1'!$H:$H,"支出",'フォームの回答 1'!$D:$D,$A10)-SUMIFS('フォームの回答 1'!$E:$E,'フォームの回答 1'!$B:$B,">"&H1,'フォームの回答 1'!$H:$H,"支出",'フォームの回答 1'!$D:$D,$A10) -> 4070 | H10: =SUMIFS('フォームの回答 1'!$E:$E,'フォームの回答 1'!$B:$B,">="&H1,'フォームの回答 1'!$H:$H,"支出",'フォームの回答 1'!$D:$D,$A10)-SUMIFS('フォームの回答 1'!$E:$E,'フォームの回答 1'!$B:$B,">"&I1,'フォームの回答 1'!$H:$H,"支出",'フォームの回答 1'!$D:$D,$A10) -> 3388 | I10: =SUMIFS('フォームの回答 1'!$E:$E,'フォームの回答 1'!$B:$B,">="&I1,'フォームの回答 1'!$H:$H,"支出",'フォームの回答 1'!$D:$D,$A10)-SUMIFS('フォームの回答 1'!$E:$E,'フォームの回答 1'!$B:$B,">"&J1,'フォームの回答 1'!$H:$H,"支出",'フォームの回答 1'!$D:$D,$A10) -> 5522 | J10: =SUMIFS('フォームの回答 1'!$E:$E,'フォームの回答 1'!$B:$B,">="&J1,'フォームの回答 1'!$H:$H,"支出",'フォームの回答 1'!$D:$D,$A10)-SUMIFS('フォームの回答 1'!$E:$E,'フォームの回答 1'!$B:$B,">"&K1,'フォームの回答 1'!$H:$H,"支出",'フォームの回答 1'!$D:$D,$A10) -> 3388 | ... N10: =SUMIFS('フォームの回答 1'!$E:$E,'フォームの回答 1'!$B:$B,">="&N1,'フォームの回答 1'!$H:$H,"支出",'フォームの回答 1'!$D:$D,$A10)-SUMIFS('フォームの回答 1'!$E:$E,'フォームの回答 1'!$B:$B,">"&O1,'フォームの回答 1'!$H:$H,"支出",'フォームの回答 1'!$D:$D,$A10) -> 113485 | O10: =B10/12 -> 13697.083
A11: 家賃 | B11: =SUM(C11:N11) -> 2735500 | C11: =SUMIFS('フォームの回答 1'!$E:$E,'フォームの回答 1'!$B:$B,">="&C1,'フォームの回答 1'!$H:$H,"支出",'フォームの回答 1'!$D:$D,$A11)-SUMIFS('フォームの回答 1'!$E:$E,'フォームの回答 1'!$B:$B,">"&D1,'フォームの回答 1'!$H:$H,"支出",'フォームの回答 1'!$D:$D,$A11) -> 93000 | D11: =SUMIFS('フォームの回答 1'!$E:$E,'フォームの回答 1'!$B:$B,">="&D1,'フォームの回答 1'!$H:$H,"支出",'フォームの回答 1'!$D:$D,$A11)-SUMIFS('フォームの回答 1'!$E:$E,'フォームの回答 1'!$B:$B,">"&E1,'フォームの回答 1'!$H:$H,"支出",'フォームの回答 1'!$D:$D,$A11) -> 93000 | E11: =SUMIFS('フォームの回答 1'!$E:$E,'フォームの回答 1'!$B:$B,">="&E1,'フォームの回答 1'!$H:$H,"支出",'フォームの回答 1'!$D:$D,$A11)-SUMIFS('フォームの回答 1'!$E:$E,'フォームの回答 1'!$B:$B,">"&F1,'フォームの回答 1'!$H:$H,"支出",'フォームの回答 1'!$D:$D,$A11) -> 93000 | F11: =SUMIFS('フォームの回答 1'!$E:$E,'フォームの回答 1'!$B:$B,">="&F1,'フォームの回答 1'!$H:$H,"支出",'フォームの回答 1'!$D:$D,$A11)-SUMIFS('フォームの回答 1'!$E:$E,'フォームの回答 1'!$B:$B,">"&G1,'フォームの回答 1'!$H:$H,"支出",'フォームの回答 1'!$D:$D,$A11) -> 93000 | G11: =SUMIFS('フォームの回答 1'!$E:$E,'フォームの回答 1'!$B:$B,">="&G1,'フォームの回答 1'!$H:$H,"支出",'フォームの回答 1'!$D:$D,$A11)-SUMIFS('フォームの回答 1'!$E:$E,'フォームの回答 1'!$B:$B,">"&H1,'フォームの回答 1'!$H:$H,"支出",'フォームの回答 1'!$D:$D,$A11) -> 93000 | H11: =SUMIFS('フォームの回答 1'!$E:$E,'フォームの回答 1'!$B:$B,">="&H1,'フォームの回答 1'!$H:$H,"支出",'フォームの回答 1'!$D:$D,$A11)-SUMIFS('フォームの回答 1'!$E:$E,'フォームの回答 1'!$B:$B,">"&I1,'フォームの回答 1'!$H:$H,"支出",'フォームの回答 1'!$D:$D,$A11) -> 98000 | I11: =SUMIFS('フォームの回答 1'!$E:$E,'フォームの回答 1'!$B:$B,">="&I1,'フォームの回答 1'!$H:$H,"支出",'フォームの回答 1'!$D:$D,$A11)-SUMIFS('フォームの回答 1'!$E:$E,'フォームの回答 1'!$B:$B,">"&J1,'フォームの回答 1'!$H:$H,"支出",'フォームの回答 1'!$D:$D,$A11) -> 93000 | J11: =SUMIFS('フォームの回答 1'!$E:$E,'フォームの回答 1'!$B:$B,">="&J1,'フォームの回答 1'!$H:$H,"支出",'フォームの回答 1'!$D:$D,$A11)-SUMIFS('フォームの回答 1'!$E:$E,'フォームの回答 1'!$B:$B,">"&K1,'フォームの回答 1'!$H:$H,"支出",'フォームの回答 1'!$D:$D,$A11) -> 93000 | ... N11: =SUMIFS('フォームの回答 1'!$E:$E,'フォームの回答 1'!$B:$B,">="&N1,'フォームの回答 1'!$H:$H,"支出",'フォームの回答 1'!$D:$D,$A11)-SUMIFS('フォームの回答 1'!$E:$E,'フォームの回答 1'!$B:$B,">"&O1,'フォームの回答 1'!$H:$H,"支出",'フォームの回答 1'!$D:$D,$A11) -> 1707500 | O11: =B11/12 -> 227958.33
A12: 医療費 | B12: =SUM(C12:N12) -> 23671 | C12: =SUMIFS('フォームの回答 1'!$E:$E,'フォームの回答 1'!$B:$B,">="&C1,'フォームの回答 1'!$H:$H,"支出",'フォームの回答 1'!$D:$D,$A12)-SUMIFS('フォームの回答 1'!$E:$E,'フォームの回答 1'!$B:$B,">"&D1,'フォームの回答 1'!$H:$H,"支出",'フォームの回答 1'!$D:$D,$A12) -> 2136 | D12: =SUMIFS('フォームの回答 1'!$E:$E,'フォームの回答 1'!$B:$B,">="&D1,'フォームの回答 1'!$H:$H,"支出",'フォームの回答 1'!$D:$D,$A12)-SUMIFS('フォームの回答 1'!$E:$E,'フォームの回答 1'!$B:$B,">"&E1,'フォームの回答 1'!$H:$H,"支出",'フォームの回答 1'!$D:$D,$A12) -> 1405 | E12: =SUMIFS('フォームの回答 1'!$E:$E,'フォームの回答 1'!$B:$B,">="&E1,'フォームの回答 1'!$H:$H,"支出",'フォームの回答 1'!$D:$D,$A12)-SUMIFS('フォームの回答 1'!$E:$E,'フォームの回答 1'!$B:$B,">"&F1,'フォームの回答 1'!$H:$H,"支出",'フォームの回答 1'!$D:$D,$A12) -> 1889 | F12: =SUMIFS('フォームの回答 1'!$E:$E,'フォームの回答 1'!$B:$B,">="&F1,'フォームの回答 1'!$H:$H,"支出",'フォームの回答 1'!$D:$D,$A12)-SUMIFS('フォームの回答 1'!$E:$E,'フォームの回答 1'!$B:$B,">"&G1,'フォームの回答 1'!$H:$H,"支出",'フォームの回答 1'!$D:$D,$A12) -> 654 | G12: =SUMIFS('フォームの回答 1'!$E:$E,'フォームの回答 1'!$B:$B,">="&G1,'フォームの回答 1'!$H:$H,"支出",'フォームの回答 1'!$D:$D,$A12)-SUMIFS('フォームの回答 1'!$E:$E,'フォームの回答 1'!$B:$B,">"&H1,'フォームの回答 1'!$H:$H,"支出",'フォームの回答 1'!$D:$D,$A12) -> 632 | H12: =SUMIFS('フォームの回答 1'!$E:$E,'フォームの回答 1'!$B:$B,">="&H1,'フォームの回答 1'!$H:$H,"支出",'フォームの回答 1'!$D:$D,$A12)-SUMIFS('フォームの回答 1'!$E:$E,'フォームの回答 1'!$B:$B,">"&I1,'フォームの回答 1'!$H:$H,"支出",'フォームの回答 1'!$D:$D,$A12) -> 328 | I12: =SUMIFS('フォームの回答 1'!$E:$E,'フォームの回答 1'!$B:$B,">="&I1,'フォームの回答 1'!$H:$H,"支出",'フォームの回答 1'!$D:$D,$A12)-SUMIFS('フォームの回答 1'!$E:$E,'フォームの回答 1'!$B:$B,">"&J1,'フォームの回答 1'!$H:$H,"支出",'フォームの回答 1'!$D:$D,$A12) -> 0 | J12: =SUMIFS('フォームの回答 1'!$E:$E,'フォームの回答 1'!$B:$B,">="&J1,'フォームの回答 1'!$H:$H,"支出",'フォームの回答 1'!$D:$D,$A12)-SUMIFS('フォームの回答 1'!$E:$E,'フォームの回答 1'!$B:$B,">"&K1,'フォームの回答 1'!$H:$H,"支出",'フォームの回答 1'!$D:$D,$A12) -> 0 | ... N12: =SUMIFS('フォームの回答 1'!$E:$E,'フォームの回答 1'!$B:$B,">="&N1,'フォームの回答 1'!$H:$H,"支出",'フォームの回答 1'!$D:$D,$A12)-SUMIFS('フォームの回答 1'!$E:$E,'フォームの回答 1'!$B:$B,">"&O1,'フォームの回答 1'!$H:$H,"支出",'フォームの回答 1'!$D:$D,$A12) -> 13917 | O12: =B12/12 -> 1972.5833
A13: 服 | B13: =SUM(C13:N13) -> 84549 | C13: =SUMIFS('フォームの回答 1'!$E:$E,'フォームの回答 1'!$B:$B,">="&C1,'フォームの回答 1'!$H:$H,"支出",'フォームの回答 1'!$D:$D,$A13)-SUMIFS('フォームの回答 1'!$E:$E,'フォームの回答 1'!$B:$B,">"&D1,'フォームの回答 1'!$H:$H,"支出",'フォームの回答 1'!$D:$D,$A13) -> 2170 | D13: =SUMIFS('フォームの回答 1'!$E:$E,'フォームの回答 1'!$B:$B,">="&D1,'フォームの回答 1'!$H:$H,"支出",'フォームの回答 1'!$D:$D,$A13)-SUMIFS('フォームの回答 1'!$E:$E,'フォームの回答 1'!$B:$B,">"&E1,'フォームの回答 1'!$H:$H,"支出",'フォームの回答 1'!$D:$D,$A13) -> 0 | E13: =SUMIFS('フォームの回答 1'!$E:$E,'フォームの回答 1'!$B:$B,">="&E1,'フォームの回答 1'!$H:$H,"支出",'フォームの回答 1'!$D:$D,$A13)-SUMIFS('フォームの回答 1'!$E:$E,'フォームの回答 1'!$B:$B,">"&F1,'フォームの回答 1'!$H:$H,"支出",'フォームの回答 1'!$D:$D,$A13) -> 1470 | F13: =SUMIFS('フォームの回答 1'!$E:$E,'フォームの回答 1'!$B:$B,">="&F1,'フォームの回答 1'!$H:$H,"支出",'フォームの回答 1'!$D:$D,$A13)-SUMIFS('フォームの回答 1'!$E:$E,'フォームの回答 1'!$B:$B,">"&G1,'フォームの回答 1'!$H:$H,"支出",'フォームの回答 1'!$D:$D,$A13) -> 0 | G13: =SUMIFS('フォームの回答 1'!$E:$E,'フォームの回答 1'!$B:$B,">="&G1,'フォームの回答 1'!$H:$H,"支出",'フォームの回答 1'!$D:$D,$A13)-SUMIFS('フォームの回答 1'!$E:$E,'フォームの回答 1'!$B:$B,">"&H1,'フォームの回答 1'!$H:$H,"支出",'フォームの回答 1'!$D:$D,$A13) -> 0 | H13: =SUMIFS('フォームの回答 1'!$E:$E,'フォームの回答 1'!$B:$B,">="&H1,'フォームの回答 1'!$H:$H,"支出",'フォームの回答 1'!$D:$D,$A13)-SUMIFS('フォームの回答 1'!$E:$E,'フォームの回答 1'!$B:$B,">"&I1,'フォームの回答 1'!$H:$H,"支出",'フォームの回答 1'!$D:$D,$A13) -> 4509 | I13: =SUMIFS('フォームの回答 1'!$E:$E,'フォームの回答 1'!$B:$B,">="&I1,'フォームの回答 1'!$H:$H,"支出",'フォームの回答 1'!$D:$D,$A13)-SUMIFS('フォームの回答 1'!$E:$E,'フォームの回答 1'!$B:$B,">"&J1,'フォームの回答 1'!$H:$H,"支出",'フォームの回答 1'!$D:$D,$A13) -> 0 | J13: =SUMIFS('フォームの回答 1'!$E:$E,'フォームの回答 1'!$B:$B,">="&J1,'フォームの回答 1'!$H:$H,"支出",'フォームの回答 1'!$D:$D,$A13)-SUMIFS('フォームの回答 1'!$E:$E,'フォームの回答 1'!$B:$B,">"&K1,'フォームの回答 1'!$H:$H,"支出",'フォームの回答 1'!$D:$D,$A13) -> 2380 | ... N13: =SUMIFS('フォームの回答 1'!$E:$E,'フォームの回答 1'!$B:$B,">="&N1,'フォームの回答 1'!$H:$H,"支出",'フォームの回答 1'!$D:$D,$A13)-SUMIFS('フォームの回答 1'!$E:$E,'フォームの回答 1'!$B:$B,">"&O1,'フォームの回答 1'!$H:$H,"支出",'フォームの回答 1'!$D:$D,$A13) -> 46650 | O13: =B13/12 -> 7045.75
A14: 生活品 | B14: =SUM(C14:N14) -> 1004026 | C14: =SUMIFS('フォームの回答 1'!$E:$E,'フォームの回答 1'!$B:$B,">="&C1,'フォームの回答 1'!$H:$H,"支出",'フォームの回答 1'!$D:$D,$A14)-SUMIFS('フォームの回答 1'!$E:$E,'フォームの回答 1'!$B:$B,">"&D1,'フォームの回答 1'!$H:$H,"支出",'フォームの回答 1'!$D:$D,$A14) -> 13844 | D14: =SUMIFS('フォームの回答 1'!$E:$E,'フォームの回答 1'!$B:$B,">="&D1,'フォームの回答 1'!$H:$H,"支出",'フォームの回答 1'!$D:$D,$A14)-SUMIFS('フォームの回答 1'!$E:$E,'フォームの回答 1'!$B:$B,">"&E1,'フォームの回答 1'!$H:$H,"支出",'フォームの回答 1'!$D:$D,$A14) -> 20250 | E14: =SUMIFS('フォームの回答 1'!$E:$E,'フォームの回答 1'!$B:$B,">="&E1,'フォームの回答 1'!$H:$H,"支出",'フォームの回答 1'!$D:$D,$A14)-SUMIFS('フォームの回答 1'!$E:$E,'フォームの回答 1'!$B:$B,">"&F1,'フォームの回答 1'!$H:$H,"支出",'フォームの回答 1'!$D:$D,$A14) -> 40818 | F14: =SUMIFS('フォームの回答 1'!$E:$E,'フォームの回答 1'!$B:$B,">="&F1,'フォームの回答 1'!$H:$H,"支出",'フォームの回答 1'!$D:$D,$A14)-SUMIFS('フォームの回答 1'!$E:$E,'フォームの回答 1'!$B:$B,">"&G1,'フォームの回答 1'!$H:$H,"支出",'フォームの回答 1'!$D:$D,$A14) -> 48967 | G14: =SUMIFS('フォームの回答 1'!$E:$E,'フォームの回答 1'!$B:$B,">="&G1,'フォームの回答 1'!$H:$H,"支出",'フォームの回答 1'!$D:$D,$A14)-SUMIFS('フォームの回答 1'!$E:$E,'フォームの回答 1'!$B:$B,">"&H1,'フォームの回答 1'!$H:$H,"支出",'フォームの回答 1'!$D:$D,$A14) -> 77772 | H14: =SUMIFS('フォームの回答 1'!$E:$E,'フォームの回答 1'!$B:$B,">="&H1,'フォームの回答 1'!$H:$H,"支出",'フォームの回答 1'!$D:$D,$A14)-SUMIFS('フォームの回答 1'!$E:$E,'フォームの回答 1'!$B:$B,">"&I1,'フォームの回答 1'!$H:$H,"支出",'フォームの回答 1'!$D:$D,$A14) -> 33718 | I14: =SUMIFS('フォームの回答 1'!$E:$E,'フォームの回答 1'!$B:$B,">="&I1,'フォームの回答 1'!$H:$H,"支出",'フォームの回答 1'!$D:$D,$A14)-SUMIFS('フォームの回答 1'!$E:$E,'フォームの回答 1'!$B:$B,">"&J1,'フォームの回答 1'!$H:$H,"支出",'フォームの回答 1'!$D:$D,$A14) -> 23893 | J14: =SUMIFS('フォームの回答 1'!$E:$E,'フォームの回答 1'!$B:$B,">="&J1,'フォームの回答 1'!$H:$H,"支出",'フォームの回答 1'!$D:$D,$A14)-SUMIFS('フォームの回答 1'!$E:$E,'フォームの回答 1'!$B:$B,">"&K1,'フォームの回答 1'!$H:$H,"支出",'フォームの回答 1'!$D:$D,$A14) -> 31742 | ... N14: =SUMIFS('フォームの回答 1'!$E:$E,'フォームの回答 1'!$B:$B,">="&N1,'フォームの回答 1'!$H:$H,"支出",'フォームの回答 1'!$D:$D,$A14)-SUMIFS('フォームの回答 1'!$E:$E,'フォームの回答 1'!$B:$B,">"&O1,'フォームの回答 1'!$H:$H,"支出",'フォームの回答 1'!$D:$D,$A14) -> 626256 | O14: =B14/12 -> 83668.833
A15: 書籍代 | B15: =SUM(C15:N15) -> 200722 | C15: =SUMIFS('フォームの回答 1'!$E:$E,'フォームの回答 1'!$B:$B,">="&C1,'フォームの回答 1'!$H:$H,"支出",'フォームの回答 1'!$D:$D,$A15)-SUMIFS('フォームの回答 1'!$E:$E,'フォームの回答 1'!$B:$B,">"&D1,'フォームの回答 1'!$H:$H,"支出",'フォームの回答 1'!$D:$D,$A15) -> 12320 | D15: =SUMIFS('フォームの回答 1'!$E:$E,'フォームの回答 1'!$B:$B,">="&D1,'フォームの回答 1'!$H:$H,"支出",'フォームの回答 1'!$D:$D,$A15)-SUMIFS('フォームの回答 1'!$E:$E,'フォームの回答 1'!$B:$B,">"&E1,'フォームの回答 1'!$H:$H,"支出",'フォームの回答 1'!$D:$D,$A15) -> 7375 | E15: =SUMIFS('フォームの回答 1'!$E:$E,'フォームの回答 1'!$B:$B,">="&E1,'フォームの回答 1'!$H:$H,"支出",'フォームの回答 1'!$D:$D,$A15)-SUMIFS('フォームの回答 1'!$E:$E,'フォームの回答 1'!$B:$B,">"&F1,'フォームの回答 1'!$H:$H,"支出",'フォームの回答 1'!$D:$D,$A15) -> 8238 | F15: =SUMIFS('フォームの回答 1'!$E:$E,'フォームの回答 1'!$B:$B,">="&F1,'フォームの回答 1'!$H:$H,"支出",'フォームの回答 1'!$D:$D,$A15)-SUMIFS('フォームの回答 1'!$E:$E,'フォームの回答 1'!$B:$B,">"&G1,'フォームの回答 1'!$H:$H,"支出",'フォームの回答 1'!$D:$D,$A15) -> 10010 | G15: =SUMIFS('フォームの回答 1'!$E:$E,'フォームの回答 1'!$B:$B,">="&G1,'フォームの回答 1'!$H:$H,"支出",'フォームの回答 1'!$D:$D,$A15)-SUMIFS('フォームの回答 1'!$E:$E,'フォームの回答 1'!$B:$B,">"&H1,'フォームの回答 1'!$H:$H,"支出",'フォームの回答 1'!$D:$D,$A15) -> 14599 | H15: =SUMIFS('フォームの回答 1'!$E:$E,'フォームの回答 1'!$B:$B,">="&H1,'フォームの回答 1'!$H:$H,"支出",'フォームの回答 1'!$D:$D,$A15)-SUMIFS('フォームの回答 1'!$E:$E,'フォームの回答 1'!$B:$B,">"&I1,'フォームの回答 1'!$H:$H,"支出",'フォームの回答 1'!$D:$D,$A15) -> 902 | I15: =SUMIFS('フォームの回答 1'!$E:$E,'フォームの回答 1'!$B:$B,">="&I1,'フォームの回答 1'!$H:$H,"支出",'フォームの回答 1'!$D:$D,$A15)-SUMIFS('フォームの回答 1'!$E:$E,'フォームの回答 1'!$B:$B,">"&J1,'フォームの回答 1'!$H:$H,"支出",'フォームの回答 1'!$D:$D,$A15) -> 11099 | J15: =SUMIFS('フォームの回答 1'!$E:$E,'フォームの回答 1'!$B:$B,">="&J1,'フォームの回答 1'!$H:$H,"支出",'フォームの回答 1'!$D:$D,$A15)-SUMIFS('フォームの回答 1'!$E:$E,'フォームの回答 1'!$B:$B,">"&K1,'フォームの回答 1'!$H:$H,"支出",'フォームの回答 1'!$D:$D,$A15) -> 2400 | ... N15: =SUMIFS('フォームの回答 1'!$E:$E,'フォームの回答 1'!$B:$B,">="&N1,'フォームの回答 1'!$H:$H,"支出",'フォームの回答 1'!$D:$D,$A15)-SUMIFS('フォームの回答 1'!$E:$E,'フォームの回答 1'!$B:$B,">"&O1,'フォームの回答 1'!$H:$H,"支出",'フォームの回答 1'!$D:$D,$A15) -> 115837 | O15: =B15/12 -> 16726.833
A16: 奨学金・ローン返済 | B16: =SUM(C16:N16) -> 2132289 | C16: =SUMIFS('フォームの回答 1'!$E:$E,'フォームの回答 1'!$B:$B,">="&C1,'フォームの回答 1'!$H:$H,"支出",'フォームの回答 1'!$D:$D,$A16)-SUMIFS('フォームの回答 1'!$E:$E,'フォームの回答 1'!$B:$B,">"&D1,'フォームの回答 1'!$H:$H,"支出",'フォームの回答 1'!$D:$D,$A16) -> 148589 | D16: =SUMIFS('フォームの回答 1'!$E:$E,'フォームの回答 1'!$B:$B,">="&D1,'フォームの回答 1'!$H:$H,"支出",'フォームの回答 1'!$D:$D,$A16)-SUMIFS('フォームの回答 1'!$E:$E,'フォームの回答 1'!$B:$B,">"&E1,'フォームの回答 1'!$H:$H,"支出",'フォームの回答 1'!$D:$D,$A16) -> 67000 | E16: =SUMIFS('フォームの回答 1'!$E:$E,'フォームの回答 1'!$B:$B,">="&E1,'フォームの回答 1'!$H:$H,"支出",'フォームの回答 1'!$D:$D,$A16)-SUMIFS('フォームの回答 1'!$E:$E,'フォームの回答 1'!$B:$B,">"&F1,'フォームの回答 1'!$H:$H,"支出",'フォームの回答 1'!$D:$D,$A16) -> 67000 | F16: =SUMIFS('フォームの回答 1'!$E:$E,'フォームの回答 1'!$B:$B,">="&F1,'フォームの回答 1'!$H:$H,"支出",'フォームの回答 1'!$D:$D,$A16)-SUMIFS('フォームの回答 1'!$E:$E,'フォームの回答 1'!$B:$B,">"&G1,'フォームの回答 1'!$H:$H,"支出",'フォームの回答 1'!$D:$D,$A16) -> 67000 | G16: =SUMIFS('フォームの回答 1'!$E:$E,'フォームの回答 1'!$B:$B,">="&G1,'フォームの回答 1'!$H:$H,"支出",'フォームの回答 1'!$D:$D,$A16)-SUMIFS('フォームの回答 1'!$E:$E,'フォームの回答 1'!$B:$B,">"&H1,'フォームの回答 1'!$H:$H,"支出",'フォームの回答 1'!$D:$D,$A16) -> 67000 | H16: =SUMIFS('フォームの回答 1'!$E:$E,'フォームの回答 1'!$B:$B,">="&H1,'フォームの回答 1'!$H:$H,"支出",'フォームの回答 1'!$D:$D,$A16)-SUMIFS('フォームの回答 1'!$E:$E,'フォームの回答 1'!$B:$B,">"&I1,'フォームの回答 1'!$H:$H,"支出",'フォームの回答 1'!$D:$D,$A16) -> 67000 | I16: =SUMIFS('フォームの回答 1'!$E:$E,'フォームの回答 1'!$B:$B,">="&I1,'フォームの回答 1'!$H:$H,"支出",'フォームの回答 1'!$D:$D,$A16)-SUMIFS('フォームの回答 1'!$E:$E,'フォームの回答 1'!$B:$B,">"&J1,'フォームの回答 1'!$H:$H,"支出",'フォームの回答 1'!$D:$D,$A16) -> 68500 | J16: =SUMIFS('フォームの回答 1'!$E:$E,'フォームの回答 1'!$B:$B,">="&J1,'フォームの回答 1'!$H:$H,"支出",'フォームの回答 1'!$D:$D,$A16)-SUMIFS('フォームの回答 1'!$E:$E,'フォームの回答 1'!$B:$B,">"&K1,'フォームの回答 1'!$H:$H,"支出",'フォームの回答 1'!$D:$D,$A16) -> 67000 | ... N16: =SUMIFS('フォームの回答 1'!$E:$E,'フォームの回答 1'!$B:$B,">="&N1,'フォームの回答 1'!$H:$H,"支出",'フォームの回答 1'!$D:$D,$A16)-SUMIFS('フォームの回答 1'!$E:$E,'フォームの回答 1'!$B:$B,">"&O1,'フォームの回答 1'!$H:$H,"支出",'フォームの回答 1'!$D:$D,$A16) -> 1312200 | O16: =B16/12 -> 177690.75
A17: ツール | B17: =SUM(C17:N17) -> 160747 | C17: =SUMIFS('フォームの回答 1'!$E:$E,'フォームの回答 1'!$B:$B,">="&C1,'フォームの回答 1'!$H:$H,"支出",'フォームの回答 1'!$D:$D,$A17)-SUMIFS('フォームの回答 1'!$E:$E,'フォームの回答 1'!$B:$B,">"&D1,'フォームの回答 1'!$H:$H,"支出",'フォームの回答 1'!$D:$D,$A17) -> 2060 | D17: =SUMIFS('フォームの回答 1'!$E:$E,'フォームの回答 1'!$B:$B,">="&D1,'フォームの回答 1'!$H:$H,"支出",'フォームの回答 1'!$D:$D,$A17)-SUMIFS('フォームの回答 1'!$E:$E,'フォームの回答 1'!$B:$B,">"&E1,'フォームの回答 1'!$H:$H,"支出",'フォームの回答 1'!$D:$D,$A17) -> 880 | E17: =SUMIFS('フォームの回答 1'!$E:$E,'フォームの回答 1'!$B:$B,">="&E1,'フォームの回答 1'!$H:$H,"支出",'フォームの回答 1'!$D:$D,$A17)-SUMIFS('フォームの回答 1'!$E:$E,'フォームの回答 1'!$B:$B,">"&F1,'フォームの回答 1'!$H:$H,"支出",'フォームの回答 1'!$D:$D,$A17) -> 2060 | F17: =SUMIFS('フォームの回答 1'!$E:$E,'フォームの回答 1'!$B:$B,">="&F1,'フォームの回答 1'!$H:$H,"支出",'フォームの回答 1'!$D:$D,$A17)-SUMIFS('フォームの回答 1'!$E:$E,'フォームの回答 1'!$B:$B,">"&G1,'フォームの回答 1'!$H:$H,"支出",'フォームの回答 1'!$D:$D,$A17) -> 2060 | G17: =SUMIFS('フォームの回答 1'!$E:$E,'フォームの回答 1'!$B:$B,">="&G1,'フォームの回答 1'!$H:$H,"支出",'フォームの回答 1'!$D:$D,$A17)-SUMIFS('フォームの回答 1'!$E:$E,'フォームの回答 1'!$B:$B,">"&H1,'フォームの回答 1'!$H:$H,"支出",'フォームの回答 1'!$D:$D,$A17) -> 4076 | H17: =SUMIFS('フォームの回答 1'!$E:$E,'フォームの回答 1'!$B:$B,">="&H1,'フォームの回答 1'!$H:$H,"支出",'フォームの回答 1'!$D:$D,$A17)-SUMIFS('フォームの回答 1'!$E:$E,'フォームの回答 1'!$B:$B,">"&I1,'フォームの回答 1'!$H:$H,"支出",'フォームの回答 1'!$D:$D,$A17) -> 4097 | I17: =SUMIFS('フォームの回答 1'!$E:$E,'フォームの回答 1'!$B:$B,">="&I1,'フォームの回答 1'!$H:$H,"支出",'フォームの回答 1'!$D:$D,$A17)-SUMIFS('フォームの回答 1'!$E:$E,'フォームの回答 1'!$B:$B,">"&J1,'フォームの回答 1'!$H:$H,"支出",'フォームの回答 1'!$D:$D,$A17) -> 4269 | J17: =SUMIFS('フォームの回答 1'!$E:$E,'フォームの回答 1'!$B:$B,">="&J1,'フォームの回答 1'!$H:$H,"支出",'フォームの回答 1'!$D:$D,$A17)-SUMIFS('フォームの回答 1'!$E:$E,'フォームの回答 1'!$B:$B,">"&K1,'フォームの回答 1'!$H:$H,"支出",'フォームの回答 1'!$D:$D,$A17) -> 3905 | ... N17: =SUMIFS('フォームの回答 1'!$E:$E,'フォームの回答 1'!$B:$B,">="&N1,'フォームの回答 1'!$H:$H,"支出",'フォームの回答 1'!$D:$D,$A17)-SUMIFS('フォームの回答 1'!$E:$E,'フォームの回答 1'!$B:$B,">"&O1,'フォームの回答 1'!$H:$H,"支出",'フォームの回答 1'!$D:$D,$A17) -> 112577 | O17: =B17/12 -> 13395.583
A18: 勉強費 | B18: =SUM(C18:N18) -> 226758 | C18: =SUMIFS('フォームの回答 1'!$E:$E,'フォームの回答 1'!$B:$B,">="&C1,'フォームの回答 1'!$H:$H,"支出",'フォームの回答 1'!$D:$D,$A18)-SUMIFS('フォームの回答 1'!$E:$E,'フォームの回答 1'!$B:$B,">"&D1,'フォームの回答 1'!$H:$H,"支出",'フォームの回答 1'!$D:$D,$A18) -> 7480 | D18: =SUMIFS('フォームの回答 1'!$E:$E,'フォームの回答 1'!$B:$B,">="&D1,'フォームの回答 1'!$H:$H,"支出",'フォームの回答 1'!$D:$D,$A18)-SUMIFS('フォームの回答 1'!$E:$E,'フォームの回答 1'!$B:$B,">"&E1,'フォームの回答 1'!$H:$H,"支出",'フォームの回答 1'!$D:$D,$A18) -> 7480 | E18: =SUMIFS('フォームの回答 1'!$E:$E,'フォームの回答 1'!$B:$B,">="&E1,'フォームの回答 1'!$H:$H,"支出",'フォームの回答 1'!$D:$D,$A18)-SUMIFS('フォームの回答 1'!$E:$E,'フォームの回答 1'!$B:$B,">"&F1,'フォームの回答 1'!$H:$H,"支出",'フォームの回答 1'!$D:$D,$A18) -> 7480 | F18: =SUMIFS('フォームの回答 1'!$E:$E,'フォームの回答 1'!$B:$B,">="&F1,'フォームの回答 1'!$H:$H,"支出",'フォームの回答 1'!$D:$D,$A18)-SUMIFS('フォームの回答 1'!$E:$E,'フォームの回答 1'!$B:$B,">"&G1,'フォームの回答 1'!$H:$H,"支出",'フォームの回答 1'!$D:$D,$A18) -> 8880 | G18: =SUMIFS('フォームの回答 1'!$E:$E,'フォームの回答 1'!$B:$B,">="&G1,'フォームの回答 1'!$H:$H,"支出",'フォームの回答 1'!$D:$D,$A18)-SUMIFS('フォームの回答 1'!$E:$E,'フォームの回答 1'!$B:$B,">"&H1,'フォームの回答 1'!$H:$H,"支出",'フォームの回答 1'!$D:$D,$A18) -> 11420 | H18: =SUMIFS('フォームの回答 1'!$E:$E,'フォームの回答 1'!$B:$B,">="&H1,'フォームの回答 1'!$H:$H,"支出",'フォームの回答 1'!$D:$D,$A18)-SUMIFS('フォームの回答 1'!$E:$E,'フォームの回答 1'!$B:$B,">"&I1,'フォームの回答 1'!$H:$H,"支出",'フォームの回答 1'!$D:$D,$A18) -> 7480 | I18: =SUMIFS('フォームの回答 1'!$E:$E,'フォームの回答 1'!$B:$B,">="&I1,'フォームの回答 1'!$H:$H,"支出",'フォームの回答 1'!$D:$D,$A18)-SUMIFS('フォームの回答 1'!$E:$E,'フォームの回答 1'!$B:$B,">"&J1,'フォームの回答 1'!$H:$H,"支出",'フォームの回答 1'!$D:$D,$A18) -> 7480 | J18: =SUMIFS('フォームの回答 1'!$E:$E,'フォームの回答 1'!$B:$B,">="&J1,'フォームの回答 1'!$H:$H,"支出",'フォームの回答 1'!$D:$D,$A18)-SUMIFS('フォームの回答 1'!$E:$E,'フォームの回答 1'!$B:$B,">"&K1,'フォームの回答 1'!$H:$H,"支出",'フォームの回答 1'!$D:$D,$A18) -> 8880 | ... N18: =SUMIFS('フォームの回答 1'!$E:$E,'フォームの回答 1'!$B:$B,">="&N1,'フォームの回答 1'!$H:$H,"支出",'フォームの回答 1'!$D:$D,$A18)-SUMIFS('フォームの回答 1'!$E:$E,'フォームの回答 1'!$B:$B,">"&O1,'フォームの回答 1'!$H:$H,"支出",'フォームの回答 1'!$D:$D,$A18) -> 127738 | O18: =B18/12 -> 18896.5

Sheet 【Monthly】2025年
B1: 合計金額 | C1: 45658 | D1: 45689 | E1: 45717 | F1: 45748 | G1: 45778 | H1: 45809 | I1: 45839 | J1: 45870 | K1: 45901 | L1: 45931 | M1: 45962 | N1: 45992
A2: 収入 | B2: =SUM(C2:H2) -> 2435991 | C2: =SUMIFS('フォームの回答 1'!$E:$E,'フォームの回答 1'!$B:$B,">="&C1,'フォームの回答 1'!$H:$H,"収入")-SUMIFS('フォームの回答 1'!$E:$E,'フォームの回答 1'!$B:$B,">"&D1,'フォームの回答 1'!$H:$H,"収入") -> 386393 | D2: =SUMIFS('フォームの回答 1'!$E:$E,'フォームの回答 1'!$B:$B,">="&D1,'フォームの回答 1'!$H:$H,"収入")-SUMIFS('フォームの回答 1'!$E:$E,'フォームの回答 1'!$B:$B,">"&E1,'フォームの回答 1'!$H:$H,"収入") -> 413503 | E2: =SUMIFS('フォームの回答 1'!$E:$E,'フォームの回答 1'!$B:$B,">="&E1,'フォームの回答 1'!$H:$H,"収入")-SUMIFS('フォームの回答 1'!$E:$E,'フォームの回答 1'!$B:$B,">"&F1,'フォームの回答 1'!$H:$H,"収入") -> 427908 | F2: =SUMIFS('フォームの回答 1'!$E:$E,'フォームの回答 1'!$B:$B,">="&F1,'フォームの回答 1'!$H:$H,"収入")-SUMIFS('フォームの回答 1'!$E:$E,'フォームの回答 1'!$B:$B,">"&G1,'フォームの回答 1'!$H:$H,"収入") -> 426469 | G2: =SUMIFS('フォームの回答 1'!$E:$E,'フォームの回答 1'!$B:$B,">="&G1,'フォームの回答 1'!$H:$H,"収入")-SUMIFS('フォームの回答 1'!$E:$E,'フォームの回答 1'!$B:$B,">"&H1,'フォームの回答 1'!$H:$H,"収入") -> 395695 | H2: =SUMIFS('フォームの回答 1'!$E:$E,'フォームの回答 1'!$B:$B,">="&H1,'フォームの回答 1'!$H:$H,"収入")-SUMIFS('フォームの回答 1'!$E:$E,'フォームの回答 1'!$B:$B,">"&I1,'フォームの回答 1'!$H:$H,"収入") -> 386023 | I2: =SUMIFS('フォームの回答 1'!$E:$E,'フォームの回答 1'!$B:$B,">="&I1,'フォームの回答 1'!$H:$H,"収入")-SUMIFS('フォームの回答 1'!$E:$E,'フォームの回答 1'!$B:$B,">"&J1,'フォームの回答 1'!$H:$H,"収入") -> 525773 | J2: =SUMIFS('フォームの回答 1'!$E:$E,'フォームの回答 1'!$B:$B,">="&J1,'フォームの回答 1'!$H:$H,"収入")-SUMIFS('フォームの回答 1'!$E:$E,'フォームの回答 1'!$B:$B,">"&K1,'フォームの回答 1'!$H:$H,"収入") -> 403616 | ... N2: =SUMIFS('フォームの回答 1'!$E:$E,'フォームの回答 1'!$B:$B,">="&N1,'フォームの回答 1'!$H:$H,"収入")-SUMIFS('フォームの回答 1'!$E:$E,'フォームの回答 1'!$B:$B,">"&O1,'フォームの回答 1'!$H:$H,"収入") -> 2174466
A3: 支出 | B3: =SUM(C3:H3) -> 2706670 | C3: =SUMIFS('フォームの回答 1'!$E:$E,'フォームの回答 1'!$B:$B,">="&C1,'フォームの回答 1'!$H:$H,"支出")-SUMIFS('フォームの回答 1'!$E:$E,'フォームの回答 1'!$B:$B,">"&D1,'フォームの回答 1'!$H:$H,"支出") -> 425964 | D3: =SUMIFS('フォームの回答 1'!$E:$E,'フォームの回答 1'!$B:$B,">="&D1,'フォームの回答 1'!$H:$H,"支出")-SUMIFS('フォームの回答 1'!$E:$E,'フォームの回答 1'!$B:$B,">"&E1,'フォームの回答 1'!$H:$H,"支出") -> 396721 | E3: =SUMIFS('フォームの回答 1'!$E:$E,'フォームの回答 1'!$B:$B,">="&E1,'フォームの回答 1'!$H:$H,"支出")-SUMIFS('フォームの回答 1'!$E:$E,'フォームの回答 1'!$B:$B,">"&F1,'フォームの回答 1'!$H:$H,"支出") -> 375567 | F3: =SUMIFS('フォームの回答 1'!$E:$E,'フォームの回答 1'!$B:$B,">="&F1,'フォームの回答 1'!$H:$H,"支出")-SUMIFS('フォームの回答 1'!$E:$E,'フォームの回答 1'!$B:$B,">"&G1,'フォームの回答 1'!$H:$H,"支出") -> 423153 | G3: =SUMIFS('フォームの回答 1'!$E:$E,'フォームの回答 1'!$B:$B,">="&G1,'フォームの回答 1'!$H:$H,"支出")-SUMIFS('フォームの回答 1'!$E:$E,'フォームの回答 1'!$B:$B,">"&H1,'フォームの回答 1'!$H:$H,"支出") -> 572535 | H3: =SUMIFS('フォームの回答 1'!$E:$E,'フォームの回答 1'!$B:$B,">="&H1,'フォームの回答 1'!$H:$H,"支出")-SUMIFS('フォームの回答 1'!$E:$E,'フォームの回答 1'!$B:$B,">"&I1,'フォームの回答 1'!$H:$H,"支出") -> 512730 | I3: =SUMIFS('フォームの回答 1'!$E:$E,'フォームの回答 1'!$B:$B,">="&I1,'フォームの回答 1'!$H:$H,"支出")-SUMIFS('フォームの回答 1'!$E:$E,'フォームの回答 1'!$B:$B,">"&J1,'フォームの回答 1'!$H:$H,"支出") -> 440281 | J3: =SUMIFS('フォームの回答 1'!$E:$E,'フォームの回答 1'!$B:$B,">="&J1,'フォームの回答 1'!$H:$H,"支出")-SUMIFS('フォームの回答 1'!$E:$E,'フォームの回答 1'!$B:$B,">"&K1,'フォームの回答 1'!$H:$H,"支出") -> 432558 | ... N3: =SUMIFS('フォームの回答 1'!$E:$E,'フォームの回答 1'!$B:$B,">="&N1,'フォームの回答 1'!$H:$H,"支出")-SUMIFS('フォームの回答 1'!$E:$E,'フォームの回答 1'!$B:$B,">"&O1,'フォームの回答 1'!$H:$H,"支出") -> 2304517
A4: 差額 | B4: =SUM(C4:H4) -> -270679 | C4: =C2-C3 -> -39571 | D4: =D2-D3 -> 16782 | E4: =E2-E3 -> 52341 | F4: =F2-F3 -> 3316 | G4: =G2-G3 -> -176840 | H4: =H2-H3 -> -126707 | I4: =I2-I3 -> 85492 | J4: =J2-J3 -> -28942 | ... N4: =N2-N3 -> -130051
B5: 内訳
A6: 食費 | B6: =SUM(C6:I6) -> 283870 | C6: =SUMIFS('フォームの回答 1'!$E:$E,'フォームの回答 1'!$B:$B,">="&C1,'フォームの回答 1'!$H:$H,"支出",'フォームの回答 1'!$D:$D,$A6)-SUMIFS('フォームの回答 1'!$E:$E,'フォームの回答 1'!$B:$B,">"&D1,'フォームの回答 1'!$H:$H,"支出",'フォームの回答 1'!$D:$D,$A6) -> 41207 | D6: =SUMIFS('フォームの回答 1'!$E:$E,'フォームの回答 1'!$B:$B,">="&D1,'フォームの回答 1'!$H:$H,"支出",'フォームの回答 1'!$D:$D,$A6)-SUMIFS('フォームの回答 1'!$E:$E,'フォームの回答 1'!$B:$B,">"&E1,'フォームの回答 1'!$H:$H,"支出",'フォームの回答 1'!$D:$D,$A6) -> 28100 | E6: =SUMIFS('フォームの回答 1'!$E:$E,'フォームの回答 1'!$B:$B,">="&E1,'フォームの回答 1'!$H:$H,"支出",'フォームの回答 1'!$D:$D,$A6)-SUMIFS('フォームの回答 1'!$E:$E,'フォームの回答 1'!$B:$B,">"&F1,'フォームの回答 1'!$H:$H,"支出",'フォームの回答 1'!$D:$D,$A6) -> 39863 | F6: =SUMIFS('フォームの回答 1'!$E:$E,'フォームの回答 1'!$B:$B,">="&F1,'フォームの回答 1'!$H:$H,"支出",'フォームの回答 1'!$D:$D,$A6)-SUMIFS('フォームの回答 1'!$E:$E,'フォームの回答 1'!$B:$B,">"&G1,'フォームの回答 1'!$H:$H,"支出",'フォームの回答 1'!$D:$D,$A6) -> 36592 | G6: =SUMIFS('フォームの回答 1'!$E:$E,'フォームの回答 1'!$B:$B,">="&G1,'フォームの回答 1'!$H:$H,"支出",'フォームの回答 1'!$D:$D,$A6)-SUMIFS('フォームの回答 1'!$E:$E,'フォームの回答 1'!$B:$B,">"&H1,'フォームの回答 1'!$H:$H,"支出",'フォームの回答 1'!$D:$D,$A6) -> 44509 | H6: =SUMIFS('フォームの回答 1'!$E:$E,'フォームの回答 1'!$B:$B,">="&H1,'フォームの回答 1'!$H:$H,"支出",'フォームの回答 1'!$D:$D,$A6)-SUMIFS('フォームの回答 1'!$E:$E,'フォームの回答 1'!$B:$B,">"&I1,'フォームの回答 1'!$H:$H,"支出",'フォームの回答 1'!$D:$D,$A6) -> 43062 | I6: =SUMIFS('フォームの回答 1'!$E:$E,'フォームの回答 1'!$B:$B,">="&I1,'フォームの回答 1'!$H:$H,"支出",'フォームの回答 1'!$D:$D,$A6)-SUMIFS('フォームの回答 1'!$E:$E,'フォームの回答 1'!$B:$B,">"&J1,'フォームの回答 1'!$H:$H,"支出",'フォームの回答 1'!$D:$D,$A6) -> 50537 | J6: =SUMIFS('フォームの回答 1'!$E:$E,'フォームの回答 1'!$B:$B,">="&J1,'フォームの回答 1'!$H:$H,"支出",'フォームの回答 1'!$D:$D,$A6)-SUMIFS('フォームの回答 1'!$E:$E,'フォームの回答 1'!$B:$B,">"&K1,'フォームの回答 1'!$H:$H,"支出",'フォームの回答 1'!$D:$D,$A6) -> 49659 | ... N6: =SUMIFS('フォームの回答 1'!$E:$E,'フォームの回答 1'!$B:$B,">="&N1,'フォームの回答 1'!$H:$H,"支出",'フォームの回答 1'!$D:$D,$A6)-SUMIFS('フォームの回答 1'!$E:$E,'フォームの回答 1'!$B:$B,">"&O1,'フォームの回答 1'!$H:$H,"支出",'フォームの回答 1'!$D:$D,$A6) -> 156324
A7: 接待交際費 | B7: =SUM(C7:I7) -> 491254 | C7: =SUMIFS('フォームの回答 1'!$E:$E,'フォームの回答 1'!$B:$B,">="&C1,'フォームの回答 1'!$H:$H,"支出",'フォームの回答 1'!$D:$D,$A7)-SUMIFS('フォームの回答 1'!$E:$E,'フォームの回答 1'!$B:$B,">"&D1,'フォームの回答 1'!$H:$H,"支出",'フォームの回答 1'!$D:$D,$A7) -> 35920 | D7: =SUMIFS('フォームの回答 1'!$E:$E,'フォームの回答 1'!$B:$B,">="&D1,'フォームの回答 1'!$H:$H,"支出",'フォームの回答 1'!$D:$D,$A7)-SUMIFS('フォームの回答 1'!$E:$E,'フォームの回答 1'!$B:$B,">"&E1,'フォームの回答 1'!$H:$H,"支出",'フォームの回答 1'!$D:$D,$A7) -> 81496 | E7: =SUMIFS('フォームの回答 1'!$E:$E,'フォームの回答 1'!$B:$B,">="&E1,'フォームの回答 1'!$H:$H,"支出",'フォームの回答 1'!$D:$D,$A7)-SUMIFS('フォームの回答 1'!$E:$E,'フォームの回答 1'!$B:$B,">"&F1,'フォームの回答 1'!$H:$H,"支出",'フォームの回答 1'!$D:$D,$A7) -> 35321 | F7: =SUMIFS('フォームの回答 1'!$E:$E,'フォームの回答 1'!$B:$B,">="&F1,'フォームの回答 1'!$H:$H,"支出",'フォームの回答 1'!$D:$D,$A7)-SUMIFS('フォームの回答 1'!$E:$E,'フォームの回答 1'!$B:$B,">"&G1,'フォームの回答 1'!$H:$H,"支出",'フォームの回答 1'!$D:$D,$A7) -> 83624 | G7: =SUMIFS('フォームの回答 1'!$E:$E,'フォームの回答 1'!$B:$B,">="&G1,'フォームの回答 1'!$H:$H,"支出",'フォームの回答 1'!$D:$D,$A7)-SUMIFS('フォームの回答 1'!$E:$E,'フォームの回答 1'!$B:$B,">"&H1,'フォームの回答 1'!$H:$H,"支出",'フォームの回答 1'!$D:$D,$A7) -> 71718 | H7: =SUMIFS('フォームの回答 1'!$E:$E,'フォームの回答 1'!$B:$B,">="&H1,'フォームの回答 1'!$H:$H,"支出",'フォームの回答 1'!$D:$D,$A7)-SUMIFS('フォームの回答 1'!$E:$E,'フォームの回答 1'!$B:$B,">"&I1,'フォームの回答 1'!$H:$H,"支出",'フォームの回答 1'!$D:$D,$A7) -> 140899 | I7: =SUMIFS('フォームの回答 1'!$E:$E,'フォームの回答 1'!$B:$B,">="&I1,'フォームの回答 1'!$H:$H,"支出",'フォームの回答 1'!$D:$D,$A7)-SUMIFS('フォームの回答 1'!$E:$E,'フォームの回答 1'!$B:$B,">"&J1,'フォームの回答 1'!$H:$H,"支出",'フォームの回答 1'!$D:$D,$A7) -> 42276 | J7: =SUMIFS('フォームの回答 1'!$E:$E,'フォームの回答 1'!$B:$B,">="&J1,'フォームの回答 1'!$H:$H,"支出",'フォームの回答 1'!$D:$D,$A7)-SUMIFS('フォームの回答 1'!$E:$E,'フォームの回答 1'!$B:$B,">"&K1,'フォームの回答 1'!$H:$H,"支出",'フォームの回答 1'!$D:$D,$A7) -> 76542 | ... N7: =SUMIFS('フォームの回答 1'!$E:$E,'フォームの回答 1'!$B:$B,">="&N1,'フォームの回答 1'!$H:$H,"支出",'フォームの回答 1'!$D:$D,$A7)-SUMIFS('フォームの回答 1'!$E:$E,'フォームの回答 1'!$B:$B,">"&O1,'フォームの回答 1'!$H:$H,"支出",'フォームの回答 1'!$D:$D,$A7) -> 366572
A8: 交通費 | B8: =SUM(C8:I8) -> 314930 | C8: =SUMIFS('フォームの回答 1'!$E:$E,'フォームの回答 1'!$B:$B,">="&C1,'フォームの回答 1'!$H:$H,"支出",'フォームの回答 1'!$D:$D,$A8)-SUMIFS('フォームの回答 1'!$E:$E,'フォームの回答 1'!$B:$B,">"&D1,'フォームの回答 1'!$H:$H,"支出",'フォームの回答 1'!$D:$D,$A8) -> 27430 | D8: =SUMIFS('フォームの回答 1'!$E:$E,'フォームの回答 1'!$B:$B,">="&D1,'フォームの回答 1'!$H:$H,"支出",'フォームの回答 1'!$D:$D,$A8)-SUMIFS('フォームの回答 1'!$E:$E,'フォームの回答 1'!$B:$B,">"&E1,'フォームの回答 1'!$H:$H,"支出",'フォームの回答 1'!$D:$D,$A8) -> 32090 | E8: =SUMIFS('フォームの回答 1'!$E:$E,'フォームの回答 1'!$B:$B,">="&E1,'フォームの回答 1'!$H:$H,"支出",'フォームの回答 1'!$D:$D,$A8)-SUMIFS('フォームの回答 1'!$E:$E,'フォームの回答 1'!$B:$B,">"&F1,'フォームの回答 1'!$H:$H,"支出",'フォームの回答 1'!$D:$D,$A8) -> 39220 | F8: =SUMIFS('フォームの回答 1'!$E:$E,'フォームの回答 1'!$B:$B,">="&F1,'フォームの回答 1'!$H:$H,"支出",'フォームの回答 1'!$D:$D,$A8)-SUMIFS('フォームの回答 1'!$E:$E,'フォームの回答 1'!$B:$B,">"&G1,'フォームの回答 1'!$H:$H,"支出",'フォームの回答 1'!$D:$D,$A8) -> 44510 | G8: =SUMIFS('フォームの回答 1'!$E:$E,'フォームの回答 1'!$B:$B,">="&G1,'フォームの回答 1'!$H:$H,"支出",'フォームの回答 1'!$D:$D,$A8)-SUMIFS('フォームの回答 1'!$E:$E,'フォームの回答 1'!$B:$B,">"&H1,'フォームの回答 1'!$H:$H,"支出",'フォームの回答 1'!$D:$D,$A8) -> 45550 | H8: =SUMIFS('フォームの回答 1'!$E:$E,'フォームの回答 1'!$B:$B,">="&H1,'フォームの回答 1'!$H:$H,"支出",'フォームの回答 1'!$D:$D,$A8)-SUMIFS('フォームの回答 1'!$E:$E,'フォームの回答 1'!$B:$B,">"&I1,'フォームの回答 1'!$H:$H,"支出",'フォームの回答 1'!$D:$D,$A8) -> 38490 | I8: =SUMIFS('フォームの回答 1'!$E:$E,'フォームの回答 1'!$B:$B,">="&I1,'フォームの回答 1'!$H:$H,"支出",'フォームの回答 1'!$D:$D,$A8)-SUMIFS('フォームの回答 1'!$E:$E,'フォームの回答 1'!$B:$B,">"&J1,'フォームの回答 1'!$H:$H,"支出",'フォームの回答 1'!$D:$D,$A8) -> 87640 | J8: =SUMIFS('フォームの回答 1'!$E:$E,'フォームの回答 1'!$B:$B,">="&J1,'フォームの回答 1'!$H:$H,"支出",'フォームの回答 1'!$D:$D,$A8)-SUMIFS('フォームの回答 1'!$E:$E,'フォームの回答 1'!$B:$B,">"&K1,'フォームの回答 1'!$H:$H,"支出",'フォームの回答 1'!$D:$D,$A8) -> 36410 | ... N8: =SUMIFS('フォームの回答 1'!$E:$E,'フォームの回答 1'!$B:$B,">="&N1,'フォームの回答 1'!$H:$H,"支出",'フォームの回答 1'!$D:$D,$A8)-SUMIFS('フォームの回答 1'!$E:$E,'フォームの回答 1'!$B:$B,">"&O1,'フォームの回答 1'!$H:$H,"支出",'フォームの回答 1'!$D:$D,$A8) -> 227257
A9: 光熱費 | B9: =SUM(C9:I9) -> 89906 | C9: =SUMIFS('フォームの回答 1'!$E:$E,'フォームの回答 1'!$B:$B,">="&C1,'フォームの回答 1'!$H:$H,"支出",'フォームの回答 1'!$D:$D,$A9)-SUMIFS('フォームの回答 1'!$E:$E,'フォームの回答 1'!$B:$B,">"&D1,'フォームの回答 1'!$H:$H,"支出",'フォームの回答 1'!$D:$D,$A9) -> 5868 | D9: =SUMIFS('フォームの回答 1'!$E:$E,'フォームの回答 1'!$B:$B,">="&D1,'フォームの回答 1'!$H:$H,"支出",'フォームの回答 1'!$D:$D,$A9)-SUMIFS('フォームの回答 1'!$E:$E,'フォームの回答 1'!$B:$B,">"&E1,'フォームの回答 1'!$H:$H,"支出",'フォームの回答 1'!$D:$D,$A9) -> 9282 | E9: =SUMIFS('フォームの回答 1'!$E:$E,'フォームの回答 1'!$B:$B,">="&E1,'フォームの回答 1'!$H:$H,"支出",'フォームの回答 1'!$D:$D,$A9)-SUMIFS('フォームの回答 1'!$E:$E,'フォームの回答 1'!$B:$B,">"&F1,'フォームの回答 1'!$H:$H,"支出",'フォームの回答 1'!$D:$D,$A9) -> 11853 | F9: =SUMIFS('フォームの回答 1'!$E:$E,'フォームの回答 1'!$B:$B,">="&F1,'フォームの回答 1'!$H:$H,"支出",'フォームの回答 1'!$D:$D,$A9)-SUMIFS('フォームの回答 1'!$E:$E,'フォームの回答 1'!$B:$B,">"&G1,'フォームの回答 1'!$H:$H,"支出",'フォームの回答 1'!$D:$D,$A9) -> 19858 | G9: =SUMIFS('フォームの回答 1'!$E:$E,'フォームの回答 1'!$B:$B,">="&G1,'フォームの回答 1'!$H:$H,"支出",'フォームの回答 1'!$D:$D,$A9)-SUMIFS('フォームの回答 1'!$E:$E,'フォームの回答 1'!$B:$B,">"&H1,'フォームの回答 1'!$H:$H,"支出",'フォームの回答 1'!$D:$D,$A9) -> 10725 | H9: =SUMIFS('フォームの回答 1'!$E:$E,'フォームの回答 1'!$B:$B,">="&H1,'フォームの回答 1'!$H:$H,"支出",'フォームの回答 1'!$D:$D,$A9)-SUMIFS('フォームの回答 1'!$E:$E,'フォームの回答 1'!$B:$B,">"&I1,'フォームの回答 1'!$H:$H,"支出",'フォームの回答 1'!$D:$D,$A9) -> 17245 | I9: =SUMIFS('フォームの回答 1'!$E:$E,'フォームの回答 1'!$B:$B,">="&I1,'フォームの回答 1'!$H:$H,"支出",'フォームの回答 1'!$D:$D,$A9)-SUMIFS('フォームの回答 1'!$E:$E,'フォームの回答 1'!$B:$B,">"&J1,'フォームの回答 1'!$H:$H,"支出",'フォームの回答 1'!$D:$D,$A9) -> 15075 | J9: =SUMIFS('フォームの回答 1'!$E:$E,'フォームの回答 1'!$B:$B,">="&J1,'フォームの回答 1'!$H:$H,"支出",'フォームの回答 1'!$D:$D,$A9)-SUMIFS('フォームの回答 1'!$E:$E,'フォームの回答 1'!$B:$B,">"&K1,'フォームの回答 1'!$H:$H,"支出",'フォームの回答 1'!$D:$D,$A9) -> 14436 | ... N9: =SUMIFS('フォームの回答 1'!$E:$E,'フォームの回答 1'!$B:$B,">="&N1,'フォームの回答 1'!$H:$H,"支出",'フォームの回答 1'!$D:$D,$A9)-SUMIFS('フォームの回答 1'!$E:$E,'フォームの回答 1'!$B:$B,">"&O1,'フォームの回答 1'!$H:$H,"支出",'フォームの回答 1'!$D:$D,$A9) -> 70937
A10: スマホ代 | B10: =SUM(C10:I10) -> 46338 | C10: =SUMIFS('フォームの回答 1'!$E:$E,'フォームの回答 1'!$B:$B,">="&C1,'フォームの回答 1'!$H:$H,"支出",'フォームの回答 1'!$D:$D,$A10)-SUMIFS('フォームの回答 1'!$E:$E,'フォームの回答 1'!$B:$B,">"&D1,'フォームの回答 1'!$H:$H,"支出",'フォームの回答 1'!$D:$D,$A10) -> 4528 | D10: =SUMIFS('フォームの回答 1'!$E:$E,'フォームの回答 1'!$B:$B,">="&D1,'フォームの回答 1'!$H:$H,"支出",'フォームの回答 1'!$D:$D,$A10)-SUMIFS('フォームの回答 1'!$E:$E,'フォームの回答 1'!$B:$B,">"&E1,'フォームの回答 1'!$H:$H,"支出",'フォームの回答 1'!$D:$D,$A10) -> 3388 | E10: =SUMIFS('フォームの回答 1'!$E:$E,'フォームの回答 1'!$B:$B,">="&E1,'フォームの回答 1'!$H:$H,"支出",'フォームの回答 1'!$D:$D,$A10)-SUMIFS('フォームの回答 1'!$E:$E,'フォームの回答 1'!$B:$B,">"&F1,'フォームの回答 1'!$H:$H,"支出",'フォームの回答 1'!$D:$D,$A10) -> 6895 | F10: =SUMIFS('フォームの回答 1'!$E:$E,'フォームの回答 1'!$B:$B,">="&F1,'フォームの回答 1'!$H:$H,"支出",'フォームの回答 1'!$D:$D,$A10)-SUMIFS('フォームの回答 1'!$E:$E,'フォームの回答 1'!$B:$B,">"&G1,'フォームの回答 1'!$H:$H,"支出",'フォームの回答 1'!$D:$D,$A10) -> 7370 | G10: =SUMIFS('フォームの回答 1'!$E:$E,'フォームの回答 1'!$B:$B,">="&G1,'フォームの回答 1'!$H:$H,"支出",'フォームの回答 1'!$D:$D,$A10)-SUMIFS('フォームの回答 1'!$E:$E,'フォームの回答 1'!$B:$B,">"&H1,'フォームの回答 1'!$H:$H,"支出",'フォームの回答 1'!$D:$D,$A10) -> 8801 | H10: =SUMIFS('フォームの回答 1'!$E:$E,'フォームの回答 1'!$B:$B,">="&H1,'フォームの回答 1'!$H:$H,"支出",'フォームの回答 1'!$D:$D,$A10)-SUMIFS('フォームの回答 1'!$E:$E,'フォームの回答 1'!$B:$B,">"&I1,'フォームの回答 1'!$H:$H,"支出",'フォームの回答 1'!$D:$D,$A10) -> 8404 | I10: =SUMIFS('フォームの回答 1'!$E:$E,'フォームの回答 1'!$B:$B,">="&I1,'フォームの回答 1'!$H:$H,"支出",'フォームの回答 1'!$D:$D,$A10)-SUMIFS('フォームの回答 1'!$E:$E,'フォームの回答 1'!$B:$B,">"&J1,'フォームの回答 1'!$H:$H,"支出",'フォームの回答 1'!$D:$D,$A10) -> 6952 | J10: =SUMIFS('フォームの回答 1'!$E:$E,'フォームの回答 1'!$B:$B,">="&J1,'フォームの回答 1'!$H:$H,"支出",'フォームの回答 1'!$D:$D,$A10)-SUMIFS('フォームの回答 1'!$E:$E,'フォームの回答 1'!$B:$B,">"&K1,'フォームの回答 1'!$H:$H,"支出",'フォームの回答 1'!$D:$D,$A10) -> 6050 | ... N10: =SUMIFS('フォームの回答 1'!$E:$E,'フォームの回答 1'!$B:$B,">="&N1,'フォームの回答 1'!$H:$H,"支出",'フォームの回答 1'!$D:$D,$A10)-SUMIFS('フォームの回答 1'!$E:$E,'フォームの回答 1'!$B:$B,">"&O1,'フォームの回答 1'!$H:$H,"支出",'フォームの回答 1'!$D:$D,$A10) -> 36276
A11: 家賃 | B11: =SUM(C11:I11) -> 777500 | C11: =SUMIFS('フォームの回答 1'!$E:$E,'フォームの回答 1'!$B:$B,">="&C1,'フォームの回答 1'!$H:$H,"支出",'フォームの回答 1'!$D:$D,$A11)-SUMIFS('フォームの回答 1'!$E:$E,'フォームの回答 1'!$B:$B,">"&D1,'フォームの回答 1'!$H:$H,"支出",'フォームの回答 1'!$D:$D,$A11) -> 93000 | D11: =SUMIFS('フォームの回答 1'!$E:$E,'フォームの回答 1'!$B:$B,">="&D1,'フォームの回答 1'!$H:$H,"支出",'フォームの回答 1'!$D:$D,$A11)-SUMIFS('フォームの回答 1'!$E:$E,'フォームの回答 1'!$B:$B,">"&E1,'フォームの回答 1'!$H:$H,"支出",'フォームの回答 1'!$D:$D,$A11) -> 93000 | E11: =SUMIFS('フォームの回答 1'!$E:$E,'フォームの回答 1'!$B:$B,">="&E1,'フォームの回答 1'!$H:$H,"支出",'フォームの回答 1'!$D:$D,$A11)-SUMIFS('フォームの回答 1'!$E:$E,'フォームの回答 1'!$B:$B,">"&F1,'フォームの回答 1'!$H:$H,"支出",'フォームの回答 1'!$D:$D,$A11) -> 93000 | F11: =SUMIFS('フォームの回答 1'!$E:$E,'フォームの回答 1'!$B:$B,">="&F1,'フォームの回答 1'!$H:$H,"支出",'フォームの回答 1'!$D:$D,$A11)-SUMIFS('フォームの回答 1'!$E:$E,'フォームの回答 1'!$B:$B,">"&G1,'フォームの回答 1'!$H:$H,"支出",'フォームの回答 1'!$D:$D,$A11) -> 93000 | G11: =SUMIFS('フォームの回答 1'!$E:$E,'フォームの回答 1'!$B:$B,">="&G1,'フォームの回答 1'!$H:$H,"支出",'フォームの回答 1'!$D:$D,$A11)-SUMIFS('フォームの回答 1'!$E:$E,'フォームの回答 1'!$B:$B,">"&H1,'フォームの回答 1'!$H:$H,"支出",'フォームの回答 1'!$D:$D,$A11) -> 219500 | H11: =SUMIFS('フォームの回答 1'!$E:$E,'フォームの回答 1'!$B:$B,">="&H1,'フォームの回答 1'!$H:$H,"支出",'フォームの回答 1'!$D:$D,$A11)-SUMIFS('フォームの回答 1'!$E:$E,'フォームの回答 1'!$B:$B,">"&I1,'フォームの回答 1'!$H:$H,"支出",'フォームの回答 1'!$D:$D,$A11) -> 93000 | I11: =SUMIFS('フォームの回答 1'!$E:$E,'フォームの回答 1'!$B:$B,">="&I1,'フォームの回答 1'!$H:$H,"支出",'フォームの回答 1'!$D:$D,$A11)-SUMIFS('フォームの回答 1'!$E:$E,'フォームの回答 1'!$B:$B,">"&J1,'フォームの回答 1'!$H:$H,"支出",'フォームの回答 1'!$D:$D,$A11) -> 93000 | J11: =SUMIFS('フォームの回答 1'!$E:$E,'フォームの回答 1'!$B:$B,">="&J1,'フォームの回答 1'!$H:$H,"支出",'フォームの回答 1'!$D:$D,$A11)-SUMIFS('フォームの回答 1'!$E:$E,'フォームの回答 1'!$B:$B,">"&K1,'フォームの回答 1'!$H:$H,"支出",'フォームの回答 1'!$D:$D,$A11) -> 93000 | ... N11: =SUMIFS('フォームの回答 1'!$E:$E,'フォームの回答 1'!$B:$B,">="&N1,'フォームの回答 1'!$H:$H,"支出",'フォームの回答 1'!$D:$D,$A11)-SUMIFS('フォームの回答 1'!$E:$E,'フォームの回答 1'!$B:$B,">"&O1,'フォームの回答 1'!$H:$H,"支出",'フォームの回答 1'!$D:$D,$A11) -> 465000
A12: 医療費 | B12: =SUM(C12:I12) -> 7946 | C12: =SUMIFS('フォームの回答 1'!$E:$E,'フォームの回答 1'!$B:$B,">="&C1,'フォームの回答 1'!$H:$H,"支出",'フォームの回答 1'!$D:$D,$A12)-SUMIFS('フォームの回答 1'!$E:$E,'フォームの回答 1'!$B:$B,">"&D1,'フォームの回答 1'!$H:$H,"支出",'フォームの回答 1'!$D:$D,$A12) -> 0 | D12: =SUMIFS('フォームの回答 1'!$E:$E,'フォームの回答 1'!$B:$B,">="&D1,'フォームの回答 1'!$H:$H,"支出",'フォームの回答 1'!$D:$D,$A12)-SUMIFS('フォームの回答 1'!$E:$E,'フォームの回答 1'!$B:$B,">"&E1,'フォームの回答 1'!$H:$H,"支出",'フォームの回答 1'!$D:$D,$A12) -> 0 | E12: =SUMIFS('フォームの回答 1'!$E:$E,'フォームの回答 1'!$B:$B,">="&E1,'フォームの回答 1'!$H:$H,"支出",'フォームの回答 1'!$D:$D,$A12)-SUMIFS('フォームの回答 1'!$E:$E,'フォームの回答 1'!$B:$B,">"&F1,'フォームの回答 1'!$H:$H,"支出",'フォームの回答 1'!$D:$D,$A12) -> 0 | F12: =SUMIFS('フォームの回答 1'!$E:$E,'フォームの回答 1'!$B:$B,">="&F1,'フォームの回答 1'!$H:$H,"支出",'フォームの回答 1'!$D:$D,$A12)-SUMIFS('フォームの回答 1'!$E:$E,'フォームの回答 1'!$B:$B,">"&G1,'フォームの回答 1'!$H:$H,"支出",'フォームの回答 1'!$D:$D,$A12) -> 0 | G12: =SUMIFS('フォームの回答 1'!$E:$E,'フォームの回答 1'!$B:$B,">="&G1,'フォームの回答 1'!$H:$H,"支出",'フォームの回答 1'!$D:$D,$A12)-SUMIFS('フォームの回答 1'!$E:$E,'フォームの回答 1'!$B:$B,">"&H1,'フォームの回答 1'!$H:$H,"支出",'フォームの回答 1'!$D:$D,$A12) -> 6254 | H12: =SUMIFS('フォームの回答 1'!$E:$E,'フォームの回答 1'!$B:$B,">="&H1,'フォームの回答 1'!$H:$H,"支出",'フォームの回答 1'!$D:$D,$A12)-SUMIFS('フォームの回答 1'!$E:$E,'フォームの回答 1'!$B:$B,">"&I1,'フォームの回答 1'!$H:$H,"支出",'フォームの回答 1'!$D:$D,$A12) -> 1692 | I12: =SUMIFS('フォームの回答 1'!$E:$E,'フォームの回答 1'!$B:$B,">="&I1,'フォームの回答 1'!$H:$H,"支出",'フォームの回答 1'!$D:$D,$A12)-SUMIFS('フォームの回答 1'!$E:$E,'フォームの回答 1'!$B:$B,">"&J1,'フォームの回答 1'!$H:$H,"支出",'フォームの回答 1'!$D:$D,$A12) -> 0 | J12: =SUMIFS('フォームの回答 1'!$E:$E,'フォームの回答 1'!$B:$B,">="&J1,'フォームの回答 1'!$H:$H,"支出",'フォームの回答 1'!$D:$D,$A12)-SUMIFS('フォームの回答 1'!$E:$E,'フォームの回答 1'!$B:$B,">"&K1,'フォームの回答 1'!$H:$H,"支出",'フォームの回答 1'!$D:$D,$A12) -> 767 | ... N12: =SUMIFS('フォームの回答 1'!$E:$E,'フォームの回答 1'!$B:$B,">="&N1,'フォームの回答 1'!$H:$H,"支出",'フォームの回答 1'!$D:$D,$A12)-SUMIFS('フォームの回答 1'!$E:$E,'フォームの回答 1'!$B:$B,">"&O1,'フォームの回答 1'!$H:$H,"支出",'フォームの回答 1'!$D:$D,$A12) -> 4487
A13: 服 | B13: =SUM(C13:I13) -> 36190 | C13: =SUMIFS('フォームの回答 1'!$E:$E,'フォームの回答 1'!$B:$B,">="&C1,'フォームの回答 1'!$H:$H,"支出",'フォームの回答 1'!$D:$D,$A13)-SUMIFS('フォームの回答 1'!$E:$E,'フォームの回答 1'!$B:$B,">"&D1,'フォームの回答 1'!$H:$H,"支出",'フォームの回答 1'!$D:$D,$A13) -> 0 | D13: =SUMIFS('フォームの回答 1'!$E:$E,'フォームの回答 1'!$B:$B,">="&D1,'フォームの回答 1'!$H:$H,"支出",'フォームの回答 1'!$D:$D,$A13)-SUMIFS('フォームの回答 1'!$E:$E,'フォームの回答 1'!$B:$B,">"&E1,'フォームの回答 1'!$H:$H,"支出",'フォームの回答 1'!$D:$D,$A13) -> 0 | E13: =SUMIFS('フォームの回答 1'!$E:$E,'フォームの回答 1'!$B:$B,">="&E1,'フォームの回答 1'!$H:$H,"支出",'フォームの回答 1'!$D:$D,$A13)-SUMIFS('フォームの回答 1'!$E:$E,'フォームの回答 1'!$B:$B,">"&F1,'フォームの回答 1'!$H:$H,"支出",'フォームの回答 1'!$D:$D,$A13) -> 4990 | F13: =SUMIFS('フォームの回答 1'!$E:$E,'フォームの回答 1'!$B:$B,">="&F1,'フォームの回答 1'!$H:$H,"支出",'フォームの回答 1'!$D:$D,$A13)-SUMIFS('フォームの回答 1'!$E:$E,'フォームの回答 1'!$B:$B,">"&G1,'フォームの回答 1'!$H:$H,"支出",'フォームの回答 1'!$D:$D,$A13) -> 20200 | G13: =SUMIFS('フォームの回答 1'!$E:$E,'フォームの回答 1'!$B:$B,">="&G1,'フォームの回答 1'!$H:$H,"支出",'フォームの回答 1'!$D:$D,$A13)-SUMIFS('フォームの回答 1'!$E:$E,'フォームの回答 1'!$B:$B,">"&H1,'フォームの回答 1'!$H:$H,"支出",'フォームの回答 1'!$D:$D,$A13) -> 5850 | H13: =SUMIFS('フォームの回答 1'!$E:$E,'フォームの回答 1'!$B:$B,">="&H1,'フォームの回答 1'!$H:$H,"支出",'フォームの回答 1'!$D:$D,$A13)-SUMIFS('フォームの回答 1'!$E:$E,'フォームの回答 1'!$B:$B,">"&I1,'フォームの回答 1'!$H:$H,"支出",'フォームの回答 1'!$D:$D,$A13) -> 3160 | I13: =SUMIFS('フォームの回答 1'!$E:$E,'フォームの回答 1'!$B:$B,">="&I1,'フォームの回答 1'!$H:$H,"支出",'フォームの回答 1'!$D:$D,$A13)-SUMIFS('フォームの回答 1'!$E:$E,'フォームの回答 1'!$B:$B,">"&J1,'フォームの回答 1'!$H:$H,"支出",'フォームの回答 1'!$D:$D,$A13) -> 1990 | J13: =SUMIFS('フォームの回答 1'!$E:$E,'フォームの回答 1'!$B:$B,">="&J1,'フォームの回答 1'!$H:$H,"支出",'フォームの回答 1'!$D:$D,$A13)-SUMIFS('フォームの回答 1'!$E:$E,'フォームの回答 1'!$B:$B,">"&K1,'フォームの回答 1'!$H:$H,"支出",'フォームの回答 1'!$D:$D,$A13) -> 1180 | ... N13: =SUMIFS('フォームの回答 1'!$E:$E,'フォームの回答 1'!$B:$B,">="&N1,'フォームの回答 1'!$H:$H,"支出",'フォームの回答 1'!$D:$D,$A13)-SUMIFS('フォームの回答 1'!$E:$E,'フォームの回答 1'!$B:$B,">"&O1,'フォームの回答 1'!$H:$H,"支出",'フォームの回答 1'!$D:$D,$A13) -> 0
A14: 生活品 | B14: =SUM(C14:I14) -> 334820 | C14: =SUMIFS('フォームの回答 1'!$E:$E,'フォームの回答 1'!$B:$B,">="&C1,'フォームの回答 1'!$H:$H,"支出",'フォームの回答 1'!$D:$D,$A14)-SUMIFS('フォームの回答 1'!$E:$E,'フォームの回答 1'!$B:$B,">"&D1,'フォームの回答 1'!$H:$H,"支出",'フォームの回答 1'!$D:$D,$A14) -> 119601 | D14: =SUMIFS('フォームの回答 1'!$E:$E,'フォームの回答 1'!$B:$B,">="&D1,'フォームの回答 1'!$H:$H,"支出",'フォームの回答 1'!$D:$D,$A14)-SUMIFS('フォームの回答 1'!$E:$E,'フォームの回答 1'!$B:$B,">"&E1,'フォームの回答 1'!$H:$H,"支出",'フォームの回答 1'!$D:$D,$A14) -> 28034 | E14: =SUMIFS('フォームの回答 1'!$E:$E,'フォームの回答 1'!$B:$B,">="&E1,'フォームの回答 1'!$H:$H,"支出",'フォームの回答 1'!$D:$D,$A14)-SUMIFS('フォームの回答 1'!$E:$E,'フォームの回答 1'!$B:$B,">"&F1,'フォームの回答 1'!$H:$H,"支出",'フォームの回答 1'!$D:$D,$A14) -> 36354 | F14: =SUMIFS('フォームの回答 1'!$E:$E,'フォームの回答 1'!$B:$B,">="&F1,'フォームの回答 1'!$H:$H,"支出",'フォームの回答 1'!$D:$D,$A14)-SUMIFS('フォームの回答 1'!$E:$E,'フォームの回答 1'!$B:$B,">"&G1,'フォームの回答 1'!$H:$H,"支出",'フォームの回答 1'!$D:$D,$A14) -> 19489 | G14: =SUMIFS('フォームの回答 1'!$E:$E,'フォームの回答 1'!$B:$B,">="&G1,'フォームの回答 1'!$H:$H,"支出",'フォームの回答 1'!$D:$D,$A14)-SUMIFS('フォームの回答 1'!$E:$E,'フォームの回答 1'!$B:$B,">"&H1,'フォームの回答 1'!$H:$H,"支出",'フォームの回答 1'!$D:$D,$A14) -> 51671 | H14: =SUMIFS('フォームの回答 1'!$E:$E,'フォームの回答 1'!$B:$B,">="&H1,'フォームの回答 1'!$H:$H,"支出",'フォームの回答 1'!$D:$D,$A14)-SUMIFS('フォームの回答 1'!$E:$E,'フォームの回答 1'!$B:$B,">"&I1,'フォームの回答 1'!$H:$H,"支出",'フォームの回答 1'!$D:$D,$A14) -> 57047 | I14: =SUMIFS('フォームの回答 1'!$E:$E,'フォームの回答 1'!$B:$B,">="&I1,'フォームの回答 1'!$H:$H,"支出",'フォームの回答 1'!$D:$D,$A14)-SUMIFS('フォームの回答 1'!$E:$E,'フォームの回答 1'!$B:$B,">"&J1,'フォームの回答 1'!$H:$H,"支出",'フォームの回答 1'!$D:$D,$A14) -> 22624 | J14: =SUMIFS('フォームの回答 1'!$E:$E,'フォームの回答 1'!$B:$B,">="&J1,'フォームの回答 1'!$H:$H,"支出",'フォームの回答 1'!$D:$D,$A14)-SUMIFS('フォームの回答 1'!$E:$E,'フォームの回答 1'!$B:$B,">"&K1,'フォームの回答 1'!$H:$H,"支出",'フォームの回答 1'!$D:$D,$A14) -> 30365 | ... N14: =SUMIFS('フォームの回答 1'!$E:$E,'フォームの回答 1'!$B:$B,">="&N1,'フォームの回答 1'!$H:$H,"支出",'フォームの回答 1'!$D:$D,$A14)-SUMIFS('フォームの回答 1'!$E:$E,'フォームの回答 1'!$B:$B,">"&O1,'フォームの回答 1'!$H:$H,"支出",'フォームの回答 1'!$D:$D,$A14) -> 149693
A15: 書籍代 | B15: =SUM(C15:I15) -> 39303 | C15: =SUMIFS('フォームの回答 1'!$E:$E,'フォームの回答 1'!$B:$B,">="&C1,'フォームの回答 1'!$H:$H,"支出",'フォームの回答 1'!$D:$D,$A15)-SUMIFS('フォームの回答 1'!$E:$E,'フォームの回答 1'!$B:$B,">"&D1,'フォームの回答 1'!$H:$H,"支出",'フォームの回答 1'!$D:$D,$A15) -> 3461 | D15: =SUMIFS('フォームの回答 1'!$E:$E,'フォームの回答 1'!$B:$B,">="&D1,'フォームの回答 1'!$H:$H,"支出",'フォームの回答 1'!$D:$D,$A15)-SUMIFS('フォームの回答 1'!$E:$E,'フォームの回答 1'!$B:$B,">"&E1,'フォームの回答 1'!$H:$H,"支出",'フォームの回答 1'!$D:$D,$A15) -> 2937 | E15: =SUMIFS('フォームの回答 1'!$E:$E,'フォームの回答 1'!$B:$B,">="&E1,'フォームの回答 1'!$H:$H,"支出",'フォームの回答 1'!$D:$D,$A15)-SUMIFS('フォームの回答 1'!$E:$E,'フォームの回答 1'!$B:$B,">"&F1,'フォームの回答 1'!$H:$H,"支出",'フォームの回答 1'!$D:$D,$A15) -> 8386 | F15: =SUMIFS('フォームの回答 1'!$E:$E,'フォームの回答 1'!$B:$B,">="&F1,'フォームの回答 1'!$H:$H,"支出",'フォームの回答 1'!$D:$D,$A15)-SUMIFS('フォームの回答 1'!$E:$E,'フォームの回答 1'!$B:$B,">"&G1,'フォームの回答 1'!$H:$H,"支出",'フォームの回答 1'!$D:$D,$A15) -> 5490 | G15: =SUMIFS('フォームの回答 1'!$E:$E,'フォームの回答 1'!$B:$B,">="&G1,'フォームの回答 1'!$H:$H,"支出",'フォームの回答 1'!$D:$D,$A15)-SUMIFS('フォームの回答 1'!$E:$E,'フォームの回答 1'!$B:$B,">"&H1,'フォームの回答 1'!$H:$H,"支出",'フォームの回答 1'!$D:$D,$A15) -> 7907 | H15: =SUMIFS('フォームの回答 1'!$E:$E,'フォームの回答 1'!$B:$B,">="&H1,'フォームの回答 1'!$H:$H,"支出",'フォームの回答 1'!$D:$D,$A15)-SUMIFS('フォームの回答 1'!$E:$E,'フォームの回答 1'!$B:$B,">"&I1,'フォームの回答 1'!$H:$H,"支出",'フォームの回答 1'!$D:$D,$A15) -> 4112 | I15: =SUMIFS('フォームの回答 1'!$E:$E,'フォームの回答 1'!$B:$B,">="&I1,'フォームの回答 1'!$H:$H,"支出",'フォームの回答 1'!$D:$D,$A15)-SUMIFS('フォームの回答 1'!$E:$E,'フォームの回答 1'!$B:$B,">"&J1,'フォームの回答 1'!$H:$H,"支出",'フォームの回答 1'!$D:$D,$A15) -> 7010 | J15: =SUMIFS('フォームの回答 1'!$E:$E,'フォームの回答 1'!$B:$B,">="&J1,'フォームの回答 1'!$H:$H,"支出",'フォームの回答 1'!$D:$D,$A15)-SUMIFS('フォームの回答 1'!$E:$E,'フォームの回答 1'!$B:$B,">"&K1,'フォームの回答 1'!$H:$H,"支出",'フォームの回答 1'!$D:$D,$A15) -> 4312 | ... N15: =SUMIFS('フォームの回答 1'!$E:$E,'フォームの回答 1'!$B:$B,">="&N1,'フォームの回答 1'!$H:$H,"支出",'フォームの回答 1'!$D:$D,$A15)-SUMIFS('フォームの回答 1'!$E:$E,'フォームの回答 1'!$B:$B,">"&O1,'フォームの回答 1'!$H:$H,"支出",'フォームの回答 1'!$D:$D,$A15) -> 38747
A16: 奨学金・ローン返済 | B16: =SUM(C16:I16) -> 509600 | C16: =SUMIFS('フォームの回答 1'!$E:$E,'フォームの回答 1'!$B:$B,">="&C1,'フォームの回答 1'!$H:$H,"支出",'フォームの回答 1'!$D:$D,$A16)-SUMIFS('フォームの回答 1'!$E:$E,'フォームの回答 1'!$B:$B,">"&D1,'フォームの回答 1'!$H:$H,"支出",'フォームの回答 1'!$D:$D,$A16) -> 67000 | D16: =SUMIFS('フォームの回答 1'!$E:$E,'フォームの回答 1'!$B:$B,">="&D1,'フォームの回答 1'!$H:$H,"支出",'フォームの回答 1'!$D:$D,$A16)-SUMIFS('フォームの回答 1'!$E:$E,'フォームの回答 1'!$B:$B,">"&E1,'フォームの回答 1'!$H:$H,"支出",'フォームの回答 1'!$D:$D,$A16) -> 69000 | E16: =SUMIFS('フォームの回答 1'!$E:$E,'フォームの回答 1'!$B:$B,">="&E1,'フォームの回答 1'!$H:$H,"支出",'フォームの回答 1'!$D:$D,$A16)-SUMIFS('フォームの回答 1'!$E:$E,'フォームの回答 1'!$B:$B,">"&F1,'フォームの回答 1'!$H:$H,"支出",'フォームの回答 1'!$D:$D,$A16) -> 67000 | F16: =SUMIFS('フォームの回答 1'!$E:$E,'フォームの回答 1'!$B:$B,">="&F1,'フォームの回答 1'!$H:$H,"支出",'フォームの回答 1'!$D:$D,$A16)-SUMIFS('フォームの回答 1'!$E:$E,'フォームの回答 1'!$B:$B,">"&G1,'フォームの回答 1'!$H:$H,"支出",'フォームの回答 1'!$D:$D,$A16) -> 67000 | G16: =SUMIFS('フォームの回答 1'!$E:$E,'フォームの回答 1'!$B:$B,">="&G1,'フォームの回答 1'!$H:$H,"支出",'フォームの回答 1'!$D:$D,$A16)-SUMIFS('フォームの回答 1'!$E:$E,'フォームの回答 1'!$B:$B,">"&H1,'フォームの回答 1'!$H:$H,"支出",'フォームの回答 1'!$D:$D,$A16) -> 77200 | H16: =SUMIFS('フォームの回答 1'!$E:$E,'フォームの回答 1'!$B:$B,">="&H1,'フォームの回答 1'!$H:$H,"支出",'フォームの回答 1'!$D:$D,$A16)-SUMIFS('フォームの回答 1'!$E:$E,'フォームの回答 1'!$B:$B,">"&I1,'フォームの回答 1'!$H:$H,"支出",'フォームの回答 1'!$D:$D,$A16) -> 81200 | I16: =SUMIFS('フォームの回答 1'!$E:$E,'フォームの回答 1'!$B:$B,">="&I1,'フォームの回答 1'!$H:$H,"支出",'フォームの回答 1'!$D:$D,$A16)-SUMIFS('フォームの回答 1'!$E:$E,'フォームの回答 1'!$B:$B,">"&J1,'フォームの回答 1'!$H:$H,"支出",'フォームの回答 1'!$D:$D,$A16) -> 81200 | J16: =SUMIFS('フォームの回答 1'!$E:$E,'フォームの回答 1'!$B:$B,">="&J1,'フォームの回答 1'!$H:$H,"支出",'フォームの回答 1'!$D:$D,$A16)-SUMIFS('フォームの回答 1'!$E:$E,'フォームの回答 1'!$B:$B,">"&K1,'フォームの回答 1'!$H:$H,"支出",'フォームの回答 1'!$D:$D,$A16) -> 81200 | ... N16: =SUMIFS('フォームの回答 1'!$E:$E,'フォームの回答 1'!$B:$B,">="&N1,'フォームの回答 1'!$H:$H,"支出",'フォームの回答 1'!$D:$D,$A16)-SUMIFS('フォームの回答 1'!$E:$E,'フォームの回答 1'!$B:$B,">"&O1,'フォームの回答 1'!$H:$H,"支出",'フォームの回答 1'!$D:$D,$A16) -> 409400
A17: ツール | B17: =SUM(C17:I17) -> 40637 | C17: =SUMIFS('フォームの回答 1'!$E:$E,'フォームの回答 1'!$B:$B,">="&C1,'フォームの回答 1'!$H:$H,"支出",'フォームの回答 1'!$D:$D,$A17)-SUMIFS('フォームの回答 1'!$E:$E,'フォームの回答 1'!$B:$B,">"&D1,'フォームの回答 1'!$H:$H,"支出",'フォームの回答 1'!$D:$D,$A17) -> 4432 | D17: =SUMIFS('フォームの回答 1'!$E:$E,'フォームの回答 1'!$B:$B,">="&D1,'フォームの回答 1'!$H:$H,"支出",'フォームの回答 1'!$D:$D,$A17)-SUMIFS('フォームの回答 1'!$E:$E,'フォームの回答 1'!$B:$B,">"&E1,'フォームの回答 1'!$H:$H,"支出",'フォームの回答 1'!$D:$D,$A17) -> 4508 | E17: =SUMIFS('フォームの回答 1'!$E:$E,'フォームの回答 1'!$B:$B,">="&E1,'フォームの回答 1'!$H:$H,"支出",'フォームの回答 1'!$D:$D,$A17)-SUMIFS('フォームの回答 1'!$E:$E,'フォームの回答 1'!$B:$B,">"&F1,'フォームの回答 1'!$H:$H,"支出",'フォームの回答 1'!$D:$D,$A17) -> 10467 | F17: =SUMIFS('フォームの回答 1'!$E:$E,'フォームの回答 1'!$B:$B,">="&F1,'フォームの回答 1'!$H:$H,"支出",'フォームの回答 1'!$D:$D,$A17)-SUMIFS('フォームの回答 1'!$E:$E,'フォームの回答 1'!$B:$B,">"&G1,'フォームの回答 1'!$H:$H,"支出",'フォームの回答 1'!$D:$D,$A17) -> 5360 | G17: =SUMIFS('フォームの回答 1'!$E:$E,'フォームの回答 1'!$B:$B,">="&G1,'フォームの回答 1'!$H:$H,"支出",'フォームの回答 1'!$D:$D,$A17)-SUMIFS('フォームの回答 1'!$E:$E,'フォームの回答 1'!$B:$B,">"&H1,'フォームの回答 1'!$H:$H,"支出",'フォームの回答 1'!$D:$D,$A17) -> 4370 | H17: =SUMIFS('フォームの回答 1'!$E:$E,'フォームの回答 1'!$B:$B,">="&H1,'フォームの回答 1'!$H:$H,"支出",'フォームの回答 1'!$D:$D,$A17)-SUMIFS('フォームの回答 1'!$E:$E,'フォームの回答 1'!$B:$B,">"&I1,'フォームの回答 1'!$H:$H,"支出",'フォームの回答 1'!$D:$D,$A17) -> 5919 | I17: =SUMIFS('フォームの回答 1'!$E:$E,'フォームの回答 1'!$B:$B,">="&I1,'フォームの回答 1'!$H:$H,"支出",'フォームの回答 1'!$D:$D,$A17)-SUMIFS('フォームの回答 1'!$E:$E,'フォームの回答 1'!$B:$B,">"&J1,'フォームの回答 1'!$H:$H,"支出",'フォームの回答 1'!$D:$D,$A17) -> 5581 | J17: =SUMIFS('フォームの回答 1'!$E:$E,'フォームの回答 1'!$B:$B,">="&J1,'フォームの回答 1'!$H:$H,"支出",'フォームの回答 1'!$D:$D,$A17)-SUMIFS('フォームの回答 1'!$E:$E,'フォームの回答 1'!$B:$B,">"&K1,'フォームの回答 1'!$H:$H,"支出",'フォームの回答 1'!$D:$D,$A17) -> 4416 | ... N17: =SUMIFS('フォームの回答 1'!$E:$E,'フォームの回答 1'!$B:$B,">="&N1,'フォームの回答 1'!$H:$H,"支出",'フォームの回答 1'!$D:$D,$A17)-SUMIFS('フォームの回答 1'!$E:$E,'フォームの回答 1'!$B:$B,">"&O1,'フォームの回答 1'!$H:$H,"支出",'フォームの回答 1'!$D:$D,$A17) -> 43771
A18: 勉強費 | B18: =SUM(C18:I18) -> 59598 | C18: =SUMIFS('フォームの回答 1'!$E:$E,'フォームの回答 1'!$B:$B,">="&C1,'フォームの回答 1'!$H:$H,"支出",'フォームの回答 1'!$D:$D,$A18)-SUMIFS('フォームの回答 1'!$E:$E,'フォームの回答 1'!$B:$B,">"&D1,'フォームの回答 1'!$H:$H,"支出",'フォームの回答 1'!$D:$D,$A18) -> 9980 | D18: =SUMIFS('フォームの回答 1'!$E:$E,'フォームの回答 1'!$B:$B,">="&D1,'フォームの回答 1'!$H:$H,"支出",'フォームの回答 1'!$D:$D,$A18)-SUMIFS('フォームの回答 1'!$E:$E,'フォームの回答 1'!$B:$B,">"&E1,'フォームの回答 1'!$H:$H,"支出",'フォームの回答 1'!$D:$D,$A18) -> 7480 | E18: =SUMIFS('フォームの回答 1'!$E:$E,'フォームの回答 1'!$B:$B,">="&E1,'フォームの回答 1'!$H:$H,"支出",'フォームの回答 1'!$D:$D,$A18)-SUMIFS('フォームの回答 1'!$E:$E,'フォームの回答 1'!$B:$B,">"&F1,'フォームの回答 1'!$H:$H,"支出",'フォームの回答 1'!$D:$D,$A18) -> 12218 | F18: =SUMIFS('フォームの回答 1'!$E:$E,'フォームの回答 1'!$B:$B,">="&F1,'フォームの回答 1'!$H:$H,"支出",'フォームの回答 1'!$D:$D,$A18)-SUMIFS('フォームの回答 1'!$E:$E,'フォームの回答 1'!$B:$B,">"&G1,'フォームの回答 1'!$H:$H,"支出",'フォームの回答 1'!$D:$D,$A18) -> 10660 | G18: =SUMIFS('フォームの回答 1'!$E:$E,'フォームの回答 1'!$B:$B,">="&G1,'フォームの回答 1'!$H:$H,"支出",'フォームの回答 1'!$D:$D,$A18)-SUMIFS('フォームの回答 1'!$E:$E,'フォームの回答 1'!$B:$B,">"&H1,'フォームの回答 1'!$H:$H,"支出",'フォームの回答 1'!$D:$D,$A18) -> 8480 | H18: =SUMIFS('フォームの回答 1'!$E:$E,'フォームの回答 1'!$B:$B,">="&H1,'フォームの回答 1'!$H:$H,"支出",'フォームの回答 1'!$D:$D,$A18)-SUMIFS('フォームの回答 1'!$E:$E,'フォームの回答 1'!$B:$B,">"&I1,'フォームの回答 1'!$H:$H,"支出",'フォームの回答 1'!$D:$D,$A18) -> 3500 | I18: =SUMIFS('フォームの回答 1'!$E:$E,'フォームの回答 1'!$B:$B,">="&I1,'フォームの回答 1'!$H:$H,"支出",'フォームの回答 1'!$D:$D,$A18)-SUMIFS('フォームの回答 1'!$E:$E,'フォームの回答 1'!$B:$B,">"&J1,'フォームの回答 1'!$H:$H,"支出",'フォームの回答 1'!$D:$D,$A18) -> 7280 | J18: =SUMIFS('フォームの回答 1'!$E:$E,'フォームの回答 1'!$B:$B,">="&J1,'フォームの回答 1'!$H:$H,"支出",'フォームの回答 1'!$D:$D,$A18)-SUMIFS('フォームの回答 1'!$E:$E,'フォームの回答 1'!$B:$B,">"&K1,'フォームの回答 1'!$H:$H,"支出",'フォームの回答 1'!$D:$D,$A18) -> 7280 | ... N18: =SUMIFS('フォームの回答 1'!$E:$E,'フォームの回答 1'!$B:$B,">="&N1,'フォームの回答 1'!$H:$H,"支出",'フォームの回答 1'!$D:$D,$A18)-SUMIFS('フォームの回答 1'!$E:$E,'フォームの回答 1'!$B:$B,">"&O1,'フォームの回答 1'!$H:$H,"支出",'フォームの回答 1'!$D:$D,$A18) -> 31440

Sheet 【Monthly】2026年
B1: 合計金額 | C1: 46023 | D1: 46054 | E1: 46082 | F1: 46113 | G1: 46143 | H1: 46174 | I1: 46204 | J1: 46235 | K1: 46266 | L1: 46296 | M1: 46327 | N1: 46357
A2: 収入 | B2: =SUM(C2:H2) -> 1758140 | C2: =SUMIFS('フォームの回答 1'!$E:$E,'フォームの回答 1'!$B:$B,">="&C1,'フォームの回答 1'!$H:$H,"収入")-SUMIFS('フォームの回答 1'!$E:$E,'フォームの回答 1'!$B:$B,">"&D1,'フォームの回答 1'!$H:$H,"収入") -> 463915 | D2: =SUMIFS('フォームの回答 1'!$E:$E,'フォームの回答 1'!$B:$B,">="&D1,'フォームの回答 1'!$H:$H,"収入")-SUMIFS('フォームの回答 1'!$E:$E,'フォームの回答 1'!$B:$B,">"&E1,'フォームの回答 1'!$H:$H,"収入") -> 425879 | E2: =SUMIFS('フォームの回答 1'!$E:$E,'フォームの回答 1'!$B:$B,">="&E1,'フォームの回答 1'!$H:$H,"収入")-SUMIFS('フォームの回答 1'!$E:$E,'フォームの回答 1'!$B:$B,">"&F1,'フォームの回答 1'!$H:$H,"収入") -> 417513 | F2: =SUMIFS('フォームの回答 1'!$E:$E,'フォームの回答 1'!$B:$B,">="&F1,'フォームの回答 1'!$H:$H,"収入")-SUMIFS('フォームの回答 1'!$E:$E,'フォームの回答 1'!$B:$B,">"&G1,'フォームの回答 1'!$H:$H,"収入") -> 450833 | G2: =SUMIFS('フォームの回答 1'!$E:$E,'フォームの回答 1'!$B:$B,">="&G1,'フォームの回答 1'!$H:$H,"収入")-SUMIFS('フォームの回答 1'!$E:$E,'フォームの回答 1'!$B:$B,">"&H1,'フォームの回答 1'!$H:$H,"収入") -> 0 | H2: =SUMIFS('フォームの回答 1'!$E:$E,'フォームの回答 1'!$B:$B,">="&H1,'フォームの回答 1'!$H:$H,"収入")-SUMIFS('フォームの回答 1'!$E:$E,'フォームの回答 1'!$B:$B,">"&I1,'フォームの回答 1'!$H:$H,"収入") -> 0 | I2: =SUMIFS('フォームの回答 1'!$E:$E,'フォームの回答 1'!$B:$B,">="&I1,'フォームの回答 1'!$H:$H,"収入")-SUMIFS('フォームの回答 1'!$E:$E,'フォームの回答 1'!$B:$B,">"&J1,'フォームの回答 1'!$H:$H,"収入") -> 0 | J2: =SUMIFS('フォームの回答 1'!$E:$E,'フォームの回答 1'!$B:$B,">="&J1,'フォームの回答 1'!$H:$H,"収入")-SUMIFS('フォームの回答 1'!$E:$E,'フォームの回答 1'!$B:$B,">"&K1,'フォームの回答 1'!$H:$H,"収入") -> 0 | ... N2: =SUMIFS('フォームの回答 1'!$E:$E,'フォームの回答 1'!$B:$B,">="&N1,'フォームの回答 1'!$H:$H,"収入")-SUMIFS('フォームの回答 1'!$E:$E,'フォームの回答 1'!$B:$B,">"&O1,'フォームの回答 1'!$H:$H,"収入") -> 0
A3: 支出 | B3: =SUM(C3:H3) -> 1857637 | C3: =SUMIFS('フォームの回答 1'!$E:$E,'フォームの回答 1'!$B:$B,">="&C1,'フォームの回答 1'!$H:$H,"支出")-SUMIFS('フォームの回答 1'!$E:$E,'フォームの回答 1'!$B:$B,">"&D1,'フォームの回答 1'!$H:$H,"支出") -> 445187 | D3: =SUMIFS('フォームの回答 1'!$E:$E,'フォームの回答 1'!$B:$B,">="&D1,'フォームの回答 1'!$H:$H,"支出")-SUMIFS('フォームの回答 1'!$E:$E,'フォームの回答 1'!$B:$B,">"&E1,'フォームの回答 1'!$H:$H,"支出") -> 428664 | E3: =SUMIFS('フォームの回答 1'!$E:$E,'フォームの回答 1'!$B:$B,">="&E1,'フォームの回答 1'!$H:$H,"支出")-SUMIFS('フォームの回答 1'!$E:$E,'フォームの回答 1'!$B:$B,">"&F1,'フォームの回答 1'!$H:$H,"支出") -> 535984 | F3: =SUMIFS('フォームの回答 1'!$E:$E,'フォームの回答 1'!$B:$B,">="&F1,'フォームの回答 1'!$H:$H,"支出")-SUMIFS('フォームの回答 1'!$E:$E,'フォームの回答 1'!$B:$B,">"&G1,'フォームの回答 1'!$H:$H,"支出") -> 447802 | G3: =SUMIFS('フォームの回答 1'!$E:$E,'フォームの回答 1'!$B:$B,">="&G1,'フォームの回答 1'!$H:$H,"支出")-SUMIFS('フォームの回答 1'!$E:$E,'フォームの回答 1'!$B:$B,">"&H1,'フォームの回答 1'!$H:$H,"支出") -> 0 | H3: =SUMIFS('フォームの回答 1'!$E:$E,'フォームの回答 1'!$B:$B,">="&H1,'フォームの回答 1'!$H:$H,"支出")-SUMIFS('フォームの回答 1'!$E:$E,'フォームの回答 1'!$B:$B,">"&I1,'フォームの回答 1'!$H:$H,"支出") -> 0 | I3: =SUMIFS('フォームの回答 1'!$E:$E,'フォームの回答 1'!$B:$B,">="&I1,'フォームの回答 1'!$H:$H,"支出")-SUMIFS('フォームの回答 1'!$E:$E,'フォームの回答 1'!$B:$B,">"&J1,'フォームの回答 1'!$H:$H,"支出") -> 0 | J3: =SUMIFS('フォームの回答 1'!$E:$E,'フォームの回答 1'!$B:$B,">="&J1,'フォームの回答 1'!$H:$H,"支出")-SUMIFS('フォームの回答 1'!$E:$E,'フォームの回答 1'!$B:$B,">"&K1,'フォームの回答 1'!$H:$H,"支出") -> 0 | ... N3: =SUMIFS('フォームの回答 1'!$E:$E,'フォームの回答 1'!$B:$B,">="&N1,'フォームの回答 1'!$H:$H,"支出")-SUMIFS('フォームの回答 1'!$E:$E,'フォームの回答 1'!$B:$B,">"&O1,'フォームの回答 1'!$H:$H,"支出") -> 0
A4: 差額 | B4: =SUM(C4:H4) -> -99497 | C4: =C2-C3 -> 18728 | D4: =D2-D3 -> -2785 | E4: =E2-E3 -> -118471 | F4: =F2-F3 -> 3031 | G4: =G2-G3 -> 0 | H4: =H2-H3 -> 0 | I4: =I2-I3 -> 0 | J4: =J2-J3 -> 0 | ... N4: =N2-N3 -> 0
B5: 内訳
A6: 食費 | B6: =SUM(C6:I6) -> 127244 | C6: =SUMIFS('フォームの回答 1'!$E:$E,'フォームの回答 1'!$B:$B,">="&C1,'フォームの回答 1'!$H:$H,"支出",'フォームの回答 1'!$D:$D,$A6)-SUMIFS('フォームの回答 1'!$E:$E,'フォームの回答 1'!$B:$B,">"&D1,'フォームの回答 1'!$H:$H,"支出",'フォームの回答 1'!$D:$D,$A6) -> 37129 | D6: =SUMIFS('フォームの回答 1'!$E:$E,'フォームの回答 1'!$B:$B,">="&D1,'フォームの回答 1'!$H:$H,"支出",'フォームの回答 1'!$D:$D,$A6)-SUMIFS('フォームの回答 1'!$E:$E,'フォームの回答 1'!$B:$B,">"&E1,'フォームの回答 1'!$H:$H,"支出",'フォームの回答 1'!$D:$D,$A6) -> 26827 | E6: =SUMIFS('フォームの回答 1'!$E:$E,'フォームの回答 1'!$B:$B,">="&E1,'フォームの回答 1'!$H:$H,"支出",'フォームの回答 1'!$D:$D,$A6)-SUMIFS('フォームの回答 1'!$E:$E,'フォームの回答 1'!$B:$B,">"&F1,'フォームの回答 1'!$H:$H,"支出",'フォームの回答 1'!$D:$D,$A6) -> 39943 | F6: =SUMIFS('フォームの回答 1'!$E:$E,'フォームの回答 1'!$B:$B,">="&F1,'フォームの回答 1'!$H:$H,"支出",'フォームの回答 1'!$D:$D,$A6)-SUMIFS('フォームの回答 1'!$E:$E,'フォームの回答 1'!$B:$B,">"&G1,'フォームの回答 1'!$H:$H,"支出",'フォームの回答 1'!$D:$D,$A6) -> 23345 | G6: =SUMIFS('フォームの回答 1'!$E:$E,'フォームの回答 1'!$B:$B,">="&G1,'フォームの回答 1'!$H:$H,"支出",'フォームの回答 1'!$D:$D,$A6)-SUMIFS('フォームの回答 1'!$E:$E,'フォームの回答 1'!$B:$B,">"&H1,'フォームの回答 1'!$H:$H,"支出",'フォームの回答 1'!$D:$D,$A6) -> 0 | H6: =SUMIFS('フォームの回答 1'!$E:$E,'フォームの回答 1'!$B:$B,">="&H1,'フォームの回答 1'!$H:$H,"支出",'フォームの回答 1'!$D:$D,$A6)-SUMIFS('フォームの回答 1'!$E:$E,'フォームの回答 1'!$B:$B,">"&I1,'フォームの回答 1'!$H:$H,"支出",'フォームの回答 1'!$D:$D,$A6) -> 0 | I6: =SUMIFS('フォームの回答 1'!$E:$E,'フォームの回答 1'!$B:$B,">="&I1,'フォームの回答 1'!$H:$H,"支出",'フォームの回答 1'!$D:$D,$A6)-SUMIFS('フォームの回答 1'!$E:$E,'フォームの回答 1'!$B:$B,">"&J1,'フォームの回答 1'!$H:$H,"支出",'フォームの回答 1'!$D:$D,$A6) -> 0 | J6: =SUMIFS('フォームの回答 1'!$E:$E,'フォームの回答 1'!$B:$B,">="&J1,'フォームの回答 1'!$H:$H,"支出",'フォームの回答 1'!$D:$D,$A6)-SUMIFS('フォームの回答 1'!$E:$E,'フォームの回答 1'!$B:$B,">"&K1,'フォームの回答 1'!$H:$H,"支出",'フォームの回答 1'!$D:$D,$A6) -> 0 | ... N6: =SUMIFS('フォームの回答 1'!$E:$E,'フォームの回答 1'!$B:$B,">="&N1,'フォームの回答 1'!$H:$H,"支出",'フォームの回答 1'!$D:$D,$A6)-SUMIFS('フォームの回答 1'!$E:$E,'フォームの回答 1'!$B:$B,">"&O1,'フォームの回答 1'!$H:$H,"支出",'フォームの回答 1'!$D:$D,$A6) -> 0
A7: 外食費 | B7: =SUM(C7:I7) -> 108898 | C7: =SUMIFS('フォームの回答 1'!$E:$E,'フォームの回答 1'!$B:$B,">="&C1,'フォームの回答 1'!$H:$H,"支出",'フォームの回答 1'!$D:$D,$A7)-SUMIFS('フォームの回答 1'!$E:$E,'フォームの回答 1'!$B:$B,">"&D1,'フォームの回答 1'!$H:$H,"支出",'フォームの回答 1'!$D:$D,$A7) -> 20134 | D7: =SUMIFS('フォームの回答 1'!$E:$E,'フォームの回答 1'!$B:$B,">="&D1,'フォームの回答 1'!$H:$H,"支出",'フォームの回答 1'!$D:$D,$A7)-SUMIFS('フォームの回答 1'!$E:$E,'フォームの回答 1'!$B:$B,">"&E1,'フォームの回答 1'!$H:$H,"支出",'フォームの回答 1'!$D:$D,$A7) -> 16690 | E7: =SUMIFS('フォームの回答 1'!$E:$E,'フォームの回答 1'!$B:$B,">="&E1,'フォームの回答 1'!$H:$H,"支出",'フォームの回答 1'!$D:$D,$A7)-SUMIFS('フォームの回答 1'!$E:$E,'フォームの回答 1'!$B:$B,">"&F1,'フォームの回答 1'!$H:$H,"支出",'フォームの回答 1'!$D:$D,$A7) -> 21560 | F7: =SUMIFS('フォームの回答 1'!$E:$E,'フォームの回答 1'!$B:$B,">="&F1,'フォームの回答 1'!$H:$H,"支出",'フォームの回答 1'!$D:$D,$A7)-SUMIFS('フォームの回答 1'!$E:$E,'フォームの回答 1'!$B:$B,">"&G1,'フォームの回答 1'!$H:$H,"支出",'フォームの回答 1'!$D:$D,$A7) -> 50514 | G7: =SUMIFS('フォームの回答 1'!$E:$E,'フォームの回答 1'!$B:$B,">="&G2,'フォームの回答 1'!$H:$H,"支出",'フォームの回答 1'!$D:$D,$A7)-SUMIFS('フォームの回答 1'!$E:$E,'フォームの回答 1'!$B:$B,">"&H2,'フォームの回答 1'!$H:$H,"支出",'フォームの回答 1'!$D:$D,$A7) -> 0 | H7: =SUMIFS('フォームの回答 1'!$E:$E,'フォームの回答 1'!$B:$B,">="&H2,'フォームの回答 1'!$H:$H,"支出",'フォームの回答 1'!$D:$D,$A7)-SUMIFS('フォームの回答 1'!$E:$E,'フォームの回答 1'!$B:$B,">"&I2,'フォームの回答 1'!$H:$H,"支出",'フォームの回答 1'!$D:$D,$A7) -> 0 | I7: =SUMIFS('フォームの回答 1'!$E:$E,'フォームの回答 1'!$B:$B,">="&I2,'フォームの回答 1'!$H:$H,"支出",'フォームの回答 1'!$D:$D,$A7)-SUMIFS('フォームの回答 1'!$E:$E,'フォームの回答 1'!$B:$B,">"&J2,'フォームの回答 1'!$H:$H,"支出",'フォームの回答 1'!$D:$D,$A7) -> 0 | J7: =SUMIFS('フォームの回答 1'!$E:$E,'フォームの回答 1'!$B:$B,">="&J2,'フォームの回答 1'!$H:$H,"支出",'フォームの回答 1'!$D:$D,$A7)-SUMIFS('フォームの回答 1'!$E:$E,'フォームの回答 1'!$B:$B,">"&K2,'フォームの回答 1'!$H:$H,"支出",'フォームの回答 1'!$D:$D,$A7) -> 0 | K7: =SUMIFS('フォームの回答 1'!$E:$E,'フォームの回答 1'!$B:$B,">="&K2,'フォームの回答 1'!$H:$H,"支出",'フォームの回答 1'!$D:$D,$A7)-SUMIFS('フォームの回答 1'!$E:$E,'フォームの回答 1'!$B:$B,">"&L2,'フォームの回答 1'!$H:$H,"支出",'フォームの回答 1'!$D:$D,$A7) -> 0 | L7: =SUMIFS('フォームの回答 1'!$E:$E,'フォームの回答 1'!$B:$B,">="&L2,'フォームの回答 1'!$H:$H,"支出",'フォームの回答 1'!$D:$D,$A7)-SUMIFS('フォームの回答 1'!$E:$E,'フォームの回答 1'!$B:$B,">"&M2,'フォームの回答 1'!$H:$H,"支出",'フォームの回答 1'!$D:$D,$A7) -> 0 | M7: =SUMIFS('フォームの回答 1'!$E:$E,'フォームの回答 1'!$B:$B,">="&M2,'フォームの回答 1'!$H:$H,"支出",'フォームの回答 1'!$D:$D,$A7)-SUMIFS('フォームの回答 1'!$E:$E,'フォームの回答 1'!$B:$B,">"&N2,'フォームの回答 1'!$H:$H,"支出",'フォームの回答 1'!$D:$D,$A7) -> 0 | N7: =SUMIFS('フォームの回答 1'!$E:$E,'フォームの回答 1'!$B:$B,">="&N2,'フォームの回答 1'!$H:$H,"支出",'フォームの回答 1'!$D:$D,$A7)-SUMIFS('フォームの回答 1'!$E:$E,'フォームの回答 1'!$B:$B,">"&O2,'フォームの回答 1'!$H:$H,"支出",'フォームの回答 1'!$D:$D,$A7) -> 104668
A8: 接待交際費 | B8: =SUM(C8:I8) -> 260820 | C8: =SUMIFS('フォームの回答 1'!$E:$E,'フォームの回答 1'!$B:$B,">="&C1,'フォームの回答 1'!$H:$H,"支出",'フォームの回答 1'!$D:$D,$A8)-SUMIFS('フォームの回答 1'!$E:$E,'フォームの回答 1'!$B:$B,">"&D1,'フォームの回答 1'!$H:$H,"支出",'フォームの回答 1'!$D:$D,$A8) -> 57610 | D8: =SUMIFS('フォームの回答 1'!$E:$E,'フォームの回答 1'!$B:$B,">="&D1,'フォームの回答 1'!$H:$H,"支出",'フォームの回答 1'!$D:$D,$A8)-SUMIFS('フォームの回答 1'!$E:$E,'フォームの回答 1'!$B:$B,">"&E1,'フォームの回答 1'!$H:$H,"支出",'フォームの回答 1'!$D:$D,$A8) -> 64563 | E8: =SUMIFS('フォームの回答 1'!$E:$E,'フォームの回答 1'!$B:$B,">="&E1,'フォームの回答 1'!$H:$H,"支出",'フォームの回答 1'!$D:$D,$A8)-SUMIFS('フォームの回答 1'!$E:$E,'フォームの回答 1'!$B:$B,">"&F1,'フォームの回答 1'!$H:$H,"支出",'フォームの回答 1'!$D:$D,$A8) -> 103406 | F8: =SUMIFS('フォームの回答 1'!$E:$E,'フォームの回答 1'!$B:$B,">="&F1,'フォームの回答 1'!$H:$H,"支出",'フォームの回答 1'!$D:$D,$A8)-SUMIFS('フォームの回答 1'!$E:$E,'フォームの回答 1'!$B:$B,">"&G1,'フォームの回答 1'!$H:$H,"支出",'フォームの回答 1'!$D:$D,$A8) -> 35241 | G8: =SUMIFS('フォームの回答 1'!$E:$E,'フォームの回答 1'!$B:$B,">="&G1,'フォームの回答 1'!$H:$H,"支出",'フォームの回答 1'!$D:$D,$A8)-SUMIFS('フォームの回答 1'!$E:$E,'フォームの回答 1'!$B:$B,">"&H1,'フォームの回答 1'!$H:$H,"支出",'フォームの回答 1'!$D:$D,$A8) -> 0 | H8: =SUMIFS('フォームの回答 1'!$E:$E,'フォームの回答 1'!$B:$B,">="&H1,'フォームの回答 1'!$H:$H,"支出",'フォームの回答 1'!$D:$D,$A8)-SUMIFS('フォームの回答 1'!$E:$E,'フォームの回答 1'!$B:$B,">"&I1,'フォームの回答 1'!$H:$H,"支出",'フォームの回答 1'!$D:$D,$A8) -> 0 | I8: =SUMIFS('フォームの回答 1'!$E:$E,'フォームの回答 1'!$B:$B,">="&I1,'フォームの回答 1'!$H:$H,"支出",'フォームの回答 1'!$D:$D,$A8)-SUMIFS('フォームの回答 1'!$E:$E,'フォームの回答 1'!$B:$B,">"&J1,'フォームの回答 1'!$H:$H,"支出",'フォームの回答 1'!$D:$D,$A8) -> 0 | J8: =SUMIFS('フォームの回答 1'!$E:$E,'フォームの回答 1'!$B:$B,">="&J1,'フォームの回答 1'!$H:$H,"支出",'フォームの回答 1'!$D:$D,$A8)-SUMIFS('フォームの回答 1'!$E:$E,'フォームの回答 1'!$B:$B,">"&K1,'フォームの回答 1'!$H:$H,"支出",'フォームの回答 1'!$D:$D,$A8) -> 0 | ... N8: =SUMIFS('フォームの回答 1'!$E:$E,'フォームの回答 1'!$B:$B,">="&N1,'フォームの回答 1'!$H:$H,"支出",'フォームの回答 1'!$D:$D,$A8)-SUMIFS('フォームの回答 1'!$E:$E,'フォームの回答 1'!$B:$B,">"&O1,'フォームの回答 1'!$H:$H,"支出",'フォームの回答 1'!$D:$D,$A8) -> 0
A9: 娯楽費 | B9: =SUM(C9:I9) -> -32820 | C9: =SUMIFS('フォームの回答 1'!$E:$E,'フォームの回答 1'!$B:$B,">="&C1,'フォームの回答 1'!$H:$H,"支出",'フォームの回答 1'!$D:$D,$A9)-SUMIFS('フォームの回答 1'!$E:$E,'フォームの回答 1'!$B:$B,">"&D1,'フォームの回答 1'!$H:$H,"支出",'フォームの回答 1'!$D:$D,$A9) -> 24695 | D9: =SUMIFS('フォームの回答 1'!$E:$E,'フォームの回答 1'!$B:$B,">="&D1,'フォームの回答 1'!$H:$H,"支出",'フォームの回答 1'!$D:$D,$A9)-SUMIFS('フォームの回答 1'!$E:$E,'フォームの回答 1'!$B:$B,">"&E1,'フォームの回答 1'!$H:$H,"支出",'フォームの回答 1'!$D:$D,$A9) -> 12670 | E9: =SUMIFS('フォームの回答 1'!$E:$E,'フォームの回答 1'!$B:$B,">="&E2,'フォームの回答 1'!$H:$H,"支出",'フォームの回答 1'!$D:$D,$A9)-SUMIFS('フォームの回答 1'!$E:$E,'フォームの回答 1'!$B:$B,">"&F2,'フォームの回答 1'!$H:$H,"支出",'フォームの回答 1'!$D:$D,$A9) -> 0 | F9: =SUMIFS('フォームの回答 1'!$E:$E,'フォームの回答 1'!$B:$B,">="&F2,'フォームの回答 1'!$H:$H,"支出",'フォームの回答 1'!$D:$D,$A9)-SUMIFS('フォームの回答 1'!$E:$E,'フォームの回答 1'!$B:$B,">"&G2,'フォームの回答 1'!$H:$H,"支出",'フォームの回答 1'!$D:$D,$A9) -> -70185 | G9: =SUMIFS('フォームの回答 1'!$E:$E,'フォームの回答 1'!$B:$B,">="&G2,'フォームの回答 1'!$H:$H,"支出",'フォームの回答 1'!$D:$D,$A9)-SUMIFS('フォームの回答 1'!$E:$E,'フォームの回答 1'!$B:$B,">"&H2,'フォームの回答 1'!$H:$H,"支出",'フォームの回答 1'!$D:$D,$A9) -> 0 | H9: =SUMIFS('フォームの回答 1'!$E:$E,'フォームの回答 1'!$B:$B,">="&H2,'フォームの回答 1'!$H:$H,"支出",'フォームの回答 1'!$D:$D,$A9)-SUMIFS('フォームの回答 1'!$E:$E,'フォームの回答 1'!$B:$B,">"&I2,'フォームの回答 1'!$H:$H,"支出",'フォームの回答 1'!$D:$D,$A9) -> 0 | I9: =SUMIFS('フォームの回答 1'!$E:$E,'フォームの回答 1'!$B:$B,">="&I2,'フォームの回答 1'!$H:$H,"支出",'フォームの回答 1'!$D:$D,$A9)-SUMIFS('フォームの回答 1'!$E:$E,'フォームの回答 1'!$B:$B,">"&J2,'フォームの回答 1'!$H:$H,"支出",'フォームの回答 1'!$D:$D,$A9) -> 0 | J9: =SUMIFS('フォームの回答 1'!$E:$E,'フォームの回答 1'!$B:$B,">="&J2,'フォームの回答 1'!$H:$H,"支出",'フォームの回答 1'!$D:$D,$A9)-SUMIFS('フォームの回答 1'!$E:$E,'フォームの回答 1'!$B:$B,">"&K2,'フォームの回答 1'!$H:$H,"支出",'フォームの回答 1'!$D:$D,$A9) -> 0 | K9: =SUMIFS('フォームの回答 1'!$E:$E,'フォームの回答 1'!$B:$B,">="&K2,'フォームの回答 1'!$H:$H,"支出",'フォームの回答 1'!$D:$D,$A9)-SUMIFS('フォームの回答 1'!$E:$E,'フォームの回答 1'!$B:$B,">"&L2,'フォームの回答 1'!$H:$H,"支出",'フォームの回答 1'!$D:$D,$A9) -> 0 | L9: =SUMIFS('フォームの回答 1'!$E:$E,'フォームの回答 1'!$B:$B,">="&L2,'フォームの回答 1'!$H:$H,"支出",'フォームの回答 1'!$D:$D,$A9)-SUMIFS('フォームの回答 1'!$E:$E,'フォームの回答 1'!$B:$B,">"&M2,'フォームの回答 1'!$H:$H,"支出",'フォームの回答 1'!$D:$D,$A9) -> 0 | ... N9: =SUMIFS('フォームの回答 1'!$E:$E,'フォームの回答 1'!$B:$B,">="&N2,'フォームの回答 1'!$H:$H,"支出",'フォームの回答 1'!$D:$D,$A9)-SUMIFS('フォームの回答 1'!$E:$E,'フォームの回答 1'!$B:$B,">"&O2,'フォームの回答 1'!$H:$H,"支出",'フォームの回答 1'!$D:$D,$A9) -> 70185
A10: 交通費 | B10: =SUM(C10:I10) -> 173147 | C10: =SUMIFS('フォームの回答 1'!$E:$E,'フォームの回答 1'!$B:$B,">="&C1,'フォームの回答 1'!$H:$H,"支出",'フォームの回答 1'!$D:$D,$A10)-SUMIFS('フォームの回答 1'!$E:$E,'フォームの回答 1'!$B:$B,">"&D1,'フォームの回答 1'!$H:$H,"支出",'フォームの回答 1'!$D:$D,$A10) -> 33949 | D10: =SUMIFS('フォームの回答 1'!$E:$E,'フォームの回答 1'!$B:$B,">="&D1,'フォームの回答 1'!$H:$H,"支出",'フォームの回答 1'!$D:$D,$A10)-SUMIFS('フォームの回答 1'!$E:$E,'フォームの回答 1'!$B:$B,">"&E1,'フォームの回答 1'!$H:$H,"支出",'フォームの回答 1'!$D:$D,$A10) -> 25188 | E10: =SUMIFS('フォームの回答 1'!$E:$E,'フォームの回答 1'!$B:$B,">="&E1,'フォームの回答 1'!$H:$H,"支出",'フォームの回答 1'!$D:$D,$A10)-SUMIFS('フォームの回答 1'!$E:$E,'フォームの回答 1'!$B:$B,">"&F1,'フォームの回答 1'!$H:$H,"支出",'フォームの回答 1'!$D:$D,$A10) -> 65620 | F10: =SUMIFS('フォームの回答 1'!$E:$E,'フォームの回答 1'!$B:$B,">="&F1,'フォームの回答 1'!$H:$H,"支出",'フォームの回答 1'!$D:$D,$A10)-SUMIFS('フォームの回答 1'!$E:$E,'フォームの回答 1'!$B:$B,">"&G1,'フォームの回答 1'!$H:$H,"支出",'フォームの回答 1'!$D:$D,$A10) -> 48390 | G10: =SUMIFS('フォームの回答 1'!$E:$E,'フォームの回答 1'!$B:$B,">="&G1,'フォームの回答 1'!$H:$H,"支出",'フォームの回答 1'!$D:$D,$A10)-SUMIFS('フォームの回答 1'!$E:$E,'フォームの回答 1'!$B:$B,">"&H1,'フォームの回答 1'!$H:$H,"支出",'フォームの回答 1'!$D:$D,$A10) -> 0 | H10: =SUMIFS('フォームの回答 1'!$E:$E,'フォームの回答 1'!$B:$B,">="&H1,'フォームの回答 1'!$H:$H,"支出",'フォームの回答 1'!$D:$D,$A10)-SUMIFS('フォームの回答 1'!$E:$E,'フォームの回答 1'!$B:$B,">"&I1,'フォームの回答 1'!$H:$H,"支出",'フォームの回答 1'!$D:$D,$A10) -> 0 | I10: =SUMIFS('フォームの回答 1'!$E:$E,'フォームの回答 1'!$B:$B,">="&I1,'フォームの回答 1'!$H:$H,"支出",'フォームの回答 1'!$D:$D,$A10)-SUMIFS('フォームの回答 1'!$E:$E,'フォームの回答 1'!$B:$B,">"&J1,'フォームの回答 1'!$H:$H,"支出",'フォームの回答 1'!$D:$D,$A10) -> 0 | J10: =SUMIFS('フォームの回答 1'!$E:$E,'フォームの回答 1'!$B:$B,">="&J1,'フォームの回答 1'!$H:$H,"支出",'フォームの回答 1'!$D:$D,$A10)-SUMIFS('フォームの回答 1'!$E:$E,'フォームの回答 1'!$B:$B,">"&K1,'フォームの回答 1'!$H:$H,"支出",'フォームの回答 1'!$D:$D,$A10) -> 0 | ... N10: =SUMIFS('フォームの回答 1'!$E:$E,'フォームの回答 1'!$B:$B,">="&N1,'フォームの回答 1'!$H:$H,"支出",'フォームの回答 1'!$D:$D,$A10)-SUMIFS('フォームの回答 1'!$E:$E,'フォームの回答 1'!$B:$B,">"&O1,'フォームの回答 1'!$H:$H,"支出",'フォームの回答 1'!$D:$D,$A10) -> 0
A11: 光熱費 | B11: =SUM(C11:I11) -> 62364 | C11: =SUMIFS('フォームの回答 1'!$E:$E,'フォームの回答 1'!$B:$B,">="&C1,'フォームの回答 1'!$H:$H,"支出",'フォームの回答 1'!$D:$D,$A11)-SUMIFS('フォームの回答 1'!$E:$E,'フォームの回答 1'!$B:$B,">"&D1,'フォームの回答 1'!$H:$H,"支出",'フォームの回答 1'!$D:$D,$A11) -> 11352 | D11: =SUMIFS('フォームの回答 1'!$E:$E,'フォームの回答 1'!$B:$B,">="&D1,'フォームの回答 1'!$H:$H,"支出",'フォームの回答 1'!$D:$D,$A11)-SUMIFS('フォームの回答 1'!$E:$E,'フォームの回答 1'!$B:$B,">"&E1,'フォームの回答 1'!$H:$H,"支出",'フォームの回答 1'!$D:$D,$A11) -> 16702 | E11: =SUMIFS('フォームの回答 1'!$E:$E,'フォームの回答 1'!$B:$B,">="&E1,'フォームの回答 1'!$H:$H,"支出",'フォームの回答 1'!$D:$D,$A11)-SUMIFS('フォームの回答 1'!$E:$E,'フォームの回答 1'!$B:$B,">"&F1,'フォームの回答 1'!$H:$H,"支出",'フォームの回答 1'!$D:$D,$A11) -> 19554 | F11: =SUMIFS('フォームの回答 1'!$E:$E,'フォームの回答 1'!$B:$B,">="&F1,'フォームの回答 1'!$H:$H,"支出",'フォームの回答 1'!$D:$D,$A11)-SUMIFS('フォームの回答 1'!$E:$E,'フォームの回答 1'!$B:$B,">"&G1,'フォームの回答 1'!$H:$H,"支出",'フォームの回答 1'!$D:$D,$A11) -> 14756 | G11: =SUMIFS('フォームの回答 1'!$E:$E,'フォームの回答 1'!$B:$B,">="&G1,'フォームの回答 1'!$H:$H,"支出",'フォームの回答 1'!$D:$D,$A11)-SUMIFS('フォームの回答 1'!$E:$E,'フォームの回答 1'!$B:$B,">"&H1,'フォームの回答 1'!$H:$H,"支出",'フォームの回答 1'!$D:$D,$A11) -> 0 | H11: =SUMIFS('フォームの回答 1'!$E:$E,'フォームの回答 1'!$B:$B,">="&H1,'フォームの回答 1'!$H:$H,"支出",'フォームの回答 1'!$D:$D,$A11)-SUMIFS('フォームの回答 1'!$E:$E,'フォームの回答 1'!$B:$B,">"&I1,'フォームの回答 1'!$H:$H,"支出",'フォームの回答 1'!$D:$D,$A11) -> 0 | I11: =SUMIFS('フォームの回答 1'!$E:$E,'フォームの回答 1'!$B:$B,">="&I1,'フォームの回答 1'!$H:$H,"支出",'フォームの回答 1'!$D:$D,$A11)-SUMIFS('フォームの回答 1'!$E:$E,'フォームの回答 1'!$B:$B,">"&J1,'フォームの回答 1'!$H:$H,"支出",'フォームの回答 1'!$D:$D,$A11) -> 0 | J11: =SUMIFS('フォームの回答 1'!$E:$E,'フォームの回答 1'!$B:$B,">="&J1,'フォームの回答 1'!$H:$H,"支出",'フォームの回答 1'!$D:$D,$A11)-SUMIFS('フォームの回答 1'!$E:$E,'フォームの回答 1'!$B:$B,">"&K1,'フォームの回答 1'!$H:$H,"支出",'フォームの回答 1'!$D:$D,$A11) -> 0 | ... N11: =SUMIFS('フォームの回答 1'!$E:$E,'フォームの回答 1'!$B:$B,">="&N1,'フォームの回答 1'!$H:$H,"支出",'フォームの回答 1'!$D:$D,$A11)-SUMIFS('フォームの回答 1'!$E:$E,'フォームの回答 1'!$B:$B,">"&O1,'フォームの回答 1'!$H:$H,"支出",'フォームの回答 1'!$D:$D,$A11) -> 0
A12: スマホ代 | B12: =SUM(C12:I12) -> 29126 | C12: =SUMIFS('フォームの回答 1'!$E:$E,'フォームの回答 1'!$B:$B,">="&C1,'フォームの回答 1'!$H:$H,"支出",'フォームの回答 1'!$D:$D,$A12)-SUMIFS('フォームの回答 1'!$E:$E,'フォームの回答 1'!$B:$B,">"&D1,'フォームの回答 1'!$H:$H,"支出",'フォームの回答 1'!$D:$D,$A12) -> 5652 | D12: =SUMIFS('フォームの回答 1'!$E:$E,'フォームの回答 1'!$B:$B,">="&D1,'フォームの回答 1'!$H:$H,"支出",'フォームの回答 1'!$D:$D,$A12)-SUMIFS('フォームの回答 1'!$E:$E,'フォームの回答 1'!$B:$B,">"&E1,'フォームの回答 1'!$H:$H,"支出",'フォームの回答 1'!$D:$D,$A12) -> 6974 | E12: =SUMIFS('フォームの回答 1'!$E:$E,'フォームの回答 1'!$B:$B,">="&E1,'フォームの回答 1'!$H:$H,"支出",'フォームの回答 1'!$D:$D,$A12)-SUMIFS('フォームの回答 1'!$E:$E,'フォームの回答 1'!$B:$B,">"&F1,'フォームの回答 1'!$H:$H,"支出",'フォームの回答 1'!$D:$D,$A12) -> 8910 | F12: =SUMIFS('フォームの回答 1'!$E:$E,'フォームの回答 1'!$B:$B,">="&F1,'フォームの回答 1'!$H:$H,"支出",'フォームの回答 1'!$D:$D,$A12)-SUMIFS('フォームの回答 1'!$E:$E,'フォームの回答 1'!$B:$B,">"&G1,'フォームの回答 1'!$H:$H,"支出",'フォームの回答 1'!$D:$D,$A12) -> 7590 | G12: =SUMIFS('フォームの回答 1'!$E:$E,'フォームの回答 1'!$B:$B,">="&G1,'フォームの回答 1'!$H:$H,"支出",'フォームの回答 1'!$D:$D,$A12)-SUMIFS('フォームの回答 1'!$E:$E,'フォームの回答 1'!$B:$B,">"&H1,'フォームの回答 1'!$H:$H,"支出",'フォームの回答 1'!$D:$D,$A12) -> 0 | H12: =SUMIFS('フォームの回答 1'!$E:$E,'フォームの回答 1'!$B:$B,">="&H1,'フォームの回答 1'!$H:$H,"支出",'フォームの回答 1'!$D:$D,$A12)-SUMIFS('フォームの回答 1'!$E:$E,'フォームの回答 1'!$B:$B,">"&I1,'フォームの回答 1'!$H:$H,"支出",'フォームの回答 1'!$D:$D,$A12) -> 0 | I12: =SUMIFS('フォームの回答 1'!$E:$E,'フォームの回答 1'!$B:$B,">="&I1,'フォームの回答 1'!$H:$H,"支出",'フォームの回答 1'!$D:$D,$A12)-SUMIFS('フォームの回答 1'!$E:$E,'フォームの回答 1'!$B:$B,">"&J1,'フォームの回答 1'!$H:$H,"支出",'フォームの回答 1'!$D:$D,$A12) -> 0 | J12: =SUMIFS('フォームの回答 1'!$E:$E,'フォームの回答 1'!$B:$B,">="&J1,'フォームの回答 1'!$H:$H,"支出",'フォームの回答 1'!$D:$D,$A12)-SUMIFS('フォームの回答 1'!$E:$E,'フォームの回答 1'!$B:$B,">"&K1,'フォームの回答 1'!$H:$H,"支出",'フォームの回答 1'!$D:$D,$A12) -> 0 | ... N12: =SUMIFS('フォームの回答 1'!$E:$E,'フォームの回答 1'!$B:$B,">="&N1,'フォームの回答 1'!$H:$H,"支出",'フォームの回答 1'!$D:$D,$A12)-SUMIFS('フォームの回答 1'!$E:$E,'フォームの回答 1'!$B:$B,">"&O1,'フォームの回答 1'!$H:$H,"支出",'フォームの回答 1'!$D:$D,$A12) -> 0
A13: 家賃 | B13: =SUM(C13:I13) -> 372000 | C13: =SUMIFS('フォームの回答 1'!$E:$E,'フォームの回答 1'!$B:$B,">="&C1,'フォームの回答 1'!$H:$H,"支出",'フォームの回答 1'!$D:$D,$A13)-SUMIFS('フォームの回答 1'!$E:$E,'フォームの回答 1'!$B:$B,">"&D1,'フォームの回答 1'!$H:$H,"支出",'フォームの回答 1'!$D:$D,$A13) -> 93000 | D13: =SUMIFS('フォームの回答 1'!$E:$E,'フォームの回答 1'!$B:$B,">="&D1,'フォームの回答 1'!$H:$H,"支出",'フォームの回答 1'!$D:$D,$A13)-SUMIFS('フォームの回答 1'!$E:$E,'フォームの回答 1'!$B:$B,">"&E1,'フォームの回答 1'!$H:$H,"支出",'フォームの回答 1'!$D:$D,$A13) -> 93000 | E13: =SUMIFS('フォームの回答 1'!$E:$E,'フォームの回答 1'!$B:$B,">="&E1,'フォームの回答 1'!$H:$H,"支出",'フォームの回答 1'!$D:$D,$A13)-SUMIFS('フォームの回答 1'!$E:$E,'フォームの回答 1'!$B:$B,">"&F1,'フォームの回答 1'!$H:$H,"支出",'フォームの回答 1'!$D:$D,$A13) -> 93000 | F13: =SUMIFS('フォームの回答 1'!$E:$E,'フォームの回答 1'!$B:$B,">="&F1,'フォームの回答 1'!$H:$H,"支出",'フォームの回答 1'!$D:$D,$A13)-SUMIFS('フォームの回答 1'!$E:$E,'フォームの回答 1'!$B:$B,">"&G1,'フォームの回答 1'!$H:$H,"支出",'フォームの回答 1'!$D:$D,$A13) -> 93000 | G13: =SUMIFS('フォームの回答 1'!$E:$E,'フォームの回答 1'!$B:$B,">="&G1,'フォームの回答 1'!$H:$H,"支出",'フォームの回答 1'!$D:$D,$A13)-SUMIFS('フォームの回答 1'!$E:$E,'フォームの回答 1'!$B:$B,">"&H1,'フォームの回答 1'!$H:$H,"支出",'フォームの回答 1'!$D:$D,$A13) -> 0 | H13: =SUMIFS('フォームの回答 1'!$E:$E,'フォームの回答 1'!$B:$B,">="&H1,'フォームの回答 1'!$H:$H,"支出",'フォームの回答 1'!$D:$D,$A13)-SUMIFS('フォームの回答 1'!$E:$E,'フォームの回答 1'!$B:$B,">"&I1,'フォームの回答 1'!$H:$H,"支出",'フォームの回答 1'!$D:$D,$A13) -> 0 | I13: =SUMIFS('フォームの回答 1'!$E:$E,'フォームの回答 1'!$B:$B,">="&I1,'フォームの回答 1'!$H:$H,"支出",'フォームの回答 1'!$D:$D,$A13)-SUMIFS('フォームの回答 1'!$E:$E,'フォームの回答 1'!$B:$B,">"&J1,'フォームの回答 1'!$H:$H,"支出",'フォームの回答 1'!$D:$D,$A13) -> 0 | J13: =SUMIFS('フォームの回答 1'!$E:$E,'フォームの回答 1'!$B:$B,">="&J1,'フォームの回答 1'!$H:$H,"支出",'フォームの回答 1'!$D:$D,$A13)-SUMIFS('フォームの回答 1'!$E:$E,'フォームの回答 1'!$B:$B,">"&K1,'フォームの回答 1'!$H:$H,"支出",'フォームの回答 1'!$D:$D,$A13) -> 0 | ... N13: =SUMIFS('フォームの回答 1'!$E:$E,'フォームの回答 1'!$B:$B,">="&N1,'フォームの回答 1'!$H:$H,"支出",'フォームの回答 1'!$D:$D,$A13)-SUMIFS('フォームの回答 1'!$E:$E,'フォームの回答 1'!$B:$B,">"&O1,'フォームの回答 1'!$H:$H,"支出",'フォームの回答 1'!$D:$D,$A13) -> 0
A14: 医療費 | B14: =SUM(C14:I14) -> 1097 | C14: =SUMIFS('フォームの回答 1'!$E:$E,'フォームの回答 1'!$B:$B,">="&C1,'フォームの回答 1'!$H:$H,"支出",'フォームの回答 1'!$D:$D,$A14)-SUMIFS('フォームの回答 1'!$E:$E,'フォームの回答 1'!$B:$B,">"&D1,'フォームの回答 1'!$H:$H,"支出",'フォームの回答 1'!$D:$D,$A14) -> 0 | D14: =SUMIFS('フォームの回答 1'!$E:$E,'フォームの回答 1'!$B:$B,">="&D1,'フォームの回答 1'!$H:$H,"支出",'フォームの回答 1'!$D:$D,$A14)-SUMIFS('フォームの回答 1'!$E:$E,'フォームの回答 1'!$B:$B,">"&E1,'フォームの回答 1'!$H:$H,"支出",'フォームの回答 1'!$D:$D,$A14) -> 0 | E14: =SUMIFS('フォームの回答 1'!$E:$E,'フォームの回答 1'!$B:$B,">="&E1,'フォームの回答 1'!$H:$H,"支出",'フォームの回答 1'!$D:$D,$A14)-SUMIFS('フォームの回答 1'!$E:$E,'フォームの回答 1'!$B:$B,">"&F1,'フォームの回答 1'!$H:$H,"支出",'フォームの回答 1'!$D:$D,$A14) -> 0 | F14: =SUMIFS('フォームの回答 1'!$E:$E,'フォームの回答 1'!$B:$B,">="&F1,'フォームの回答 1'!$H:$H,"支出",'フォームの回答 1'!$D:$D,$A14)-SUMIFS('フォームの回答 1'!$E:$E,'フォームの回答 1'!$B:$B,">"&G1,'フォームの回答 1'!$H:$H,"支出",'フォームの回答 1'!$D:$D,$A14) -> 1097 | G14: =SUMIFS('フォームの回答 1'!$E:$E,'フォームの回答 1'!$B:$B,">="&G1,'フォームの回答 1'!$H:$H,"支出",'フォームの回答 1'!$D:$D,$A14)-SUMIFS('フォームの回答 1'!$E:$E,'フォームの回答 1'!$B:$B,">"&H1,'フォームの回答 1'!$H:$H,"支出",'フォームの回答 1'!$D:$D,$A14) -> 0 | H14: =SUMIFS('フォームの回答 1'!$E:$E,'フォームの回答 1'!$B:$B,">="&H1,'フォームの回答 1'!$H:$H,"支出",'フォームの回答 1'!$D:$D,$A14)-SUMIFS('フォームの回答 1'!$E:$E,'フォームの回答 1'!$B:$B,">"&I1,'フォームの回答 1'!$H:$H,"支出",'フォームの回答 1'!$D:$D,$A14) -> 0 | I14: =SUMIFS('フォームの回答 1'!$E:$E,'フォームの回答 1'!$B:$B,">="&I1,'フォームの回答 1'!$H:$H,"支出",'フォームの回答 1'!$D:$D,$A14)-SUMIFS('フォームの回答 1'!$E:$E,'フォームの回答 1'!$B:$B,">"&J1,'フォームの回答 1'!$H:$H,"支出",'フォームの回答 1'!$D:$D,$A14) -> 0 | J14: =SUMIFS('フォームの回答 1'!$E:$E,'フォームの回答 1'!$B:$B,">="&J1,'フォームの回答 1'!$H:$H,"支出",'フォームの回答 1'!$D:$D,$A14)-SUMIFS('フォームの回答 1'!$E:$E,'フォームの回答 1'!$B:$B,">"&K1,'フォームの回答 1'!$H:$H,"支出",'フォームの回答 1'!$D:$D,$A14) -> 0 | ... N14: =SUMIFS('フォームの回答 1'!$E:$E,'フォームの回答 1'!$B:$B,">="&N1,'フォームの回答 1'!$H:$H,"支出",'フォームの回答 1'!$D:$D,$A14)-SUMIFS('フォームの回答 1'!$E:$E,'フォームの回答 1'!$B:$B,">"&O1,'フォームの回答 1'!$H:$H,"支出",'フォームの回答 1'!$D:$D,$A14) -> 0
A15: 服 | B15: =SUM(C15:I15) -> 0 | C15: =SUMIFS('フォームの回答 1'!$E:$E,'フォームの回答 1'!$B:$B,">="&C1,'フォームの回答 1'!$H:$H,"支出",'フォームの回答 1'!$D:$D,$A15)-SUMIFS('フォームの回答 1'!$E:$E,'フォームの回答 1'!$B:$B,">"&D1,'フォームの回答 1'!$H:$H,"支出",'フォームの回答 1'!$D:$D,$A15) -> 0 | D15: =SUMIFS('フォームの回答 1'!$E:$E,'フォームの回答 1'!$B:$B,">="&D1,'フォームの回答 1'!$H:$H,"支出",'フォームの回答 1'!$D:$D,$A15)-SUMIFS('フォームの回答 1'!$E:$E,'フォームの回答 1'!$B:$B,">"&E1,'フォームの回答 1'!$H:$H,"支出",'フォームの回答 1'!$D:$D,$A15) -> 0 | E15: =SUMIFS('フォームの回答 1'!$E:$E,'フォームの回答 1'!$B:$B,">="&E1,'フォームの回答 1'!$H:$H,"支出",'フォームの回答 1'!$D:$D,$A15)-SUMIFS('フォームの回答 1'!$E:$E,'フォームの回答 1'!$B:$B,">"&F1,'フォームの回答 1'!$H:$H,"支出",'フォームの回答 1'!$D:$D,$A15) -> 0 | F15: =SUMIFS('フォームの回答 1'!$E:$E,'フォームの回答 1'!$B:$B,">="&F1,'フォームの回答 1'!$H:$H,"支出",'フォームの回答 1'!$D:$D,$A15)-SUMIFS('フォームの回答 1'!$E:$E,'フォームの回答 1'!$B:$B,">"&G1,'フォームの回答 1'!$H:$H,"支出",'フォームの回答 1'!$D:$D,$A15) -> 0 | G15: =SUMIFS('フォームの回答 1'!$E:$E,'フォームの回答 1'!$B:$B,">="&G1,'フォームの回答 1'!$H:$H,"支出",'フォームの回答 1'!$D:$D,$A15)-SUMIFS('フォームの回答 1'!$E:$E,'フォームの回答 1'!$B:$B,">"&H1,'フォームの回答 1'!$H:$H,"支出",'フォームの回答 1'!$D:$D,$A15) -> 0 | H15: =SUMIFS('フォームの回答 1'!$E:$E,'フォームの回答 1'!$B:$B,">="&H1,'フォームの回答 1'!$H:$H,"支出",'フォームの回答 1'!$D:$D,$A15)-SUMIFS('フォームの回答 1'!$E:$E,'フォームの回答 1'!$B:$B,">"&I1,'フォームの回答 1'!$H:$H,"支出",'フォームの回答 1'!$D:$D,$A15) -> 0 | I15: =SUMIFS('フォームの回答 1'!$E:$E,'フォームの回答 1'!$B:$B,">="&I1,'フォームの回答 1'!$H:$H,"支出",'フォームの回答 1'!$D:$D,$A15)-SUMIFS('フォームの回答 1'!$E:$E,'フォームの回答 1'!$B:$B,">"&J1,'フォームの回答 1'!$H:$H,"支出",'フォームの回答 1'!$D:$D,$A15) -> 0 | J15: =SUMIFS('フォームの回答 1'!$E:$E,'フォームの回答 1'!$B:$B,">="&J1,'フォームの回答 1'!$H:$H,"支出",'フォームの回答 1'!$D:$D,$A15)-SUMIFS('フォームの回答 1'!$E:$E,'フォームの回答 1'!$B:$B,">"&K1,'フォームの回答 1'!$H:$H,"支出",'フォームの回答 1'!$D:$D,$A15) -> 0 | ... N15: =SUMIFS('フォームの回答 1'!$E:$E,'フォームの回答 1'!$B:$B,">="&N1,'フォームの回答 1'!$H:$H,"支出",'フォームの回答 1'!$D:$D,$A15)-SUMIFS('フォームの回答 1'!$E:$E,'フォームの回答 1'!$B:$B,">"&O1,'フォームの回答 1'!$H:$H,"支出",'フォームの回答 1'!$D:$D,$A15) -> 0
A16: 生活品 | B16: =SUM(C16:I16) -> 117240 | C16: =SUMIFS('フォームの回答 1'!$E:$E,'フォームの回答 1'!$B:$B,">="&C1,'フォームの回答 1'!$H:$H,"支出",'フォームの回答 1'!$D:$D,$A16)-SUMIFS('フォームの回答 1'!$E:$E,'フォームの回答 1'!$B:$B,">"&D1,'フォームの回答 1'!$H:$H,"支出",'フォームの回答 1'!$D:$D,$A16) -> 30280 | D16: =SUMIFS('フォームの回答 1'!$E:$E,'フォームの回答 1'!$B:$B,">="&D1,'フォームの回答 1'!$H:$H,"支出",'フォームの回答 1'!$D:$D,$A16)-SUMIFS('フォームの回答 1'!$E:$E,'フォームの回答 1'!$B:$B,">"&E1,'フォームの回答 1'!$H:$H,"支出",'フォームの回答 1'!$D:$D,$A16) -> 36715 | E16: =SUMIFS('フォームの回答 1'!$E:$E,'フォームの回答 1'!$B:$B,">="&E1,'フォームの回答 1'!$H:$H,"支出",'フォームの回答 1'!$D:$D,$A16)-SUMIFS('フォームの回答 1'!$E:$E,'フォームの回答 1'!$B:$B,">"&F1,'フォームの回答 1'!$H:$H,"支出",'フォームの回答 1'!$D:$D,$A16) -> 31256 | F16: =SUMIFS('フォームの回答 1'!$E:$E,'フォームの回答 1'!$B:$B,">="&F1,'フォームの回答 1'!$H:$H,"支出",'フォームの回答 1'!$D:$D,$A16)-SUMIFS('フォームの回答 1'!$E:$E,'フォームの回答 1'!$B:$B,">"&G1,'フォームの回答 1'!$H:$H,"支出",'フォームの回答 1'!$D:$D,$A16) -> 18989 | G16: =SUMIFS('フォームの回答 1'!$E:$E,'フォームの回答 1'!$B:$B,">="&G1,'フォームの回答 1'!$H:$H,"支出",'フォームの回答 1'!$D:$D,$A16)-SUMIFS('フォームの回答 1'!$E:$E,'フォームの回答 1'!$B:$B,">"&H1,'フォームの回答 1'!$H:$H,"支出",'フォームの回答 1'!$D:$D,$A16) -> 0 | H16: =SUMIFS('フォームの回答 1'!$E:$E,'フォームの回答 1'!$B:$B,">="&H1,'フォームの回答 1'!$H:$H,"支出",'フォームの回答 1'!$D:$D,$A16)-SUMIFS('フォームの回答 1'!$E:$E,'フォームの回答 1'!$B:$B,">"&I1,'フォームの回答 1'!$H:$H,"支出",'フォームの回答 1'!$D:$D,$A16) -> 0 | I16: =SUMIFS('フォームの回答 1'!$E:$E,'フォームの回答 1'!$B:$B,">="&I1,'フォームの回答 1'!$H:$H,"支出",'フォームの回答 1'!$D:$D,$A16)-SUMIFS('フォームの回答 1'!$E:$E,'フォームの回答 1'!$B:$B,">"&J1,'フォームの回答 1'!$H:$H,"支出",'フォームの回答 1'!$D:$D,$A16) -> 0 | J16: =SUMIFS('フォームの回答 1'!$E:$E,'フォームの回答 1'!$B:$B,">="&J1,'フォームの回答 1'!$H:$H,"支出",'フォームの回答 1'!$D:$D,$A16)-SUMIFS('フォームの回答 1'!$E:$E,'フォームの回答 1'!$B:$B,">"&K1,'フォームの回答 1'!$H:$H,"支出",'フォームの回答 1'!$D:$D,$A16) -> 0 | ... N16: =SUMIFS('フォームの回答 1'!$E:$E,'フォームの回答 1'!$B:$B,">="&N1,'フォームの回答 1'!$H:$H,"支出",'フォームの回答 1'!$D:$D,$A16)-SUMIFS('フォームの回答 1'!$E:$E,'フォームの回答 1'!$B:$B,">"&O1,'フォームの回答 1'!$H:$H,"支出",'フォームの回答 1'!$D:$D,$A16) -> 0
A17: 書籍代 | B17: =SUM(C17:I17) -> 34947 | C17: =SUMIFS('フォームの回答 1'!$E:$E,'フォームの回答 1'!$B:$B,">="&C1,'フォームの回答 1'!$H:$H,"支出",'フォームの回答 1'!$D:$D,$A17)-SUMIFS('フォームの回答 1'!$E:$E,'フォームの回答 1'!$B:$B,">"&D1,'フォームの回答 1'!$H:$H,"支出",'フォームの回答 1'!$D:$D,$A17) -> 13782 | D17: =SUMIFS('フォームの回答 1'!$E:$E,'フォームの回答 1'!$B:$B,">="&D1,'フォームの回答 1'!$H:$H,"支出",'フォームの回答 1'!$D:$D,$A17)-SUMIFS('フォームの回答 1'!$E:$E,'フォームの回答 1'!$B:$B,">"&E1,'フォームの回答 1'!$H:$H,"支出",'フォームの回答 1'!$D:$D,$A17) -> 7810 | E17: =SUMIFS('フォームの回答 1'!$E:$E,'フォームの回答 1'!$B:$B,">="&E1,'フォームの回答 1'!$H:$H,"支出",'フォームの回答 1'!$D:$D,$A17)-SUMIFS('フォームの回答 1'!$E:$E,'フォームの回答 1'!$B:$B,">"&F1,'フォームの回答 1'!$H:$H,"支出",'フォームの回答 1'!$D:$D,$A17) -> 6380 | F17: =SUMIFS('フォームの回答 1'!$E:$E,'フォームの回答 1'!$B:$B,">="&F1,'フォームの回答 1'!$H:$H,"支出",'フォームの回答 1'!$D:$D,$A17)-SUMIFS('フォームの回答 1'!$E:$E,'フォームの回答 1'!$B:$B,">"&G1,'フォームの回答 1'!$H:$H,"支出",'フォームの回答 1'!$D:$D,$A17) -> 6975 | G17: =SUMIFS('フォームの回答 1'!$E:$E,'フォームの回答 1'!$B:$B,">="&G1,'フォームの回答 1'!$H:$H,"支出",'フォームの回答 1'!$D:$D,$A17)-SUMIFS('フォームの回答 1'!$E:$E,'フォームの回答 1'!$B:$B,">"&H1,'フォームの回答 1'!$H:$H,"支出",'フォームの回答 1'!$D:$D,$A17) -> 0 | H17: =SUMIFS('フォームの回答 1'!$E:$E,'フォームの回答 1'!$B:$B,">="&H1,'フォームの回答 1'!$H:$H,"支出",'フォームの回答 1'!$D:$D,$A17)-SUMIFS('フォームの回答 1'!$E:$E,'フォームの回答 1'!$B:$B,">"&I1,'フォームの回答 1'!$H:$H,"支出",'フォームの回答 1'!$D:$D,$A17) -> 0 | I17: =SUMIFS('フォームの回答 1'!$E:$E,'フォームの回答 1'!$B:$B,">="&I1,'フォームの回答 1'!$H:$H,"支出",'フォームの回答 1'!$D:$D,$A17)-SUMIFS('フォームの回答 1'!$E:$E,'フォームの回答 1'!$B:$B,">"&J1,'フォームの回答 1'!$H:$H,"支出",'フォームの回答 1'!$D:$D,$A17) -> 0 | J17: =SUMIFS('フォームの回答 1'!$E:$E,'フォームの回答 1'!$B:$B,">="&J1,'フォームの回答 1'!$H:$H,"支出",'フォームの回答 1'!$D:$D,$A17)-SUMIFS('フォームの回答 1'!$E:$E,'フォームの回答 1'!$B:$B,">"&K1,'フォームの回答 1'!$H:$H,"支出",'フォームの回答 1'!$D:$D,$A17) -> 0 | ... N17: =SUMIFS('フォームの回答 1'!$E:$E,'フォームの回答 1'!$B:$B,">="&N1,'フォームの回答 1'!$H:$H,"支出",'フォームの回答 1'!$D:$D,$A17)-SUMIFS('フォームの回答 1'!$E:$E,'フォームの回答 1'!$B:$B,">"&O1,'フォームの回答 1'!$H:$H,"支出",'フォームの回答 1'!$D:$D,$A17) -> 0
A18: 奨学金・ローン返済 | B18: =SUM(C18:I18) -> 326400 | C18: =SUMIFS('フォームの回答 1'!$E:$E,'フォームの回答 1'!$B:$B,">="&C1,'フォームの回答 1'!$H:$H,"支出",'フォームの回答 1'!$D:$D,$A18)-SUMIFS('フォームの回答 1'!$E:$E,'フォームの回答 1'!$B:$B,">"&D1,'フォームの回答 1'!$H:$H,"支出",'フォームの回答 1'!$D:$D,$A18) -> 81600 | D18: =SUMIFS('フォームの回答 1'!$E:$E,'フォームの回答 1'!$B:$B,">="&D1,'フォームの回答 1'!$H:$H,"支出",'フォームの回答 1'!$D:$D,$A18)-SUMIFS('フォームの回答 1'!$E:$E,'フォームの回答 1'!$B:$B,">"&E1,'フォームの回答 1'!$H:$H,"支出",'フォームの回答 1'!$D:$D,$A18) -> 81600 | E18: =SUMIFS('フォームの回答 1'!$E:$E,'フォームの回答 1'!$B:$B,">="&E1,'フォームの回答 1'!$H:$H,"支出",'フォームの回答 1'!$D:$D,$A18)-SUMIFS('フォームの回答 1'!$E:$E,'フォームの回答 1'!$B:$B,">"&F1,'フォームの回答 1'!$H:$H,"支出",'フォームの回答 1'!$D:$D,$A18) -> 81600 | F18: =SUMIFS('フォームの回答 1'!$E:$E,'フォームの回答 1'!$B:$B,">="&F1,'フォームの回答 1'!$H:$H,"支出",'フォームの回答 1'!$D:$D,$A18)-SUMIFS('フォームの回答 1'!$E:$E,'フォームの回答 1'!$B:$B,">"&G1,'フォームの回答 1'!$H:$H,"支出",'フォームの回答 1'!$D:$D,$A18) -> 81600 | G18: =SUMIFS('フォームの回答 1'!$E:$E,'フォームの回答 1'!$B:$B,">="&G1,'フォームの回答 1'!$H:$H,"支出",'フォームの回答 1'!$D:$D,$A18)-SUMIFS('フォームの回答 1'!$E:$E,'フォームの回答 1'!$B:$B,">"&H1,'フォームの回答 1'!$H:$H,"支出",'フォームの回答 1'!$D:$D,$A18) -> 0 | H18: =SUMIFS('フォームの回答 1'!$E:$E,'フォームの回答 1'!$B:$B,">="&H1,'フォームの回答 1'!$H:$H,"支出",'フォームの回答 1'!$D:$D,$A18)-SUMIFS('フォームの回答 1'!$E:$E,'フォームの回答 1'!$B:$B,">"&I1,'フォームの回答 1'!$H:$H,"支出",'フォームの回答 1'!$D:$D,$A18) -> 0 | I18: =SUMIFS('フォームの回答 1'!$E:$E,'フォームの回答 1'!$B:$B,">="&I1,'フォームの回答 1'!$H:$H,"支出",'フォームの回答 1'!$D:$D,$A18)-SUMIFS('フォームの回答 1'!$E:$E,'フォームの回答 1'!$B:$B,">"&J1,'フォームの回答 1'!$H:$H,"支出",'フォームの回答 1'!$D:$D,$A18) -> 0 | J18: =SUMIFS('フォームの回答 1'!$E:$E,'フォームの回答 1'!$B:$B,">="&J1,'フォームの回答 1'!$H:$H,"支出",'フォームの回答 1'!$D:$D,$A18)-SUMIFS('フォームの回答 1'!$E:$E,'フォームの回答 1'!$B:$B,">"&K1,'フォームの回答 1'!$H:$H,"支出",'フォームの回答 1'!$D:$D,$A18) -> 0 | ... N18: =SUMIFS('フォームの回答 1'!$E:$E,'フォームの回答 1'!$B:$B,">="&N1,'フォームの回答 1'!$H:$H,"支出",'フォームの回答 1'!$D:$D,$A18)-SUMIFS('フォームの回答 1'!$E:$E,'フォームの回答 1'!$B:$B,">"&O1,'フォームの回答 1'!$H:$H,"支出",'フォームの回答 1'!$D:$D,$A18) -> 0
A19: ツール | B19: =SUM(C19:I19) -> 37499 | C19: =SUMIFS('フォームの回答 1'!$E:$E,'フォームの回答 1'!$B:$B,">="&C1,'フォームの回答 1'!$H:$H,"支出",'フォームの回答 1'!$D:$D,$A19)-SUMIFS('フォームの回答 1'!$E:$E,'フォームの回答 1'!$B:$B,">"&D1,'フォームの回答 1'!$H:$H,"支出",'フォームの回答 1'!$D:$D,$A19) -> 8468 | D19: =SUMIFS('フォームの回答 1'!$E:$E,'フォームの回答 1'!$B:$B,">="&D1,'フォームの回答 1'!$H:$H,"支出",'フォームの回答 1'!$D:$D,$A19)-SUMIFS('フォームの回答 1'!$E:$E,'フォームの回答 1'!$B:$B,">"&E1,'フォームの回答 1'!$H:$H,"支出",'フォームの回答 1'!$D:$D,$A19) -> 8341 | E19: =SUMIFS('フォームの回答 1'!$E:$E,'フォームの回答 1'!$B:$B,">="&E1,'フォームの回答 1'!$H:$H,"支出",'フォームの回答 1'!$D:$D,$A19)-SUMIFS('フォームの回答 1'!$E:$E,'フォームの回答 1'!$B:$B,">"&F1,'フォームの回答 1'!$H:$H,"支出",'フォームの回答 1'!$D:$D,$A19) -> 14580 | F19: =SUMIFS('フォームの回答 1'!$E:$E,'フォームの回答 1'!$B:$B,">="&F1,'フォームの回答 1'!$H:$H,"支出",'フォームの回答 1'!$D:$D,$A19)-SUMIFS('フォームの回答 1'!$E:$E,'フォームの回答 1'!$B:$B,">"&G1,'フォームの回答 1'!$H:$H,"支出",'フォームの回答 1'!$D:$D,$A19) -> 6110 | G19: =SUMIFS('フォームの回答 1'!$E:$E,'フォームの回答 1'!$B:$B,">="&G1,'フォームの回答 1'!$H:$H,"支出",'フォームの回答 1'!$D:$D,$A19)-SUMIFS('フォームの回答 1'!$E:$E,'フォームの回答 1'!$B:$B,">"&H1,'フォームの回答 1'!$H:$H,"支出",'フォームの回答 1'!$D:$D,$A19) -> 0 | H19: =SUMIFS('フォームの回答 1'!$E:$E,'フォームの回答 1'!$B:$B,">="&H1,'フォームの回答 1'!$H:$H,"支出",'フォームの回答 1'!$D:$D,$A19)-SUMIFS('フォームの回答 1'!$E:$E,'フォームの回答 1'!$B:$B,">"&I1,'フォームの回答 1'!$H:$H,"支出",'フォームの回答 1'!$D:$D,$A19) -> 0 | I19: =SUMIFS('フォームの回答 1'!$E:$E,'フォームの回答 1'!$B:$B,">="&I1,'フォームの回答 1'!$H:$H,"支出",'フォームの回答 1'!$D:$D,$A19)-SUMIFS('フォームの回答 1'!$E:$E,'フォームの回答 1'!$B:$B,">"&J1,'フォームの回答 1'!$H:$H,"支出",'フォームの回答 1'!$D:$D,$A19) -> 0 | J19: =SUMIFS('フォームの回答 1'!$E:$E,'フォームの回答 1'!$B:$B,">="&J1,'フォームの回答 1'!$H:$H,"支出",'フォームの回答 1'!$D:$D,$A19)-SUMIFS('フォームの回答 1'!$E:$E,'フォームの回答 1'!$B:$B,">"&K1,'フォームの回答 1'!$H:$H,"支出",'フォームの回答 1'!$D:$D,$A19) -> 0 | ... N19: =SUMIFS('フォームの回答 1'!$E:$E,'フォームの回答 1'!$B:$B,">="&N1,'フォームの回答 1'!$H:$H,"支出",'フォームの回答 1'!$D:$D,$A19)-SUMIFS('フォームの回答 1'!$E:$E,'フォームの回答 1'!$B:$B,">"&O1,'フォームの回答 1'!$H:$H,"支出",'フォームの回答 1'!$D:$D,$A19) -> 0
A20: 勉強費 | B20: =SUM(C20:I20) -> 20260 | C20: =SUMIFS('フォームの回答 1'!$E:$E,'フォームの回答 1'!$B:$B,">="&C1,'フォームの回答 1'!$H:$H,"支出",'フォームの回答 1'!$D:$D,$A20)-SUMIFS('フォームの回答 1'!$E:$E,'フォームの回答 1'!$B:$B,">"&D1,'フォームの回答 1'!$H:$H,"支出",'フォームの回答 1'!$D:$D,$A20) -> 7980 | D20: =SUMIFS('フォームの回答 1'!$E:$E,'フォームの回答 1'!$B:$B,">="&D1,'フォームの回答 1'!$H:$H,"支出",'フォームの回答 1'!$D:$D,$A20)-SUMIFS('フォームの回答 1'!$E:$E,'フォームの回答 1'!$B:$B,">"&E1,'フォームの回答 1'!$H:$H,"支出",'フォームの回答 1'!$D:$D,$A20) -> 7980 | E20: =SUMIFS('フォームの回答 1'!$E:$E,'フォームの回答 1'!$B:$B,">="&E1,'フォームの回答 1'!$H:$H,"支出",'フォームの回答 1'!$D:$D,$A20)-SUMIFS('フォームの回答 1'!$E:$E,'フォームの回答 1'!$B:$B,">"&F1,'フォームの回答 1'!$H:$H,"支出",'フォームの回答 1'!$D:$D,$A20) -> 2500 | F20: =SUMIFS('フォームの回答 1'!$E:$E,'フォームの回答 1'!$B:$B,">="&F1,'フォームの回答 1'!$H:$H,"支出",'フォームの回答 1'!$D:$D,$A20)-SUMIFS('フォームの回答 1'!$E:$E,'フォームの回答 1'!$B:$B,">"&G1,'フォームの回答 1'!$H:$H,"支出",'フォームの回答 1'!$D:$D,$A20) -> 1800 | G20: =SUMIFS('フォームの回答 1'!$E:$E,'フォームの回答 1'!$B:$B,">="&G1,'フォームの回答 1'!$H:$H,"支出",'フォームの回答 1'!$D:$D,$A20)-SUMIFS('フォームの回答 1'!$E:$E,'フォームの回答 1'!$B:$B,">"&H1,'フォームの回答 1'!$H:$H,"支出",'フォームの回答 1'!$D:$D,$A20) -> 0 | H20: =SUMIFS('フォームの回答 1'!$E:$E,'フォームの回答 1'!$B:$B,">="&H1,'フォームの回答 1'!$H:$H,"支出",'フォームの回答 1'!$D:$D,$A20)-SUMIFS('フォームの回答 1'!$E:$E,'フォームの回答 1'!$B:$B,">"&I1,'フォームの回答 1'!$H:$H,"支出",'フォームの回答 1'!$D:$D,$A20) -> 0 | I20: =SUMIFS('フォームの回答 1'!$E:$E,'フォームの回答 1'!$B:$B,">="&I1,'フォームの回答 1'!$H:$H,"支出",'フォームの回答 1'!$D:$D,$A20)-SUMIFS('フォームの回答 1'!$E:$E,'フォームの回答 1'!$B:$B,">"&J1,'フォームの回答 1'!$H:$H,"支出",'フォームの回答 1'!$D:$D,$A20) -> 0 | J20: =SUMIFS('フォームの回答 1'!$E:$E,'フォームの回答 1'!$B:$B,">="&J1,'フォームの回答 1'!$H:$H,"支出",'フォームの回答 1'!$D:$D,$A20)-SUMIFS('フォームの回答 1'!$E:$E,'フォームの回答 1'!$B:$B,">"&K1,'フォームの回答 1'!$H:$H,"支出",'フォームの回答 1'!$D:$D,$A20) -> 0 | ... N20: =SUMIFS('フォームの回答 1'!$E:$E,'フォームの回答 1'!$B:$B,">="&N1,'フォームの回答 1'!$H:$H,"支出",'フォームの回答 1'!$D:$D,$A20)-SUMIFS('フォームの回答 1'!$E:$E,'フォームの回答 1'!$B:$B,">"&O1,'フォームの回答 1'!$H:$H,"支出",'フォームの回答 1'!$D:$D,$A20) -> 0

Sheet 【Daily】2024年
B1: 1月
B2: 合計金額 | C2: 45292 | D2: 45293 | E2: 45294 | F2: 45295 | G2: 45296 | H2: 45297 | I2: 45298 | J2: 45299 | K2: 45300 | L2: 45301 | M2: 45302 | N2: 45303 | O2: 45304 | P2: 45305 | Q2: 45306 | R2: 45307 | S2: 45308 | T2: 45309 | U2: 45310 | V2: 45311 | W2: 45312 | X2: 45313 | Y2: 45314 | Z2: 45315 | AA2: 45316 | AB2: 45317 | AC2: 45318 | AD2: 45319 | AE2: 45320 | AF2: 45321 | AG2: 45322 | AI2: 1月クレジット引き落とし
A3: 収入 | B3: =SUM(V3:AG3) -> 322710 | C3: =SUMIFS('フォームの回答 1'!$E:$E,'フォームの回答 1'!$B:$B,C2,'フォームの回答 1'!$H:$H,$A3) -> 0 | D3: =SUMIFS('フォームの回答 1'!$E:$E,'フォームの回答 1'!$B:$B,D2,'フォームの回答 1'!$H:$H,$A3) -> 0 | E3: =SUMIFS('フォームの回答 1'!$E:$E,'フォームの回答 1'!$B:$B,E2,'フォームの回答 1'!$H:$H,$A3) -> 0 | F3: =SUMIFS('フォームの回答 1'!$E:$E,'フォームの回答 1'!$B:$B,F2,'フォームの回答 1'!$H:$H,$A3) -> 8600 | G3: =SUMIFS('フォームの回答 1'!$E:$E,'フォームの回答 1'!$B:$B,G2,'フォームの回答 1'!$H:$H,$A3) -> 0 | H3: =SUMIFS('フォームの回答 1'!$E:$E,'フォームの回答 1'!$B:$B,H2,'フォームの回答 1'!$H:$H,$A3) -> 0 | I3: =SUMIFS('フォームの回答 1'!$E:$E,'フォームの回答 1'!$B:$B,I2,'フォームの回答 1'!$H:$H,$A3) -> 2010 | J3: =SUMIFS('フォームの回答 1'!$E:$E,'フォームの回答 1'!$B:$B,J2,'フォームの回答 1'!$H:$H,$A3) -> 0 | ... AG3: =SUMIFS('フォームの回答 1'!$E:$E,'フォームの回答 1'!$B:$B,AG2,'フォームの回答 1'!$H:$H,$A3) -> 30000 | AI3: =161547 -> 161547
A4: 支出 | B4: =SUM(V4:AG4) -> 363205 | C4: =SUMIFS('フォームの回答 1'!$E:$E,'フォームの回答 1'!$B:$B,C2,'フォームの回答 1'!$H:$H,$A4,'フォームの回答 1'!$F:$F,"Cash") -> 1616 | D4: =SUMIFS('フォームの回答 1'!$E:$E,'フォームの回答 1'!$B:$B,D2,'フォームの回答 1'!$H:$H,$A4,'フォームの回答 1'!$F:$F,"Cash") -> 2270 | E4: =SUMIFS('フォームの回答 1'!$E:$E,'フォームの回答 1'!$B:$B,E2,'フォームの回答 1'!$H:$H,$A4,'フォームの回答 1'!$F:$F,"Cash") -> 22641 | F4: =SUMIFS('フォームの回答 1'!$E:$E,'フォームの回答 1'!$B:$B,F2,'フォームの回答 1'!$H:$H,$A4,'フォームの回答 1'!$F:$F,"Cash") -> 5569 | G4: =SUMIFS('フォームの回答 1'!$E:$E,'フォームの回答 1'!$B:$B,G2,'フォームの回答 1'!$H:$H,$A4,'フォームの回答 1'!$F:$F,"Cash") -> 11848 | H4: =SUMIFS('フォームの回答 1'!$E:$E,'フォームの回答 1'!$B:$B,H2,'フォームの回答 1'!$H:$H,$A4,'フォームの回答 1'!$F:$F,"Cash") -> 1295 | I4: =SUMIFS('フォームの回答 1'!$E:$E,'フォームの回答 1'!$B:$B,I2,'フォームの回答 1'!$H:$H,$A4,'フォームの回答 1'!$F:$F,"Cash") -> 2540 | J4: =SUMIFS('フォームの回答 1'!$E:$E,'フォームの回答 1'!$B:$B,J2,'フォームの回答 1'!$H:$H,$A4,'フォームの回答 1'!$F:$F,"Cash") -> 4160 | ... AB4: =SUMIFS('フォームの回答 1'!$E:$E,'フォームの回答 1'!$B:$B,AB2,'フォームの回答 1'!$H:$H,$A4,'フォームの回答 1'!$F:$F,"Cash") -> 31506 | AC4: =SUMIFS('フォームの回答 1'!$E:$E,'フォームの回答 1'!$B:$B,AC2,'フォームの回答 1'!$H:$H,$A4,'フォームの回答 1'!$F:$F,"Cash")+AI3 -> 169227 | AD4: =SUMIFS('フォームの回答 1'!$E:$E,'フォームの回答 1'!$B:$B,AD2,'フォームの回答 1'!$H:$H,$A4,'フォームの回答 1'!$F:$F,"Cash") -> 2673 | AE4: =SUMIFS('フォームの回答 1'!$E:$E,'フォームの回答 1'!$B:$B,AE2,'フォームの回答 1'!$H:$H,$A4,'フォームの回答 1'!$F:$F,"Cash") -> 145804 | AF4: =SUMIFS('フォームの回答 1'!$E:$E,'フォームの回答 1'!$B:$B,AF2,'フォームの回答 1'!$H:$H,$A4,'フォームの回答 1'!$F:$F,"Cash") -> 1000 | AG4: =SUMIFS('フォームの回答 1'!$E:$E,'フォームの回答 1'!$B:$B,AG2,'フォームの回答 1'!$H:$H,$A4,'フォームの回答 1'!$F:$F,"Cash") -> 1646
A5: 残高 | C5: =【Daily】2023年!AG35+C3-C4 -> 53654 | D5: =C5+D3-D4 -> 51384 | E5: =D5+E3-E4 -> 28743 | F5: =E5+F3-F4 -> 31774 | G5: =F5+G3-G4 -> 19926 | H5: =G5+H3-H4 -> 18631 | I5: =H5+I3-I4 -> 18101 | J5: =I5+J3-J4 -> 13941 | K5: =J5+K3-K4 -> 27961 | ... AG5: =AF5+AG3-AG4 -> 31209
B7: 2月
B8: 合計金額 | C8: 45323 | D8: 45324 | E8: 45325 | F8: 45326 | G8: 45327 | H8: 45328 | I8: 45329 | J8: 45330 | K8: 45331 | L8: 45332 | M8: 45333 | N8: 45334 | O8: 45335 | P8: 45336 | Q8: 45337 | R8: 45338 | S8: 45339 | T8: 45340 | U8: 45341 | V8: 45342 | W8: 45343 | X8: 45344 | Y8: 45345 | Z8: 45346 | AA8: 45347 | AB8: 45348 | AC8: 45349 | AD8: 45350 | AE8: 45351 | AI8: 2月クレジット引き落とし
A9: 収入 | B9: =SUM(V9:AG9) -> 377823 | C9: =SUMIFS('フォームの回答 1'!$E:$E,'フォームの回答 1'!$B:$B,C8,'フォームの回答 1'!$H:$H,$A9) -> 0 | D9: =SUMIFS('フォームの回答 1'!$E:$E,'フォームの回答 1'!$B:$B,D8,'フォームの回答 1'!$H:$H,$A9) -> 0 | E9: =SUMIFS('フォームの回答 1'!$E:$E,'フォームの回答 1'!$B:$B,E8,'フォームの回答 1'!$H:$H,$A9) -> 0 | F9: =SUMIFS('フォームの回答 1'!$E:$E,'フォームの回答 1'!$B:$B,F8,'フォームの回答 1'!$H:$H,$A9) -> 0 | G9: =SUMIFS('フォームの回答 1'!$E:$E,'フォームの回答 1'!$B:$B,G8,'フォームの回答 1'!$H:$H,$A9) -> 0 | H9: =SUMIFS('フォームの回答 1'!$E:$E,'フォームの回答 1'!$B:$B,H8,'フォームの回答 1'!$H:$H,$A9) -> 78070 | I9: =SUMIFS('フォームの回答 1'!$E:$E,'フォームの回答 1'!$B:$B,I8,'フォームの回答 1'!$H:$H,$A9) -> 0 | J9: =SUMIFS('フォームの回答 1'!$E:$E,'フォームの回答 1'!$B:$B,J8,'フォームの回答 1'!$H:$H,$A9) -> 0 | ... U9: =SUMIFS('フォームの回答 1'!$E:$E,'フォームの回答 1'!$B:$B,U8,'フォームの回答 1'!$H:$H,$A9) -> 0 | V9: =SUMIFS('フォームの回答 1'!$E:$E,'フォームの回答 1'!$B:$B,V8,'フォームの回答 1'!$H:$H,$A9)+AJ11 -> 0 | W9: =SUMIFS('フォームの回答 1'!$E:$E,'フォームの回答 1'!$B:$B,W8,'フォームの回答 1'!$H:$H,$A9) -> 0 | X9: =SUMIFS('フォームの回答 1'!$E:$E,'フォームの回答 1'!$B:$B,X8,'フォームの回答 1'!$H:$H,$A9) -> 377823 | Y9: =SUMIFS('フォームの回答 1'!$E:$E,'フォームの回答 1'!$B:$B,Y8,'フォームの回答 1'!$H:$H,$A9) -> 0 | Z9: =SUMIFS('フォームの回答 1'!$E:$E,'フォームの回答 1'!$B:$B,Z8,'フォームの回答 1'!$H:$H,$A9) -> 0 | AA9: =SUMIFS('フォームの回答 1'!$E:$E,'フォームの回答 1'!$B:$B,AA8,'フォームの回答 1'!$H:$H,$A9) -> 0 | AB9: =SUMIFS('フォームの回答 1'!$E:$E,'フォームの回答 1'!$B:$B,AB8,'フォームの回答 1'!$H:$H,$A9) -> 0 | AC9: =SUMIFS('フォームの回答 1'!$E:$E,'フォームの回答 1'!$B:$B,AC8,'フォームの回答 1'!$H:$H,$A9) -> 0 | AD9: =SUMIFS('フォームの回答 1'!$E:$E,'フォームの回答 1'!$B:$B,AD8,'フォームの回答 1'!$H:$H,$A9) -> 0 | AE9: =SUMIFS('フォームの回答 1'!$E:$E,'フォームの回答 1'!$B:$B,AE8,'フォームの回答 1'!$H:$H,$A9) -> 0 | AI9: =188506 -> 188506
A10: 支出 | B10: =SUM(V10:AG10) -> 383264 | C10: =SUMIFS('フォームの回答 1'!$E:$E,'フォームの回答 1'!$B:$B,C8,'フォームの回答 1'!$H:$H,$A10,'フォームの回答 1'!$F:$F,"Cash") -> 1500 | D10: =SUMIFS('フォームの回答 1'!$E:$E,'フォームの回答 1'!$B:$B,D8,'フォームの回答 1'!$H:$H,$A10,'フォームの回答 1'!$F:$F,"Cash") -> 8450 | E10: =SUMIFS('フォームの回答 1'!$E:$E,'フォームの回答 1'!$B:$B,E8,'フォームの回答 1'!$H:$H,$A10,'フォームの回答 1'!$F:$F,"Cash") -> 5065 | F10: =SUMIFS('フォームの回答 1'!$E:$E,'フォームの回答 1'!$B:$B,F8,'フォームの回答 1'!$H:$H,$A10,'フォームの回答 1'!$F:$F,"Cash") -> 1887 | G10: =SUMIFS('フォームの回答 1'!$E:$E,'フォームの回答 1'!$B:$B,G8,'フォームの回答 1'!$H:$H,$A10,'フォームの回答 1'!$F:$F,"Cash") -> 12000 | H10: =SUMIFS('フォームの回答 1'!$E:$E,'フォームの回答 1'!$B:$B,H8,'フォームの回答 1'!$H:$H,$A10,'フォームの回答 1'!$F:$F,"Cash") -> 358 | I10: =SUMIFS('フォームの回答 1'!$E:$E,'フォームの回答 1'!$B:$B,I8,'フォームの回答 1'!$H:$H,$A10,'フォームの回答 1'!$F:$F,"Cash") -> 4596 | J10: =SUMIFS('フォームの回答 1'!$E:$E,'フォームの回答 1'!$B:$B,J8,'フォームの回答 1'!$H:$H,$A10,'フォームの回答 1'!$F:$F,"Cash") -> 1496 | ... AB10: =SUMIFS('フォームの回答 1'!$E:$E,'フォームの回答 1'!$B:$B,AB8,'フォームの回答 1'!$H:$H,$A10,'フォームの回答 1'!$F:$F,"Cash") -> 15262 | AC10: =SUMIFS('フォームの回答 1'!$E:$E,'フォームの回答 1'!$B:$B,AC8,'フォームの回答 1'!$H:$H,$A10,'フォームの回答 1'!$F:$F,"Cash")+AI9 -> 354904 | AD10: =SUMIFS('フォームの回答 1'!$E:$E,'フォームの回答 1'!$B:$B,AD8,'フォームの回答 1'!$H:$H,$A10,'フォームの回答 1'!$F:$F,"Cash") -> 0 | AE10: =SUMIFS('フォームの回答 1'!$E:$E,'フォームの回答 1'!$B:$B,AE8,'フォームの回答 1'!$H:$H,$A10,'フォームの回答 1'!$F:$F,"Cash") -> 1990
A11: 残高 | C11: =AG5+C9-C10 -> 29709 | D11: =C11+D9-D10 -> 21259 | E11: =D11+E9-E10 -> 16194 | F11: =E11+F9-F10 -> 14307 | G11: =F11+G9-G10 -> 2307 | H11: =G11+H9-H10 -> 80019 | I11: =H11+I9-I10 -> 75423 | J11: =I11+J9-J10 -> 73927 | K11: =J11+K9-K10 -> 71362 | ... AE11: =AD11+AE9-AE10 -> 36965
B13: 3月
B14: 合計金額 | C14: 45352 | D14: 45353 | E14: 45354 | F14: 45355 | G14: 45356 | H14: 45357 | I14: 45358 | J14: 45359 | K14: 45360 | L14: 45361 | M14: 45362 | N14: 45363 | O14: 45364 | P14: 45365 | Q14: 45366 | R14: 45367 | S14: 45368 | T14: 45369 | U14: 45370 | V14: 45371 | W14: 45372 | X14: 45373 | Y14: 45374 | Z14: 45375 | AA14: 45376 | AB14: 45377 | AC14: 45378 | AD14: 45379 | AE14: 45380 | AF14: 45381 | AG14: 45382 | AI14: 3月クレジット引き落とし
A15: 収入 | B15: =SUM(V15:AG15) -> 343450 | C15: =SUMIFS('フォームの回答 1'!$E:$E,'フォームの回答 1'!$B:$B,C14,'フォームの回答 1'!$H:$H,$A15) -> 0 | D15: =SUMIFS('フォームの回答 1'!$E:$E,'フォームの回答 1'!$B:$B,D14,'フォームの回答 1'!$H:$H,$A15) -> 0 | E15: =SUMIFS('フォームの回答 1'!$E:$E,'フォームの回答 1'!$B:$B,E14,'フォームの回答 1'!$H:$H,$A15) -> 0 | F15: =SUMIFS('フォームの回答 1'!$E:$E,'フォームの回答 1'!$B:$B,F14,'フォームの回答 1'!$H:$H,$A15) -> 0 | G15: =SUMIFS('フォームの回答 1'!$E:$E,'フォームの回答 1'!$B:$B,G14,'フォームの回答 1'!$H:$H,$A15) -> 18840 | H15: =SUMIFS('フォームの回答 1'!$E:$E,'フォームの回答 1'!$B:$B,H14,'フォームの回答 1'!$H:$H,$A15) -> 200 | I15: =SUMIFS('フォームの回答 1'!$E:$E,'フォームの回答 1'!$B:$B,I14,'フォームの回答 1'!$H:$H,$A15) -> 0 | J15: =SUMIFS('フォームの回答 1'!$E:$E,'フォームの回答 1'!$B:$B,J14,'フォームの回答 1'!$H:$H,$A15) -> 50000 | ... AA15: =SUMIFS('フォームの回答 1'!$E:$E,'フォームの回答 1'!$B:$B,AA14,'フォームの回答 1'!$H:$H,$A15) -> 343450 | AB15: =SUMIFS('フォームの回答 1'!$E:$E,'フォームの回答 1'!$B:$B,AB14,'フォームの回答 1'!$H:$H,$A15)+AJ23 -> 0 | AC15: =SUMIFS('フォームの回答 1'!$E:$E,'フォームの回答 1'!$B:$B,AC14,'フォームの回答 1'!$H:$H,$A15) -> 0 | AD15: =SUMIFS('フォームの回答 1'!$E:$E,'フォームの回答 1'!$B:$B,AD14,'フォームの回答 1'!$H:$H,$A15) -> 0 | AE15: =SUMIFS('フォームの回答 1'!$E:$E,'フォームの回答 1'!$B:$B,AE14,'フォームの回答 1'!$H:$H,$A15) -> 0 | AF15: =SUMIFS('フォームの回答 1'!$E:$E,'フォームの回答 1'!$B:$B,AF14,'フォームの回答 1'!$H:$H,$A15) -> 0 | AG15: =SUMIFS('フォームの回答 1'!$E:$E,'フォームの回答 1'!$B:$B,AG14,'フォームの回答 1'!$H:$H,$A15) -> 0 | AI15: =149159 -> 149159
A16: 支出 | B16: =SUM(V16:AG16) -> 352998 | C16: =SUMIFS('フォームの回答 1'!$E:$E,'フォームの回答 1'!$B:$B,C14,'フォームの回答 1'!$H:$H,$A16,'フォームの回答 1'!$F:$F,"Cash") -> 880 | D16: =SUMIFS('フォームの回答 1'!$E:$E,'フォームの回答 1'!$B:$B,D14,'フォームの回答 1'!$H:$H,$A16,'フォームの回答 1'!$F:$F,"Cash") -> 4833 | E16: =SUMIFS('フォームの回答 1'!$E:$E,'フォームの回答 1'!$B:$B,E14,'フォームの回答 1'!$H:$H,$A16,'フォームの回答 1'!$F:$F,"Cash") -> 4307 | F16: =SUMIFS('フォームの回答 1'!$E:$E,'フォームの回答 1'!$B:$B,F14,'フォームの回答 1'!$H:$H,$A16,'フォームの回答 1'!$F:$F,"Cash") -> 0 | G16: =SUMIFS('フォームの回答 1'!$E:$E,'フォームの回答 1'!$B:$B,G14,'フォームの回答 1'!$H:$H,$A16,'フォームの回答 1'!$F:$F,"Cash") -> 1206 | H16: =SUMIFS('フォームの回答 1'!$E:$E,'フォームの回答 1'!$B:$B,H14,'フォームの回答 1'!$H:$H,$A16,'フォームの回答 1'!$F:$F,"Cash") -> 1577 | I16: =SUMIFS('フォームの回答 1'!$E:$E,'フォームの回答 1'!$B:$B,I14,'フォームの回答 1'!$H:$H,$A16,'フォームの回答 1'!$F:$F,"Cash") -> 1962 | J16: =SUMIFS('フォームの回答 1'!$E:$E,'フォームの回答 1'!$B:$B,J14,'フォームの回答 1'!$H:$H,$A16,'フォームの回答 1'!$F:$F,"Cash") -> 6500 | ... AB16: =SUMIFS('フォームの回答 1'!$E:$E,'フォームの回答 1'!$B:$B,AB14,'フォームの回答 1'!$H:$H,$A16,'フォームの回答 1'!$F:$F,"Cash") -> 1872 | AC16: =SUMIFS('フォームの回答 1'!$E:$E,'フォームの回答 1'!$B:$B,AC14,'フォームの回答 1'!$H:$H,$A16,'フォームの回答 1'!$F:$F,"Cash")+AI15 -> 327629 | AD16: =SUMIFS('フォームの回答 1'!$E:$E,'フォームの回答 1'!$B:$B,AD14,'フォームの回答 1'!$H:$H,$A16,'フォームの回答 1'!$F:$F,"Cash") -> 975 | AE16: =SUMIFS('フォームの回答 1'!$E:$E,'フォームの回答 1'!$B:$B,AE14,'フォームの回答 1'!$H:$H,$A16,'フォームの回答 1'!$F:$F,"Cash") -> 327 | AF16: =SUMIFS('フォームの回答 1'!$E:$E,'フォームの回答 1'!$B:$B,AF14,'フォームの回答 1'!$H:$H,$A16,'フォームの回答 1'!$F:$F,"Cash") -> 3701 | AG16: =SUMIFS('フォームの回答 1'!$E:$E,'フォームの回答 1'!$B:$B,AG14,'フォームの回答 1'!$H:$H,$A16,'フォームの回答 1'!$F:$F,"Cash") -> 4911
A17: 残高 | C17: =AE11+C15-C16 -> 36085 | D17: =C17+D15-D16 -> 31252 | E17: =D17+E15-E16 -> 26945 | F17: =E17+F15-F16 -> 26945 | G17: =F17+G15-G16 -> 44579 | H17: =G17+H15-H16 -> 43202 | I17: =H17+I15-I16 -> 41240 | J17: =I17+J15-J16 -> 84740 | K17: =J17+K15-K16 -> 85500 | ... AG17: =AF17+AG15-AG16 -> 35089
B19: 4月 | AI19: 4月クレジット引き落とし
B20: 合計金額 | C20: 45383 | D20: 45384 | E20: 45385 | F20: 45386 | G20: 45387 | H20: 45388 | I20: 45389 | J20: 45390 | K20: 45391 | L20: 45392 | M20: 45393 | N20: 45394 | O20: 45395 | P20: 45396 | Q20: 45397 | R20: 45398 | S20: 45399 | T20: 45400 | U20: 45401 | V20: 45402 | W20: 45403 | X20: 45404 | Y20: 45405 | Z20: 45406 | AA20: 45407 | AB20: 45408 | AC20: 45409 | AD20: 45410 | AE20: 45411 | AF20: 45412 | AI20: =115462 -> 115462
A21: 収入 | B21: =SUM(V21:AG21) -> 351790 | C21: =SUMIFS('フォームの回答 1'!$E:$E,'フォームの回答 1'!$B:$B,C20,'フォームの回答 1'!$H:$H,$A21) -> 0 | D21: =SUMIFS('フォームの回答 1'!$E:$E,'フォームの回答 1'!$B:$B,D20,'フォームの回答 1'!$H:$H,$A21) -> 10378 | E21: =SUMIFS('フォームの回答 1'!$E:$E,'フォームの回答 1'!$B:$B,E20,'フォームの回答 1'!$H:$H,$A21) -> 0 | F21: =SUMIFS('フォームの回答 1'!$E:$E,'フォームの回答 1'!$B:$B,F20,'フォームの回答 1'!$H:$H,$A21) -> 5000 | G21: =SUMIFS('フォームの回答 1'!$E:$E,'フォームの回答 1'!$B:$B,G20,'フォームの回答 1'!$H:$H,$A21) -> 0 | H21: =SUMIFS('フォームの回答 1'!$E:$E,'フォームの回答 1'!$B:$B,H20,'フォームの回答 1'!$H:$H,$A21) -> 0 | I21: =SUMIFS('フォームの回答 1'!$E:$E,'フォームの回答 1'!$B:$B,I20,'フォームの回答 1'!$H:$H,$A21) -> 0 | J21: =SUMIFS('フォームの回答 1'!$E:$E,'フォームの回答 1'!$B:$B,J20,'フォームの回答 1'!$H:$H,$A21) -> 0 | ... AF21: =SUMIFS('フォームの回答 1'!$E:$E,'フォームの回答 1'!$B:$B,AF20,'フォームの回答 1'!$H:$H,$A21) -> 0
A22: 支出 | B22: =SUM(V22:AG22) -> 317403 | C22: =SUMIFS('フォームの回答 1'!$E:$E,'フォームの回答 1'!$B:$B,C20,'フォームの回答 1'!$H:$H,$A22,'フォームの回答 1'!$F:$F,"Cash") -> 1000 | D22: =SUMIFS('フォームの回答 1'!$E:$E,'フォームの回答 1'!$B:$B,D20,'フォームの回答 1'!$H:$H,$A22,'フォームの回答 1'!$F:$F,"Cash") -> 1795 | E22: =SUMIFS('フォームの回答 1'!$E:$E,'フォームの回答 1'!$B:$B,E20,'フォームの回答 1'!$H:$H,$A22,'フォームの回答 1'!$F:$F,"Cash") -> 7323 | F22: =SUMIFS('フォームの回答 1'!$E:$E,'フォームの回答 1'!$B:$B,F20,'フォームの回答 1'!$H:$H,$A22,'フォームの回答 1'!$F:$F,"Cash") -> 1312 | G22: =SUMIFS('フォームの回答 1'!$E:$E,'フォームの回答 1'!$B:$B,G20,'フォームの回答 1'!$H:$H,$A22,'フォームの回答 1'!$F:$F,"Cash") -> 980 | H22: =SUMIFS('フォームの回答 1'!$E:$E,'フォームの回答 1'!$B:$B,H20,'フォームの回答 1'!$H:$H,$A22,'フォームの回答 1'!$F:$F,"Cash") -> 1629 | I22: =SUMIFS('フォームの回答 1'!$E:$E,'フォームの回答 1'!$B:$B,I20,'フォームの回答 1'!$H:$H,$A22,'フォームの回答 1'!$F:$F,"Cash") -> 3464 | J22: =SUMIFS('フォームの回答 1'!$E:$E,'フォームの回答 1'!$B:$B,J20,'フォームの回答 1'!$H:$H,$A22,'フォームの回答 1'!$F:$F,"Cash") -> 1840 | ... AB22: =SUMIFS('フォームの回答 1'!$E:$E,'フォームの回答 1'!$B:$B,AB20,'フォームの回答 1'!$H:$H,$A22,'フォームの回答 1'!$F:$F,"Cash") -> 47946 | AC22: =SUMIFS('フォームの回答 1'!$E:$E,'フォームの回答 1'!$B:$B,AC20,'フォームの回答 1'!$H:$H,$A22,'フォームの回答 1'!$F:$F,"Cash")+AI20 -> 121974 | AD22: =SUMIFS('フォームの回答 1'!$E:$E,'フォームの回答 1'!$B:$B,AD20,'フォームの回答 1'!$H:$H,$A22,'フォームの回答 1'!$F:$F,"Cash") -> 4138 | AE22: =SUMIFS('フォームの回答 1'!$E:$E,'フォームの回答 1'!$B:$B,AE20,'フォームの回答 1'!$H:$H,$A22,'フォームの回答 1'!$F:$F,"Cash") -> 1952 | AF22: =SUMIFS('フォームの回答 1'!$E:$E,'フォームの回答 1'!$B:$B,AF20,'フォームの回答 1'!$H:$H,$A22,'フォームの回答 1'!$F:$F,"Cash") -> 137218
A23: 残高 | C23: =AG17+C21-C22 -> 34089 | D23: =C23+D21-D22 -> 42672 | E23: =D23+E21-E22 -> 35349 | F23: =E23+F21-F22 -> 39037 | G23: =F23+G21-G22 -> 38057 | H23: =G23+H21-H22 -> 36428 | I23: =H23+I21-I22 -> 32964 | J23: =I23+J21-J22 -> 31124 | K23: =J23+K21-K22 -> 30464 | ... AF23: =AE23+AF21-AF22 -> 49200
B25: 5月 | AI25: 5月クレジット引き落とし
B26: 合計金額 | C26: 45413 | D26: 45414 | E26: 45415 | F26: 45416 | G26: 45417 | H26: 45418 | I26: 45419 | J26: 45420 | K26: 45421 | L26: 45422 | M26: 45423 | N26: 45424 | O26: 45425 | P26: 45426 | Q26: 45427 | R26: 45428 | S26: 45429 | T26: 45430 | U26: 45431 | V26: 45432 | W26: 45433 | X26: 45434 | Y26: 45435 | Z26: 45436 | AA26: 45437 | AB26: 45438 | AC26: 45439 | AD26: 45440 | AE26: 45441 | AF26: 45442 | AG26: 45443 | AI26: =113190 -> 113190
A27: 収入 | B27: =SUM(V27:AG27) -> 387163 | C27: =SUMIFS('フォームの回答 1'!$E:$E,'フォームの回答 1'!$B:$B,C26,'フォームの回答 1'!$H:$H,$A27) -> 0 | D27: =SUMIFS('フォームの回答 1'!$E:$E,'フォームの回答 1'!$B:$B,D26,'フォームの回答 1'!$H:$H,$A27) -> 0 | E27: =SUMIFS('フォームの回答 1'!$E:$E,'フォームの回答 1'!$B:$B,E26,'フォームの回答 1'!$H:$H,$A27) -> 0 | F27: =SUMIFS('フォームの回答 1'!$E:$E,'フォームの回答 1'!$B:$B,F26,'フォームの回答 1'!$H:$H,$A27) -> 0 | G27: =SUMIFS('フォームの回答 1'!$E:$E,'フォームの回答 1'!$B:$B,G26,'フォームの回答 1'!$H:$H,$A27) -> 0 | H27: =SUMIFS('フォームの回答 1'!$E:$E,'フォームの回答 1'!$B:$B,H26,'フォームの回答 1'!$H:$H,$A27) -> 0 | I27: =SUMIFS('フォームの回答 1'!$E:$E,'フォームの回答 1'!$B:$B,I26,'フォームの回答 1'!$H:$H,$A27) -> 9380 | J27: =SUMIFS('フォームの回答 1'!$E:$E,'フォームの回答 1'!$B:$B,J26,'フォームの回答 1'!$H:$H,$A27) -> 0 | ... Z27: =SUMIFS('フォームの回答 1'!$E:$E,'フォームの回答 1'!$B:$B,Z26,'フォームの回答 1'!$H:$H,$A27) -> 376163 | AA27: =SUMIFS('フォームの回答 1'!$E:$E,'フォームの回答 1'!$B:$B,AA26,'フォームの回答 1'!$H:$H,$A27)+AJ18 -> 6000 | AB27: =SUMIFS('フォームの回答 1'!$E:$E,'フォームの回答 1'!$B:$B,AB26,'フォームの回答 1'!$H:$H,$A27) -> 0 | AC27: =SUMIFS('フォームの回答 1'!$E:$E,'フォームの回答 1'!$B:$B,AC26,'フォームの回答 1'!$H:$H,$A27) -> 0 | AD27: =SUMIFS('フォームの回答 1'!$E:$E,'フォームの回答 1'!$B:$B,AD26,'フォームの回答 1'!$H:$H,$A27) -> 0 | AE27: =SUMIFS('フォームの回答 1'!$E:$E,'フォームの回答 1'!$B:$B,AE26,'フォームの回答 1'!$H:$H,$A27) -> 0 | AF27: =SUMIFS('フォームの回答 1'!$E:$E,'フォームの回答 1'!$B:$B,AF26,'フォームの回答 1'!$H:$H,$A27) -> 0 | AG27: =SUMIFS('フォームの回答 1'!$E:$E,'フォームの回答 1'!$B:$B,AG26,'フォームの回答 1'!$H:$H,$A27) -> 0
A28: 支出 | B28: =SUM(C28:AG28) -> 373807 | C28: =SUMIFS('フォームの回答 1'!$E:$E,'フォームの回答 1'!$B:$B,C26,'フォームの回答 1'!$H:$H,$A28,'フォームの回答 1'!$F:$F,"Cash") -> 5918 | D28: =SUMIFS('フォームの回答 1'!$E:$E,'フォームの回答 1'!$B:$B,D26,'フォームの回答 1'!$H:$H,$A28,'フォームの回答 1'!$F:$F,"Cash") -> 1348 | E28: =SUMIFS('フォームの回答 1'!$E:$E,'フォームの回答 1'!$B:$B,E26,'フォームの回答 1'!$H:$H,$A28,'フォームの回答 1'!$F:$F,"Cash") -> 5544 | F28: =SUMIFS('フォームの回答 1'!$E:$E,'フォームの回答 1'!$B:$B,F26,'フォームの回答 1'!$H:$H,$A28,'フォームの回答 1'!$F:$F,"Cash") -> 2622 | G28: =SUMIFS('フォームの回答 1'!$E:$E,'フォームの回答 1'!$B:$B,G26,'フォームの回答 1'!$H:$H,$A28,'フォームの回答 1'!$F:$F,"Cash") -> 1000 | H28: =SUMIFS('フォームの回答 1'!$E:$E,'フォームの回答 1'!$B:$B,H26,'フォームの回答 1'!$H:$H,$A28,'フォームの回答 1'!$F:$F,"Cash") -> 2652 | I28: =SUMIFS('フォームの回答 1'!$E:$E,'フォームの回答 1'!$B:$B,I26,'フォームの回答 1'!$H:$H,$A28,'フォームの回答 1'!$F:$F,"Cash") -> 2126 | J28: =SUMIFS('フォームの回答 1'!$E:$E,'フォームの回答 1'!$B:$B,J26,'フォームの回答 1'!$H:$H,$A28,'フォームの回答 1'!$F:$F,"Cash") -> 890 | ... AB28: =SUMIFS('フォームの回答 1'!$E:$E,'フォームの回答 1'!$B:$B,AB26,'フォームの回答 1'!$H:$H,$A28,'フォームの回答 1'!$F:$F,"Cash") -> 4537 | AC28: =SUMIFS('フォームの回答 1'!$E:$E,'フォームの回答 1'!$B:$B,AC26,'フォームの回答 1'!$H:$H,$A28,'フォームの回答 1'!$F:$F,"Cash")+AI26 -> 262960 | AD28: =SUMIFS('フォームの回答 1'!$E:$E,'フォームの回答 1'!$B:$B,AD26,'フォームの回答 1'!$H:$H,$A28,'フォームの回答 1'!$F:$F,"Cash") -> 3257 | AE28: =SUMIFS('フォームの回答 1'!$E:$E,'フォームの回答 1'!$B:$B,AE26,'フォームの回答 1'!$H:$H,$A28,'フォームの回答 1'!$F:$F,"Cash") -> 1325 | AF28: =SUMIFS('フォームの回答 1'!$E:$E,'フォームの回答 1'!$B:$B,AF26,'フォームの回答 1'!$H:$H,$A28,'フォームの回答 1'!$F:$F,"Cash") -> 1575 | AG28: =SUMIFS('フォームの回答 1'!$E:$E,'フォームの回答 1'!$B:$B,AG26,'フォームの回答 1'!$H:$H,$A28,'フォームの回答 1'!$F:$F,"Cash") -> 9245
A29: 残高 | C29: =AF23+C27-C28 -> 43282 | D29: =C29+D27-D28 -> 41934 | E29: =D29+E27-E28 -> 36390 | F29: =E29+F27-F28 -> 33768 | G29: =F29+G27-G28 -> 32768 | H29: =G29+H27-H28 -> 30116 | I29: =H29+I27-I28 -> 37370 | J29: =I29+J27-J28 -> 36480 | K29: =J29+K27-K28 -> 34980 | ... AG29: =AF29+AG27-AG28 -> 76436
B31: 6月 | AI31: 6月クレジット引き落とし
B32: 合計金額 | C32: 45444 | D32: 45445 | E32: 45446 | F32: 45447 | G32: 45448 | H32: 45449 | I32: 45450 | J32: 45451 | K32: 45452 | L32: 45453 | M32: 45454 | N32: 45455 | O32: 45456 | P32: 45457 | Q32: 45458 | R32: 45459 | S32: 45460 | T32: 45461 | U32: 45462 | V32: 45463 | W32: 45464 | X32: 45465 | Y32: 45466 | Z32: 45467 | AA32: 45468 | AB32: 45469 | AC32: 45470 | AD32: 45471 | AE32: 45472 | AF32: 45473 | AI32: =167013 -> 167013
A33: 収入 | B33: =SUM(V33:AG33) -> 362320 | C33: =SUMIFS('フォームの回答 1'!$E:$E,'フォームの回答 1'!$B:$B,C32,'フォームの回答 1'!$H:$H,$A33) -> 0 | D33: =SUMIFS('フォームの回答 1'!$E:$E,'フォームの回答 1'!$B:$B,D32,'フォームの回答 1'!$H:$H,$A33) -> 0 | E33: =SUMIFS('フォームの回答 1'!$E:$E,'フォームの回答 1'!$B:$B,E32,'フォームの回答 1'!$H:$H,$A33) -> 0 | F33: =SUMIFS('フォームの回答 1'!$E:$E,'フォームの回答 1'!$B:$B,F32,'フォームの回答 1'!$H:$H,$A33) -> 0 | G33: =SUMIFS('フォームの回答 1'!$E:$E,'フォームの回答 1'!$B:$B,G32,'フォームの回答 1'!$H:$H,$A33) -> 17385 | H33: =SUMIFS('フォームの回答 1'!$E:$E,'フォームの回答 1'!$B:$B,H32,'フォームの回答 1'!$H:$H,$A33) -> 0 | I33: =SUMIFS('フォームの回答 1'!$E:$E,'フォームの回答 1'!$B:$B,I32,'フォームの回答 1'!$H:$H,$A33) -> 0 | J33: =SUMIFS('フォームの回答 1'!$E:$E,'フォームの回答 1'!$B:$B,J32,'フォームの回答 1'!$H:$H,$A33) -> 0 | ... Z33: =SUMIFS('フォームの回答 1'!$E:$E,'フォームの回答 1'!$B:$B,Z32,'フォームの回答 1'!$H:$H,$A33) -> 0 | AA33: =SUMIFS('フォームの回答 1'!$E:$E,'フォームの回答 1'!$B:$B,AA32,'フォームの回答 1'!$H:$H,$A33)+AJ24 -> 356320 | AB33: =SUMIFS('フォームの回答 1'!$E:$E,'フォームの回答 1'!$B:$B,AB32,'フォームの回答 1'!$H:$H,$A33) -> 3000 | AC33: =SUMIFS('フォームの回答 1'!$E:$E,'フォームの回答 1'!$B:$B,AC32,'フォームの回答 1'!$H:$H,$A33) -> 0 | AD33: =SUMIFS('フォームの回答 1'!$E:$E,'フォームの回答 1'!$B:$B,AD32,'フォームの回答 1'!$H:$H,$A33) -> 3000 | AE33: =SUMIFS('フォームの回答 1'!$E:$E,'フォームの回答 1'!$B:$B,AE32,'フォームの回答 1'!$H:$H,$A33) -> 0 | AF33: =SUMIFS('フォームの回答 1'!$E:$E,'フォームの回答 1'!$B:$B,AF32,'フォームの回答 1'!$H:$H,$A33) -> 0
A34: 支出 | B34: =SUM(C34:AG34) -> 456671 | C34: =SUMIFS('フォームの回答 1'!$E:$E,'フォームの回答 1'!$B:$B,C32,'フォームの回答 1'!$H:$H,$A34,'フォームの回答 1'!$F:$F,"Cash") -> 3360 | D34: =SUMIFS('フォームの回答 1'!$E:$E,'フォームの回答 1'!$B:$B,D32,'フォームの回答 1'!$H:$H,$A34,'フォームの回答 1'!$F:$F,"Cash") -> 6239 | E34: =SUMIFS('フォームの回答 1'!$E:$E,'フォームの回答 1'!$B:$B,E32,'フォームの回答 1'!$H:$H,$A34,'フォームの回答 1'!$F:$F,"Cash") -> 1172 | F34: =SUMIFS('フォームの回答 1'!$E:$E,'フォームの回答 1'!$B:$B,F32,'フォームの回答 1'!$H:$H,$A34,'フォームの回答 1'!$F:$F,"Cash") -> 1939 | G34: =SUMIFS('フォームの回答 1'!$E:$E,'フォームの回答 1'!$B:$B,G32,'フォームの回答 1'!$H:$H,$A34,'フォームの回答 1'!$F:$F,"Cash") -> 8262 | H34: =SUMIFS('フォームの回答 1'!$E:$E,'フォームの回答 1'!$B:$B,H32,'フォームの回答 1'!$H:$H,$A34,'フォームの回答 1'!$F:$F,"Cash") -> 1358 | I34: =SUMIFS('フォームの回答 1'!$E:$E,'フォームの回答 1'!$B:$B,I32,'フォームの回答 1'!$H:$H,$A34,'フォームの回答 1'!$F:$F,"Cash") -> 1700 | J34: =SUMIFS('フォームの回答 1'!$E:$E,'フォームの回答 1'!$B:$B,J32,'フォームの回答 1'!$H:$H,$A34,'フォームの回答 1'!$F:$F,"Cash") -> 0 | ... AB34: =SUMIFS('フォームの回答 1'!$E:$E,'フォームの回答 1'!$B:$B,AB32,'フォームの回答 1'!$H:$H,$A34,'フォームの回答 1'!$F:$F,"Cash") -> 9736 | AC34: =SUMIFS('フォームの回答 1'!$E:$E,'フォームの回答 1'!$B:$B,AC32,'フォームの回答 1'!$H:$H,$A34,'フォームの回答 1'!$F:$F,"Cash")+AI32 -> 342243 | AD34: =SUMIFS('フォームの回答 1'!$E:$E,'フォームの回答 1'!$B:$B,AD32,'フォームの回答 1'!$H:$H,$A34,'フォームの回答 1'!$F:$F,"Cash") -> 9000 | AE34: =SUMIFS('フォームの回答 1'!$E:$E,'フォームの回答 1'!$B:$B,AE32,'フォームの回答 1'!$H:$H,$A34,'フォームの回答 1'!$F:$F,"Cash") -> 2628 | AF34: =SUMIFS('フォームの回答 1'!$E:$E,'フォームの回答 1'!$B:$B,AF32,'フォームの回答 1'!$H:$H,$A34,'フォームの回答 1'!$F:$F,"Cash") -> 400
A35: 残高 | C35: =AG29+C33-C34 -> 73076 | D35: =C35+D33-D34 -> 66837 | E35: =D35+E33-E34 -> 65665 | F35: =E35+F33-F34 -> 63726 | G35: =F35+G33-G34 -> 72849 | H35: =G35+H33-H34 -> 71491 | I35: =H35+I33-I34 -> 69791 | J35: =I35+J33-J34 -> 69791 | K35: =J35+K33-K34 -> 61342 | ... AF35: =AE35+AF33-AF34 -> 42970
B37: 7月 | AI37: 7月クレジット引き落とし
B38: 合計金額 | C38: 45474 | D38: 45475 | E38: 45476 | F38: 45477 | G38: 45478 | H38: 45479 | I38: 45480 | J38: 45481 | K38: 45482 | L38: 45483 | M38: 45484 | N38: 45485 | O38: 45486 | P38: 45487 | Q38: 45488 | R38: 45489 | S38: 45490 | T38: 45491 | U38: 45492 | V38: 45493 | W38: 45494 | X38: 45495 | Y38: 45496 | Z38: 45497 | AA38: 45498 | AB38: 45499 | AC38: 45500 | AD38: 45501 | AE38: 45502 | AF38: 45503 | AG38: 45504 | AI38: 131313
A39: 収入 | B39: =SUM(V39:AG39) -> 348520 | C39: =SUMIFS('フォームの回答 1'!$E:$E,'フォームの回答 1'!$B:$B,C38,'フォームの回答 1'!$H:$H,$A39) -> 0 | D39: =SUMIFS('フォームの回答 1'!$E:$E,'フォームの回答 1'!$B:$B,D38,'フォームの回答 1'!$H:$H,$A39) -> 0 | E39: =SUMIFS('フォームの回答 1'!$E:$E,'フォームの回答 1'!$B:$B,E38,'フォームの回答 1'!$H:$H,$A39) -> 0 | F39: =SUMIFS('フォームの回答 1'!$E:$E,'フォームの回答 1'!$B:$B,F38,'フォームの回答 1'!$H:$H,$A39) -> 4980 | G39: =SUMIFS('フォームの回答 1'!$E:$E,'フォームの回答 1'!$B:$B,G38,'フォームの回答 1'!$H:$H,$A39) -> 0 | H39: =SUMIFS('フォームの回答 1'!$E:$E,'フォームの回答 1'!$B:$B,H38,'フォームの回答 1'!$H:$H,$A39) -> 0 | I39: =SUMIFS('フォームの回答 1'!$E:$E,'フォームの回答 1'!$B:$B,I38,'フォームの回答 1'!$H:$H,$A39) -> 0 | J39: =SUMIFS('フォームの回答 1'!$E:$E,'フォームの回答 1'!$B:$B,J38,'フォームの回答 1'!$H:$H,$A39) -> 0 | ... Z39: =SUMIFS('フォームの回答 1'!$E:$E,'フォームの回答 1'!$B:$B,Z38,'フォームの回答 1'!$H:$H,$A39) -> 0 | AA39: =SUMIFS('フォームの回答 1'!$E:$E,'フォームの回答 1'!$B:$B,AA38,'フォームの回答 1'!$H:$H,$A39)+AJ30 -> 341520 | AB39: =SUMIFS('フォームの回答 1'!$E:$E,'フォームの回答 1'!$B:$B,AB38,'フォームの回答 1'!$H:$H,$A39) -> 0 | AC39: =SUMIFS('フォームの回答 1'!$E:$E,'フォームの回答 1'!$B:$B,AC38,'フォームの回答 1'!$H:$H,$A39) -> 0 | AD39: =SUMIFS('フォームの回答 1'!$E:$E,'フォームの回答 1'!$B:$B,AD38,'フォームの回答 1'!$H:$H,$A39) -> 0 | AE39: =SUMIFS('フォームの回答 1'!$E:$E,'フォームの回答 1'!$B:$B,AE38,'フォームの回答 1'!$H:$H,$A39) -> 0 | AF39: =SUMIFS('フォームの回答 1'!$E:$E,'フォームの回答 1'!$B:$B,AF38,'フォームの回答 1'!$H:$H,$A39) -> 0 | AG39: =SUMIFS('フォームの回答 1'!$E:$E,'フォームの回答 1'!$B:$B,AG38,'フォームの回答 1'!$H:$H,$A39) -> 0
A40: 支出 | B40: =SUM(C40:AG40) -> 386999 | C40: =SUMIFS('フォームの回答 1'!$E:$E,'フォームの回答 1'!$B:$B,C38,'フォームの回答 1'!$H:$H,$A40,'フォームの回答 1'!$F:$F,"Cash") -> 6990 | D40: =SUMIFS('フォームの回答 1'!$E:$E,'フォームの回答 1'!$B:$B,D38,'フォームの回答 1'!$H:$H,$A40,'フォームの回答 1'!$F:$F,"Cash") -> 1995 | E40: =SUMIFS('フォームの回答 1'!$E:$E,'フォームの回答 1'!$B:$B,E38,'フォームの回答 1'!$H:$H,$A40,'フォームの回答 1'!$F:$F,"Cash") -> 382 | F40: =SUMIFS('フォームの回答 1'!$E:$E,'フォームの回答 1'!$B:$B,F38,'フォームの回答 1'!$H:$H,$A40,'フォームの回答 1'!$F:$F,"Cash") -> 1260 | G40: =SUMIFS('フォームの回答 1'!$E:$E,'フォームの回答 1'!$B:$B,G38,'フォームの回答 1'!$H:$H,$A40,'フォームの回答 1'!$F:$F,"Cash") -> 2700 | H40: =SUMIFS('フォームの回答 1'!$E:$E,'フォームの回答 1'!$B:$B,H38,'フォームの回答 1'!$H:$H,$A40,'フォームの回答 1'!$F:$F,"Cash") -> 5180 | I40: =SUMIFS('フォームの回答 1'!$E:$E,'フォームの回答 1'!$B:$B,I38,'フォームの回答 1'!$H:$H,$A40,'フォームの回答 1'!$F:$F,"Cash") -> 4300 | J40: =SUMIFS('フォームの回答 1'!$E:$E,'フォームの回答 1'!$B:$B,J38,'フォームの回答 1'!$H:$H,$A40,'フォームの回答 1'!$F:$F,"Cash") -> 0 | ... AB40: =SUMIFS('フォームの回答 1'!$E:$E,'フォームの回答 1'!$B:$B,AB38,'フォームの回答 1'!$H:$H,$A40,'フォームの回答 1'!$F:$F,"Cash") -> 179138 | AC40: =SUMIFS('フォームの回答 1'!$E:$E,'フォームの回答 1'!$B:$B,AC38,'フォームの回答 1'!$H:$H,$A40,'フォームの回答 1'!$F:$F,"Cash")+AI38 -> 134382 | AD40: =SUMIFS('フォームの回答 1'!$E:$E,'フォームの回答 1'!$B:$B,AD38,'フォームの回答 1'!$H:$H,$A40,'フォームの回答 1'!$F:$F,"Cash") -> 1800 | AE40: =SUMIFS('フォームの回答 1'!$E:$E,'フォームの回答 1'!$B:$B,AE38,'フォームの回答 1'!$H:$H,$A40,'フォームの回答 1'!$F:$F,"Cash") -> 0 | AF40: =SUMIFS('フォームの回答 1'!$E:$E,'フォームの回答 1'!$B:$B,AF38,'フォームの回答 1'!$H:$H,$A40,'フォームの回答 1'!$F:$F,"Cash") -> 1620 | AG40: =SUMIFS('フォームの回答 1'!$E:$E,'フォームの回答 1'!$B:$B,AG38,'フォームの回答 1'!$H:$H,$A40,'フォームの回答 1'!$F:$F,"Cash") -> 0
A41: 残高 | C41: =AF35+C39-C40 -> 35980 | D41: =C41+D39-D40 -> 33985 | E41: =D41+E39-E40 -> 33603 | F41: =E41+F39-F40 -> 37323 | G41: =F41+G39-G40 -> 34623 | H41: =G41+H39-H40 -> 29443 | I41: =H41+I39-I40 -> 25143 | J41: =I41+J39-J40 -> 25143 | K41: =J41+K39-K40 -> 24923 | ... AG41: =AF41+AG39-AG40 -> 40471
B43: 8月 | AI43: 8月クレジット引き落とし
B44: 合計金額 | C44: 45505 | D44: 45506 | E44: 45507 | F44: 45508 | G44: 45509 | H44: 45510 | I44: 45511 | J44: 45512 | K44: 45513 | L44: 45514 | M44: 45515 | N44: 45516 | O44: 45517 | P44: 45518 | Q44: 45519 | R44: 45520 | S44: 45521 | T44: 45522 | U44: 45523 | V44: 45524 | W44: 45525 | X44: 45526 | Y44: 45527 | Z44: 45528 | AA44: 45529 | AB44: 45530 | AC44: 45531 | AD44: 45532 | AE44: 45533 | AF44: 45534 | AG44: 45535 | AI44: 112151
A45: 収入 | B45: =SUM(V45:AG45) -> 344837 | C45: =SUMIFS('フォームの回答 1'!$E:$E,'フォームの回答 1'!$B:$B,C44,'フォームの回答 1'!$H:$H,$A45) -> 0 | D45: =SUMIFS('フォームの回答 1'!$E:$E,'フォームの回答 1'!$B:$B,D44,'フォームの回答 1'!$H:$H,$A45) -> 0 | E45: =SUMIFS('フォームの回答 1'!$E:$E,'フォームの回答 1'!$B:$B,E44,'フォームの回答 1'!$H:$H,$A45) -> 0 | F45: =SUMIFS('フォームの回答 1'!$E:$E,'フォームの回答 1'!$B:$B,F44,'フォームの回答 1'!$H:$H,$A45) -> 0 | G45: =SUMIFS('フォームの回答 1'!$E:$E,'フォームの回答 1'!$B:$B,G44,'フォームの回答 1'!$H:$H,$A45) -> 0 | H45: =SUMIFS('フォームの回答 1'!$E:$E,'フォームの回答 1'!$B:$B,H44,'フォームの回答 1'!$H:$H,$A45) -> 17965 | I45: =SUMIFS('フォームの回答 1'!$E:$E,'フォームの回答 1'!$B:$B,I44,'フォームの回答 1'!$H:$H,$A45) -> 0 | J45: =SUMIFS('フォームの回答 1'!$E:$E,'フォームの回答 1'!$B:$B,J44,'フォームの回答 1'!$H:$H,$A45) -> 0 | ... Z45: =SUMIFS('フォームの回答 1'!$E:$E,'フォームの回答 1'!$B:$B,Z44,'フォームの回答 1'!$H:$H,$A45) -> 0 | AA45: =SUMIFS('フォームの回答 1'!$E:$E,'フォームの回答 1'!$B:$B,AA44,'フォームの回答 1'!$H:$H,$A45)+AJ36 -> 0 | AB45: =SUMIFS('フォームの回答 1'!$E:$E,'フォームの回答 1'!$B:$B,AB44,'フォームの回答 1'!$H:$H,$A45) -> 0 | AC45: =SUMIFS('フォームの回答 1'!$E:$E,'フォームの回答 1'!$B:$B,AC44,'フォームの回答 1'!$H:$H,$A45) -> 0 | AD45: =SUMIFS('フォームの回答 1'!$E:$E,'フォームの回答 1'!$B:$B,AD44,'フォームの回答 1'!$H:$H,$A45) -> 0 | AE45: =SUMIFS('フォームの回答 1'!$E:$E,'フォームの回答 1'!$B:$B,AE44,'フォームの回答 1'!$H:$H,$A45) -> 0 | AF45: =SUMIFS('フォームの回答 1'!$E:$E,'フォームの回答 1'!$B:$B,AF44,'フォームの回答 1'!$H:$H,$A45) -> 0 | AG45: =SUMIFS('フォームの回答 1'!$E:$E,'フォームの回答 1'!$B:$B,AG44,'フォームの回答 1'!$H:$H,$A45) -> 0
A46: 支出 | B46: =SUM(C46:AG46) -> 356517 | C46: =SUMIFS('フォームの回答 1'!$E:$E,'フォームの回答 1'!$B:$B,C44,'フォームの回答 1'!$H:$H,$A46,'フォームの回答 1'!$F:$F,"Cash") -> 0 | D46: =SUMIFS('フォームの回答 1'!$E:$E,'フォームの回答 1'!$B:$B,D44,'フォームの回答 1'!$H:$H,$A46,'フォームの回答 1'!$F:$F,"Cash") -> 1259 | E46: =SUMIFS('フォームの回答 1'!$E:$E,'フォームの回答 1'!$B:$B,E44,'フォームの回答 1'!$H:$H,$A46,'フォームの回答 1'!$F:$F,"Cash") -> 4022 | F46: =SUMIFS('フォームの回答 1'!$E:$E,'フォームの回答 1'!$B:$B,F44,'フォームの回答 1'!$H:$H,$A46,'フォームの回答 1'!$F:$F,"Cash") -> 6593 | G46: =SUMIFS('フォームの回答 1'!$E:$E,'フォームの回答 1'!$B:$B,G44,'フォームの回答 1'!$H:$H,$A46,'フォームの回答 1'!$F:$F,"Cash") -> 322 | H46: =SUMIFS('フォームの回答 1'!$E:$E,'フォームの回答 1'!$B:$B,H44,'フォームの回答 1'!$H:$H,$A46,'フォームの回答 1'!$F:$F,"Cash") -> 138 | I46: =SUMIFS('フォームの回答 1'!$E:$E,'フォームの回答 1'!$B:$B,I44,'フォームの回答 1'!$H:$H,$A46,'フォームの回答 1'!$F:$F,"Cash") -> 0 | J46: =SUMIFS('フォームの回答 1'!$E:$E,'フォームの回答 1'!$B:$B,J44,'フォームの回答 1'!$H:$H,$A46,'フォームの回答 1'!$F:$F,"Cash") -> 1750 | ... AB46: =SUMIFS('フォームの回答 1'!$E:$E,'フォームの回答 1'!$B:$B,AB44,'フォームの回答 1'!$H:$H,$A46,'フォームの回答 1'!$F:$F,"Cash") -> 3786 | AC46: =SUMIFS('フォームの回答 1'!$E:$E,'フォームの回答 1'!$B:$B,AC44,'フォームの回答 1'!$H:$H,$A46,'フォームの回答 1'!$F:$F,"Cash")+AI44 -> 257221 | AD46: =SUMIFS('フォームの回答 1'!$E:$E,'フォームの回答 1'!$B:$B,AD44,'フォームの回答 1'!$H:$H,$A46,'フォームの回答 1'!$F:$F,"Cash") -> 1892 | AE46: =SUMIFS('フォームの回答 1'!$E:$E,'フォームの回答 1'!$B:$B,AE44,'フォームの回答 1'!$H:$H,$A46,'フォームの回答 1'!$F:$F,"Cash") -> 3350 | AF46: =SUMIFS('フォームの回答 1'!$E:$E,'フォームの回答 1'!$B:$B,AF44,'フォームの回答 1'!$H:$H,$A46,'フォームの回答 1'!$F:$F,"Cash") -> 0 | AG46: =SUMIFS('フォームの回答 1'!$E:$E,'フォームの回答 1'!$B:$B,AG44,'フォームの回答 1'!$H:$H,$A46,'フォームの回答 1'!$F:$F,"Cash") -> 0
A47: 残高 | C47: =AG41+C45-C46 -> 40471 | D47: =C47+D45-D46 -> 39212 | E47: =D47+E45-E46 -> 35190 | F47: =E47+F45-F46 -> 28597 | G47: =F47+G45-G46 -> 28275 | H47: =G47+H45-H46 -> 46102 | I47: =H47+I45-I46 -> 46102 | J47: =I47+J45-J46 -> 44352 | K47: =J47+K45-K46 -> 39412 | ... AG47: =AF47+AG45-AG46 -> 46756
B49: 9月 | AI49: 9月クレジット引き落とし
B50: 合計金額 | C50: 45536 | D50: 45537 | E50: 45538 | F50: 45539 | G50: 45540 | H50: 45541 | I50: 45542 | J50: 45543 | K50: 45544 | L50: 45545 | M50: 45546 | N50: 45547 | O50: 45548 | P50: 45549 | Q50: 45550 | R50: 45551 | S50: 45552 | T50: 45553 | U50: 45554 | V50: 45555 | W50: 45556 | X50: 45557 | Y50: 45558 | Z50: 45559 | AA50: 45560 | AB50: 45561 | AC50: 45562 | AD50: 45563 | AE50: 45564 | AF50: 45565 | AI50: 139210
A51: 収入 | B51: =SUM(V51:AG51) -> 390997 | C51: =SUMIFS('フォームの回答 1'!$E:$E,'フォームの回答 1'!$B:$B,C50,'フォームの回答 1'!$H:$H,$A51) -> 0 | D51: =SUMIFS('フォームの回答 1'!$E:$E,'フォームの回答 1'!$B:$B,D50,'フォームの回答 1'!$H:$H,$A51) -> 0 | E51: =SUMIFS('フォームの回答 1'!$E:$E,'フォームの回答 1'!$B:$B,E50,'フォームの回答 1'!$H:$H,$A51) -> 0 | F51: =SUMIFS('フォームの回答 1'!$E:$E,'フォームの回答 1'!$B:$B,F50,'フォームの回答 1'!$H:$H,$A51) -> 11080 | G51: =SUMIFS('フォームの回答 1'!$E:$E,'フォームの回答 1'!$B:$B,G50,'フォームの回答 1'!$H:$H,$A51) -> 0 | H51: =SUMIFS('フォームの回答 1'!$E:$E,'フォームの回答 1'!$B:$B,H50,'フォームの回答 1'!$H:$H,$A51) -> 0 | I51: =SUMIFS('フォームの回答 1'!$E:$E,'フォームの回答 1'!$B:$B,I50,'フォームの回答 1'!$H:$H,$A51) -> 0 | J51: =SUMIFS('フォームの回答 1'!$E:$E,'フォームの回答 1'!$B:$B,J50,'フォームの回答 1'!$H:$H,$A51) -> 0 | ... Z51: =SUMIFS('フォームの回答 1'!$E:$E,'フォームの回答 1'!$B:$B,Z50,'フォームの回答 1'!$H:$H,$A51) -> 0 | AA51: =SUMIFS('フォームの回答 1'!$E:$E,'フォームの回答 1'!$B:$B,AA50,'フォームの回答 1'!$H:$H,$A51)+AJ42 -> 340997 | AB51: =SUMIFS('フォームの回答 1'!$E:$E,'フォームの回答 1'!$B:$B,AB50,'フォームの回答 1'!$H:$H,$A51) -> 0 | AC51: =SUMIFS('フォームの回答 1'!$E:$E,'フォームの回答 1'!$B:$B,AC50,'フォームの回答 1'!$H:$H,$A51) -> 0 | AD51: =SUMIFS('フォームの回答 1'!$E:$E,'フォームの回答 1'!$B:$B,AD50,'フォームの回答 1'!$H:$H,$A51) -> 0 | AE51: =SUMIFS('フォームの回答 1'!$E:$E,'フォームの回答 1'!$B:$B,AE50,'フォームの回答 1'!$H:$H,$A51) -> 50000 | AF51: =SUMIFS('フォームの回答 1'!$E:$E,'フォームの回答 1'!$B:$B,AF50,'フォームの回答 1'!$H:$H,$A51) -> 0
A52: 支出 | B52: =SUM(C52:AG52) -> 390731 | C52: =SUMIFS('フォームの回答 1'!$E:$E,'フォームの回答 1'!$B:$B,C50,'フォームの回答 1'!$H:$H,$A52,'フォームの回答 1'!$F:$F,"Cash") -> 6668 | D52: =SUMIFS('フォームの回答 1'!$E:$E,'フォームの回答 1'!$B:$B,D50,'フォームの回答 1'!$H:$H,$A52,'フォームの回答 1'!$F:$F,"Cash") -> 1620 | E52: =SUMIFS('フォームの回答 1'!$E:$E,'フォームの回答 1'!$B:$B,E50,'フォームの回答 1'!$H:$H,$A52,'フォームの回答 1'!$F:$F,"Cash") -> 0 | F52: =SUMIFS('フォームの回答 1'!$E:$E,'フォームの回答 1'!$B:$B,F50,'フォームの回答 1'!$H:$H,$A52,'フォームの回答 1'!$F:$F,"Cash") -> 3658 | G52: =SUMIFS('フォームの回答 1'!$E:$E,'フォームの回答 1'!$B:$B,G50,'フォームの回答 1'!$H:$H,$A52,'フォームの回答 1'!$F:$F,"Cash") -> 370 | H52: =SUMIFS('フォームの回答 1'!$E:$E,'フォームの回答 1'!$B:$B,H50,'フォームの回答 1'!$H:$H,$A52,'フォームの回答 1'!$F:$F,"Cash") -> 7620 | I52: =SUMIFS('フォームの回答 1'!$E:$E,'フォームの回答 1'!$B:$B,I50,'フォームの回答 1'!$H:$H,$A52,'フォームの回答 1'!$F:$F,"Cash") -> 6677 | J52: =SUMIFS('フォームの回答 1'!$E:$E,'フォームの回答 1'!$B:$B,J50,'フォームの回答 1'!$H:$H,$A52,'フォームの回答 1'!$F:$F,"Cash") -> 1140 | ... AB52: =SUMIFS('フォームの回答 1'!$E:$E,'フォームの回答 1'!$B:$B,AB50,'フォームの回答 1'!$H:$H,$A52,'フォームの回答 1'!$F:$F,"Cash") -> 14570 | AC52: =SUMIFS('フォームの回答 1'!$E:$E,'フォームの回答 1'!$B:$B,AC50,'フォームの回答 1'!$H:$H,$A52,'フォームの回答 1'!$F:$F,"Cash")+AI50 -> 305338 | AD52: =SUMIFS('フォームの回答 1'!$E:$E,'フォームの回答 1'!$B:$B,AD50,'フォームの回答 1'!$H:$H,$A52,'フォームの回答 1'!$F:$F,"Cash") -> 7988 | AE52: =SUMIFS('フォームの回答 1'!$E:$E,'フォームの回答 1'!$B:$B,AE50,'フォームの回答 1'!$H:$H,$A52,'フォームの回答 1'!$F:$F,"Cash") -> 0 | AF52: =SUMIFS('フォームの回答 1'!$E:$E,'フォームの回答 1'!$B:$B,AF50,'フォームの回答 1'!$H:$H,$A52,'フォームの回答 1'!$F:$F,"Cash") -> 3324
A53: 残高 | C53: =AG47+C51-C52 -> 40088 | D53: =C53+D51-D52 -> 38468 | E53: =D53+E51-E52 -> 38468 | F53: =E53+F51-F52 -> 45890 | G53: =F53+G51-G52 -> 45520 | H53: =G53+H51-H52 -> 37900 | I53: =H53+I51-I52 -> 31223 | J53: =I53+J51-J52 -> 30083 | K53: =J53+K51-K52 -> 29083 | ... AF53: =AE53+AF51-AF52 -> 58102
B55: 10月 | AI55: 10月クレジット引き落とし
B56: 合計金額 | C56: 45566 | D56: 45567 | E56: 45568 | F56: 45569 | G56: 45570 | H56: 45571 | I56: 45572 | J56: 45573 | K56: 45574 | L56: 45575 | M56: 45576 | N56: 45577 | O56: 45578 | P56: 45579 | Q56: 45580 | R56: 45581 | S56: 45582 | T56: 45583 | U56: 45584 | V56: 45585 | W56: 45586 | X56: 45587 | Y56: 45588 | Z56: 45589 | AA56: 45590 | AB56: 45591 | AC56: 45592 | AD56: 45593 | AE56: 45594 | AF56: 45595 | AG56: 45596 | AI56: 114925
A57: 収入 | B57: =SUM(V57:AG57) -> 349297 | C57: =SUMIFS('フォームの回答 1'!$E:$E,'フォームの回答 1'!$B:$B,C56,'フォームの回答 1'!$H:$H,$A57) -> 0 | D57: =SUMIFS('フォームの回答 1'!$E:$E,'フォームの回答 1'!$B:$B,D56,'フォームの回答 1'!$H:$H,$A57) -> 0 | E57: =SUMIFS('フォームの回答 1'!$E:$E,'フォームの回答 1'!$B:$B,E56,'フォームの回答 1'!$H:$H,$A57) -> 6999 | F57: =SUMIFS('フォームの回答 1'!$E:$E,'フォームの回答 1'!$B:$B,F56,'フォームの回答 1'!$H:$H,$A57) -> 0 | G57: =SUMIFS('フォームの回答 1'!$E:$E,'フォームの回答 1'!$B:$B,G56,'フォームの回答 1'!$H:$H,$A57) -> 0 | H57: =SUMIFS('フォームの回答 1'!$E:$E,'フォームの回答 1'!$B:$B,H56,'フォームの回答 1'!$H:$H,$A57) -> 0 | I57: =SUMIFS('フォームの回答 1'!$E:$E,'フォームの回答 1'!$B:$B,I56,'フォームの回答 1'!$H:$H,$A57) -> 0 | J57: =SUMIFS('フォームの回答 1'!$E:$E,'フォームの回答 1'!$B:$B,J56,'フォームの回答 1'!$H:$H,$A57) -> 0 | ... Z57: =SUMIFS('フォームの回答 1'!$E:$E,'フォームの回答 1'!$B:$B,Z56,'フォームの回答 1'!$H:$H,$A57) -> 0 | AA57: =SUMIFS('フォームの回答 1'!$E:$E,'フォームの回答 1'!$B:$B,AA56,'フォームの回答 1'!$H:$H,$A57)+AJ48 -> 340997 | AB57: =SUMIFS('フォームの回答 1'!$E:$E,'フォームの回答 1'!$B:$B,AB56,'フォームの回答 1'!$H:$H,$A57) -> 0 | AC57: =SUMIFS('フォームの回答 1'!$E:$E,'フォームの回答 1'!$B:$B,AC56,'フォームの回答 1'!$H:$H,$A57) -> 5000 | AD57: =SUMIFS('フォームの回答 1'!$E:$E,'フォームの回答 1'!$B:$B,AD56,'フォームの回答 1'!$H:$H,$A57) -> 0 | AE57: =SUMIFS('フォームの回答 1'!$E:$E,'フォームの回答 1'!$B:$B,AE56,'フォームの回答 1'!$H:$H,$A57) -> 0 | AF57: =SUMIFS('フォームの回答 1'!$E:$E,'フォームの回答 1'!$B:$B,AF56,'フォームの回答 1'!$H:$H,$A57) -> 0 | AG57: =SUMIFS('フォームの回答 1'!$E:$E,'フォームの回答 1'!$B:$B,AG56,'フォームの回答 1'!$H:$H,$A57) -> 3300
A58: 支出 | B58: =SUM(C58:AG58) -> 373580 | C58: =SUMIFS('フォームの回答 1'!$E:$E,'フォームの回答 1'!$B:$B,C56,'フォームの回答 1'!$H:$H,$A58,'フォームの回答 1'!$F:$F,"Cash") -> 0 | D58: =SUMIFS('フォームの回答 1'!$E:$E,'フォームの回答 1'!$B:$B,D56,'フォームの回答 1'!$H:$H,$A58,'フォームの回答 1'!$F:$F,"Cash") -> 4520 | E58: =SUMIFS('フォームの回答 1'!$E:$E,'フォームの回答 1'!$B:$B,E56,'フォームの回答 1'!$H:$H,$A58,'フォームの回答 1'!$F:$F,"Cash") -> 822 | F58: =SUMIFS('フォームの回答 1'!$E:$E,'フォームの回答 1'!$B:$B,F56,'フォームの回答 1'!$H:$H,$A58,'フォームの回答 1'!$F:$F,"Cash") -> 0 | G58: =SUMIFS('フォームの回答 1'!$E:$E,'フォームの回答 1'!$B:$B,G56,'フォームの回答 1'!$H:$H,$A58,'フォームの回答 1'!$F:$F,"Cash") -> 4240 | H58: =SUMIFS('フォームの回答 1'!$E:$E,'フォームの回答 1'!$B:$B,H56,'フォームの回答 1'!$H:$H,$A58,'フォームの回答 1'!$F:$F,"Cash") -> 2090 | I58: =SUMIFS('フォームの回答 1'!$E:$E,'フォームの回答 1'!$B:$B,I56,'フォームの回答 1'!$H:$H,$A58,'フォームの回答 1'!$F:$F,"Cash") -> 0 | J58: =SUMIFS('フォームの回答 1'!$E:$E,'フォームの回答 1'!$B:$B,J56,'フォームの回答 1'!$H:$H,$A58,'フォームの回答 1'!$F:$F,"Cash") -> 1100 | ... AB58: =SUMIFS('フォームの回答 1'!$E:$E,'フォームの回答 1'!$B:$B,AB56,'フォームの回答 1'!$H:$H,$A58,'フォームの回答 1'!$F:$F,"Cash") -> 330 | AC58: =SUMIFS('フォームの回答 1'!$E:$E,'フォームの回答 1'!$B:$B,AC56,'フォームの回答 1'!$H:$H,$A58,'フォームの回答 1'!$F:$F,"Cash")+AI56 -> 126719 | AD58: =SUMIFS('フォームの回答 1'!$E:$E,'フォームの回答 1'!$B:$B,AD56,'フォームの回答 1'!$H:$H,$A58,'フォームの回答 1'!$F:$F,"Cash") -> 175790 | AE58: =SUMIFS('フォームの回答 1'!$E:$E,'フォームの回答 1'!$B:$B,AE56,'フォームの回答 1'!$H:$H,$A58,'フォームの回答 1'!$F:$F,"Cash") -> 2746 | AF58: =SUMIFS('フォームの回答 1'!$E:$E,'フォームの回答 1'!$B:$B,AF56,'フォームの回答 1'!$H:$H,$A58,'フォームの回答 1'!$F:$F,"Cash") -> 1652 | AG58: =SUMIFS('フォームの回答 1'!$E:$E,'フォームの回答 1'!$B:$B,AG56,'フォームの回答 1'!$H:$H,$A58,'フォームの回答 1'!$F:$F,"Cash") -> 8180
A59: 残高 | C59: =AF53+C57-C58 -> 58102 | D59: =C59+D57-D58 -> 53582 | E59: =D59+E57-E58 -> 59759 | F59: =E59+F57-F58 -> 59759 | G59: =F59+G57-G58 -> 55519 | H59: =G59+H57-H58 -> 53429 | I59: =H59+I57-I58 -> 53429 | J59: =I59+J57-J58 -> 52329 | K59: =J59+K57-K58 -> 50529 | ... AG59: =AF59+AG57-AG58 -> 43818
B61: 11月 | AI61: 11月クレジット引き落とし
B62: 合計金額 | C62: 45597 | D62: 45598 | E62: 45599 | F62: 45600 | G62: 45601 | H62: 45602 | I62: 45603 | J62: 45604 | K62: 45605 | L62: 45606 | M62: 45607 | N62: 45608 | O62: 45609 | P62: 45610 | Q62: 45611 | R62: 45612 | S62: 45613 | T62: 45614 | U62: 45615 | V62: 45616 | W62: 45617 | X62: 45618 | Y62: 45619 | Z62: 45620 | AA62: 45621 | AB62: 45622 | AC62: 45623 | AD62: 45624 | AE62: 45625 | AF62: 45626 | AI62: 131725
A63: 収入 | B63: =SUM(V63:AG63) -> 340997 | C63: =SUMIFS('フォームの回答 1'!$E:$E,'フォームの回答 1'!$B:$B,C62,'フォームの回答 1'!$H:$H,$A63) -> 0 | D63: =SUMIFS('フォームの回答 1'!$E:$E,'フォームの回答 1'!$B:$B,D62,'フォームの回答 1'!$H:$H,$A63) -> 0 | E63: =SUMIFS('フォームの回答 1'!$E:$E,'フォームの回答 1'!$B:$B,E62,'フォームの回答 1'!$H:$H,$A63) -> 0 | F63: =SUMIFS('フォームの回答 1'!$E:$E,'フォームの回答 1'!$B:$B,F62,'フォームの回答 1'!$H:$H,$A63) -> 0 | G63: =SUMIFS('フォームの回答 1'!$E:$E,'フォームの回答 1'!$B:$B,G62,'フォームの回答 1'!$H:$H,$A63) -> 0 | H63: =SUMIFS('フォームの回答 1'!$E:$E,'フォームの回答 1'!$B:$B,H62,'フォームの回答 1'!$H:$H,$A63) -> 18406 | I63: =SUMIFS('フォームの回答 1'!$E:$E,'フォームの回答 1'!$B:$B,I62,'フォームの回答 1'!$H:$H,$A63) -> 0 | J63: =SUMIFS('フォームの回答 1'!$E:$E,'フォームの回答 1'!$B:$B,J62,'フォームの回答 1'!$H:$H,$A63) -> 0 | ... Z63: =SUMIFS('フォームの回答 1'!$E:$E,'フォームの回答 1'!$B:$B,Z62,'フォームの回答 1'!$H:$H,$A63) -> 0 | AA63: =SUMIFS('フォームの回答 1'!$E:$E,'フォームの回答 1'!$B:$B,AA62,'フォームの回答 1'!$H:$H,$A63)+AJ54 -> 340997 | AB63: =SUMIFS('フォームの回答 1'!$E:$E,'フォームの回答 1'!$B:$B,AB62,'フォームの回答 1'!$H:$H,$A63) -> 0 | AC63: =SUMIFS('フォームの回答 1'!$E:$E,'フォームの回答 1'!$B:$B,AC62,'フォームの回答 1'!$H:$H,$A63) -> 0 | AD63: =SUMIFS('フォームの回答 1'!$E:$E,'フォームの回答 1'!$B:$B,AD62,'フォームの回答 1'!$H:$H,$A63) -> 0 | AE63: =SUMIFS('フォームの回答 1'!$E:$E,'フォームの回答 1'!$B:$B,AE62,'フォームの回答 1'!$H:$H,$A63) -> 0 | AF63: =SUMIFS('フォームの回答 1'!$E:$E,'フォームの回答 1'!$B:$B,AF62,'フォームの回答 1'!$H:$H,$A63) -> 0
A64: 支出 | B64: =SUM(C64:AG64) -> 370634 | C64: =SUMIFS('フォームの回答 1'!$E:$E,'フォームの回答 1'!$B:$B,C62,'フォームの回答 1'!$H:$H,$A64,'フォームの回答 1'!$F:$F,"Cash") -> 1700 | D64: =SUMIFS('フォームの回答 1'!$E:$E,'フォームの回答 1'!$B:$B,D62,'フォームの回答 1'!$H:$H,$A64,'フォームの回答 1'!$F:$F,"Cash") -> 1817 | E64: =SUMIFS('フォームの回答 1'!$E:$E,'フォームの回答 1'!$B:$B,E62,'フォームの回答 1'!$H:$H,$A64,'フォームの回答 1'!$F:$F,"Cash") -> 426 | F64: =SUMIFS('フォームの回答 1'!$E:$E,'フォームの回答 1'!$B:$B,F62,'フォームの回答 1'!$H:$H,$A64,'フォームの回答 1'!$F:$F,"Cash") -> 3688 | G64: =SUMIFS('フォームの回答 1'!$E:$E,'フォームの回答 1'!$B:$B,G62,'フォームの回答 1'!$H:$H,$A64,'フォームの回答 1'!$F:$F,"Cash") -> 120 | H64: =SUMIFS('フォームの回答 1'!$E:$E,'フォームの回答 1'!$B:$B,H62,'フォームの回答 1'!$H:$H,$A64,'フォームの回答 1'!$F:$F,"Cash") -> 1158 | I64: =SUMIFS('フォームの回答 1'!$E:$E,'フォームの回答 1'!$B:$B,I62,'フォームの回答 1'!$H:$H,$A64,'フォームの回答 1'!$F:$F,"Cash") -> 3900 | J64: =SUMIFS('フォームの回答 1'!$E:$E,'フォームの回答 1'!$B:$B,J62,'フォームの回答 1'!$H:$H,$A64,'フォームの回答 1'!$F:$F,"Cash") -> 1220 | ... AB64: =SUMIFS('フォームの回答 1'!$E:$E,'フォームの回答 1'!$B:$B,AB62,'フォームの回答 1'!$H:$H,$A64,'フォームの回答 1'!$F:$F,"Cash") -> 5620 | AC64: =SUMIFS('フォームの回答 1'!$E:$E,'フォームの回答 1'!$B:$B,AC62,'フォームの回答 1'!$H:$H,$A64,'フォームの回答 1'!$F:$F,"Cash")+AI62 -> 278215 | AD64: =SUMIFS('フォームの回答 1'!$E:$E,'フォームの回答 1'!$B:$B,AD62,'フォームの回答 1'!$H:$H,$A64,'フォームの回答 1'!$F:$F,"Cash") -> 500 | AE64: =SUMIFS('フォームの回答 1'!$E:$E,'フォームの回答 1'!$B:$B,AE62,'フォームの回答 1'!$H:$H,$A64,'フォームの回答 1'!$F:$F,"Cash") -> 1190 | AF64: =SUMIFS('フォームの回答 1'!$E:$E,'フォームの回答 1'!$B:$B,AF62,'フォームの回答 1'!$H:$H,$A64,'フォームの回答 1'!$F:$F,"Cash") -> 892
A65: 残高 | C65: =AG59+C63-C64 -> 42118 | D65: =C65+D63-D64 -> 40301 | E65: =D65+E63-E64 -> 39875 | F65: =E65+F63-F64 -> 36187 | G65: =F65+G63-G64 -> 36067 | H65: =G65+H63-H64 -> 53315 | I65: =H65+I63-I64 -> 49415 | J65: =I65+J63-J64 -> 48195 | K65: =J65+K63-K64 -> 45582 | ... AF65: =AE65+AF63-AF64 -> 39587
B67: 12月 | AI67: 12月クレジット引き落とし
B68: 合計金額 | C68: 45627 | D68: 45628 | E68: 45629 | F68: 45630 | G68: 45631 | H68: 45632 | I68: 45633 | J68: 45634 | K68: 45635 | L68: 45636 | M68: 45637 | N68: 45638 | O68: 45639 | P68: 45640 | Q68: 45641 | R68: 45642 | S68: 45643 | T68: 45644 | U68: 45645 | V68: 45646 | W68: 45647 | X68: 45648 | Y68: 45649 | Z68: 45650 | AA68: 45651 | AB68: 45652 | AC68: 45653 | AD68: 45654 | AE68: 45655 | AF68: 45656 | AG68: 45657 | AI68: 154272
A69: 収入 | B69: =SUM(V69:AG69) -> 359044 | C69: =SUMIFS('フォームの回答 1'!$E:$E,'フォームの回答 1'!$B:$B,C68,'フォームの回答 1'!$H:$H,$A69) -> 0 | D69: =SUMIFS('フォームの回答 1'!$E:$E,'フォームの回答 1'!$B:$B,D68,'フォームの回答 1'!$H:$H,$A69) -> 0 | E69: =SUMIFS('フォームの回答 1'!$E:$E,'フォームの回答 1'!$B:$B,E68,'フォームの回答 1'!$H:$H,$A69) -> 0 | F69: =SUMIFS('フォームの回答 1'!$E:$E,'フォームの回答 1'!$B:$B,F68,'フォームの回答 1'!$H:$H,$A69) -> 28643 | G69: =SUMIFS('フォームの回答 1'!$E:$E,'フォームの回答 1'!$B:$B,G68,'フォームの回答 1'!$H:$H,$A69) -> 0 | H69: =SUMIFS('フォームの回答 1'!$E:$E,'フォームの回答 1'!$B:$B,H68,'フォームの回答 1'!$H:$H,$A69) -> 0 | I69: =SUMIFS('フォームの回答 1'!$E:$E,'フォームの回答 1'!$B:$B,I68,'フォームの回答 1'!$H:$H,$A69) -> 0 | J69: =SUMIFS('フォームの回答 1'!$E:$E,'フォームの回答 1'!$B:$B,J68,'フォームの回答 1'!$H:$H,$A69) -> 0 | ... Z69: =SUMIFS('フォームの回答 1'!$E:$E,'フォームの回答 1'!$B:$B,Z68,'フォームの回答 1'!$H:$H,$A69) -> 0 | AA69: =SUMIFS('フォームの回答 1'!$E:$E,'フォームの回答 1'!$B:$B,AA68,'フォームの回答 1'!$H:$H,$A69)+AJ60 -> 356924 | AB69: =SUMIFS('フォームの回答 1'!$E:$E,'フォームの回答 1'!$B:$B,AB68,'フォームの回答 1'!$H:$H,$A69) -> 0 | AC69: =SUMIFS('フォームの回答 1'!$E:$E,'フォームの回答 1'!$B:$B,AC68,'フォームの回答 1'!$H:$H,$A69) -> 0 | AD69: =SUMIFS('フォームの回答 1'!$E:$E,'フォームの回答 1'!$B:$B,AD68,'フォームの回答 1'!$H:$H,$A69) -> 0 | AE69: =SUMIFS('フォームの回答 1'!$E:$E,'フォームの回答 1'!$B:$B,AE68,'フォームの回答 1'!$H:$H,$A69) -> 2120 | AF69: =SUMIFS('フォームの回答 1'!$E:$E,'フォームの回答 1'!$B:$B,AF68,'フォームの回答 1'!$H:$H,$A69) -> 0 | AG69: =SUMIFS('フォームの回答 1'!$E:$E,'フォームの回答 1'!$B:$B,AG68,'フォームの回答 1'!$H:$H,$A69) -> 0
A70: 支出 | B70: =SUM(C70:AG70) -> 431222 | C70: =SUMIFS('フォームの回答 1'!$E:$E,'フォームの回答 1'!$B:$B,C68,'フォームの回答 1'!$H:$H,$A70,'フォームの回答 1'!$F:$F,"Cash") -> 1980 | D70: =SUMIFS('フォームの回答 1'!$E:$E,'フォームの回答 1'!$B:$B,D68,'フォームの回答 1'!$H:$H,$A70,'フォームの回答 1'!$F:$F,"Cash") -> 2373 | E70: =SUMIFS('フォームの回答 1'!$E:$E,'フォームの回答 1'!$B:$B,E68,'フォームの回答 1'!$H:$H,$A70,'フォームの回答 1'!$F:$F,"Cash") -> 556 | F70: =SUMIFS('フォームの回答 1'!$E:$E,'フォームの回答 1'!$B:$B,F68,'フォームの回答 1'!$H:$H,$A70,'フォームの回答 1'!$F:$F,"Cash") -> 0 | G70: =SUMIFS('フォームの回答 1'!$E:$E,'フォームの回答 1'!$B:$B,G68,'フォームの回答 1'!$H:$H,$A70,'フォームの回答 1'!$F:$F,"Cash") -> 1420 | H70: =SUMIFS('フォームの回答 1'!$E:$E,'フォームの回答 1'!$B:$B,H68,'フォームの回答 1'!$H:$H,$A70,'フォームの回答 1'!$F:$F,"Cash") -> 6169 | I70: =SUMIFS('フォームの回答 1'!$E:$E,'フォームの回答 1'!$B:$B,I68,'フォームの回答 1'!$H:$H,$A70,'フォームの回答 1'!$F:$F,"Cash") -> 1580 | J70: =SUMIFS('フォームの回答 1'!$E:$E,'フォームの回答 1'!$B:$B,J68,'フォームの回答 1'!$H:$H,$A70,'フォームの回答 1'!$F:$F,"Cash") -> 4855 | ... AB70: =SUMIFS('フォームの回答 1'!$E:$E,'フォームの回答 1'!$B:$B,AB68,'フォームの回答 1'!$H:$H,$A70,'フォームの回答 1'!$F:$F,"Cash") -> 3538 | AC70: =SUMIFS('フォームの回答 1'!$E:$E,'フォームの回答 1'!$B:$B,AC68,'フォームの回答 1'!$H:$H,$A70,'フォームの回答 1'!$F:$F,"Cash")+AI68 -> 299342 | AD70: =SUMIFS('フォームの回答 1'!$E:$E,'フォームの回答 1'!$B:$B,AD68,'フォームの回答 1'!$H:$H,$A70,'フォームの回答 1'!$F:$F,"Cash") -> 738 | AE70: =SUMIFS('フォームの回答 1'!$E:$E,'フォームの回答 1'!$B:$B,AE68,'フォームの回答 1'!$H:$H,$A70,'フォームの回答 1'!$F:$F,"Cash") -> 2273 | AF70: =SUMIFS('フォームの回答 1'!$E:$E,'フォームの回答 1'!$B:$B,AF68,'フォームの回答 1'!$H:$H,$A70,'フォームの回答 1'!$F:$F,"Cash") -> 2378 | AG70: =SUMIFS('フォームの回答 1'!$E:$E,'フォームの回答 1'!$B:$B,AG68,'フォームの回答 1'!$H:$H,$A70,'フォームの回答 1'!$F:$F,"Cash") -> 6929
A71: 残高 | C71: =AF65+C69-C70 -> 37607 | D71: =C71+D69-D70 -> 35234 | E71: =D71+E69-E70 -> 34678 | F71: =E71+F69-F70 -> 63321 | G71: =F71+G69-G70 -> 61901 | H71: =G71+H69-H70 -> 55732 | I71: =H71+I69-I70 -> 54152 | J71: =I71+J69-J70 -> 49297 | K71: =J71+K69-K70 -> 43117 | ... AG71: =AF71+AG69-AG70 -> 26052

Sheet 【Daily】2025年
B1: 1月
B2: 合計金額 | C2: 45658 | D2: 45659 | E2: 45660 | F2: 45661 | G2: 45662 | H2: 45663 | I2: 45664 | J2: 45665 | K2: 45666 | L2: 45667 | M2: 45668 | N2: 45669 | O2: 45670 | P2: 45671 | Q2: 45672 | R2: 45673 | S2: 45674 | T2: 45675 | U2: 45676 | V2: 45677 | W2: 45678 | X2: 45679 | Y2: 45680 | Z2: 45681 | AA2: 45682 | AB2: 45683 | AC2: 45684 | AD2: 45685 | AE2: 45686 | AF2: 45687 | AG2: 45688 | AI2: 1月クレジット引き落とし
A3: 収入 | B3: =SUM(V3:AG3) -> 340997 | C3: =SUMIFS('フォームの回答 1'!$E:$E,'フォームの回答 1'!$B:$B,C2,'フォームの回答 1'!$H:$H,$A3) -> 0 | D3: =SUMIFS('フォームの回答 1'!$E:$E,'フォームの回答 1'!$B:$B,D2,'フォームの回答 1'!$H:$H,$A3) -> 0 | E3: =SUMIFS('フォームの回答 1'!$E:$E,'フォームの回答 1'!$B:$B,E2,'フォームの回答 1'!$H:$H,$A3) -> 0 | F3: =SUMIFS('フォームの回答 1'!$E:$E,'フォームの回答 1'!$B:$B,F2,'フォームの回答 1'!$H:$H,$A3) -> 0 | G3: =SUMIFS('フォームの回答 1'!$E:$E,'フォームの回答 1'!$B:$B,G2,'フォームの回答 1'!$H:$H,$A3) -> 0 | H3: =SUMIFS('フォームの回答 1'!$E:$E,'フォームの回答 1'!$B:$B,H2,'フォームの回答 1'!$H:$H,$A3) -> 0 | I3: =SUMIFS('フォームの回答 1'!$E:$E,'フォームの回答 1'!$B:$B,I2,'フォームの回答 1'!$H:$H,$A3) -> 0 | J3: =SUMIFS('フォームの回答 1'!$E:$E,'フォームの回答 1'!$B:$B,J2,'フォームの回答 1'!$H:$H,$A3) -> 11396 | ... AG3: =SUMIFS('フォームの回答 1'!$E:$E,'フォームの回答 1'!$B:$B,AG2,'フォームの回答 1'!$H:$H,$A3) -> 0 | AI3: =130329 -> 130329
A4: 支出 | B4: =SUM(V4:AG4) -> 317103 | C4: =SUMIFS('フォームの回答 1'!$E:$E,'フォームの回答 1'!$B:$B,C2,'フォームの回答 1'!$H:$H,$A4,'フォームの回答 1'!$F:$F,"Cash") -> 3785 | D4: =SUMIFS('フォームの回答 1'!$E:$E,'フォームの回答 1'!$B:$B,D2,'フォームの回答 1'!$H:$H,$A4,'フォームの回答 1'!$F:$F,"Cash") -> 0 | E4: =SUMIFS('フォームの回答 1'!$E:$E,'フォームの回答 1'!$B:$B,E2,'フォームの回答 1'!$H:$H,$A4,'フォームの回答 1'!$F:$F,"Cash") -> 1100 | F4: =SUMIFS('フォームの回答 1'!$E:$E,'フォームの回答 1'!$B:$B,F2,'フォームの回答 1'!$H:$H,$A4,'フォームの回答 1'!$F:$F,"Cash") -> 1578 | G4: =SUMIFS('フォームの回答 1'!$E:$E,'フォームの回答 1'!$B:$B,G2,'フォームの回答 1'!$H:$H,$A4,'フォームの回答 1'!$F:$F,"Cash") -> 2311 | H4: =SUMIFS('フォームの回答 1'!$E:$E,'フォームの回答 1'!$B:$B,H2,'フォームの回答 1'!$H:$H,$A4,'フォームの回答 1'!$F:$F,"Cash") -> 3967 | I4: =SUMIFS('フォームの回答 1'!$E:$E,'フォームの回答 1'!$B:$B,I2,'フォームの回答 1'!$H:$H,$A4,'フォームの回答 1'!$F:$F,"Cash") -> 600 | J4: =SUMIFS('フォームの回答 1'!$E:$E,'フォームの回答 1'!$B:$B,J2,'フォームの回答 1'!$H:$H,$A4,'フォームの回答 1'!$F:$F,"Cash") -> 618 | ... AB4: =SUMIFS('フォームの回答 1'!$E:$E,'フォームの回答 1'!$B:$B,AB2,'フォームの回答 1'!$H:$H,$A4,'フォームの回答 1'!$F:$F,"Cash") -> 3113 | AC4: =SUMIFS('フォームの回答 1'!$E:$E,'フォームの回答 1'!$B:$B,AC2,'フォームの回答 1'!$H:$H,$A4,'フォームの回答 1'!$F:$F,"Cash")+AI3 -> 299288 | AD4: =SUMIFS('フォームの回答 1'!$E:$E,'フォームの回答 1'!$B:$B,AD2,'フォームの回答 1'!$H:$H,$A4,'フォームの回答 1'!$F:$F,"Cash") -> 2845 | AE4: =SUMIFS('フォームの回答 1'!$E:$E,'フォームの回答 1'!$B:$B,AE2,'フォームの回答 1'!$H:$H,$A4,'フォームの回答 1'!$F:$F,"Cash") -> 1440 | AF4: =SUMIFS('フォームの回答 1'!$E:$E,'フォームの回答 1'!$B:$B,AF2,'フォームの回答 1'!$H:$H,$A4,'フォームの回答 1'!$F:$F,"Cash") -> 0 | AG4: =SUMIFS('フォームの回答 1'!$E:$E,'フォームの回答 1'!$B:$B,AG2,'フォームの回答 1'!$H:$H,$A4,'フォームの回答 1'!$F:$F,"Cash") -> 2605
A5: 残高 | C5: =【Daily】2024年!AG71+C3-C4 -> 22267 | D5: =C5+D3-D4 -> 22267 | E5: =D5+E3-E4 -> 21167 | F5: =E5+F3-F4 -> 19589 | G5: =F5+G3-G4 -> 17278 | H5: =G5+H3-H4 -> 13311 | I5: =H5+I3-I4 -> 12711 | J5: =I5+J3-J4 -> 23489 | K5: =J5+K3-K4 -> 22489 | ... AG5: =AF5+AG3-AG4 -> 45739
B7: 2月
B8: 合計金額 | C8: 45689 | D8: 45690 | E8: 45691 | F8: 45692 | G8: 45693 | H8: 45694 | I8: 45695 | J8: 45696 | K8: 45697 | L8: 45698 | M8: 45699 | N8: 45700 | O8: 45701 | P8: 45702 | Q8: 45703 | R8: 45704 | S8: 45705 | T8: 45706 | U8: 45707 | V8: 45708 | W8: 45709 | X8: 45710 | Y8: 45711 | Z8: 45712 | AA8: 45713 | AB8: 45714 | AC8: 45715 | AD8: 45716 | AI8: 2月クレジット引き落とし
A9: 収入 | B9: =SUM(V9:AG9) -> 393067 | C9: =SUMIFS('フォームの回答 1'!$E:$E,'フォームの回答 1'!$B:$B,C8,'フォームの回答 1'!$H:$H,$A9) -> 0 | D9: =SUMIFS('フォームの回答 1'!$E:$E,'フォームの回答 1'!$B:$B,D8,'フォームの回答 1'!$H:$H,$A9) -> 0 | E9: =SUMIFS('フォームの回答 1'!$E:$E,'フォームの回答 1'!$B:$B,E8,'フォームの回答 1'!$H:$H,$A9) -> 16436 | F9: =SUMIFS('フォームの回答 1'!$E:$E,'フォームの回答 1'!$B:$B,F8,'フォームの回答 1'!$H:$H,$A9) -> 0 | G9: =SUMIFS('フォームの回答 1'!$E:$E,'フォームの回答 1'!$B:$B,G8,'フォームの回答 1'!$H:$H,$A9) -> 0 | H9: =SUMIFS('フォームの回答 1'!$E:$E,'フォームの回答 1'!$B:$B,H8,'フォームの回答 1'!$H:$H,$A9) -> 0 | I9: =SUMIFS('フォームの回答 1'!$E:$E,'フォームの回答 1'!$B:$B,I8,'フォームの回答 1'!$H:$H,$A9) -> 0 | J9: =SUMIFS('フォームの回答 1'!$E:$E,'フォームの回答 1'!$B:$B,J8,'フォームの回答 1'!$H:$H,$A9) -> 1000 | ... U9: =SUMIFS('フォームの回答 1'!$E:$E,'フォームの回答 1'!$B:$B,U8,'フォームの回答 1'!$H:$H,$A9) -> 0 | V9: =SUMIFS('フォームの回答 1'!$E:$E,'フォームの回答 1'!$B:$B,V8,'フォームの回答 1'!$H:$H,$A9)+AJ11 -> 4802 | W9: =SUMIFS('フォームの回答 1'!$E:$E,'フォームの回答 1'!$B:$B,W8,'フォームの回答 1'!$H:$H,$A9) -> 0 | X9: =SUMIFS('フォームの回答 1'!$E:$E,'フォームの回答 1'!$B:$B,X8,'フォームの回答 1'!$H:$H,$A9) -> 0 | Y9: =SUMIFS('フォームの回答 1'!$E:$E,'フォームの回答 1'!$B:$B,Y8,'フォームの回答 1'!$H:$H,$A9) -> 0 | Z9: =SUMIFS('フォームの回答 1'!$E:$E,'フォームの回答 1'!$B:$B,Z8,'フォームの回答 1'!$H:$H,$A9) -> 3000 | AA9: =SUMIFS('フォームの回答 1'!$E:$E,'フォームの回答 1'!$B:$B,AA8,'フォームの回答 1'!$H:$H,$A9) -> 385265 | AB9: =SUMIFS('フォームの回答 1'!$E:$E,'フォームの回答 1'!$B:$B,AB8,'フォームの回答 1'!$H:$H,$A9) -> 0 | AC9: =SUMIFS('フォームの回答 1'!$E:$E,'フォームの回答 1'!$B:$B,AC8,'フォームの回答 1'!$H:$H,$A9) -> 0 | AD9: =SUMIFS('フォームの回答 1'!$E:$E,'フォームの回答 1'!$B:$B,AD8,'フォームの回答 1'!$H:$H,$A9) -> 0 | AI9: =158596 -> 158596
A10: 支出 | B10: =SUM(V10:AG10) -> 377876 | C10: =SUMIFS('フォームの回答 1'!$E:$E,'フォームの回答 1'!$B:$B,C8,'フォームの回答 1'!$H:$H,$A10,'フォームの回答 1'!$F:$F,"Cash") -> 241 | D10: =SUMIFS('フォームの回答 1'!$E:$E,'フォームの回答 1'!$B:$B,D8,'フォームの回答 1'!$H:$H,$A10,'フォームの回答 1'!$F:$F,"Cash") -> 1421 | E10: =SUMIFS('フォームの回答 1'!$E:$E,'フォームの回答 1'!$B:$B,E8,'フォームの回答 1'!$H:$H,$A10,'フォームの回答 1'!$F:$F,"Cash") -> 2348 | F10: =SUMIFS('フォームの回答 1'!$E:$E,'フォームの回答 1'!$B:$B,F8,'フォームの回答 1'!$H:$H,$A10,'フォームの回答 1'!$F:$F,"Cash") -> 0 | G10: =SUMIFS('フォームの回答 1'!$E:$E,'フォームの回答 1'!$B:$B,G8,'フォームの回答 1'!$H:$H,$A10,'フォームの回答 1'!$F:$F,"Cash") -> 626 | H10: =SUMIFS('フォームの回答 1'!$E:$E,'フォームの回答 1'!$B:$B,H8,'フォームの回答 1'!$H:$H,$A10,'フォームの回答 1'!$F:$F,"Cash") -> 0 | I10: =SUMIFS('フォームの回答 1'!$E:$E,'フォームの回答 1'!$B:$B,I8,'フォームの回答 1'!$H:$H,$A10,'フォームの回答 1'!$F:$F,"Cash") -> 8250 | J10: =SUMIFS('フォームの回答 1'!$E:$E,'フォームの回答 1'!$B:$B,J8,'フォームの回答 1'!$H:$H,$A10,'フォームの回答 1'!$F:$F,"Cash") -> 5610 | ... AB10: =SUMIFS('フォームの回答 1'!$E:$E,'フォームの回答 1'!$B:$B,AB8,'フォームの回答 1'!$H:$H,$A10,'フォームの回答 1'!$F:$F,"Cash") -> 857 | AC10: =SUMIFS('フォームの回答 1'!$E:$E,'フォームの回答 1'!$B:$B,AC8,'フォームの回答 1'!$H:$H,$A10,'フォームの回答 1'!$F:$F,"Cash")+AI9 -> 339966 | AD10: =SUMIFS('フォームの回答 1'!$E:$E,'フォームの回答 1'!$B:$B,AD8,'フォームの回答 1'!$H:$H,$A10,'フォームの回答 1'!$F:$F,"Cash") -> 2740
A11: 残高 | C11: =AG5+C9-C10 -> 45498 | D11: =C11+D9-D10 -> 44077 | E11: =D11+E9-E10 -> 58165 | F11: =E11+F9-F10 -> 58165 | G11: =F11+G9-G10 -> 57539 | H11: =G11+H9-H10 -> 57539 | I11: =H11+I9-I10 -> 49289 | J11: =I11+J9-J10 -> 44679 | K11: =J11+K9-K10 -> 32327 | ... AD11: =AC11+AD9-AD10 -> 32733
B13: 3月
B14: 合計金額 | C14: 45717 | D14: 45718 | E14: 45719 | F14: 45720 | G14: 45721 | H14: 45722 | I14: 45723 | J14: 45724 | K14: 45725 | L14: 45726 | M14: 45727 | N14: 45728 | O14: 45729 | P14: 45730 | Q14: 45731 | R14: 45732 | S14: 45733 | T14: 45734 | U14: 45735 | V14: 45736 | W14: 45737 | X14: 45738 | Y14: 45739 | Z14: 45740 | AA14: 45741 | AB14: 45742 | AC14: 45743 | AD14: 45744 | AE14: 45745 | AF14: 45746 | AG14: 45747 | AI14: 3月クレジット引き落とし
A15: 収入 | B15: =SUM(V15:AG15) -> 389942 | C15: =SUMIFS('フォームの回答 1'!$E:$E,'フォームの回答 1'!$B:$B,C14,'フォームの回答 1'!$H:$H,$A15) -> 0 | D15: =SUMIFS('フォームの回答 1'!$E:$E,'フォームの回答 1'!$B:$B,D14,'フォームの回答 1'!$H:$H,$A15) -> 0 | E15: =SUMIFS('フォームの回答 1'!$E:$E,'フォームの回答 1'!$B:$B,E14,'フォームの回答 1'!$H:$H,$A15) -> 0 | F15: =SUMIFS('フォームの回答 1'!$E:$E,'フォームの回答 1'!$B:$B,F14,'フォームの回答 1'!$H:$H,$A15) -> 0 | G15: =SUMIFS('フォームの回答 1'!$E:$E,'フォームの回答 1'!$B:$B,G14,'フォームの回答 1'!$H:$H,$A15) -> 35966 | H15: =SUMIFS('フォームの回答 1'!$E:$E,'フォームの回答 1'!$B:$B,H14,'フォームの回答 1'!$H:$H,$A15) -> 0 | I15: =SUMIFS('フォームの回答 1'!$E:$E,'フォームの回答 1'!$B:$B,I14,'フォームの回答 1'!$H:$H,$A15) -> 0 | J15: =SUMIFS('フォームの回答 1'!$E:$E,'フォームの回答 1'!$B:$B,J14,'フォームの回答 1'!$H:$H,$A15) -> 0 | ... AA15: =SUMIFS('フォームの回答 1'!$E:$E,'フォームの回答 1'!$B:$B,AA14,'フォームの回答 1'!$H:$H,$A15) -> 385265 | AB15: =SUMIFS('フォームの回答 1'!$E:$E,'フォームの回答 1'!$B:$B,AB14,'フォームの回答 1'!$H:$H,$A15)+AJ23 -> 1500 | AC15: =SUMIFS('フォームの回答 1'!$E:$E,'フォームの回答 1'!$B:$B,AC14,'フォームの回答 1'!$H:$H,$A15) -> 0 | AD15: =SUMIFS('フォームの回答 1'!$E:$E,'フォームの回答 1'!$B:$B,AD14,'フォームの回答 1'!$H:$H,$A15) -> 0 | AE15: =SUMIFS('フォームの回答 1'!$E:$E,'フォームの回答 1'!$B:$B,AE14,'フォームの回答 1'!$H:$H,$A15) -> 3177 | AF15: =SUMIFS('フォームの回答 1'!$E:$E,'フォームの回答 1'!$B:$B,AF14,'フォームの回答 1'!$H:$H,$A15) -> 0 | AG15: =SUMIFS('フォームの回答 1'!$E:$E,'フォームの回答 1'!$B:$B,AG14,'フォームの回答 1'!$H:$H,$A15) -> 0 | AI15: =156613 -> 156613
A16: 支出 | B16: =SUM(V16:AG16) -> 356364 | C16: =SUMIFS('フォームの回答 1'!$E:$E,'フォームの回答 1'!$B:$B,C14,'フォームの回答 1'!$H:$H,$A16,'フォームの回答 1'!$F:$F,"Cash") -> 500 | D16: =SUMIFS('フォームの回答 1'!$E:$E,'フォームの回答 1'!$B:$B,D14,'フォームの回答 1'!$H:$H,$A16,'フォームの回答 1'!$F:$F,"Cash") -> 10285 | E16: =SUMIFS('フォームの回答 1'!$E:$E,'フォームの回答 1'!$B:$B,E14,'フォームの回答 1'!$H:$H,$A16,'フォームの回答 1'!$F:$F,"Cash") -> 1300 | F16: =SUMIFS('フォームの回答 1'!$E:$E,'フォームの回答 1'!$B:$B,F14,'フォームの回答 1'!$H:$H,$A16,'フォームの回答 1'!$F:$F,"Cash") -> 900 | G16: =SUMIFS('フォームの回答 1'!$E:$E,'フォームの回答 1'!$B:$B,G14,'フォームの回答 1'!$H:$H,$A16,'フォームの回答 1'!$F:$F,"Cash") -> 0 | H16: =SUMIFS('フォームの回答 1'!$E:$E,'フォームの回答 1'!$B:$B,H14,'フォームの回答 1'!$H:$H,$A16,'フォームの回答 1'!$F:$F,"Cash") -> 522 | I16: =SUMIFS('フォームの回答 1'!$E:$E,'フォームの回答 1'!$B:$B,I14,'フォームの回答 1'!$H:$H,$A16,'フォームの回答 1'!$F:$F,"Cash") -> 0 | J16: =SUMIFS('フォームの回答 1'!$E:$E,'フォームの回答 1'!$B:$B,J14,'フォームの回答 1'!$H:$H,$A16,'フォームの回答 1'!$F:$F,"Cash") -> 1780 | ... AB16: =SUMIFS('フォームの回答 1'!$E:$E,'フォームの回答 1'!$B:$B,AB14,'フォームの回答 1'!$H:$H,$A16,'フォームの回答 1'!$F:$F,"Cash") -> 2649 | AC16: =SUMIFS('フォームの回答 1'!$E:$E,'フォームの回答 1'!$B:$B,AC14,'フォームの回答 1'!$H:$H,$A16,'フォームの回答 1'!$F:$F,"Cash")+AI15 -> 336183 | AD16: =SUMIFS('フォームの回答 1'!$E:$E,'フォームの回答 1'!$B:$B,AD14,'フォームの回答 1'!$H:$H,$A16,'フォームの回答 1'!$F:$F,"Cash") -> 0 | AE16: =SUMIFS('フォームの回答 1'!$E:$E,'フォームの回答 1'!$B:$B,AE14,'フォームの回答 1'!$H:$H,$A16,'フォームの回答 1'!$F:$F,"Cash") -> 1190 | AF16: =SUMIFS('フォームの回答 1'!$E:$E,'フォームの回答 1'!$B:$B,AF14,'フォームの回答 1'!$H:$H,$A16,'フォームの回答 1'!$F:$F,"Cash") -> 4179 | AG16: =SUMIFS('フォームの回答 1'!$E:$E,'フォームの回答 1'!$B:$B,AG14,'フォームの回答 1'!$H:$H,$A16,'フォームの回答 1'!$F:$F,"Cash") -> 1916
A17: 残高 | C17: =AD11+C15-C16 -> 32233 | D17: =C17+D15-D16 -> 21948 | E17: =D17+E15-E16 -> 20648 | F17: =E17+F15-F16 -> 19748 | G17: =F17+G15-G16 -> 55714 | H17: =G17+H15-H16 -> 55192 | I17: =H17+I15-I16 -> 55192 | J17: =I17+J15-J16 -> 53412 | K17: =J17+K15-K16 -> 48261 | ... AG17: =AF17+AG15-AG16 -> 67197
B19: 4月 | AI19: 4月クレジット引き落とし
B20: 合計金額 | C20: 45748 | D20: 45749 | E20: 45750 | F20: 45751 | G20: 45752 | H20: 45753 | I20: 45754 | J20: 45755 | K20: 45756 | L20: 45757 | M20: 45758 | N20: 45759 | O20: 45760 | P20: 45761 | Q20: 45762 | R20: 45763 | S20: 45764 | T20: 45765 | U20: 45766 | V20: 45767 | W20: 45768 | X20: 45769 | Y20: 45770 | Z20: 45771 | AA20: 45772 | AB20: 45773 | AC20: 45774 | AD20: 45775 | AE20: 45776 | AF20: 45777 | AI20: =130531 -> 130531
A21: 収入 | B21: =SUM(V21:AG21) -> 392705 | C21: =SUMIFS('フォームの回答 1'!$E:$E,'フォームの回答 1'!$B:$B,C20,'フォームの回答 1'!$H:$H,$A21) -> 0 | D21: =SUMIFS('フォームの回答 1'!$E:$E,'フォームの回答 1'!$B:$B,D20,'フォームの回答 1'!$H:$H,$A21) -> 12864 | E21: =SUMIFS('フォームの回答 1'!$E:$E,'フォームの回答 1'!$B:$B,E20,'フォームの回答 1'!$H:$H,$A21) -> 0 | F21: =SUMIFS('フォームの回答 1'!$E:$E,'フォームの回答 1'!$B:$B,F20,'フォームの回答 1'!$H:$H,$A21) -> 0 | G21: =SUMIFS('フォームの回答 1'!$E:$E,'フォームの回答 1'!$B:$B,G20,'フォームの回答 1'!$H:$H,$A21) -> 4900 | H21: =SUMIFS('フォームの回答 1'!$E:$E,'フォームの回答 1'!$B:$B,H20,'フォームの回答 1'!$H:$H,$A21) -> 16000 | I21: =SUMIFS('フォームの回答 1'!$E:$E,'フォームの回答 1'!$B:$B,I20,'フォームの回答 1'!$H:$H,$A21) -> 0 | J21: =SUMIFS('フォームの回答 1'!$E:$E,'フォームの回答 1'!$B:$B,J20,'フォームの回答 1'!$H:$H,$A21) -> 0 | ... AF21: =SUMIFS('フォームの回答 1'!$E:$E,'フォームの回答 1'!$B:$B,AF20,'フォームの回答 1'!$H:$H,$A21) -> 0
A22: 支出 | B22: =SUM(V22:AG22) -> 330347 | C22: =SUMIFS('フォームの回答 1'!$E:$E,'フォームの回答 1'!$B:$B,C20,'フォームの回答 1'!$H:$H,$A22,'フォームの回答 1'!$F:$F,"Cash") -> 1300 | D22: =SUMIFS('フォームの回答 1'!$E:$E,'フォームの回答 1'!$B:$B,D20,'フォームの回答 1'!$H:$H,$A22,'フォームの回答 1'!$F:$F,"Cash") -> 940 | E22: =SUMIFS('フォームの回答 1'!$E:$E,'フォームの回答 1'!$B:$B,E20,'フォームの回答 1'!$H:$H,$A22,'フォームの回答 1'!$F:$F,"Cash") -> 0 | F22: =SUMIFS('フォームの回答 1'!$E:$E,'フォームの回答 1'!$B:$B,F20,'フォームの回答 1'!$H:$H,$A22,'フォームの回答 1'!$F:$F,"Cash") -> 1218 | G22: =SUMIFS('フォームの回答 1'!$E:$E,'フォームの回答 1'!$B:$B,G20,'フォームの回答 1'!$H:$H,$A22,'フォームの回答 1'!$F:$F,"Cash") -> 10500 | H22: =SUMIFS('フォームの回答 1'!$E:$E,'フォームの回答 1'!$B:$B,H20,'フォームの回答 1'!$H:$H,$A22,'フォームの回答 1'!$F:$F,"Cash") -> 27681 | I22: =SUMIFS('フォームの回答 1'!$E:$E,'フォームの回答 1'!$B:$B,I20,'フォームの回答 1'!$H:$H,$A22,'フォームの回答 1'!$F:$F,"Cash") -> 1117 | J22: =SUMIFS('フォームの回答 1'!$E:$E,'フォームの回答 1'!$B:$B,J20,'フォームの回答 1'!$H:$H,$A22,'フォームの回答 1'!$F:$F,"Cash") -> 1620 | ... AB22: =SUMIFS('フォームの回答 1'!$E:$E,'フォームの回答 1'!$B:$B,AB20,'フォームの回答 1'!$H:$H,$A22,'フォームの回答 1'!$F:$F,"Cash") -> 5078 | AC22: =SUMIFS('フォームの回答 1'!$E:$E,'フォームの回答 1'!$B:$B,AC20,'フォームの回答 1'!$H:$H,$A22,'フォームの回答 1'!$F:$F,"Cash")+AI20 -> 161964 | AD22: =SUMIFS('フォームの回答 1'!$E:$E,'フォームの回答 1'!$B:$B,AD20,'フォームの回答 1'!$H:$H,$A22,'フォームの回答 1'!$F:$F,"Cash") -> 149370 | AE22: =SUMIFS('フォームの回答 1'!$E:$E,'フォームの回答 1'!$B:$B,AE20,'フォームの回答 1'!$H:$H,$A22,'フォームの回答 1'!$F:$F,"Cash") -> 2571 | AF22: =SUMIFS('フォームの回答 1'!$E:$E,'フォームの回答 1'!$B:$B,AF20,'フォームの回答 1'!$H:$H,$A22,'フォームの回答 1'!$F:$F,"Cash") -> 4450
A23: 残高 | C23: =AG17+C21-C22 -> 65897 | D23: =C23+D21-D22 -> 77821 | E23: =D23+E21-E22 -> 77821 | F23: =E23+F21-F22 -> 76603 | G23: =F23+G21-G22 -> 71003 | H23: =G23+H21-H22 -> 59322 | I23: =H23+I21-I22 -> 58205 | J23: =I23+J21-J22 -> 56585 | K23: =J23+K21-K22 -> 56585 | ... AF23: =AE23+AF21-AF22 -> 85249
B25: 5月 | AI25: 5月クレジット引き落とし
B26: 合計金額 | C26: 45778 | D26: 45779 | E26: 45780 | F26: 45781 | G26: 45782 | H26: 45783 | I26: 45784 | J26: 45785 | K26: 45786 | L26: 45787 | M26: 45788 | N26: 45789 | O26: 45790 | P26: 45791 | Q26: 45792 | R26: 45793 | S26: 45794 | T26: 45795 | U26: 45796 | V26: 45797 | W26: 45798 | X26: 45799 | Y26: 45800 | Z26: 45801 | AA26: 45802 | AB26: 45803 | AC26: 45804 | AD26: 45805 | AE26: 45806 | AF26: 45807 | AG26: 45808 | AI26: =177989 -> 177989
A27: 収入 | B27: =SUM(V27:AG27) -> 535505 | C27: =SUMIFS('フォームの回答 1'!$E:$E,'フォームの回答 1'!$B:$B,C26,'フォームの回答 1'!$H:$H,$A27) -> 0 | D27: =SUMIFS('フォームの回答 1'!$E:$E,'フォームの回答 1'!$B:$B,D26,'フォームの回答 1'!$H:$H,$A27) -> 0 | E27: =SUMIFS('フォームの回答 1'!$E:$E,'フォームの回答 1'!$B:$B,E26,'フォームの回答 1'!$H:$H,$A27) -> 250 | F27: =SUMIFS('フォームの回答 1'!$E:$E,'フォームの回答 1'!$B:$B,F26,'フォームの回答 1'!$H:$H,$A27) -> 0 | G27: =SUMIFS('フォームの回答 1'!$E:$E,'フォームの回答 1'!$B:$B,G26,'フォームの回答 1'!$H:$H,$A27) -> 0 | H27: =SUMIFS('フォームの回答 1'!$E:$E,'フォームの回答 1'!$B:$B,H26,'フォームの回答 1'!$H:$H,$A27) -> 0 | I27: =SUMIFS('フォームの回答 1'!$E:$E,'フォームの回答 1'!$B:$B,I26,'フォームの回答 1'!$H:$H,$A27) -> 0 | J27: =SUMIFS('フォームの回答 1'!$E:$E,'フォームの回答 1'!$B:$B,J26,'フォームの回答 1'!$H:$H,$A27) -> 0 | ... Z27: =SUMIFS('フォームの回答 1'!$E:$E,'フォームの回答 1'!$B:$B,Z26,'フォームの回答 1'!$H:$H,$A27) -> 0 | AA27: =SUMIFS('フォームの回答 1'!$E:$E,'フォームの回答 1'!$B:$B,AA26,'フォームの回答 1'!$H:$H,$A27)+AJ18 -> 0 | AB27: =SUMIFS('フォームの回答 1'!$E:$E,'フォームの回答 1'!$B:$B,AB26,'フォームの回答 1'!$H:$H,$A27)+AI28 -> 150000 | AC27: =SUMIFS('フォームの回答 1'!$E:$E,'フォームの回答 1'!$B:$B,AC26,'フォームの回答 1'!$H:$H,$A27) -> 0 | AD27: =SUMIFS('フォームの回答 1'!$E:$E,'フォームの回答 1'!$B:$B,AD26,'フォームの回答 1'!$H:$H,$A27) -> 0 | AE27: =SUMIFS('フォームの回答 1'!$E:$E,'フォームの回答 1'!$B:$B,AE26,'フォームの回答 1'!$H:$H,$A27) -> 0 | AF27: =SUMIFS('フォームの回答 1'!$E:$E,'フォームの回答 1'!$B:$B,AF26,'フォームの回答 1'!$H:$H,$A27) -> 0 | AG27: =SUMIFS('フォームの回答 1'!$E:$E,'フォームの回答 1'!$B:$B,AG26,'フォームの回答 1'!$H:$H,$A27) -> 0 | AI27: ローン追加
A28: 支出 | B28: =SUM(C28:AG28) -> 581673 | C28: =SUMIFS('フォームの回答 1'!$E:$E,'フォームの回答 1'!$B:$B,C26,'フォームの回答 1'!$H:$H,$A28,'フォームの回答 1'!$F:$F,"Cash") -> 352 | D28: =SUMIFS('フォームの回答 1'!$E:$E,'フォームの回答 1'!$B:$B,D26,'フォームの回答 1'!$H:$H,$A28,'フォームの回答 1'!$F:$F,"Cash") -> 10191 | E28: =SUMIFS('フォームの回答 1'!$E:$E,'フォームの回答 1'!$B:$B,E26,'フォームの回答 1'!$H:$H,$A28,'フォームの回答 1'!$F:$F,"Cash") -> 5693 | F28: =SUMIFS('フォームの回答 1'!$E:$E,'フォームの回答 1'!$B:$B,F26,'フォームの回答 1'!$H:$H,$A28,'フォームの回答 1'!$F:$F,"Cash") -> 871 | G28: =SUMIFS('フォームの回答 1'!$E:$E,'フォームの回答 1'!$B:$B,G26,'フォームの回答 1'!$H:$H,$A28,'フォームの回答 1'!$F:$F,"Cash") -> 0 | H28: =SUMIFS('フォームの回答 1'!$E:$E,'フォームの回答 1'!$B:$B,H26,'フォームの回答 1'!$H:$H,$A28,'フォームの回答 1'!$F:$F,"Cash") -> 1320 | I28: =SUMIFS('フォームの回答 1'!$E:$E,'フォームの回答 1'!$B:$B,I26,'フォームの回答 1'!$H:$H,$A28,'フォームの回答 1'!$F:$F,"Cash") -> 2127 | J28: =SUMIFS('フォームの回答 1'!$E:$E,'フォームの回答 1'!$B:$B,J26,'フォームの回答 1'!$H:$H,$A28,'フォームの回答 1'!$F:$F,"Cash") -> 3250 | ... AB28: =SUMIFS('フォームの回答 1'!$E:$E,'フォームの回答 1'!$B:$B,AB26,'フォームの回答 1'!$H:$H,$A28,'フォームの回答 1'!$F:$F,"Cash") -> 131510 | AC28: =SUMIFS('フォームの回答 1'!$E:$E,'フォームの回答 1'!$B:$B,AC26,'フォームの回答 1'!$H:$H,$A28,'フォームの回答 1'!$F:$F,"Cash")+AI26 -> 359389 | AD28: =SUMIFS('フォームの回答 1'!$E:$E,'フォームの回答 1'!$B:$B,AD26,'フォームの回答 1'!$H:$H,$A28,'フォームの回答 1'!$F:$F,"Cash") -> 3745 | AE28: =SUMIFS('フォームの回答 1'!$E:$E,'フォームの回答 1'!$B:$B,AE26,'フォームの回答 1'!$H:$H,$A28,'フォームの回答 1'!$F:$F,"Cash") -> 1990 | AF28: =SUMIFS('フォームの回答 1'!$E:$E,'フォームの回答 1'!$B:$B,AF26,'フォームの回答 1'!$H:$H,$A28,'フォームの回答 1'!$F:$F,"Cash") -> 1453 | AG28: =SUMIFS('フォームの回答 1'!$E:$E,'フォームの回答 1'!$B:$B,AG26,'フォームの回答 1'!$H:$H,$A28,'フォームの回答 1'!$F:$F,"Cash") -> 1884 | AI28: 150000
A29: 残高 | C29: =AF23+C27-C28 -> 84897 | D29: =C29+D27-D28 -> 74706 | E29: =D29+E27-E28 -> 69263 | F29: =E29+F27-F28 -> 68392 | G29: =F29+G27-G28 -> 68392 | H29: =G29+H27-H28 -> 67072 | I29: =H29+I27-I28 -> 64945 | J29: =I29+J27-J28 -> 61695 | K29: =J29+K27-K28 -> 61695 | ... AG29: =AF29+AG27-AG28 -> 49271
B31: 6月 | AI31: 6月クレジット引き落とし
B32: 合計金額 | C32: 45809 | D32: 45810 | E32: 45811 | F32: 45812 | G32: 45813 | H32: 45814 | I32: 45815 | J32: 45816 | K32: 45817 | L32: 45818 | M32: 45819 | N32: 45820 | O32: 45821 | P32: 45822 | Q32: 45823 | R32: 45824 | S32: 45825 | T32: 45826 | U32: 45827 | V32: 45828 | W32: 45829 | X32: 45830 | Y32: 45831 | Z32: 45832 | AA32: 45833 | AB32: 45834 | AC32: 45835 | AD32: 45836 | AE32: 45837 | AF32: 45838 | AI32: =153036 -> 153036
A33: 収入 | B33: =SUM(V33:AG33) -> 378905 | C33: =SUMIFS('フォームの回答 1'!$E:$E,'フォームの回答 1'!$B:$B,C32,'フォームの回答 1'!$H:$H,$A33) -> 0 | D33: =SUMIFS('フォームの回答 1'!$E:$E,'フォームの回答 1'!$B:$B,D32,'フォームの回答 1'!$H:$H,$A33) -> 0 | E33: =SUMIFS('フォームの回答 1'!$E:$E,'フォームの回答 1'!$B:$B,E32,'フォームの回答 1'!$H:$H,$A33) -> 0 | F33: =SUMIFS('フォームの回答 1'!$E:$E,'フォームの回答 1'!$B:$B,F32,'フォームの回答 1'!$H:$H,$A33) -> 0 | G33: =SUMIFS('フォームの回答 1'!$E:$E,'フォームの回答 1'!$B:$B,G32,'フォームの回答 1'!$H:$H,$A33) -> 0 | H33: =SUMIFS('フォームの回答 1'!$E:$E,'フォームの回答 1'!$B:$B,H32,'フォームの回答 1'!$H:$H,$A33) -> 7118 | I33: =SUMIFS('フォームの回答 1'!$E:$E,'フォームの回答 1'!$B:$B,I32,'フォームの回答 1'!$H:$H,$A33) -> 0 | J33: =SUMIFS('フォームの回答 1'!$E:$E,'フォームの回答 1'!$B:$B,J32,'フォームの回答 1'!$H:$H,$A33) -> 0 | ... Z33: =SUMIFS('フォームの回答 1'!$E:$E,'フォームの回答 1'!$B:$B,Z32,'フォームの回答 1'!$H:$H,$A33) -> 0 | AA33: =SUMIFS('フォームの回答 1'!$E:$E,'フォームの回答 1'!$B:$B,AA32,'フォームの回答 1'!$H:$H,$A33)+AJ24 -> 378905 | AB33: =SUMIFS('フォームの回答 1'!$E:$E,'フォームの回答 1'!$B:$B,AB32,'フォームの回答 1'!$H:$H,$A33) -> 0 | AC33: =SUMIFS('フォームの回答 1'!$E:$E,'フォームの回答 1'!$B:$B,AC32,'フォームの回答 1'!$H:$H,$A33) -> 0 | AD33: =SUMIFS('フォームの回答 1'!$E:$E,'フォームの回答 1'!$B:$B,AD32,'フォームの回答 1'!$H:$H,$A33) -> 0 | AE33: =SUMIFS('フォームの回答 1'!$E:$E,'フォームの回答 1'!$B:$B,AE32,'フォームの回答 1'!$H:$H,$A33) -> 0 | AF33: =SUMIFS('フォームの回答 1'!$E:$E,'フォームの回答 1'!$B:$B,AF32,'フォームの回答 1'!$H:$H,$A33) -> 0
A34: 支出 | B34: =SUM(C34:AG34) -> 414509 | C34: =SUMIFS('フォームの回答 1'!$E:$E,'フォームの回答 1'!$B:$B,C32,'フォームの回答 1'!$H:$H,$A34,'フォームの回答 1'!$F:$F,"Cash") -> 9396 | D34: =SUMIFS('フォームの回答 1'!$E:$E,'フォームの回答 1'!$B:$B,D32,'フォームの回答 1'!$H:$H,$A34,'フォームの回答 1'!$F:$F,"Cash") -> 1300 | E34: =SUMIFS('フォームの回答 1'!$E:$E,'フォームの回答 1'!$B:$B,E32,'フォームの回答 1'!$H:$H,$A34,'フォームの回答 1'!$F:$F,"Cash") -> 899 | F34: =SUMIFS('フォームの回答 1'!$E:$E,'フォームの回答 1'!$B:$B,F32,'フォームの回答 1'!$H:$H,$A34,'フォームの回答 1'!$F:$F,"Cash") -> 500 | G34: =SUMIFS('フォームの回答 1'!$E:$E,'フォームの回答 1'!$B:$B,G32,'フォームの回答 1'!$H:$H,$A34,'フォームの回答 1'!$F:$F,"Cash") -> 1107 | H34: =SUMIFS('フォームの回答 1'!$E:$E,'フォームの回答 1'!$B:$B,H32,'フォームの回答 1'!$H:$H,$A34,'フォームの回答 1'!$F:$F,"Cash") -> 2318 | I34: =SUMIFS('フォームの回答 1'!$E:$E,'フォームの回答 1'!$B:$B,I32,'フォームの回答 1'!$H:$H,$A34,'フォームの回答 1'!$F:$F,"Cash") -> 7123 | J34: =SUMIFS('フォームの回答 1'!$E:$E,'フォームの回答 1'!$B:$B,J32,'フォームの回答 1'!$H:$H,$A34,'フォームの回答 1'!$F:$F,"Cash") -> 0 | ... AB34: =SUMIFS('フォームの回答 1'!$E:$E,'フォームの回答 1'!$B:$B,AB32,'フォームの回答 1'!$H:$H,$A34,'フォームの回答 1'!$F:$F,"Cash") -> 239 | AC34: =SUMIFS('フォームの回答 1'!$E:$E,'フォームの回答 1'!$B:$B,AC32,'フォームの回答 1'!$H:$H,$A34,'フォームの回答 1'!$F:$F,"Cash")+AI32 -> 342236 | AD34: =SUMIFS('フォームの回答 1'!$E:$E,'フォームの回答 1'!$B:$B,AD32,'フォームの回答 1'!$H:$H,$A34,'フォームの回答 1'!$F:$F,"Cash") -> 3929 | AE34: =SUMIFS('フォームの回答 1'!$E:$E,'フォームの回答 1'!$B:$B,AE32,'フォームの回答 1'!$H:$H,$A34,'フォームの回答 1'!$F:$F,"Cash") -> 1677 | AF34: =SUMIFS('フォームの回答 1'!$E:$E,'フォームの回答 1'!$B:$B,AF32,'フォームの回答 1'!$H:$H,$A34,'フォームの回答 1'!$F:$F,"Cash") -> 0
A35: 残高 | C35: =AG29+C33-C34 -> 39875 | D35: =C35+D33-D34 -> 38575 | E35: =D35+E33-E34 -> 37676 | F35: =E35+F33-F34 -> 37176 | G35: =F35+G33-G34 -> 36069 | H35: =G35+H33-H34 -> 40869 | I35: =H35+I33-I34 -> 33746 | J35: =I35+J33-J34 -> 33746 | K35: =J35+K33-K34 -> 32766 | ... AF35: =AE35+AF33-AF34 -> 20785
B37: 7月 | AI37: 7月クレジット引き落とし
B38: 合計金額 | C38: 45839 | D38: 45840 | E38: 45841 | F38: 45842 | G38: 45843 | H38: 45844 | I38: 45845 | J38: 45846 | K38: 45847 | L38: 45848 | M38: 45849 | N38: 45850 | O38: 45851 | P38: 45852 | Q38: 45853 | R38: 45854 | S38: 45855 | T38: 45856 | U38: 45857 | V38: 45858 | W38: 45859 | X38: 45860 | Y38: 45861 | Z38: 45862 | AA38: 45863 | AB38: 45864 | AC38: 45865 | AD38: 45866 | AE38: 45867 | AF38: 45868 | AG38: 45869 | AI38: 198038
A39: 収入 | B39: =SUM(V39:AG39) -> 481705 | C39: =SUMIFS('フォームの回答 1'!$E:$E,'フォームの回答 1'!$B:$B,C38,'フォームの回答 1'!$H:$H,$A39) -> 0 | D39: =SUMIFS('フォームの回答 1'!$E:$E,'フォームの回答 1'!$B:$B,D38,'フォームの回答 1'!$H:$H,$A39) -> 6287 | E39: =SUMIFS('フォームの回答 1'!$E:$E,'フォームの回答 1'!$B:$B,E38,'フォームの回答 1'!$H:$H,$A39) -> 8361 | F39: =SUMIFS('フォームの回答 1'!$E:$E,'フォームの回答 1'!$B:$B,F38,'フォームの回答 1'!$H:$H,$A39) -> 0 | G39: =SUMIFS('フォームの回答 1'!$E:$E,'フォームの回答 1'!$B:$B,G38,'フォームの回答 1'!$H:$H,$A39) -> 0 | H39: =SUMIFS('フォームの回答 1'!$E:$E,'フォームの回答 1'!$B:$B,H38,'フォームの回答 1'!$H:$H,$A39) -> 0 | I39: =SUMIFS('フォームの回答 1'!$E:$E,'フォームの回答 1'!$B:$B,I38,'フォームの回答 1'!$H:$H,$A39) -> 0 | J39: =SUMIFS('フォームの回答 1'!$E:$E,'フォームの回答 1'!$B:$B,J38,'フォームの回答 1'!$H:$H,$A39) -> 0 | ... Z39: =SUMIFS('フォームの回答 1'!$E:$E,'フォームの回答 1'!$B:$B,Z38,'フォームの回答 1'!$H:$H,$A39) -> 900 | AA39: =SUMIFS('フォームの回答 1'!$E:$E,'フォームの回答 1'!$B:$B,AA38,'フォームの回答 1'!$H:$H,$A39)+AJ30 -> 379705 | AB39: =SUMIFS('フォームの回答 1'!$E:$E,'フォームの回答 1'!$B:$B,AB38,'フォームの回答 1'!$H:$H,$A39) -> 0 | AC39: =SUMIFS('フォームの回答 1'!$E:$E,'フォームの回答 1'!$B:$B,AC38,'フォームの回答 1'!$H:$H,$A39) -> 100000 | AD39: =SUMIFS('フォームの回答 1'!$E:$E,'フォームの回答 1'!$B:$B,AD38,'フォームの回答 1'!$H:$H,$A39) -> 0 | AE39: =SUMIFS('フォームの回答 1'!$E:$E,'フォームの回答 1'!$B:$B,AE38,'フォームの回答 1'!$H:$H,$A39) -> 0 | AF39: =SUMIFS('フォームの回答 1'!$E:$E,'フォームの回答 1'!$B:$B,AF38,'フォームの回答 1'!$H:$H,$A39) -> 0 | AG39: =SUMIFS('フォームの回答 1'!$E:$E,'フォームの回答 1'!$B:$B,AG38,'フォームの回答 1'!$H:$H,$A39) -> 0 | AI39: 100000
A40: 支出 | B40: =SUM(C40:AG40) -> 463902 | C40: =SUMIFS('フォームの回答 1'!$E:$E,'フォームの回答 1'!$B:$B,C38,'フォームの回答 1'!$H:$H,$A40,'フォームの回答 1'!$F:$F,"Cash") -> 1950 | D40: =SUMIFS('フォームの回答 1'!$E:$E,'フォームの回答 1'!$B:$B,D38,'フォームの回答 1'!$H:$H,$A40,'フォームの回答 1'!$F:$F,"Cash") -> 4481 | E40: =SUMIFS('フォームの回答 1'!$E:$E,'フォームの回答 1'!$B:$B,E38,'フォームの回答 1'!$H:$H,$A40,'フォームの回答 1'!$F:$F,"Cash") -> 1504 | F40: =SUMIFS('フォームの回答 1'!$E:$E,'フォームの回答 1'!$B:$B,F38,'フォームの回答 1'!$H:$H,$A40,'フォームの回答 1'!$F:$F,"Cash") -> 3780 | G40: =SUMIFS('フォームの回答 1'!$E:$E,'フォームの回答 1'!$B:$B,G38,'フォームの回答 1'!$H:$H,$A40,'フォームの回答 1'!$F:$F,"Cash") -> 220 | H40: =SUMIFS('フォームの回答 1'!$E:$E,'フォームの回答 1'!$B:$B,H38,'フォームの回答 1'!$H:$H,$A40,'フォームの回答 1'!$F:$F,"Cash") -> 6681 | I40: =SUMIFS('フォームの回答 1'!$E:$E,'フォームの回答 1'!$B:$B,I38,'フォームの回答 1'!$H:$H,$A40,'フォームの回答 1'!$F:$F,"Cash") -> 3080 | J40: =SUMIFS('フォームの回答 1'!$E:$E,'フォームの回答 1'!$B:$B,J38,'フォームの回答 1'!$H:$H,$A40,'フォームの回答 1'!$F:$F,"Cash") -> 0 | ... AC40: =SUMIFS('フォームの回答 1'!$E:$E,'フォームの回答 1'!$B:$B,AC38,'フォームの回答 1'!$H:$H,$A40,'フォームの回答 1'!$F:$F,"Cash") -> 1960 | AD40: =SUMIFS('フォームの回答 1'!$E:$E,'フォームの回答 1'!$B:$B,AD38,'フォームの回答 1'!$H:$H,$A40,'フォームの回答 1'!$F:$F,"Cash")+AI38 -> 349116 | AE40: =SUMIFS('フォームの回答 1'!$E:$E,'フォームの回答 1'!$B:$B,AE38,'フォームの回答 1'!$H:$H,$A40,'フォームの回答 1'!$F:$F,"Cash") -> 5849 | AF40: =SUMIFS('フォームの回答 1'!$E:$E,'フォームの回答 1'!$B:$B,AF38,'フォームの回答 1'!$H:$H,$A40,'フォームの回答 1'!$F:$F,"Cash") -> 1100 | AG40: =SUMIFS('フォームの回答 1'!$E:$E,'フォームの回答 1'!$B:$B,AG38,'フォームの回答 1'!$H:$H,$A40,'フォームの回答 1'!$F:$F,"Cash") -> 500
A41: 残高 | C41: =AF35+C39-C40 -> 18835 | D41: =C41+D39-D40 -> 20641 | E41: =D41+E39-E40 -> 27498 | F41: =E41+F39-F40 -> 23718 | G41: =F41+G39-G40 -> 23498 | H41: =G41+H39-H40 -> 16817 | I41: =H41+I39-I40 -> 13737 | J41: =I41+J39-J40 -> 13737 | K41: =J41+K39-K40 -> 13448 | ... AG41: =AF41+AG39-AG40 -> 82656
B43: 8月 | AI43: 8月クレジット引き落とし
B44: 合計金額 | C44: 45870 | D44: 45871 | E44: 45872 | F44: 45873 | G44: 45874 | H44: 45875 | I44: 45876 | J44: 45877 | K44: 45878 | L44: 45879 | M44: 45880 | N44: 45881 | O44: 45882 | P44: 45883 | Q44: 45884 | R44: 45885 | S44: 45886 | T44: 45887 | U44: 45888 | V44: 45889 | W44: 45890 | X44: 45891 | Y44: 45892 | Z44: 45893 | AA44: 45894 | AB44: 45895 | AC44: 45896 | AD44: 45897 | AE44: 45898 | AF44: 45899 | AG44: 45900 | AI44: 167345
A45: 収入 | B45: =SUM(V45:AG45) -> 389705 | C45: =SUMIFS('フォームの回答 1'!$E:$E,'フォームの回答 1'!$B:$B,C44,'フォームの回答 1'!$H:$H,$A45) -> 0 | D45: =SUMIFS('フォームの回答 1'!$E:$E,'フォームの回答 1'!$B:$B,D44,'フォームの回答 1'!$H:$H,$A45) -> 0 | E45: =SUMIFS('フォームの回答 1'!$E:$E,'フォームの回答 1'!$B:$B,E44,'フォームの回答 1'!$H:$H,$A45) -> 0 | F45: =SUMIFS('フォームの回答 1'!$E:$E,'フォームの回答 1'!$B:$B,F44,'フォームの回答 1'!$H:$H,$A45) -> 0 | G45: =SUMIFS('フォームの回答 1'!$E:$E,'フォームの回答 1'!$B:$B,G44,'フォームの回答 1'!$H:$H,$A45) -> 0 | H45: =SUMIFS('フォームの回答 1'!$E:$E,'フォームの回答 1'!$B:$B,H44,'フォームの回答 1'!$H:$H,$A45) -> 0 | I45: =SUMIFS('フォームの回答 1'!$E:$E,'フォームの回答 1'!$B:$B,I44,'フォームの回答 1'!$H:$H,$A45) -> 0 | J45: =SUMIFS('フォームの回答 1'!$E:$E,'フォームの回答 1'!$B:$B,J44,'フォームの回答 1'!$H:$H,$A45) -> 0 | ... Z45: =SUMIFS('フォームの回答 1'!$E:$E,'フォームの回答 1'!$B:$B,Z44,'フォームの回答 1'!$H:$H,$A45) -> 0 | AA45: =SUMIFS('フォームの回答 1'!$E:$E,'フォームの回答 1'!$B:$B,AA44,'フォームの回答 1'!$H:$H,$A45)+AJ36 -> 379705 | AB45: =SUMIFS('フォームの回答 1'!$E:$E,'フォームの回答 1'!$B:$B,AB44,'フォームの回答 1'!$H:$H,$A45) -> 0 | AC45: =SUMIFS('フォームの回答 1'!$E:$E,'フォームの回答 1'!$B:$B,AC44,'フォームの回答 1'!$H:$H,$A45) -> 0 | AD45: =SUMIFS('フォームの回答 1'!$E:$E,'フォームの回答 1'!$B:$B,AD44,'フォームの回答 1'!$H:$H,$A45) -> 0 | AE45: =SUMIFS('フォームの回答 1'!$E:$E,'フォームの回答 1'!$B:$B,AE44,'フォームの回答 1'!$H:$H,$A45) -> 0 | AF45: =SUMIFS('フォームの回答 1'!$E:$E,'フォームの回答 1'!$B:$B,AF44,'フォームの回答 1'!$H:$H,$A45) -> 0 | AG45: =SUMIFS('フォームの回答 1'!$E:$E,'フォームの回答 1'!$B:$B,AG44,'フォームの回答 1'!$H:$H,$A45) -> 10000
A46: 支出 | B46: =SUM(C46:AG46) -> 445157 | C46: =SUMIFS('フォームの回答 1'!$E:$E,'フォームの回答 1'!$B:$B,C44,'フォームの回答 1'!$H:$H,$A46,'フォームの回答 1'!$F:$F,"Cash") -> 850 | D46: =SUMIFS('フォームの回答 1'!$E:$E,'フォームの回答 1'!$B:$B,D44,'フォームの回答 1'!$H:$H,$A46,'フォームの回答 1'!$F:$F,"Cash") -> 2044 | E46: =SUMIFS('フォームの回答 1'!$E:$E,'フォームの回答 1'!$B:$B,E44,'フォームの回答 1'!$H:$H,$A46,'フォームの回答 1'!$F:$F,"Cash") -> 1190 | F46: =SUMIFS('フォームの回答 1'!$E:$E,'フォームの回答 1'!$B:$B,F44,'フォームの回答 1'!$H:$H,$A46,'フォームの回答 1'!$F:$F,"Cash") -> 2847 | G46: =SUMIFS('フォームの回答 1'!$E:$E,'フォームの回答 1'!$B:$B,G44,'フォームの回答 1'!$H:$H,$A46,'フォームの回答 1'!$F:$F,"Cash") -> 0 | H46: =SUMIFS('フォームの回答 1'!$E:$E,'フォームの回答 1'!$B:$B,H44,'フォームの回答 1'!$H:$H,$A46,'フォームの回答 1'!$F:$F,"Cash") -> 4448 | I46: =SUMIFS('フォームの回答 1'!$E:$E,'フォームの回答 1'!$B:$B,I44,'フォームの回答 1'!$H:$H,$A46,'フォームの回答 1'!$F:$F,"Cash") -> 0 | J46: =SUMIFS('フォームの回答 1'!$E:$E,'フォームの回答 1'!$B:$B,J44,'フォームの回答 1'!$H:$H,$A46,'フォームの回答 1'!$F:$F,"Cash") -> 1230 | ... AB46: =SUMIFS('フォームの回答 1'!$E:$E,'フォームの回答 1'!$B:$B,AB44,'フォームの回答 1'!$H:$H,$A46,'フォームの回答 1'!$F:$F,"Cash") -> 5251 | AC46: =SUMIFS('フォームの回答 1'!$E:$E,'フォームの回答 1'!$B:$B,AC44,'フォームの回答 1'!$H:$H,$A46,'フォームの回答 1'!$F:$F,"Cash")+AI44 -> 317415 | AD46: =SUMIFS('フォームの回答 1'!$E:$E,'フォームの回答 1'!$B:$B,AD44,'フォームの回答 1'!$H:$H,$A46,'フォームの回答 1'!$F:$F,"Cash") -> 1300 | AE46: =SUMIFS('フォームの回答 1'!$E:$E,'フォームの回答 1'!$B:$B,AE44,'フォームの回答 1'!$H:$H,$A46,'フォームの回答 1'!$F:$F,"Cash") -> 1386 | AF46: =SUMIFS('フォームの回答 1'!$E:$E,'フォームの回答 1'!$B:$B,AF44,'フォームの回答 1'!$H:$H,$A46,'フォームの回答 1'!$F:$F,"Cash") -> 1941 | AG46: =SUMIFS('フォームの回答 1'!$E:$E,'フォームの回答 1'!$B:$B,AG44,'フォームの回答 1'!$H:$H,$A46,'フォームの回答 1'!$F:$F,"Cash") -> 447
A47: 残高 | C47: =AG41+C45-C46 -> 81806 | D47: =C47+D45-D46 -> 79762 | E47: =D47+E45-E46 -> 78572 | F47: =E47+F45-F46 -> 75725 | G47: =F47+G45-G46 -> 75725 | H47: =G47+H45-H46 -> 71277 | I47: =H47+I45-I46 -> 71277 | J47: =I47+J45-J46 -> 70047 | K47: =J47+K45-K46 -> 49616 | ... AG47: =AF47+AG45-AG46 -> 27204
B49: 9月 | AI49: 9月クレジット引き落とし
B50: 合計金額 | C50: 45901 | D50: 45902 | E50: 45903 | F50: 45904 | G50: 45905 | H50: 45906 | I50: 45907 | J50: 45908 | K50: 45909 | L50: 45910 | M50: 45911 | N50: 45912 | O50: 45913 | P50: 45914 | Q50: 45915 | R50: 45916 | S50: 45917 | T50: 45918 | U50: 45919 | V50: 45920 | W50: 45921 | X50: 45922 | Y50: 45923 | Z50: 45924 | AA50: 45925 | AB50: 45926 | AC50: 45927 | AD50: 45928 | AE50: 45929 | AF50: 45930 | AI50: 166252
A51: 収入 | B51: =SUM(V51:AG51) -> 379705 | C51: =SUMIFS('フォームの回答 1'!$E:$E,'フォームの回答 1'!$B:$B,C50,'フォームの回答 1'!$H:$H,$A51) -> 13911 | D51: =SUMIFS('フォームの回答 1'!$E:$E,'フォームの回答 1'!$B:$B,D50,'フォームの回答 1'!$H:$H,$A51) -> 0 | E51: =SUMIFS('フォームの回答 1'!$E:$E,'フォームの回答 1'!$B:$B,E50,'フォームの回答 1'!$H:$H,$A51) -> 0 | F51: =SUMIFS('フォームの回答 1'!$E:$E,'フォームの回答 1'!$B:$B,F50,'フォームの回答 1'!$H:$H,$A51) -> 8672 | G51: =SUMIFS('フォームの回答 1'!$E:$E,'フォームの回答 1'!$B:$B,G50,'フォームの回答 1'!$H:$H,$A51) -> 3500 | H51: =SUMIFS('フォームの回答 1'!$E:$E,'フォームの回答 1'!$B:$B,H50,'フォームの回答 1'!$H:$H,$A51) -> 0 | I51: =SUMIFS('フォームの回答 1'!$E:$E,'フォームの回答 1'!$B:$B,I50,'フォームの回答 1'!$H:$H,$A51) -> 0 | J51: =SUMIFS('フォームの回答 1'!$E:$E,'フォームの回答 1'!$B:$B,J50,'フォームの回答 1'!$H:$H,$A51) -> 0 | ... Z51: =SUMIFS('フォームの回答 1'!$E:$E,'フォームの回答 1'!$B:$B,Z50,'フォームの回答 1'!$H:$H,$A51) -> 0 | AA51: =SUMIFS('フォームの回答 1'!$E:$E,'フォームの回答 1'!$B:$B,AA50,'フォームの回答 1'!$H:$H,$A51)+AJ42 -> 379705 | AB51: =SUMIFS('フォームの回答 1'!$E:$E,'フォームの回答 1'!$B:$B,AB50,'フォームの回答 1'!$H:$H,$A51) -> 0 | AC51: =SUMIFS('フォームの回答 1'!$E:$E,'フォームの回答 1'!$B:$B,AC50,'フォームの回答 1'!$H:$H,$A51) -> 0 | AD51: =SUMIFS('フォームの回答 1'!$E:$E,'フォームの回答 1'!$B:$B,AD50,'フォームの回答 1'!$H:$H,$A51) -> 0 | AE51: =SUMIFS('フォームの回答 1'!$E:$E,'フォームの回答 1'!$B:$B,AE50,'フォームの回答 1'!$H:$H,$A51) -> 0 | AF51: =SUMIFS('フォームの回答 1'!$E:$E,'フォームの回答 1'!$B:$B,AF50,'フォームの回答 1'!$H:$H,$A51) -> 0
A52: 支出 | B52: =SUM(C52:AG52) -> 416812 | C52: =SUMIFS('フォームの回答 1'!$E:$E,'フォームの回答 1'!$B:$B,C50,'フォームの回答 1'!$H:$H,$A52,'フォームの回答 1'!$F:$F,"Cash") -> 852 | D52: =SUMIFS('フォームの回答 1'!$E:$E,'フォームの回答 1'!$B:$B,D50,'フォームの回答 1'!$H:$H,$A52,'フォームの回答 1'!$F:$F,"Cash") -> 472 | E52: =SUMIFS('フォームの回答 1'!$E:$E,'フォームの回答 1'!$B:$B,E50,'フォームの回答 1'!$H:$H,$A52,'フォームの回答 1'!$F:$F,"Cash") -> 4532 | F52: =SUMIFS('フォームの回答 1'!$E:$E,'フォームの回答 1'!$B:$B,F50,'フォームの回答 1'!$H:$H,$A52,'フォームの回答 1'!$F:$F,"Cash") -> 1065 | G52: =SUMIFS('フォームの回答 1'!$E:$E,'フォームの回答 1'!$B:$B,G50,'フォームの回答 1'!$H:$H,$A52,'フォームの回答 1'!$F:$F,"Cash") -> 2193 | H52: =SUMIFS('フォームの回答 1'!$E:$E,'フォームの回答 1'!$B:$B,H50,'フォームの回答 1'!$H:$H,$A52,'フォームの回答 1'!$F:$F,"Cash") -> 4084 | I52: =SUMIFS('フォームの回答 1'!$E:$E,'フォームの回答 1'!$B:$B,I50,'フォームの回答 1'!$H:$H,$A52,'フォームの回答 1'!$F:$F,"Cash") -> 130 | J52: =SUMIFS('フォームの回答 1'!$E:$E,'フォームの回答 1'!$B:$B,J50,'フォームの回答 1'!$H:$H,$A52,'フォームの回答 1'!$F:$F,"Cash") -> 1100 | ... AB52: =SUMIFS('フォームの回答 1'!$E:$E,'フォームの回答 1'!$B:$B,AB50,'フォームの回答 1'!$H:$H,$A52,'フォームの回答 1'!$F:$F,"Cash") -> 999 | AC52: =SUMIFS('フォームの回答 1'!$E:$E,'フォームの回答 1'!$B:$B,AC50,'フォームの回答 1'!$H:$H,$A52,'フォームの回答 1'!$F:$F,"Cash")+AI50 -> 206252 | AD52: =SUMIFS('フォームの回答 1'!$E:$E,'フォームの回答 1'!$B:$B,AD50,'フォームの回答 1'!$H:$H,$A52,'フォームの回答 1'!$F:$F,"Cash") -> 5477 | AE52: =SUMIFS('フォームの回答 1'!$E:$E,'フォームの回答 1'!$B:$B,AE50,'フォームの回答 1'!$H:$H,$A52,'フォームの回答 1'!$F:$F,"Cash") -> 146687 | AF52: =SUMIFS('フォームの回答 1'!$E:$E,'フォームの回答 1'!$B:$B,AF50,'フォームの回答 1'!$H:$H,$A52,'フォームの回答 1'!$F:$F,"Cash") -> 1762
A53: 残高 | C53: =AG47+C51-C52 -> 40263 | D53: =C53+D51-D52 -> 39791 | E53: =D53+E51-E52 -> 35259 | F53: =E53+F51-F52 -> 42866 | G53: =F53+G51-G52 -> 44173 | H53: =G53+H51-H52 -> 40089 | I53: =H53+I51-I52 -> 39959 | J53: =I53+J51-J52 -> 38859 | K53: =J53+K51-K52 -> 38859 | ... AF53: =AE53+AF51-AF52 -> 20680
B55: 10月 | AI55: 10月クレジット引き落とし
B56: 合計金額 | C56: 45931 | D56: 45932 | E56: 45933 | F56: 45934 | G56: 45935 | H56: 45936 | I56: 45937 | J56: 45938 | K56: 45939 | L56: 45940 | M56: 45941 | N56: 45942 | O56: 45943 | P56: 45944 | Q56: 45945 | R56: 45946 | S56: 45947 | T56: 45948 | U56: 45949 | V56: 45950 | W56: 45951 | X56: 45952 | Y56: 45953 | Z56: 45954 | AA56: 45955 | AB56: 45956 | AC56: 45957 | AD56: 45958 | AE56: 45959 | AF56: 45960 | AG56: 45961 | AI56: 231826
A57: 収入 | B57: =SUM(V57:AG57) -> 375775 | C57: =SUMIFS('フォームの回答 1'!$E:$E,'フォームの回答 1'!$B:$B,C56,'フォームの回答 1'!$H:$H,$A57) -> 3523 | D57: =SUMIFS('フォームの回答 1'!$E:$E,'フォームの回答 1'!$B:$B,D56,'フォームの回答 1'!$H:$H,$A57) -> 0 | E57: =SUMIFS('フォームの回答 1'!$E:$E,'フォームの回答 1'!$B:$B,E56,'フォームの回答 1'!$H:$H,$A57) -> 0 | F57: =SUMIFS('フォームの回答 1'!$E:$E,'フォームの回答 1'!$B:$B,F56,'フォームの回答 1'!$H:$H,$A57) -> 0 | G57: =SUMIFS('フォームの回答 1'!$E:$E,'フォームの回答 1'!$B:$B,G56,'フォームの回答 1'!$H:$H,$A57) -> 0 | H57: =SUMIFS('フォームの回答 1'!$E:$E,'フォームの回答 1'!$B:$B,H56,'フォームの回答 1'!$H:$H,$A57) -> 0 | I57: =SUMIFS('フォームの回答 1'!$E:$E,'フォームの回答 1'!$B:$B,I56,'フォームの回答 1'!$H:$H,$A57) -> 0 | J57: =SUMIFS('フォームの回答 1'!$E:$E,'フォームの回答 1'!$B:$B,J56,'フォームの回答 1'!$H:$H,$A57) -> 0 | ... Z57: =SUMIFS('フォームの回答 1'!$E:$E,'フォームの回答 1'!$B:$B,Z56,'フォームの回答 1'!$H:$H,$A57) -> 375775 | AA57: =SUMIFS('フォームの回答 1'!$E:$E,'フォームの回答 1'!$B:$B,AA56,'フォームの回答 1'!$H:$H,$A57)+AJ48 -> 0 | AB57: =SUMIFS('フォームの回答 1'!$E:$E,'フォームの回答 1'!$B:$B,AB56,'フォームの回答 1'!$H:$H,$A57) -> 0 | AC57: =SUMIFS('フォームの回答 1'!$E:$E,'フォームの回答 1'!$B:$B,AC56,'フォームの回答 1'!$H:$H,$A57) -> 0 | AD57: =SUMIFS('フォームの回答 1'!$E:$E,'フォームの回答 1'!$B:$B,AD56,'フォームの回答 1'!$H:$H,$A57) -> 0 | AE57: =SUMIFS('フォームの回答 1'!$E:$E,'フォームの回答 1'!$B:$B,AE56,'フォームの回答 1'!$H:$H,$A57) -> 0 | AF57: =SUMIFS('フォームの回答 1'!$E:$E,'フォームの回答 1'!$B:$B,AF56,'フォームの回答 1'!$H:$H,$A57) -> 0 | AG57: =SUMIFS('フォームの回答 1'!$E:$E,'フォームの回答 1'!$B:$B,AG56,'フォームの回答 1'!$H:$H,$A57) -> 0
A58: 支出 | B58: =SUM(C58:AG58) -> 487446 | C58: =SUMIFS('フォームの回答 1'!$E:$E,'フォームの回答 1'!$B:$B,C56,'フォームの回答 1'!$H:$H,$A58,'フォームの回答 1'!$F:$F,"Cash") -> 3260 | D58: =SUMIFS('フォームの回答 1'!$E:$E,'フォームの回答 1'!$B:$B,D56,'フォームの回答 1'!$H:$H,$A58,'フォームの回答 1'!$F:$F,"Cash") -> 3642 | E58: =SUMIFS('フォームの回答 1'!$E:$E,'フォームの回答 1'!$B:$B,E56,'フォームの回答 1'!$H:$H,$A58,'フォームの回答 1'!$F:$F,"Cash") -> 1100 | F58: =SUMIFS('フォームの回答 1'!$E:$E,'フォームの回答 1'!$B:$B,F56,'フォームの回答 1'!$H:$H,$A58,'フォームの回答 1'!$F:$F,"Cash") -> 2460 | G58: =SUMIFS('フォームの回答 1'!$E:$E,'フォームの回答 1'!$B:$B,G56,'フォームの回答 1'!$H:$H,$A58,'フォームの回答 1'!$F:$F,"Cash") -> 680 | H58: =SUMIFS('フォームの回答 1'!$E:$E,'フォームの回答 1'!$B:$B,H56,'フォームの回答 1'!$H:$H,$A58,'フォームの回答 1'!$F:$F,"Cash") -> 1350 | I58: =SUMIFS('フォームの回答 1'!$E:$E,'フォームの回答 1'!$B:$B,I56,'フォームの回答 1'!$H:$H,$A58,'フォームの回答 1'!$F:$F,"Cash") -> 3308 | J58: =SUMIFS('フォームの回答 1'!$E:$E,'フォームの回答 1'!$B:$B,J56,'フォームの回答 1'!$H:$H,$A58,'フォームの回答 1'!$F:$F,"Cash") -> 950 | ... AB58: =SUMIFS('フォームの回答 1'!$E:$E,'フォームの回答 1'!$B:$B,AB56,'フォームの回答 1'!$H:$H,$A58,'フォームの回答 1'!$F:$F,"Cash") -> 4380 | AC58: =SUMIFS('フォームの回答 1'!$E:$E,'フォームの回答 1'!$B:$B,AC56,'フォームの回答 1'!$H:$H,$A58,'フォームの回答 1'!$F:$F,"Cash")+AI56 -> 381926 | AD58: =SUMIFS('フォームの回答 1'!$E:$E,'フォームの回答 1'!$B:$B,AD56,'フォームの回答 1'!$H:$H,$A58,'フォームの回答 1'!$F:$F,"Cash") -> 300 | AE58: =SUMIFS('フォームの回答 1'!$E:$E,'フォームの回答 1'!$B:$B,AE56,'フォームの回答 1'!$H:$H,$A58,'フォームの回答 1'!$F:$F,"Cash") -> 1570 | AF58: =SUMIFS('フォームの回答 1'!$E:$E,'フォームの回答 1'!$B:$B,AF56,'フォームの回答 1'!$H:$H,$A58,'フォームの回答 1'!$F:$F,"Cash") -> 1909 | AG58: =SUMIFS('フォームの回答 1'!$E:$E,'フォームの回答 1'!$B:$B,AG56,'フォームの回答 1'!$H:$H,$A58,'フォームの回答 1'!$F:$F,"Cash") -> 2175
A59: 残高 | C59: =AF53+C57-C58 -> 20943 | D59: =C59+D57-D58 -> 17301 | E59: =D59+E57-E58 -> 16201 | F59: =E59+F57-F58 -> 13741 | G59: =F59+G57-G58 -> 13061 | H59: =G59+H57-H58 -> 11711 | I59: =H59+I57-I58 -> 8403 | J59: =I59+J57-J58 -> 7453 | K59: =J59+K57-K58 -> 7453 | ... AG59: =AF59+AG57-AG58 -> 16507
B61: 11月 | AI61: 11月クレジット引き落とし
B62: 合計金額 | C62: 45962 | D62: 45963 | E62: 45964 | F62: 45965 | G62: 45966 | H62: 45967 | I62: 45968 | J62: 45969 | K62: 45970 | L62: 45971 | M62: 45972 | N62: 45973 | O62: 45974 | P62: 45975 | Q62: 45976 | R62: 45977 | S62: 45978 | T62: 45979 | U62: 45980 | V62: 45981 | W62: 45982 | X62: 45983 | Y62: 45984 | Z62: 45985 | AA62: 45986 | AB62: 45987 | AC62: 45988 | AD62: 45989 | AE62: 45990 | AF62: 45991 | AI62: 251749
A63: 収入 | B63: =SUM(V63:AG63) -> 525775 | C63: =SUMIFS('フォームの回答 1'!$E:$E,'フォームの回答 1'!$B:$B,C62,'フォームの回答 1'!$H:$H,$A63) -> 5250 | D63: =SUMIFS('フォームの回答 1'!$E:$E,'フォームの回答 1'!$B:$B,D62,'フォームの回答 1'!$H:$H,$A63) -> 1189 | E63: =SUMIFS('フォームの回答 1'!$E:$E,'フォームの回答 1'!$B:$B,E62,'フォームの回答 1'!$H:$H,$A63) -> 0 | F63: =SUMIFS('フォームの回答 1'!$E:$E,'フォームの回答 1'!$B:$B,F62,'フォームの回答 1'!$H:$H,$A63) -> 0 | G63: =SUMIFS('フォームの回答 1'!$E:$E,'フォームの回答 1'!$B:$B,G62,'フォームの回答 1'!$H:$H,$A63) -> 0 | H63: =SUMIFS('フォームの回答 1'!$E:$E,'フォームの回答 1'!$B:$B,H62,'フォームの回答 1'!$H:$H,$A63) -> 8040 | I63: =SUMIFS('フォームの回答 1'!$E:$E,'フォームの回答 1'!$B:$B,I62,'フォームの回答 1'!$H:$H,$A63) -> 0 | J63: =SUMIFS('フォームの回答 1'!$E:$E,'フォームの回答 1'!$B:$B,J62,'フォームの回答 1'!$H:$H,$A63) -> 0 | ... Z63: =SUMIFS('フォームの回答 1'!$E:$E,'フォームの回答 1'!$B:$B,Z62,'フォームの回答 1'!$H:$H,$A63) -> 0 | AA63: =SUMIFS('フォームの回答 1'!$E:$E,'フォームの回答 1'!$B:$B,AA62,'フォームの回答 1'!$H:$H,$A63)+AI64 -> 375775 | AB63: =SUMIFS('フォームの回答 1'!$E:$E,'フォームの回答 1'!$B:$B,AB62,'フォームの回答 1'!$H:$H,$A63) -> 0 | AC63: =SUMIFS('フォームの回答 1'!$E:$E,'フォームの回答 1'!$B:$B,AC62,'フォームの回答 1'!$H:$H,$A63) -> 150000 | AD63: =SUMIFS('フォームの回答 1'!$E:$E,'フォームの回答 1'!$B:$B,AD62,'フォームの回答 1'!$H:$H,$A63) -> 0 | AE63: =SUMIFS('フォームの回答 1'!$E:$E,'フォームの回答 1'!$B:$B,AE62,'フォームの回答 1'!$H:$H,$A63) -> 0 | AF63: =SUMIFS('フォームの回答 1'!$E:$E,'フォームの回答 1'!$B:$B,AF62,'フォームの回答 1'!$H:$H,$A63) -> 0
A64: 支出 | B64: =SUM(C64:AG64) -> 533102 | C64: =SUMIFS('フォームの回答 1'!$E:$E,'フォームの回答 1'!$B:$B,C62,'フォームの回答 1'!$H:$H,$A64,'フォームの回答 1'!$F:$F,"Cash") -> 5654 | D64: =SUMIFS('フォームの回答 1'!$E:$E,'フォームの回答 1'!$B:$B,D62,'フォームの回答 1'!$H:$H,$A64,'フォームの回答 1'!$F:$F,"Cash") -> 1940 | E64: =SUMIFS('フォームの回答 1'!$E:$E,'フォームの回答 1'!$B:$B,E62,'フォームの回答 1'!$H:$H,$A64,'フォームの回答 1'!$F:$F,"Cash") -> 688 | F64: =SUMIFS('フォームの回答 1'!$E:$E,'フォームの回答 1'!$B:$B,F62,'フォームの回答 1'!$H:$H,$A64,'フォームの回答 1'!$F:$F,"Cash") -> 1400 | G64: =SUMIFS('フォームの回答 1'!$E:$E,'フォームの回答 1'!$B:$B,G62,'フォームの回答 1'!$H:$H,$A64,'フォームの回答 1'!$F:$F,"Cash") -> 531 | H64: =SUMIFS('フォームの回答 1'!$E:$E,'フォームの回答 1'!$B:$B,H62,'フォームの回答 1'!$H:$H,$A64,'フォームの回答 1'!$F:$F,"Cash") -> 1620 | I64: =SUMIFS('フォームの回答 1'!$E:$E,'フォームの回答 1'!$B:$B,I62,'フォームの回答 1'!$H:$H,$A64,'フォームの回答 1'!$F:$F,"Cash") -> 7193 | J64: =SUMIFS('フォームの回答 1'!$E:$E,'フォームの回答 1'!$B:$B,J62,'フォームの回答 1'!$H:$H,$A64,'フォームの回答 1'!$F:$F,"Cash") -> 914 | ... AB64: =SUMIFS('フォームの回答 1'!$E:$E,'フォームの回答 1'!$B:$B,AB62,'フォームの回答 1'!$H:$H,$A64,'フォームの回答 1'!$F:$F,"Cash") -> 43525 | AC64: =SUMIFS('フォームの回答 1'!$E:$E,'フォームの回答 1'!$B:$B,AC62,'フォームの回答 1'!$H:$H,$A64,'フォームの回答 1'!$F:$F,"Cash")+AI62 -> 399609 | AD64: =SUMIFS('フォームの回答 1'!$E:$E,'フォームの回答 1'!$B:$B,AD62,'フォームの回答 1'!$H:$H,$A64,'フォームの回答 1'!$F:$F,"Cash") -> 5185 | AE64: =SUMIFS('フォームの回答 1'!$E:$E,'フォームの回答 1'!$B:$B,AE62,'フォームの回答 1'!$H:$H,$A64,'フォームの回答 1'!$F:$F,"Cash") -> 4335 | AF64: =SUMIFS('フォームの回答 1'!$E:$E,'フォームの回答 1'!$B:$B,AF62,'フォームの回答 1'!$H:$H,$A64,'フォームの回答 1'!$F:$F,"Cash") -> 799
A65: 残高 | C65: =AG59+C63-C64 -> 16103 | D65: =C65+D63-D64 -> 15352 | E65: =D65+E63-E64 -> 14664 | F65: =E65+F63-F64 -> 13264 | G65: =F65+G63-G64 -> 12733 | H65: =G65+H63-H64 -> 19153 | I65: =H65+I63-I64 -> 11960 | J65: =I65+J63-J64 -> 11046 | K65: =J65+K63-K64 -> 6548 | ... AF65: =AE65+AF63-AF64 -> 75159
B67: 12月 | AI67: 12月クレジット引き落とし
B68: 合計金額 | C68: 45992 | D68: 45993 | E68: 45994 | F68: 45995 | G68: 45996 | H68: 45997 | I68: 45998 | J68: 45999 | K68: 46000 | L68: 46001 | M68: 46002 | N68: 46003 | O68: 46004 | P68: 46005 | Q68: 46006 | R68: 46007 | S68: 46008 | T68: 46009 | U68: 46010 | V68: 46011 | W68: 46012 | X68: 46013 | Y68: 46014 | Z68: 46015 | AA68: 46016 | AB68: 46017 | AC68: 46018 | AD68: 46019 | AE68: 46020 | AF68: 46021 | AG68: 46022 | AI68: 146700
A69: 収入 | B69: =SUM(V69:AG69) -> 420185 | C69: =SUMIFS('フォームの回答 1'!$E:$E,'フォームの回答 1'!$B:$B,C68,'フォームの回答 1'!$H:$H,$A69) -> 2641 | D69: =SUMIFS('フォームの回答 1'!$E:$E,'フォームの回答 1'!$B:$B,D68,'フォームの回答 1'!$H:$H,$A69) -> 0 | E69: =SUMIFS('フォームの回答 1'!$E:$E,'フォームの回答 1'!$B:$B,E68,'フォームの回答 1'!$H:$H,$A69) -> 0 | F69: =SUMIFS('フォームの回答 1'!$E:$E,'フォームの回答 1'!$B:$B,F68,'フォームの回答 1'!$H:$H,$A69) -> 0 | G69: =SUMIFS('フォームの回答 1'!$E:$E,'フォームの回答 1'!$B:$B,G68,'フォームの回答 1'!$H:$H,$A69) -> 0 | H69: =SUMIFS('フォームの回答 1'!$E:$E,'フォームの回答 1'!$B:$B,H68,'フォームの回答 1'!$H:$H,$A69) -> 0 | I69: =SUMIFS('フォームの回答 1'!$E:$E,'フォームの回答 1'!$B:$B,I68,'フォームの回答 1'!$H:$H,$A69) -> 0 | J69: =SUMIFS('フォームの回答 1'!$E:$E,'フォームの回答 1'!$B:$B,J68,'フォームの回答 1'!$H:$H,$A69) -> 0 | ... Z69: =SUMIFS('フォームの回答 1'!$E:$E,'フォームの回答 1'!$B:$B,Z68,'フォームの回答 1'!$H:$H,$A69) -> 0 | AA69: =SUMIFS('フォームの回答 1'!$E:$E,'フォームの回答 1'!$B:$B,AA68,'フォームの回答 1'!$H:$H,$A69)+AJ60 -> 412385 | AB69: =SUMIFS('フォームの回答 1'!$E:$E,'フォームの回答 1'!$B:$B,AB68,'フォームの回答 1'!$H:$H,$A69) -> 0 | AC69: =SUMIFS('フォームの回答 1'!$E:$E,'フォームの回答 1'!$B:$B,AC68,'フォームの回答 1'!$H:$H,$A69) -> 0 | AD69: =SUMIFS('フォームの回答 1'!$E:$E,'フォームの回答 1'!$B:$B,AD68,'フォームの回答 1'!$H:$H,$A69) -> 0 | AE69: =SUMIFS('フォームの回答 1'!$E:$E,'フォームの回答 1'!$B:$B,AE68,'フォームの回答 1'!$H:$H,$A69) -> 0 | AF69: =SUMIFS('フォームの回答 1'!$E:$E,'フォームの回答 1'!$B:$B,AF68,'フォームの回答 1'!$H:$H,$A69) -> 0 | AG69: =SUMIFS('フォームの回答 1'!$E:$E,'フォームの回答 1'!$B:$B,AG68,'フォームの回答 1'!$H:$H,$A69) -> 0
